Workbook

Sheet 개요
A1: Roma 이탈리아어 낭독 교재 — 캐릭터 바이블 (부활자 특별편)
A2: v1.0 · 로마 배경 13부작 옴니버스(156화) · 부활 7인 = Cesare·Machiavelli·Garibaldi·Dante·Gramsci·Galileo·Montessori
B4: 기본 설정
B5: 부 수 | C5: 13 | D5: 1 사무소(Testaccio, 개소 1개월 후, 6사건×2화) → 2~5 각자의 과거 → 6 만남 → 7 전면전 → 8 창당 → 9 시의회·주의회 → 10 총선·총리 선출 → 11 국정 I(EU 협상·Cesare 사망) → 12 국정 II(장례·유고 메모 승계) → 13 귀환(원형 구조)
B6: 부당 화 수 | C6: 12 | D6: 각 부 12화
B7: 총 화 수 | C7: =C5*C6 | D7: 부 수 × 부당 화 수 (자동 계산)
B8: 등장인물 수 | C8: =COUNTA(캐릭터!$D$5:$D$19) | D8: 캐릭터 시트의 약칭 개수
B9: 남성 인물 수 | C9: =COUNTIF(캐릭터!$G$5:$G$19,"남") | D9: 부활 7인 중 6인이 남성인 역사 인물이라 남 10 : 여 5. 여성 화자(Giulia·Chiara·Rosa·Sofia·Montessori)의 대사 비중을 높게 유지해 음색 균형을 맞춘다.
B10: 여성 인물 수 | C10: =COUNTIF(캐릭터!$G$5:$G$19,"여")
B11: 1부→11부 경과 연수 (가정) | C11: 6 | D11: 가정값: Cesare가 1부 55세(암살 당시 나이로 부활) → 11부 약 61세가 되도록 잡음. 확정 시 이 셀만 수정하면 캐릭터 시트의 나이가 자동 갱신. (캐릭터 시트 '나이(11부)' 열)
B12: 배경·언어 | C12: 로마 (테스타초) | D12: 표준 이탈리아어: 친한 사이 tu, 공식 석상은 Lei/공식 호칭. Rosa·Paolo의 로마 사투리(romanesco)는 양념 수준으로.
B13: 형식 | C13: 전 화 100% 대화문, 화당 120턴 | D13: ="지문(narrazione) 없음. 화당 "&턴_설계!$B$5&"턴 × "&C7&"화 = "&TEXT(C7*턴_설계!$B$5,"#,##0")&"턴. 상세는 '대화문규칙'·'턴_설계' 시트."
B15: 그룹별 인원
B16: 주력 4인 | C16: =COUNTIF(캐릭터!$B$5:$B$19,B16) | D16: Marco(변호사)·Giulia(의사)·Alessandro(회계사)·Chiara(컨설턴트)
B17: 부활 7인 | C17: =COUNTIF(캐릭터!$B$5:$B$19,B17) | D17: Cesare(전 독재관)·Machiavelli(정치사상가)·Garibaldi(통일운동가)·Dante(시인)·Gramsci(사상가)·Galileo(과학자)·Montessori(교육학자) ※ 각자의 시대에 죽었다가 이유 없이 현재 로마에 되살아나 사무소에 합류
B18: 서민·청년 | C18: =COUNTIF(캐릭터!$B$5:$B$19,B18) | D18: Rosa(트라토리아 사장)·Paolo(노조위원장)·Sofia M.(인턴)
B19: 금융 | C19: =COUNTIF(캐릭터!$B$5:$B$19,B19) | D19: Francesco(전 은행 지점장)
B22: 시트 안내 (클릭하면 이동)
B23: 캐릭터 | C23: 기준표 | D23: 15인의 이름·나이·결핍·말투·시그니처·낭독 포인트·대화문 장치·직책·현안 담당
B24: 등장비중 | C24: 기준표 | D24: 13부 배분표, 합계·비중·등급(수식), 조연 단독 중심 화 목표
B25: 턴_설계 | C25: 기준표 | D25: 화당 120턴 설계: 13부 × 화자 점유율(턴 기준), 평균 단어/턴, 화당 단어·낭독 시간(수식), 화 유형별 턴 구성, 집필 규칙
B26: 13부_구성 | C26: 구조 | D26: 13부 한눈에 보기: 배경·핵심 내용·난이도(CEFR)·반영 제도
B27: 아크_구성계획 | C27: 구성 계획 | D27: 1~13부 아크별 구성 계획: 서사 기능·로그라인·비트·인물 아크·복선·현안·언어 설계
B28: 화별목차_전체 | C28: 목차 | D28: 1~13부 156화의 서사 기능·제목(이탈리아어)·핵심 사건·반영 제도·인물·현안 (필터 가능)
B29: 복선_회수 | C29: 구성 계획 | D29: 복선 설치→회수 28건과 간격(부)을 수식으로 계산
B30: 현안_배치 | C30: 현안 | D30: 이탈리아 현안 18개를 어느 화에 어떻게 녹일지 배치, 균형 유의, 현실 기준값(ISTAT 등)
B31: 현안_분포 | C31: 현안 | D31: 부 × 현안 분포표: 전용 화(●)와 곁가지(○)를 수식으로 집계
B32: 정치제도 | C32: 현실 제도 | D32: 정당·선거·양원·정부 구성·주(Regione)·사법·EU 제도 기준표 (확인 상태 표시)
B33: 정치경로_의석 | C33: 현실 제도 | D33: 창당→총리 경로와 가상 의석·표결 시뮬레이션(수식): 하원·상원 신임 투표, 불신임안
B34: 호칭규칙 | C34: 규칙 | D34: tu / Lei / voi / Loro, 양원·시의회 공식 호칭, 대통령
... B39: 변경이력_미결 | C39: 관리 | D39: 변경 이력(스페인판→이탈리아판 대응표 포함)과 확정이 필요한 미결 사항
B42: 범례
B43: 파란 글씨 | C43: 직접 입력한 값 (수정 가능)
B44: 노란 배경 | C44: 가정 · 확정이 필요한 값
B45: 검정 글씨 | C45: 수식으로 계산되는 값 (직접 수정하지 말 것)
B47: 주의: 성별·나이·기관명은 기획용 가상 설정입니다. 법령 번호·조항은 교재에 넣기 전에 Normattiva(normattiva.it)·Gazzetta Ufficiale의 현행 통합본으로 확인하세요.

Sheet 캐릭터
A1: 캐릭터 바이블 — 15인 (Roma 이탈리아어 낭독 교재 — 캐릭터 바이블 (부활자 특별편))
A2: v1.0 · 로마 배경 13부작 옴니버스(156화) · 부활 7인 = Cesare·Machiavelli·Garibaldi·Dante·Gramsci·Galileo·Montessori
A4: No | B4: 그룹 | C4: 이름 | D4: 약칭 | E4: 나이 (1부) | F4: 나이 (11부) | G4: 성별 | H4: 직업·신분 | I4: 전 소속 (가상) | J4: 결핍 (Herida) | K4: 말투 | L4: 시그니처 표현 | M4: 낭독 포인트 | N4: 대화문 장치 (지문 대체) | O4: 정치 직책 (8~12부, 제안) | P4: 1부 등장 방식 | Q4: 등장 화 수 | R4: 등급 | S4: 현안 담당 (ID)
A5: 1 | B5: 주력 4인 | C5: Marco Ferrari | D5: Marco | E5: 39 | F5: =E5+개요!$C$11 | G5: 남 | H5: 변호사 (기업·규제 전문) | I5: Ferrari & Colombo Studio Legale (전 파트너 후보) | J5: 승소율은 높지만, 강제퇴거 소송에서 이긴 사건 하나가 계속 마음에 걸린다. | K5: 문장이 완결되고 격식체. 초반엔 차갑게 조항을 인용, 후반엔 연설가로 성장. | L5: Andiamo con ordine.\nCon tutto il rispetto, la legge non dice questo.\n(후반) Non vi chiedo di credermi. Vi chiedo di leggere il testo. | M5: 또박또박, 중저음. | N5: 법조문을 소리 내어 읽어 상황을 설명한다. | O5: 당 대표(8부) → 하원의원·총리 후보(10부) → 총리 | P5: 본격 | Q5: =INDEX(등장비중!$O$5:$O$19,MATCH($D5,등장비중!$A$5:$A$19,0)) | R5: =INDEX(등장비중!$Q$5:$Q$19,MATCH($D5,등장비중!$A$5:$A$19,0)) | S5: P1·P3·E1·N4
A6: 2 | B6: 주력 4인 | C6: Giulia Romano | D6: Giulia | E6: 41 | F6: =E6+개요!$C$11 | G6: 여 | H6: 응급의학과 전문의 | I6: Ospedale San Camillo (가상) | J6: 살리지 못한 환자의 이름을 전부 외우고 있다. | K6: 짧고 명령형, 블랙유머. | L6: Questa non è una statistica, è una persona.\nPrima, respira.\nHo visto di peggio in un martedì qualsiasi. | M6: 빠른 템포, 짧은 호흡. | N6: 명령형으로 행동을 말하며 진행한다. | O6: 주의회 의원(9부) → 보건부 장관 | P6: 본격 | Q6: =INDEX(등장비중!$O$5:$O$19,MATCH($D6,등장비중!$A$5:$A$19,0)) | R6: =INDEX(등장비중!$Q$5:$Q$19,MATCH($D6,등장비중!$A$5:$A$19,0)) | S6: S3·S4·S2·N8
A7: 3 | B7: 주력 4인 | C7: Alessandro Conti | D7: Alessandro | E7: 37 | F7: =E7+개요!$C$11 | G7: 남 | H7: 공인회계사 (감사) | I7: Conti Revisori (전 시니어 파트너) | J7: 부정을 발견하고도 서명했던 기억. | K7: 건조하고 정확, 비꼬는 유머. | L7: Fammi vedere le carte.\nQuesto non torna.\nMostrami i numeri e ti dirò chi sei. | M7: 일정한 속도, 결론에서 톤을 낮춘다. | N7: 숫자를 소리 내어 읽는다. | O7: 시의원(9부) → 경제재정부 장관 | P7: 본격 | Q7: =INDEX(등장비중!$O$5:$O$19,MATCH($D7,등장비중!$A$5:$A$19,0)) | R7: =INDEX(등장비중!$Q$5:$Q$19,MATCH($D7,등장비중!$A$5:$A$19,0)) | S7: E3·E1·N2
A8: 4 | B8: 주력 4인 | C8: Chiara Bianchi | D8: Chiara | E8: 36 | F8: =E8+개요!$C$11 | G8: 여 | H8: 전략 컨설턴트 | I8: Zenit Consulting (전 소속) | J8: 구조조정 표 한 칸이 수백 명의 해고였음을 뒤늦게 안다. | K8: 영어식 경영 용어가 섞인 빠른 말투, 후반 쉬운 말로 성장. | L8: Mettiamolo in una matrice.\n(후반) Ok, senza slide: cosa ti serve davvero? | M8: 초반 숨 가쁜 톤, 후반 솔직한 톤. | N8: 프레젠테이션식 브리핑. | O8: 캠프 참모(8~10부) → 총리실 실장 | P8: 본격 | Q8: =INDEX(등장비중!$O$5:$O$19,MATCH($D8,등장비중!$A$5:$A$19,0)) | R8: =INDEX(등장비중!$Q$5:$Q$19,MATCH($D8,등장비중!$A$5:$A$19,0)) | S8: P1·E2·S1
A9: 5 | B9: 부활 7인 | C9: Gaio Giulio Cesare | D9: Cesare | E9: 55 | F9: =E9+개요!$C$11 | G9: 남 | H9: 부활한 정치가·장군 (기원전 100–44) | I9: 로마 공화정 종신독재관 | J9: 자신이 암살당하던 순간의 배신을 잊지 못하며, 누구든 너무 가까이 다가오면 본능적으로 경계한다. | K9: 위엄 있고 명령조, 3인칭으로 자기 자신을 지칭하는 버릇이 있다 (『갈리아 전기』식 문체). | L9: Cesare è venuto, ha visto, ha vinto — questa riunione durerà di meno, spero.\n(현대 용어 오해) Un „server“? Cesare capisce: un servo che non dorme mai. Molto romano.\n„Firewall“? Ai miei tempi si chiamava assedio. | M9: 느리고 육중한 리듬, 문장 끝에서 상대를 지그시 본다. | N9: '내가 갈리아에 있을 때는…' 식 회상으로 현재를 평가한다. | O9: 외교·안보 자문 (11부 12화, 브뤼셀 협상 직후 두 번째 죽음) | P9: 준본격 (겨울 복선) | Q9: =INDEX(등장비중!$O$5:$O$19,MATCH($D9,등장비중!$A$5:$A$19,0)) | R9: =INDEX(등장비중!$Q$5:$Q$19,MATCH($D9,등장비중!$A$5:$A$19,0)) | S9: N3·E3
A10: 6 | B10: 부활 7인 | C10: Niccolò Machiavelli | D10: Machiavelli | E10: 58 | F10: =E10+개요!$C$11 | G10: 남 | H10: 부활한 정치사상가 (1469–1527) | I10: 피렌체 공화국 서기관, 『군주론』 저자 | J10: 자신의 이름이 '마키아벨리즘'이라는 욕설로 남은 것에 대한 억울함을 냉소로 눌러 담는다. | K10: 건조하고 분석적, 이상과 현실을 항상 구분해서 말한다. | L10: (고전 인용) È meglio essere temuti che amati, se non si può essere entrambe le cose.\n(현대 용어 재해석) „Personal branding“? Un nome elegante per: il Principe che si vende da solo. | M10: 낮고 냉정한 톤. | N10: 상황을 '이상 vs 현실' 두 갈래로 나눠 분석해 설명한다. | O10: 정치 전략 자문 | P10: 카메오 | Q10: =INDEX(등장비중!$O$5:$O$19,MATCH($D10,등장비중!$A$5:$A$19,0)) | R10: =INDEX(등장비중!$Q$5:$Q$19,MATCH($D10,등장비중!$A$5:$A$19,0)) | S10: P1·P2
A11: 7 | B11: 부활 7인 | C11: Giuseppe Garibaldi | D11: Garibaldi | E11: 74 | F11: =E11+개요!$C$11 | G11: 남 | H11: 부활한 통일운동가 (1807–1882) | I11: 이탈리아 통일전쟁 의용군 지휘관 | J11: 통일시킨 나라가 다시 갈라지는 걸 보는 게 가장 두렵다 — 지역 갈등 이야기만 나오면 정색한다. | K11: 열정적이고 직설, 행동가 화법. 회의보다 거리로 나가고 싶어 한다. | L11: Obbedisco — ma solo quando ha senso.\n(현대 용어 오해) „Trending“? Vuol dire che il popolo si muove. Verso dove, andiamo a vedere. | M11: 빠르고 격정적. | N11: 집회 연설조로 대중의 분위기를 전달한다. | O11: 정당 창당 전략가(8부) → 지역통합 담당 장관 | P11: 카메오 | Q11: =INDEX(등장비중!$O$5:$O$19,MATCH($D11,등장비중!$A$5:$A$19,0)) | R11: =INDEX(등장비중!$Q$5:$Q$19,MATCH($D11,등장비중!$A$5:$A$19,0)) | S11: P2·S3·N1·N5
A12: 8 | B12: 부활 7인 | C12: Dante Alighieri | D12: Dante | E12: 56 | F12: =E12+개요!$C$11 | G12: 남 | H12: 부활한 시인 (1265–1321) | I12: 피렌체 추방자, 『신곡』 저자 | J12: 평생 고향에서 추방된 채 죽었다 — 지금도 '고향'이라는 말에 예민하게 반응한다. | K12: 장엄하고 상징적인 문어체, 인물마다 지옥·연옥·천국의 어느 층에 어울리는지 비유한다(개그). | L12: (현대 용어 오해) Un „influencer“? Suona come un nuovo venditore di indulgenze — li ho già messi in un girone apposito.\n„Podcast“? Una predica senza chiesa. | M12: 느리고 낭송하듯. | N12: 상대의 행동을 단테식 지옥/연옥 비유로 풍자해 설명한다. | O12: 메시지·공보 자문 | P12: 카메오 | Q12: =INDEX(등장비중!$O$5:$O$19,MATCH($D12,등장비중!$A$5:$A$19,0)) | R12: =INDEX(등장비중!$Q$5:$Q$19,MATCH($D12,등장비중!$A$5:$A$19,0)) | S12: N3·N6·N5
A13: 9 | B13: 부활 7인 | C13: Antonio Gramsci | D13: Gramsci | E13: 46 | F13: =E13+개요!$C$11 | G13: 남 | H13: 부활한 사상가 (1891–1937) | I13: 이탈리아 공산당 창립자, 파시스트 정권 옥사 | J13: 감옥에서 쓴 노트가 자신이 세상을 못 보고 죽은 채 유일하게 남긴 목소리였다는 걸 안다 — 말 한마디의 무게에 집착한다. | K13: 낮고 신중, 권력의 문화적 지배(헤게모니) 개념으로 모든 걸 분석한다. | L13: (현대 용어 재해석) „Storytelling aziendale“? Un nome nuovo per l'egemonia culturale — io l'avevo già capito in cella.\nLa crisi consiste appunto nel fatto che il vecchio muore e il nuovo non può nascere. | M13: 느리고 낮은 톤, 침묵이 길다. | N13: 현상을 '누가 문화적 헤게모니를 쥐고 있는가'로 재해석해 설명한다. | O13: 출처·기록 담당(카드) → 사회·문화 정책 자문, 스파이웨어 조사 자문(12부) | P13: 카메오 (고서점·아카이브 단골) | Q13: =INDEX(등장비중!$O$5:$O$19,MATCH($D13,등장비중!$A$5:$A$19,0)) | R13: =INDEX(등장비중!$Q$5:$Q$19,MATCH($D13,등장비중!$A$5:$A$19,0)) | S13: P3·N7·N2
A14: 10 | B14: 부활 7인 | C14: Galileo Galilei | D14: Galileo | E14: 77 | F14: =E14+개요!$C$11 | G14: 남 | H14: 부활한 과학자 (1564–1642) | I14: 종교재판에 회부됐던 천문학자 | J14: 한때 자기 눈으로 본 진실을 부정해야 목숨을 부지할 수 있었던 기억 — 지금도 침묵을 강요받으면 몸이 굳는다. | K14: 차분하고 실증적, '그래도 그것은 돈다(Eppur si muove)'는 태도로 조용히 밀어붙인다. | L14: (현대 용어 오해) „Wi-Fi“? Onde invisibili — finalmente qualcuno mi crede senza processo.\nEppur si muove — anche questa riunione, se insistiamo. | M14: 느리고 담담한 톤. | N14: 관찰과 증거로 상황을 설명한다 — 의견이 아니라 데이터로 말한다. | O14: 사무소 공론화·검증 담당 → 정부 대변인(11부~) | P14: 카메오 | Q14: =INDEX(등장비중!$O$5:$O$19,MATCH($D14,등장비중!$A$5:$A$19,0)) | R14: =INDEX(등장비중!$Q$5:$Q$19,MATCH($D14,등장비중!$A$5:$A$19,0)) | S14: P3·N7·N4
A15: 11 | B15: 서민·청년 | C15: Rosa Esposito | D15: Rosa | E15: 63 | F15: =E15+개요!$C$11 | G15: 여 | H15: 트라토리아 사장 (Trattoria da Rosa, 30년 운영) | I15: Trattoria da Rosa, Testaccio → 사무소 1층으로 이전 | J15: 임대료 폭등으로 가게를 잃었다. | K15: 로마 토박이 구어체, 누구에게나 tu, 'amore/tesoro'. | L15: Sedetevi, che vi porto qualcosa.\nA stomaco vuoto non si pensa bene.\nOffre la casa. | M15: 따뜻하고 넉넉한 톤. | N15: 시간·장소·식사를 말로 알린다. | O15: 소상공인 정책 자문 (비공식) | P15: 본격 | Q15: =INDEX(등장비중!$O$5:$O$19,MATCH($D15,등장비중!$A$5:$A$19,0)) | R15: =INDEX(등장비중!$Q$5:$Q$19,MATCH($D15,등장비중!$A$5:$A$19,0)) | S15: E1·S2·E2
A16: 12 | B16: 서민·청년 | C16: Paolo Greco | D16: Paolo | E16: 55 | F16: =E16+개요!$C$11 | G16: 남 | H16: 전 대중교통 노조위원장 | I16: 로마 대중교통 노조 (파업 책임으로 해고) | J16: 파업 책임으로 해고되어 블랙리스트에 올랐지만 후회하지 않는다. | K16: 거칠고 직설적, 구호형 문장. | L16: Qui non si arrende nessuno!\nQuesto si risolve in strada.\nNon mi rompere. | M16: 큰 볼륨, 강한 억양. | N16: 구호와 함성으로 현장 분위기를 전달한다. | O16: 사회적 대화 자문 | P16: 카메오 | Q16: =INDEX(등장비중!$O$5:$O$19,MATCH($D16,등장비중!$A$5:$A$19,0)) | R16: =INDEX(등장비중!$Q$5:$Q$19,MATCH($D16,등장비중!$A$5:$A$19,0)) | S16: S1·N6·P1
... A19: 15 | B19: 부활 7인 | C19: Maria Montessori | D19: Montessori | E19: 81 | F19: =E19+개요!$C$11 | G19: 여 | H19: 부활한 교육학자·의사 (1870–1952) | I19: 몬테소리 교육법 창시자, 이탈리아 최초 여성 의사 중 한 명 | J19: 자신의 교육법이 세계로 퍼졌지만 정작 자국 파시스트 정권에는 탄압받았던 기억이 있다. | K19: 차분하고 관찰적, 아이 대하듯 사람을 존중하며 말하지만 할 말은 다 한다. | L19: Aiutami a fare da solo.\n(현대 용어 오해) „App“? Uno strumento — ma lo strumento non deve mai sostituire la mano che impara. | M19: 부드럽고 낮은 톤. | N19: 상대의 말을 관찰하듯 되짚어 정리해 준다. | O19: 사무소 상담 담당 → 교육·청년 정신건강 정책 자문 | P19: 카메오 | Q19: =INDEX(등장비중!$O$5:$O$19,MATCH($D19,등장비중!$A$5:$A$19,0)) | R19: =INDEX(등장비중!$Q$5:$Q$19,MATCH($D19,등장비중!$A$5:$A$19,0)) | S19: N8·N4·S2

Sheet 등장비중
A1: 인물별 등장 비중 (부별 등장 화 수)
A2: 등장 화 = 대사가 있는 화 수 (기획용 초안). 파란 숫자는 직접 입력값이며 수정하면 합계·비중·등급이 자동 갱신됩니다.
A4: 인물 (약칭) | B4: 1부 사무소 | C4: 2부 Marco | D4: 3부 Giulia | E4: 4부 Alessandro | F4: 5부 Chiara | G4: 6부 만남 | H4: 7부 전면전 | I4: 8부 창당 | J4: 9부 시·주 의회 | K4: 10부 총선·총리 | L4: 11부 국정 I | M4: 12부 국정 II | N4: 13부 귀환 | O4: 합계 | P4: 비중 | Q4: 등급 | R4: 검증 (≤부당 화 수) | S4: 단독 중심 화 목표 (조연)
A5: Marco | B5: 7 | C5: 12 | D5: 3 | E5: 3 | F5: 3 | G5: 12 | H5: 11 | I5: 12 | J5: 11 | K5: 11 | L5: 10 | M5: 3 | N5: 10 | O5: =SUM(B5:N5) | P5: =O5/개요!$C$7 | Q5: =IF(P5>=$B$23,"주연",IF(P5>=$B$24,"준주연",IF(P5>=$B$25,"핵심 조연","조연"))) | R5: =IF(MAX(B5:N5)<=개요!$C$6,"OK","확인") | S5: —
A6: Giulia | B6: 6 | C6: 3 | D6: 12 | E6: 3 | F6: 3 | G6: 12 | H6: 10 | I6: 10 | J6: 8 | K6: 10 | L6: 10 | M6: 2 | N6: 9 | O6: =SUM(B6:N6) | P6: =O6/개요!$C$7 | Q6: =IF(P6>=$B$23,"주연",IF(P6>=$B$24,"준주연",IF(P6>=$B$25,"핵심 조연","조연"))) | R6: =IF(MAX(B6:N6)<=개요!$C$6,"OK","확인") | S6: —
A7: Alessandro | B7: 7 | C7: 3 | D7: 3 | E7: 12 | F7: 3 | G7: 12 | H7: 11 | I7: 10 | J7: 10 | K7: 11 | L7: 10 | M7: 8 | N7: 9 | O7: =SUM(B7:N7) | P7: =O7/개요!$C$7 | Q7: =IF(P7>=$B$23,"주연",IF(P7>=$B$24,"준주연",IF(P7>=$B$25,"핵심 조연","조연"))) | R7: =IF(MAX(B7:N7)<=개요!$C$6,"OK","확인") | S7: —
A8: Chiara | B8: 6 | C8: 3 | D8: 3 | E8: 3 | F8: 12 | G8: 12 | H8: 10 | I8: 11 | J8: 10 | K8: 10 | L8: 9 | M8: 3 | N8: 9 | O8: =SUM(B8:N8) | P8: =O8/개요!$C$7 | Q8: =IF(P8>=$B$23,"주연",IF(P8>=$B$24,"준주연",IF(P8>=$B$25,"핵심 조연","조연"))) | R8: =IF(MAX(B8:N8)<=개요!$C$6,"OK","확인") | S8: —
A9: Cesare | B9: 4 | C9: 2 | D9: 2 | E9: 2 | F9: 2 | G9: 7 | H9: 9 | I9: 7 | J9: 9 | K9: 9 | L9: 9 | M9: 0 | N9: 3 | O9: =SUM(B9:N9) | P9: =O9/개요!$C$7 | Q9: =IF(P9>=$B$23,"주연",IF(P9>=$B$24,"준주연",IF(P9>=$B$25,"핵심 조연","조연"))) | R9: =IF(MAX(B9:N9)<=개요!$C$6,"OK","확인") | S9: —
A10: Machiavelli | B10: 3 | C10: 1 | D10: 1 | E10: 1 | F10: 1 | G10: 6 | H10: 8 | I10: 9 | J10: 8 | K10: 8 | L10: 7 | M10: 4 | N10: 7 | O10: =SUM(B10:N10) | P10: =O10/개요!$C$7 | Q10: =IF(P10>=$B$23,"주연",IF(P10>=$B$24,"준주연",IF(P10>=$B$25,"핵심 조연","조연"))) | R10: =IF(MAX(B10:N10)<=개요!$C$6,"OK","확인") | S10: —
A11: Garibaldi | B11: 2 | C11: 1 | D11: 1 | E11: 3 | F11: 1 | G11: 5 | H11: 10 | I11: 7 | J11: 8 | K11: 8 | L11: 7 | M11: 3 | N11: 7 | O11: =SUM(B11:N11) | P11: =O11/개요!$C$7 | Q11: =IF(P11>=$B$23,"주연",IF(P11>=$B$24,"준주연",IF(P11>=$B$25,"핵심 조연","조연"))) | R11: =IF(MAX(B11:N11)<=개요!$C$6,"OK","확인") | S11: —
A12: Dante | B12: 1 | C12: 1 | D12: 2 | E12: 1 | F12: 2 | G12: 4 | H12: 7 | I12: 8 | J12: 6 | K12: 7 | L12: 6 | M12: 2 | N12: 7 | O12: =SUM(B12:N12) | P12: =O12/개요!$C$7 | Q12: =IF(P12>=$B$23,"주연",IF(P12>=$B$24,"준주연",IF(P12>=$B$25,"핵심 조연","조연"))) | R12: =IF(MAX(B12:N12)<=개요!$C$6,"OK","확인") | S12: —
A13: Gramsci | B13: 1 | C13: 1 | D13: 1 | E13: 1 | F13: 1 | G13: 4 | H13: 6 | I13: 9 | J13: 7 | K13: 9 | L13: 7 | M13: 4 | N13: 7 | O13: =SUM(B13:N13) | P13: =O13/개요!$C$7 | Q13: =IF(P13>=$B$23,"주연",IF(P13>=$B$24,"준주연",IF(P13>=$B$25,"핵심 조연","조연"))) | R13: =IF(MAX(B13:N13)<=개요!$C$6,"OK","확인") | S13: —
A14: Galileo | B14: 2 | C14: 1 | D14: 1 | E14: 2 | F14: 1 | G14: 4 | H14: 6 | I14: 6 | J14: 5 | K14: 6 | L14: 6 | M14: 1 | N14: 5 | O14: =SUM(B14:N14) | P14: =O14/개요!$C$7 | Q14: =IF(P14>=$B$23,"주연",IF(P14>=$B$24,"준주연",IF(P14>=$B$25,"핵심 조연","조연"))) | R14: =IF(MAX(B14:N14)<=개요!$C$6,"OK","확인") | S14: —
A15: Rosa | B15: 12 | C15: 2 | D15: 2 | E15: 2 | F15: 2 | G15: 5 | H15: 8 | I15: 6 | J15: 4 | K15: 5 | L15: 8 | M15: 3 | N15: 10 | O15: =SUM(B15:N15) | P15: =O15/개요!$C$7 | Q15: =IF(P15>=$B$23,"주연",IF(P15>=$B$24,"준주연",IF(P15>=$B$25,"핵심 조연","조연"))) | R15: =IF(MAX(B15:N15)<=개요!$C$6,"OK","확인") | S15: —
A16: Paolo | B16: 2 | C16: 1 | D16: 2 | E16: 1 | F16: 3 | G16: 5 | H16: 9 | I16: 8 | J16: 6 | K16: 6 | L16: 7 | M16: 2 | N16: 6 | O16: =SUM(B16:N16) | P16: =O16/개요!$C$7 | Q16: =IF(P16>=$B$23,"주연",IF(P16>=$B$24,"준주연",IF(P16>=$B$25,"핵심 조연","조연"))) | R16: =IF(MAX(B16:N16)<=개요!$C$6,"OK","확인") | S16: —
... A19: Montessori | B19: 1 | C19: 1 | D19: 1 | E19: 3 | F19: 1 | G19: 5 | H19: 8 | I19: 5 | J19: 6 | K19: 6 | L19: 9 | M19: 1 | N19: 6 | O19: =SUM(B19:N19) | P19: =O19/개요!$C$7 | Q19: =IF(P19>=$B$23,"주연",IF(P19>=$B$24,"준주연",IF(P19>=$B$25,"핵심 조연","조연"))) | R19: =IF(MAX(B19:N19)<=개요!$C$6,"OK","확인") | S19: —
A20: 부별 연인원 (합계) | B20: =SUM(B5:B19) | C20: =SUM(C5:C19) | D20: =SUM(D5:D19) | E20: =SUM(E5:E19) | F20: =SUM(F5:F19) | G20: =SUM(G5:G19) | H20: =SUM(H5:H19) | I20: =SUM(I5:I19) | ... O20: =SUM(O5:O19) | S20: =SUM(S5:S19)
A23: 주연 | B23: 0.69 | C23: ="← 기준값은 제안값입니다. 현재 구분: 주연 "&COUNTIF($Q$5:$Q$19,"주연")&" / 준주연 "&COUNTIF($Q$5:$Q$19,"준주연")&" / 핵심 조연 "&COUNTIF($Q$5:$Q$19,"핵심 조연")&" / 조연 "&COUNTIF($Q$5:$Q$19,"조연")&" (자동 계산)"
A24: 준주연 | B24: 0.6
A25: 핵심 조연 | B25: 0.4
A26: 조연 | B26: 그 미만
A28: 배분 원칙
A29: 1. 1부는 개소 1개월 후 시점: Sofia·Rosa가 전 화에, 주력 4인은 사건별로 교대 등장(전원 겹치지 않음). Cesare 4화, Machiavelli 3화로 자주 얼굴을 비추고 '이번 겨울이 마지막' 복선을 1화부터 깐다. 나머지는 사건마다 다른 조합으로 카메오.
A30: 2. 2~5부: 각 주인공이 자기 부 12화 전부에 나오고, 다른 주력 3인은 3화씩 스쳐 지나가며 6부 만남을 예고. Sofia는 4화씩 '사무소에서 이야기를 듣는 프레임'으로 등장해 회상을 잇는다.
A31: 3. 부활자·조연은 과거와 겹치는 곳에만 배치: Paolo-5부(Chiara의 구조조정 현장), Francesco·Galileo-4부(Alessandro의 감사 사건), Montessori-3부·5부(되받기·번아웃 상담), Garibaldi-4부(지역 회계 회상 카메오).
A32: 4. 부활자·조연 본격 비중은 7~10부에서 최고치: 7부 Galileo·Paolo·Garibaldi(공론화·현장 조직), 8부 Dante·Machiavelli·Gramsci(선언문·전략·출처), 10부 Dante·Galileo·Gramsci(취임 연설·대변인·정보 감독).
A33: 5. 11부(국정 I)는 Cesare가 9~12화에서 브뤼셀 직접 협상을 이끌며 최고치(9화)를 찍고 12화에서 사망한다. Francesco는 앞선 주거·금융 국내 현안 화에서 정점.
A34: 6. 12부(국정 II)는 Cesare 사후(0화): 1화 장례식에 Garibaldi·Gramsci·Machiavelli가 몰리고, Alessandro·Dante가 유작 메모를 이어받는 2·3화에서 비중이 오른다.
A35: 7. 13부(귀환)는 원형 구조: Sofia 12화 전부, Rosa 10화. Cesare는 유언장·회상으로 3화, 주력 4인은 사무소의 손님으로 9~10화 등장.
A36: 8. Cesare는 11부 12화(브뤼셀 승리 직후)에서 두 번째 죽음을 맞는다. 12부 1화 장례식, 2·3화 유작 메모 승계, 13부 2화 유언장까지 이어진다.
A37: 9. 등장 화 수와 대사량은 다르다: Sofia는 약 67%지만 문장이 짧아 대사량은 Marco의 절반 이하가 되게 하고, Cesare·Dante는 화당 대사가 길어도 된다.
A38: 10. 조연 11인은 화 전체의 중심이 되는 에피소드를 각자 2개 이상 배정(S열 목표). 자기 이야기가 한 번도 없으면 얇은 인물이 된다.
A39: 11. Montessori·Galileo가 가장 얇다: 3·5부 상담 장면을 늘리거나, 12부 Cesare 애도 상담(Montessori)·스파이웨어 검증(Galileo)을 맡겨 서사를 넓히는 안을 검토.

Sheet 턴_설계
A1: 대화량 설계: 화당 120턴
A2: 한 화 = 대화 120턴, 전체 156화 = 18,720턴. 점유율·평균 단어/턴·배율·낭독 속도는 가정값(파란 숫자)이며 수정하면 아래 표가 자동 갱신됩니다.
A4: 1. 기본 설정
A5: 화당 대화 턴 | B5: 120
A6: 낭독 속도 (단어/분, 가정) | B6: 130
A7: 총 화 수 | B7: =개요!$C$7
A8: 총 대화 턴 | B8: =B5*B7
A9: 턴 정의 | B9: 화자 표기 한 줄 = 1턴 (화자가 바뀌면 새 턴). 연설·조항·기사 낭독처럼 긴 발화도 1턴으로 센다.
A11: 2. 부별 화자 점유율 (턴 기준, 각 부의 합 = 100%)
A12: 인물 | B12: 평균 단어/턴 | C12: 1부 | D12: 2부 | E12: 3부 | F12: 4부 | G12: 5부 | H12: 6부 | I12: 7부 | J12: 8부 | K12: 9부 | L12: 10부 | M12: 11부 | N12: 12부 | O12: 13부
A13: Marco | B13: 13 | C13: 0.13 | D13: 0.48 | E13: 0.03 | F13: 0.02 | G13: 0.02 | H13: 0.13 | I13: 0.14 | J13: 0.14 | K13: 0.08 | L13: 0.17 | M13: 0.14 | N13: 0.15 | O13: 0.07
A14: Giulia | B14: 8 | C14: 0.12 | D14: 0.03 | E14: 0.46 | F14: 0.04 | G14: 0.03 | H14: 0.12 | I14: 0.07 | J14: 0.07 | K14: 0.11 | L14: 0.06 | M14: 0.09 | N14: 0.09 | O14: 0.06
A15: Alessandro | B15: 11 | C15: 0.12 | D15: 0.04 | E15: 0.04 | F15: 0.46 | G15: 0.04 | H15: 0.12 | I15: 0.1 | J15: 0.08 | K15: 0.14 | L15: 0.07 | M15: 0.1 | N15: 0.11 | O15: 0.07
A16: Chiara | B16: 12 | C16: 0.12 | D16: 0.05 | E16: 0.03 | F16: 0.03 | G16: 0.46 | H16: 0.12 | I16: 0.06 | J16: 0.08 | K16: 0.08 | L16: 0.1 | M16: 0.08 | N16: 0.08 | O16: 0.07
A17: Cesare | B17: 14 | C17: 0.08 | D17: 0.04 | E17: 0.04 | F17: 0.04 | G17: 0.04 | H17: 0.04 | I17: 0.06 | J17: 0.05 | K17: 0.04 | L17: 0.06 | M17: 0.04 | N17: 0 | O17: 0.02
A18: Machiavelli | B18: 11 | C18: 0.02 | D18: 0.01 | E18: 0.01 | F18: 0.01 | G18: 0.01 | H18: 0.03 | I18: 0.04 | J18: 0.06 | K18: 0.04 | L18: 0.06 | M18: 0.04 | N18: 0.05 | O18: 0.03
A19: Garibaldi | B19: 7 | C19: 0.02 | D19: 0.01 | E19: 0.01 | F19: 0.01 | G19: 0.01 | H19: 0.05 | I19: 0.06 | J19: 0.06 | K19: 0.04 | L19: 0.08 | M19: 0.07 | N19: 0.07 | O19: 0.06
A20: Dante | B20: 12 | C20: 0.02 | D20: 0.01 | E20: 0.01 | F20: 0.01 | G20: 0.01 | H20: 0.03 | I20: 0.03 | J20: 0.07 | K20: 0.05 | L20: 0.07 | M20: 0.05 | N20: 0.05 | O20: 0.05
A21: Gramsci | B21: 9 | C21: 0.02 | D21: 0.01 | E21: 0.01 | F21: 0.01 | G21: 0.01 | H21: 0.03 | I21: 0.06 | J21: 0.03 | K21: 0.04 | L21: 0.03 | M21: 0.05 | N21: 0.05 | O21: 0.08
A22: Galileo | B22: 10 | C22: 0.02 | D22: 0.01 | E22: 0.03 | F22: 0.04 | G22: 0.01 | H22: 0.03 | I22: 0.08 | J22: 0.06 | K22: 0.07 | L22: 0.05 | M22: 0.06 | N22: 0.06 | O22: 0.05
A23: Rosa | B23: 9 | C23: 0.12 | D23: 0.04 | E23: 0.03 | F23: 0.03 | G23: 0.03 | H23: 0.05 | I23: 0.04 | J23: 0.05 | K23: 0.03 | L23: 0.04 | M23: 0.04 | N23: 0.04 | O23: 0.13
A24: Paolo | B24: 10 | C24: 0.01 | D24: 0.02 | E24: 0.01 | F24: 0.01 | G24: 0.09 | H24: 0.05 | I24: 0.06 | J24: 0.08 | K24: 0.08 | L24: 0.06 | M24: 0.05 | N24: 0.05 | O24: 0.05
... A28: 엑스트라(가상) | B28: 10 | C28: 0.02 | D28: 0.14 | E28: 0.16 | F28: 0.12 | G28: 0.11 | H28: 0.04 | I28: 0.03 | J28: 0.02 | K28: 0.02 | L28: 0.02 | M28: 0.02 | N28: 0.03 | O28: 0.02
A29: 합계 | C29: =SUM(C13:C28) | D29: =SUM(D13:D28) | E29: =SUM(E13:E28) | F29: =SUM(F13:F28) | G29: =SUM(G13:G28) | H29: =SUM(H13:H28) | I29: =SUM(I13:I28) | J29: =SUM(J13:J28) | ... O29: =SUM(O13:O28)
A30: 검증 | C30: =IF(ROUND(C29,4)=1,"OK","확인") | D30: =IF(ROUND(D29,4)=1,"OK","확인") | E30: =IF(ROUND(E29,4)=1,"OK","확인") | F30: =IF(ROUND(F29,4)=1,"OK","확인") | G30: =IF(ROUND(G29,4)=1,"OK","확인") | H30: =IF(ROUND(H29,4)=1,"OK","확인") | I30: =IF(ROUND(I29,4)=1,"OK","확인") | J30: =IF(ROUND(J29,4)=1,"OK","확인") | ... O30: =IF(ROUND(O29,4)=1,"OK","확인")
A32: 3. 부별 턴·단어·낭독 시간 (수식)
A33: 부 | B33: 난이도 배율 | C33: 화당 턴 | D33: 부 총 턴 | E33: 평균 단어/턴 | F33: 화당 단어 | G33: 부 총 단어 | H33: 화당 낭독 (분) | I33: 부 총 낭독 (시간)
A34: 1부 | B34: 0.8 | C34: =$B$5 | D34: =C34*개요!$C$6 | E34: =SUMPRODUCT(C$13:C$28,$B$13:$B$28)*B34 | F34: =C34*E34 | G34: =F34*개요!$C$6 | H34: =F34/$B$6 | I34: =H34*개요!$C$6/60
A35: 2부 | B35: 1 | C35: =$B$5 | D35: =C35*개요!$C$6 | E35: =SUMPRODUCT(D$13:D$28,$B$13:$B$28)*B35 | F35: =C35*E35 | G35: =F35*개요!$C$6 | H35: =F35/$B$6 | I35: =H35*개요!$C$6/60
A36: 3부 | B36: 1 | C36: =$B$5 | D36: =C36*개요!$C$6 | E36: =SUMPRODUCT(E$13:E$28,$B$13:$B$28)*B36 | F36: =C36*E36 | G36: =F36*개요!$C$6 | H36: =F36/$B$6 | I36: =H36*개요!$C$6/60
A37: 4부 | B37: 1 | C37: =$B$5 | D37: =C37*개요!$C$6 | E37: =SUMPRODUCT(F$13:F$28,$B$13:$B$28)*B37 | F37: =C37*E37 | G37: =F37*개요!$C$6 | H37: =F37/$B$6 | I37: =H37*개요!$C$6/60
A38: 5부 | B38: 1 | C38: =$B$5 | D38: =C38*개요!$C$6 | E38: =SUMPRODUCT(G$13:G$28,$B$13:$B$28)*B38 | F38: =C38*E38 | G38: =F38*개요!$C$6 | H38: =F38/$B$6 | I38: =H38*개요!$C$6/60
A39: 6부 | B39: 1 | C39: =$B$5 | D39: =C39*개요!$C$6 | E39: =SUMPRODUCT(H$13:H$28,$B$13:$B$28)*B39 | F39: =C39*E39 | G39: =F39*개요!$C$6 | H39: =F39/$B$6 | I39: =H39*개요!$C$6/60
A40: 7부 | B40: 1 | C40: =$B$5 | D40: =C40*개요!$C$6 | E40: =SUMPRODUCT(I$13:I$28,$B$13:$B$28)*B40 | F40: =C40*E40 | G40: =F40*개요!$C$6 | H40: =F40/$B$6 | I40: =H40*개요!$C$6/60
A41: 8부 | B41: 1.1 | C41: =$B$5 | D41: =C41*개요!$C$6 | E41: =SUMPRODUCT(J$13:J$28,$B$13:$B$28)*B41 | F41: =C41*E41 | G41: =F41*개요!$C$6 | H41: =F41/$B$6 | I41: =H41*개요!$C$6/60
A42: 9부 | B42: 1.1 | C42: =$B$5 | D42: =C42*개요!$C$6 | E42: =SUMPRODUCT(K$13:K$28,$B$13:$B$28)*B42 | F42: =C42*E42 | G42: =F42*개요!$C$6 | H42: =F42/$B$6 | I42: =H42*개요!$C$6/60
A43: 10부 | B43: 1.2 | C43: =$B$5 | D43: =C43*개요!$C$6 | E43: =SUMPRODUCT(L$13:L$28,$B$13:$B$28)*B43 | F43: =C43*E43 | G43: =F43*개요!$C$6 | H43: =F43/$B$6 | I43: =H43*개요!$C$6/60
A44: 11부 | B44: 1.2 | C44: =$B$5 | D44: =C44*개요!$C$6 | E44: =SUMPRODUCT(M$13:M$28,$B$13:$B$28)*B44 | F44: =C44*E44 | G44: =F44*개요!$C$6 | H44: =F44/$B$6 | I44: =H44*개요!$C$6/60
A45: 12부 | B45: 1.2 | C45: =$B$5 | D45: =C45*개요!$C$6 | E45: =SUMPRODUCT(N$13:N$28,$B$13:$B$28)*B45 | F45: =C45*E45 | G45: =F45*개요!$C$6 | H45: =F45/$B$6 | I45: =H45*개요!$C$6/60
A46: 13부 | B46: 0.8 | C46: =$B$5 | D46: =C46*개요!$C$6 | E46: =SUMPRODUCT(O$13:O$28,$B$13:$B$28)*B46 | F46: =C46*E46 | G46: =F46*개요!$C$6 | H46: =F46/$B$6 | I46: =H46*개요!$C$6/60
A47: 전체 | D47: =SUM(D34:D46) | E47: =G47/D47 | F47: =AVERAGE(F34:F46) | G47: =SUM(G34:G46) | H47: =AVERAGE(H34:H46) | I47: =SUM(I34:I46)
A48: ※ 난이도 배율: 1·13부(B1~B2)는 짧게 0.8, 10~12부(C1~C2)는 길게 1.2. 화당 단어는 '평균 단어/턴 × 120턴', 낭독 시간은 낭독 속도로 환산한 추정치.
A50: 4. 화 유형별 턴 구성 (합계 = 화당 120턴)
A51: 화 유형 | B51: 도입 | C51: 장면 1 | D51: 장면 2 | E51: 절정·전환 | F51: 마무리 | G51: 합계 | H51: 검증 | I51: 적용
A52: 일반 화 | B52: 15 | C52: 35 | D52: 30 | E52: 25 | F52: 15 | G52: =SUM(B52:F52) | H52: =IF(G52=$B$5,"OK","확인") | I52: 발단·전개·위기 화 대부분
A53: 프레임 화 | B53: 15 | C53: 30 | D53: 30 | E53: 25 | F53: 20 | G53: =SUM(B53:F53) | H53: =IF(G53=$B$5,"OK","확인") | I53: 2~5부 1·5·9·12화: 금요일 프레임(도입·마무리)과 과거 장면
A54: 폭발·감정 정점 화 | B54: 15 | C54: 30 | D54: 25 | E54: 35 | F54: 15 | G54: =SUM(B54:F54) | H54: =IF(G54=$B$5,"OK","확인") | I54: 1부 6화, 9부 6화 등 인물의 감정이 터지는 화
A55: 표결·절차 화 | B55: 15 | C55: 30 | D55: 25 | E55: 35 | F55: 15 | G55: =SUM(B55:F55) | H55: =IF(G55=$B$5,"OK","확인") | I55: 10부 7·12화 신임 투표, 12부 7화 불신임안 (양원 의장의 결과 낭독 포함)
A56: 재난·추도 화 | B56: 10 | C56: 30 | D56: 30 | E56: 40 | F56: 10 | G56: =SUM(B56:F56) | H56: =IF(G56=$B$5,"OK","확인") | I56: 11부 12화(Cesare의 죽음), 12부 1화(장례식), 12부 8화(홍수)
A57: 원형·회고 화 | B57: 20 | C57: 25 | D57: 25 | E57: 25 | F57: 25 | G57: =SUM(B57:F57) | H57: =IF(G57=$B$5,"OK","확인") | I57: 13부 1·11·12화: 1부 대사를 되풀이하고 마무리를 길게
A59: 5. 집필 규칙
A60: 1. 1부는 한 턴 15단어 이내를 지킨다. 연설·조항·기사·카드처럼 긴 낭독은 예외로 두되 1턴으로 세고, 화당 최대 3개까지만 쓴다.
A61: 2. 지문이 없으므로 장소·시간·행동을 알리는 턴이 화당 5~10턴 필요하다 (Rosa의 시간 안내, Garibaldi의 보고, 양원 의장의 결과 낭독 등).
A62: 3. Sofia의 질문 → 쉬운 재설명 짝은 화당 3~6쌍(6~12턴)을 기본으로 한다. 어려운 용어를 도입할 때 반드시 사용한다.
A63: 4. 시그니처 표현은 화자당 1~2회. 120턴 안에서 같은 시그니처가 반복되지 않게 배분한다.
A64: 5. 화자 점유율은 턴 수 기준이다. Sofia처럼 턴은 많지만 짧게 말하는 인물은 평균 단어/턴을 낮게 잡았다. Machiavelli는 스페인판에 없던 인물이라 엑스트라 몫에서 점유율을 떼어 배정했다.
A65: 6. 표의 파란 숫자는 가정값이다. 1부 1~3화 대본을 쓴 뒤 실제 턴·단어 수를 재서 점유율과 평균 단어/턴을 교정한다.

Sheet 13부_구성
A1: 13부 구성 (13부 × 12화 = 156화)
A2: 정치 파트(8~12부)는 이탈리아의 현실 정치 제도에 맞춰 재설계했습니다. 화별 목차는 '화별목차_전체', 제도 근거는 '정치제도' 시트.
A4: 부 | B4: 제목 (IT) | C4: 한국어 | D4: 배경 | E4: 핵심 내용 | F4: 난이도 (CEFR) | G4: 반영 제도·전문 영역 | H4: 시점
A5: 1 | B5: Lo Studio di Testaccio | C5: 테스타초 사무소 | D5: Testaccio의 작은 사무실 (1층은 Rosa의 트라토리아), 개소 1개월 후 | E5: 이미 한 달째 좌충우돌 중인 팀이 이웃들의 사건 6개를 2화씩(도입→해결) 풀어 간다. 자기소개 대신 '이 사람들이 어쩌다 이렇게 됐지?' 하는 궁금증(In medias res)으로 시작. | F5: B1 | G5: 생활 법률·노동·의료·금융 기초 어휘, 반복되는 말다툼, Sofia 1차 폭발(6화) | H5: 현재(개소 후 1개월)
A6: 2 | B6: L'Avvocato | C6: 변호사 | D6: Prati(Piazza Cavour 법원가)의 대형 로펌 | E6: 승소율 100%의 이면: 갱신 거절로 비운 건물이 Marco의 결핍이 된다. | F6: B2~C1 | G6: 임대차(legge 431/1998), 소송, 퇴거 확인 절차(convalida di sfratto) | H6: 과거
A7: 3 | B7: La Dottoressa | C7: 의사 | D7: San Camillo 응급실 (가상 설정) | E7: 예산 삭감과 외주 압박 속에서 치료받지 못하는 환자들. Giulia의 이름 목록. | F7: B2~C1 | G7: 의학·보건행정, 주 보건서비스(SSR Lazio·ASL), 병원 외주(esternalizzazione) | H7: 과거
A8: 4 | B8: Il Revisore | C8: 회계사 | D8: Conti Revisori | E8: 역외 탈세·자금세탁 정황을 발견하지만 조직의 묵인 압박. 서명하지 않겠다는 다짐의 기원. | F8: B2~C1 | G8: 법정 감사(d.lgs. 39/2010), 자금세탁방지(d.lgs. 231/2007) | H8: 과거
A9: 5 | B9: La Consulente | C9: 컨설턴트 | D9: Zenit Consulting (EUR 오피스 타워 32층) | E9: 구조조정 엑셀 한 칸이 수백 명의 실직이었음을 깨닫는다. Paolo와의 첫 접점. | F9: B2~C1 | G9: 경영 전략, 집단해고(legge 223/1991), 노동법 | H9: 과거
A10: 6 | B10: L'Incontro | C10: 운명적 만남 | D10: Quarticciolo의 서민 주거 단지, 작은 바 | E10: 강제 퇴거와 의료 방치가 한 건으로 얽힌 사건에서 네 사람이 만나 사무소를 차리기로 한다. | F10: B2 | G10: 협상·설득 구어체 | H10: 현재로 수렴
A11: 7 | B11: La Rete della Resistenza | C11: 사무소 2탄: 전면전 | D11: 법원(Piazzale Clodio), Campidoglio 앞, 로마 전역 | E11: 부당 해고·의료 사고·탈세 대기업 상대 집단 대응. 내부 제보자를 보호하고 검찰에 고발한다. | F11: B2~C1 | G11: 검찰 고발(esposto-denuncia), 민사 당사자(parte civile), ANAC, 내부고발자 보호(d.lgs. 24/2023) | H11: 과거→현재
A12: 8 | B12: Il Risveglio Civico | C12: 정치적 각성과 창당 | D12: Piazza San Giovanni, 시민 집회 | E12: 폐지 국민투표가 정족수에 막히자 스스로 정당 «Casa Comune»를 창당해 첫 로마 시의회·라치오 주의회 선거에 나선다. | F12: B2~C1 | G12: 집회 사전 통지, 폐지 국민투표(헌법 제75조), 정당 등록부(d.l. 149/2013), 정당 재정, 선거운동 규칙 | H12: 정치
A13: 9 | B13: In Campidoglio e alla Pisana | C13: 시의회와 주의회 | D13: Campidoglio(Assemblea Capitolina), 라치오 주의회(Via della Pisana) | E13: Alessandro는 시의회에서 예산을, Giulia는 주의회에서 보건을 파고든다. 스캔들 폭로와 Sofia의 2차 폭발. | F13: C1 | G13: 시의회 운영(TUEL), 시 예산, 공공계약(d.lgs. 36/2023), 주 권한(보건·도시계획), 검찰 고발 | H13: 정치
A14: 10 | B14: Verso Palazzo Chigi | C14: 총선에서 총리 취임까지 | D14: Montecitorio, Palazzo Madama, Quirinale, Palazzo Chigi | E14: 해산·총선·개원·대통령 협의·첫 정부의 신임 부결·탐색 위임·재선거·상원 1표 차 신임. | F14: C1~C2 | G14: 선거 절차(legge 165/2017), 개원, 조각 위임(헌법 제92조), 신임(제94조), 해산(제88조), Quirinale 선서 | H14: 정치
A15: 11 | B15: La Grande Battaglia Sociale I | C15: 사회 현안 전투 I | D15: Palazzo Chigi, Consiglio dei Ministri, 브뤼셀 | E15: 연립 정부로 주거·보건·이민·청년·물가 국내 현안을 돌파한 뒤, Cesare가 직접 브뤼셀 협상(NATO 방위비·EU 재정규칙)에 나서 승리하고 귀국 직후 두 번째 죽음을 맞는다. | F15: C1~C2 | G15: Consiglio dei Ministri, 국가–주 협의회, NATO 방위비 목표(2025 헤이그 합의), EU 과도한 재정적자 절차 | H15: 정치
A16: 12 | B16: La Grande Battaglia Sociale II | C16: 사회 현안 전투 II | D16: Palazzo Chigi, 브뤼셀, 홍수 현장 | E16: 장례식으로 열고 Cesare의 유작 메모로 브뤼셀 후속 협상을 마무리한다. 플랫폼 노동·스파이웨어·청년 정신건강 등 새 현안과 불신임안 방어, 홍수 재난, 예산안까지. | F16: C1~C2 | G16: 메모 승계, decreto-legge vs 법률, 헌법재판소, 불신임안, 민방위(d.lgs. 1/2018), 예산 | H16: 정치
A17: 13 | B17: Ritorno a Testaccio | C17: 귀환 | D17: Testaccio, Trattoria da Rosa | E17: 1부 1화와 같은 대사로 시작해 원을 닫는다. Cesare의 유언장, 새 인턴, 이제 설명하는 쪽이 된 Sofia. | F17: B1~B2 | G17: 유언(notaio, esecutore testamentario), 정부 구성원 이해충돌 제한, 재단 전환, 원형 구조 | H17: 귀환
A19: 흐름: 현재(1) → 과거(2~5) → 교차(6) → 전면전(7) → 정치(8 창당 → 9 시·주 의회 → 10 총선·총리) → 국정(11~12) → 귀환(13, 원형 구조). 난이도는 B1 → C1/C2 → B1~B2로 올라갔다 내려와 마무리가 부드럽고, 13부에서 1부 장면을 다시 읽으면 낭독 실력의 성장을 스스로 확인할 수 있다.

Sheet 아크_구성계획
A1: 아크별 구성 계획 (1~13부)
A2: 각 부(아크)의 서사 기능, 변화, 비트(발단→결말), 인물 아크, 복선, 현안·제도, 언어 설계를 한 블록으로 정리. 화별 세부는 '화별목차_전체', 복선 추적은 '복선_회수'.
A4: 1부 | B4: Lo Studio di Testaccio — 테스타초 사무소 | 난이도 B1 | 사무소 개소 1개월 후(6부 12화로부터 약 4주). Testaccio 사무소와 1층 Rosa의 트라토리아.
A5: 서사 기능 | B5: 독자 진입 장치. 이미 굴러가는(그러나 여전히 좌충우돌하는) 사무소를 보여 주어 '이 사람들이 어쩌다 이렇게 됐지?' 하는 궁금증을 만든다. 자기소개 대신 여섯 사건을 통해 인물의 습관과 리듬을 익히게 한다. 부활한 역사 인물들이 아무렇지 않게 섞여 있는 일상이 첫 웃음 포인트.
A6: 로그라인 | B6: 개소 한 달째, 여전히 순서 하나 못 정하고 매번 다투는 네 전문가와 팀이 그래도 이웃들의 사건 여섯 개를 하나씩 해결해 나가지만, 마지막 사건의 서류에서 Marco의 옛 로펌 이름이 튀어나온다.
A7: 변화 (시작 → 끝) | B7: '한 달이나 됐는데 아직도 이 모양' → 그래도 매번 어떻게든 해결하는 팀이라는 신뢰. 그러나 각자의 과거는 여전히 미해결이고, 옛 로펌 이름이 도착한다.
A8: 핵심 갈등 | B8: 전문가의 말투 vs 이웃의 삶 / 여전히 못 정한 방법 / 각자 숨기는 과거
A9: 비트 1 | B9: 사건1 임대료 인상, 1~2화(Fatima): 도입에서 여전히 자리 못 잡은 한 달 차 팀의 말다툼을 보여 주고, 해결에서 Gramsci의 카드 #1(legge 431/1998)로 부당 인상을 막는다.
A10: 비트 2 | B10: 사건2 퇴거 집행, 3~4화: 밤 여덟 시 급보 → 아침 집행 연기. Garibaldi·Paolo 첫 카메오, 넷의 역할 분담(서류·건강·숫자·동선)이 처음으로 손발이 맞는다.
A11: 비트 3 | B11: 사건3 임금 체불·위장 인턴, 5~6화: Chiara의 컨설팅 용어가 청년 노동자를 지치게 하고, 협상 중 Sofia가 1차 폭발한다. 폭발 후 쉬운 말로 다시 협상해 해결.
A12: 비트 4 | B12: 사건4 의료 접근, 7~8화: 체류 서류 없는 가족의 아이가 진료를 못 받는다. Montessori·Dante 카메오, Cesare의 가짜 무릎이 진짜 아픈 아이 앞에서 조용해지는 대비. STP 코드로 해결.
A13: 비트 5 | B13: 사건5 금융 사기, 9~10화: 저축을 잃은 이웃을 두고 Alessandro가 장부를, 낯선 Francesco가 계좌 흐름을 추적한다. Galileo 카메오. Francesco는 설명 없이 사라지고 Alessandro는 은행 이름에 말없이 굳는다.
A14: 비트 6 | B14: 사건6 오래된 서류·훅, 11~12화: 수십 년 전 퇴거 서류의 절차 오류를 바로잡다가 서명란에서 Marco의 옛 로펌 이름을 발견한다. Marco가 얼어붙고 금요일 이야기(2부)가 예고된다.
A15: 인물 아크 | B15: Sofia=독자의 대리인(질문), 한 달이 지나도 Marco에게 Lei 유지. Cesare=심술과 복선(매년 하는 소리라는 게 드러남). Rosa=정서적 중심. 카메오는 사건별로 분산: Gramsci(1·2·6화), Machiavelli(1·5·12화), Garibaldi·Paolo(3·4화), Montessori·Dante(7화), Francesco·Galileo(9·10·11화). 폭발 화(6화)에는 Garibaldi·Rosa·Gramsci의 고정 반응만 남기고 Paolo의 욕은 9부 2차 폭발로 이관해 과밀을 해소.
... A19: 언어 설계 | B19: B1. 한 줄 15단어 이내, 현재·명령형·근과거(passato prossimo). tu·voi 중심. 낭독: 빠른 티키타카로 입 풀기. Marco·Cesare의 격식체는 한두 줄 맛보기. 매 사건 2화(도입→해결) 리듬을 반복해 구조를 익히게 한다. Rosa의 로마 사투리(romanesco)는 한 화에 한두 마디만.
A20: 대화량 (화당 120턴) | B20: ="화당 "&턴_설계!$B$5&"턴 · 부 총 "&TEXT(턴_설계!D34,"#,##0")&"턴 · 화당 약 "&TEXT(턴_설계!F34,"#,##0")&"단어 · 낭독 약 "&TEXT(턴_설계!H34,"0.0")&"분 (평균 "&TEXT(턴_설계!E34,"0.0")&"단어/턴)"
A21: Sofia 질문·Gramsci 카드 | B21: Sofia: 임대·노동·의료·금융 기초 용어(deposito cauzionale, contratto a termine, tirocinio, codice STP, conto corrente). 카드: legge 431/1998, 사전(Treccani·Accademia della Crusca).
A22: 다음 부 연결 | B22: 2부: 금요일마다 한 명씩 과거를 이야기하는 규칙 — 첫 번째는 Marco.
A24: 2부 | B24: L'Avvocato — 변호사 | 난이도 B2~C1 | 프레임: 1부와 같은 첫 겨울의 금요일 밤. 과거: 약 5년 전, Prati(Piazza Cavour 법원가)의 대형 로펌.
A25: 서사 기능 | B25: 첫 과거 회상. 공동 악역 Gruppo Meridiano를 도입하고 '법을 잘 쓰는 것과 옳은 것은 다르다'는 이 이야기의 첫 질문을 던진다. 프레임(Rosa의 식탁)과 과거를 오가는 구조 실험.
A26: 로그라인 | B26: 승소율 100%의 파트너 후보가 대형 고객의 주택 포트폴리오를 비우는 갱신 거절 전략을 설계해 재판에서 이기고, 그 승리가 한 노인의 죽음이 되었음을 알게 된다.
A27: 변화 (시작 → 끝) | B27: 자랑스러운 승자 → 자기 승리에 사직서를 낸 사람.
A28: 핵심 갈등 | B28: 잘 쓰는 법 vs 옳은 것 / 파트너 승진 vs 양심
A29: 비트 1 | B29: 발단(1~3화): 금요일 프레임, 프라티의 월요일(편의점의 Dante), VIP 고객 Santoro.
A30: 비트 2 | B30: 전개(4~5화): 실사에서 Testaccio 건물 발견 / 프레임에서 그곳이 Rosa의 거리였음이 드러남.
A31: 비트 3 | B31: 미드포인트(6화): 조항 설계 — Marco가 스스로 함정을 만든다.
A32: 비트 4 | B32: 위기(7~9화): 세입자 총회(Assunta), 재판 승소, 프레임에서 Marco의 말이 막힘.
A33: 비트 5 | B33: 절정(10~11화): 파리올리 축하 만찬 중 부고, 손녀 Marina의 방문.
... A39: 언어 설계 | B39: B2~C1. 접속법 현재·과거(congiuntivo), 수동태, 법률 문어체. 과거 장면은 격식 문어, 프레임 장면은 B1로 두어 톤을 대비. 발성: 또박또박, 중저음.
A40: 대화량 (화당 120턴) | B40: ="화당 "&턴_설계!$B$5&"턴 · 부 총 "&TEXT(턴_설계!D35,"#,##0")&"턴 · 화당 약 "&TEXT(턴_설계!F35,"#,##0")&"단어 · 낭독 약 "&TEXT(턴_설계!H35,"0.0")&"분 (평균 "&TEXT(턴_설계!E35,"0.0")&"단어/턴)"
A41: Sofia 질문·Gramsci 카드 | B41: Sofia: citazione·sentenza·clausola 등 법률 용어. 카드: Conservatoria dei Registri Immobiliari, legge 431/1998, 민사소송법의 퇴거 확인 절차(convalida di sfratto).
A42: 다음 부 연결 | B42: 3부: 응급실에서 쓰러진 Marco — 다음 금요일은 Giulia의 이야기.
A44: 3부 | B44: La Dottoressa — 의사 | 난이도 B2~C1 | 프레임: 금요일 밤. 과거: 약 4년 전, San Camillo 응급실(가상 설정).
A45: 서사 기능 | B45: 인간의 생명과 공공 보건이라는 정서적 무게. Gruppo Meridiano의 두 번째 얼굴(병원 외주)을 보여 주고, 폭염·고령 환자·서류 없는 환자 등 현안을 응급실에서 체감하게 한다.
A46: 로그라인 | B46: 응급의가 예산 삭감과 병원 외주 속에서 환자를 잃기 시작하고, 이름을 적어 두다가 내부 보고를 올리지만 징계로 돌아온다.
A47: 변화 (시작 → 끝) | B47: 시스템을 믿는 의사 → 이름 명단만 든 사직자.
A48: 핵심 갈등 | B48: 의료 윤리 vs 관리 효율 / 침묵하는 동료들
A49: 비트 1 | B49: 발단(1~3화): 금요일 프레임, 야간 근무(Marco 진료), 폭염 환자 폭증.
A50: 비트 2 | B50: 전개(4~5화): 병원 외주 발표(컨설턴트 Chiara 등장), 프레임에서 수첩 명단과 Cesare의 부은 발목(«Sono i calzari.»).
A51: 비트 3 | B51: 미드포인트(6화): '명단의 첫 번째' — 서류 없는 환자가 병상 지연으로 숨진다.
A52: 비트 4 | B52: 위기(7~9화): 원장의 통계, 징계 절차, 프레임에서 Montessori의 되받기.
A53: 비트 5 | B53: 절정(10~11화): 병상 없는 밤, 사직.
... A59: 언어 설계 | B59: B2~C1. 의학 어휘, 짧은 명령형, 긴박한 호흡. 발성: 빠른 템포와 짧은 호흡.
A60: 대화량 (화당 120턴) | B60: ="화당 "&턴_설계!$B$5&"턴 · 부 총 "&TEXT(턴_설계!D36,"#,##0")&"턴 · 화당 약 "&TEXT(턴_설계!F36,"#,##0")&"단어 · 낭독 약 "&TEXT(턴_설계!H36,"0.0")&"분 (평균 "&TEXT(턴_설계!E36,"0.0")&"단어/턴)"
A61: Sofia 질문·Gramsci 카드 | B61: Sofia: triage·parametri vitali·sepsi 등 의학 용어. 카드: legge 833/1978(국가 보건서비스 설립), legge 219/2017(동의·사전의료지시), d.lgs. 286/1998 제35조.
A62: 다음 부 연결 | B62: 4부: Alessandro — «Tocca a me.» 그 서명의 주인.
A64: 4부 | B64: Il Revisore — 회계사 | 난이도 B2~C1 | 프레임: 금요일 밤. 과거: 약 3년 전, Conti Revisori.
A65: 서사 기능 | B65: 돈의 흐름과 '서명의 책임'. 부패의 공모가 일상 업무의 얼굴로 온다는 것을 보여 주고, 이후 아크의 결정적 증거(USB)를 만든다.
A66: 로그라인 | B66: 시니어 파트너가 최대 고객의 이상 거래를 발견하지만, 압박과 승진 앞에서 결국 '깨끗한' 의견서에 서명하고 그 서명이 다른 사람의 죽음과 해고에 쓰인다.
A67: 변화 (시작 → 끝) | B67: 정확함을 자랑하던 감사인 → '서명한 사람'. 다시는 서명하지 않겠다는 다짐.
A68: 핵심 갈등 | B68: 감사인의 독립성 vs 수임료 / 정확함 vs 생존
A69: 비트 1 | B69: 발단(1~3화): '내가 서명했다' 프레임, 결산 마감, 돈 잘 주는 고객.
A70: 비트 2 | B70: 전개(4~5화): '이건 안 맞아' — 특수관계자 대출 발견 / 프레임에서 아버지 이야기.
A71: 비트 3 | B71: 미드포인트(6화): 파트너 회의 — 한정 의견 주장, 리스크 위원회로 에스컬레이션.
A72: 비트 4 | B72: 위기(7~9화): 위원회의 '증거 불충분', 파리올리의 점심(위협), 프레임 '서명했어요?'.
A73: 비트 5 | B73: 절정(10~11화): 서명, 그리고 서명 이후 — 계약 확정과 구조조정 통보, 사직.
... A79: 언어 설계 | B79: B2~C1. 숫자 낭독, 수동태·조건법, 감사 보고서체. 발성: 일정한 속도, 결론 문장에서 톤 낮춤.
A80: 대화량 (화당 120턴) | B80: ="화당 "&턴_설계!$B$5&"턴 · 부 총 "&TEXT(턴_설계!D37,"#,##0")&"턴 · 화당 약 "&TEXT(턴_설계!F37,"#,##0")&"단어 · 낭독 약 "&TEXT(턴_설계!H37,"0.0")&"분 (평균 "&TEXT(턴_설계!E37,"0.0")&"단어/턴)"
A81: Sofia 질문·Gramsci 카드 | B81: Sofia: stato patrimoniale·conto economico·significatività 등 회계 용어. 카드: d.lgs. 39/2010, 법정 감사인 등록부(Registro dei revisori legali), 기업 등록부(Registro delle imprese).
A82: 다음 부 연결 | B82: 5부: Chiara — 그 의견서 이후 시작된 구조조정 명단의 주인.
A84: 5부 | B84: La Consulente — 컨설턴트 | 난이도 B2~C1 | 프레임: 금요일 밤. 과거: 약 2년 전, EUR 오피스 타워 32층의 Zenit Consulting.
A85: 서사 기능 | B85: 효율의 이름으로 사람이 숫자가 되는 순간. 노동(Paolo), 청년 고용(S1), 영세·가족 기업 구조(E2)를 도입하고 Chiara의 말투 변화를 예고한다.
A86: 로그라인 | B86: 전략 컨설턴트가 영세 기업을 살리려던 낙관에서 출발해, 대형 고객 구조조정 모델의 셀 하나가 412명의 해고임을 알게 된다.
A87: 변화 (시작 → 끝) | B87: '스케일'을 믿던 사람 → 사람을 숫자로 본 죄책감을 인정하는 사람(프레젠테이션 톤에서 솔직한 톤으로 가는 시작).
A88: 핵심 갈등 | B88: 효율 vs 사람 / 조직 충성 vs 양심
A89: 비트 1 | B89: 발단(1~3화): 매트릭스 프레임, Zenit 32층, Ruggeri 공방(영세 기업의 실패).
A90: 비트 2 | B90: 전개(4~5화): 이카로 프로젝트 킥오프 / 프레임 '엑셀 한 장'.
A91: 비트 3 | B91: 미드포인트(6화): C47 셀 — 412개 일자리, 스푸만테.
A92: 비트 4 | B92: 위기(7~9화): 협상 테이블에서 Paolo와 대면, 잘못 보낸 이메일과 Montessori 상담, 프레임 '412'.
A93: 비트 5 | B93: 절정(10~11화): 파업과 Paolo의 해고, 마지막 회의에서 사직.
... A99: 언어 설계 | B99: B2~C1. 경영 외래어(allineare, scalabile, KPI), 프레젠테이션 톤. 발성: 숨 가쁜 톤에서 느린 솔직한 톤으로.
A100: 대화량 (화당 120턴) | B100: ="화당 "&턴_설계!$B$5&"턴 · 부 총 "&TEXT(턴_설계!D38,"#,##0")&"턴 · 화당 약 "&TEXT(턴_설계!F38,"#,##0")&"단어 · 낭독 약 "&TEXT(턴_설계!H38,"0.0")&"분 (평균 "&TEXT(턴_설계!E38,"0.0")&"단어/턴)"
A101: Sofia 질문·Gramsci 카드 | B101: Sofia: stakeholder·scalare·sinergia·KPI 등 경영 용어. 카드: legge 223/1991, 노동자 헌장(Statuto dei lavoratori, legge 300/1970).
A102: 다음 부 연결 | B102: 6부: 콰르티촐로 — 네 사람이 같은 총회에.
A104: 6부 | B104: L'Incontro — 운명적 만남 | 난이도 B2 | 약 1년 전(1부보다 앞). Quarticciolo '14번 동(lotto 14)' → Testaccio 사무소 개소.
A105: 서사 기능 | B105: 퍼즐 완성. 네 개의 과거가 하나의 이름(Gruppo Meridiano)으로 수렴하고 팀이 결성된다. 1부의 '왜?'에 대한 대답이자 시간의 고리를 닫는 아크.
A106: 로그라인 | B106: 각자 무너진 네 사람이 같은 건물을 지키려고 모였다가 자기들이 서로 다른 얼굴의 같은 회사를 도왔음을 알게 되고, 서로를 비난한 끝에 처음으로 함께 이긴다.
A107: 변화 (시작 → 끝) | B107: 혼자 무너진 네 사람 → 서로의 죄를 아는 팀.
A108: 핵심 갈등 | B108: 서로에 대한 책임(공모) vs 함께 속죄
A109: 비트 1 | B109: 발단(1~3화): 콰르티촐로의 화요일, 낯선 넷, 14번 동.
A110: 비트 2 | B110: 전개(4~5화): 계단의 밤(첫 속내), Alessandro의 서류.
A111: 비트 3 | B111: 미드포인트(6화): '같은 이름' — 네 개의 과거가 Meridiano 하나로 이어진다.
A112: 비트 4 | B112: 위기(7~9화): 서로에 대한 비난, 퇴거 아침 영시의 협업, 첫 정지 승리.
A113: 비트 5 | B113: 절정(10~11화): 테스타초의 가게, 식탁의 규칙(금요일 이야기 전통).
... A119: 언어 설계 | B119: B2. 감정 폭발·설득 구어체, 다툼과 화해. 발성: 소리 높임과 회복의 대비. Lei → tu 전환의 시작.
A120: 대화량 (화당 120턴) | B120: ="화당 "&턴_설계!$B$5&"턴 · 부 총 "&TEXT(턴_설계!D39,"#,##0")&"턴 · 화당 약 "&TEXT(턴_설계!F39,"#,##0")&"단어 · 낭독 약 "&TEXT(턴_설계!H39,"0.0")&"분 (평균 "&TEXT(턴_설계!E39,"0.0")&"단어/턴)"
A121: Sofia 질문·Gramsci 카드 | B121: Sofia: «Cos'è un fondo avvoltoio?» 등 소유 구조 용어. 카드: 기업 등록부(Registro delle imprese), 퇴거 집행 연기 규정.
A122: 다음 부 연결 | B122: 1부 1화 — 원이 닫힌다. 그리고 7부로.
A124: 7부 | B124: La Rete della Resistenza — 전면전 | 난이도 B2~C1 | 사무소 개소 1년 후. 법원(Piazzale Clodio), Campidoglio 앞, 로마 전역.
A125: 서사 기능 | B125: 전문 능력이 결합되어 첫 결정적 승리를 얻지만, 판결이 법 앞에서 무력할 수 있음을 배운다. 정치의 필요성을 낳는 아크.
A126: 로그라인 | B126: 사무소가 고발·내부고발·보도를 결합해 Gruppo Meridiano를 상대로 전면전을 벌이고 수사를 이끌어 내지만, 그 승리를 뒤집을 법이 준비되고 있음을 알게 된다.
A127: 변화 (시작 → 끝) | B127: 사건을 푸는 사무소 → 법을 바꿔야 한다는 결론.
A128: 핵심 갈등 | B128: 합법 vs 효율(도청기) / 승리의 지속 가능성
A129: 비트 1 | B129: 발단(1~3화): 1년 후, 계단 위의 줄, 피해자를 벌한 시간(N4).
A130: 비트 2 | B130: 전개(4~5화): 서류 없는 사람들(S2), Francesco의 제보.
A131: 비트 3 | B131: 미드포인트(6화): 사건 파일 — 검찰 고발장(esposto) 제출.
A132: 비트 4 | B132: 위기(7~9화): 보복, 전등 속 마이크(사용할 수 없는 증거 논쟁), 동네의 보초.
A133: 비트 5 | B133: 절정(10~11화): GIP 결정과 피의자 통지 / 다가오는 법(공직자 범죄 축소·도청 제한 법안).
... A139: 언어 설계 | B139: B2~C1. 고발장·성명서·인터뷰 어휘. 발성: 긴박한 대화와 기자회견 톤.
A140: 대화량 (화당 120턴) | B140: ="화당 "&턴_설계!$B$5&"턴 · 부 총 "&TEXT(턴_설계!D40,"#,##0")&"턴 · 화당 약 "&TEXT(턴_설계!F40,"#,##0")&"단어 · 낭독 약 "&TEXT(턴_설계!H40,"0.0")&"분 (평균 "&TEXT(턴_설계!E40,"0.0")&"단어/턴)"
...

Sheet 화별목차_전체
A1: 전체 화별 목차 (1~13부, 156화)
A2: 현실 제도와 현안(ID는 '현안_배치' 시트)을 반영한 초안. 의석 수·결과는 가상 수치. 모든 화는 지문 없이 대화문으로만 진행한다.
A4: 부 | B4: 화 | C4: 서사 기능 | D4: 제목 (IT) | E4: 한국어 | F4: 핵심 사건 | G4: 반영 제도·전문 영역 | H4: 주요 인물 | I4: 반영 현안 (ID) | J4: 턴 수
A5: 1 | B5: 1 | C5: 사건1 도입 | D5: Un'altra lettera | E5: 또 다른 편지 | F5: 사무소 개소 1개월 후. 다섯 시, 여전히 방법을 못 정한 채 매일 다투는 팀. Fatima가 두 번째로 찾아와 새 임대료 인상 통지서와 퇴거 경고장을 보인다. Sofia는 여전히 Marco에게 Lei를 쓴다. Gramsci가 지나가며 «날짜를 세어 보라»는 힌트만 던지고, Machiavelli는 «이 집의 진짜 주인이 누구인가»만 묻는다. 계약서가 없어 다음 날로 미뤄진다. | G5: 생활 법률 구어체, 반복되는 말다툼 (B1) | H5: Rosa, Marco, Giulia, Alessandro, Chiara, Sofia, Cesare, Fatima, Gramsci, Machiavelli | I5: E1 | J5: =턴_설계!$B$5
A6: 1 | B6: 2 | C6: 사건1 해결 | D6: La clausola che non sale | E6: 오르지 않는 조항 | F6: [사건1 해결] Fatima와 Sofia가 계약서를 가져온다. Gramsci의 카드 #1(legge 431/1998)로 계약에 정한 ISTAT 물가 연동 한도를 넘는 인상이 부당함을 확인하고, 기한 안에 등기우편(raccomandata) 답장을 쓴다. 사무소의 첫 번째 규칙(가난한 이웃에겐 돈을 받지 않는다)이 확인된다. | G6: 주거 임대차(legge 431/1998), ISTAT 물가 연동 조정(aggiornamento ISTAT), 기한·답변 | H6: Marco, Alessandro, Chiara, Fatima, Gramsci, Sofia, Rosa | I6: E1 | J6: =턴_설계!$B$5
A7: 1 | B7: 3 | C7: 사건2 도입 | D7: L'avviso delle otto | E7: 여덟 시의 통지 | F7: [사건2 도입] 밤 여덟 시, 퇴거 집행(sfratto)이 다음 날 아침으로 잡혔다는 급보가 온다. Garibaldi가 주민을 '의용대'처럼 조직하고 Paolo가 이웃들을 모은다. 네 사람이 각자 서류·건강·숫자·동선을 맡아 밤새 준비하지만 승산은 불투명하다. | G7: 퇴거 집행 예고(preavviso di rilascio), 긴급 동원, 이웃 조직 | H7: Marco, Giulia, Alessandro, Chiara, Garibaldi, Paolo, Sofia, Rosa | I7: E1 | J7: =턴_설계!$B$5
A8: 1 | B8: 4 | C8: 사건2 해결 | D8: Il furgone che non arrivò | E8: 오지 않은 트럭 | F8: [사건2 해결] 집행 당일 아침. Marco의 집행 연기 신청, Giulia의 취약계층 진단서, Alessandro의 체납액 계산과 비귀책 체납 기금 신청, Chiara의 동선 배치가 맞물려 집행관이 집행을 연기한다. Garibaldi의 «Nulla da segnalare» 보고로 마무리된다. | G8: 집행 연기(rinvio dell'esecuzione), 비귀책 체납 기금(Fondo morosità incolpevole), 집행관(ufficiale giudiziario) 대응 | H8: Marco, Giulia, Alessandro, Chiara, Garibaldi, Paolo, Sofia, Rosa | I8: E1 | J8: =턴_설계!$B$5
A9: 1 | B9: 5 | C9: 사건3 도입 | D9: Lo stagista della fabbrica | E9: 공장의 인턴 | F9: [사건3 도입] 임금 체불과 무급 초과근무에 지친 청년 노동자 Davide(가상)가 찾아온다. 서류상 '인턴(tirocinio)'이지만 실제로는 정규직 일을 한다. Chiara가 컨설팅 용어로 상황을 분석하려 하고 Sofia가 통역하듯 애쓰지만 Davide는 점점 지쳐 간다. | G9: 위장 인턴(tirocinio), 기간제 계약, 초과근무, 경영 용어의 벽 | H9: Chiara, Sofia, Alessandro, Rosa, Machiavelli, Davide(가상) | I9: S1 | J9: =턴_설계!$B$5
A10: 1 | B10: 6 | C10: 사건3 해결(폭발) | D10: Basta! | E10: 그만! | F10: [사건3 해결] 협상 자리에서 Chiara의 용어가 한 시간째 이어지자 Sofia가 폭발한다(1차 폭발). Giulia·Garibaldi·Rosa·Gramsci의 고정 반응, Cesare의 «Stolta… Domanda.», Alessandro의 «Traduco io.» 이후 쉬운 말로 다시 협상해 밀린 임금 지급과 정식 계약 전환에 합의한다. | G10: 감정 표현, 전문 용어 → 쉬운 말, 임금 체불 합의(conciliazione) | H10: Sofia, Chiara, Alessandro, Giulia, Cesare, Garibaldi, Rosa, Gramsci, Davide(가상) | I10: S1 | J10: =턴_설계!$B$5
A11: 1 | B11: 7 | C11: 사건4 도입 | D11: La bambina con la febbre | E11: 열이 나는 아이 | F11: [사건4 도입] 체류 서류가 없어 소아과 주치의(pediatra)를 배정받지 못하는 가족이 찾아온다. Giulia가 나서고 Montessori가 들러 «E questo come ti fa sentire?»를 처음 선보인다. 마침 들른 Dante는 Cesare에게 원고를 놀림받다 «Niente male.»라는 최고의 칭찬을 듣는다. 정작 진짜 아픈 아이 앞에서 Cesare는 자기 무릎 타령을 멈춘다. | G11: 서류 없는 가족의 의료 접근, 증상 표현 | H11: Giulia, Montessori, Cesare, Dante, Sofia, Rosa, 가족(가상: Amina·Noa) | I11: S2 | J11: =턴_설계!$B$5
A12: 1 | B12: 8 | C12: 사건4 해결 | D12: Un codice per tutti | E12: 모두를 위한 코드 | F12: [사건4 해결] Marco와 Giulia가 STP 코드(체류 서류 없는 외국인의 긴급·필수 진료 코드)와 미성년자 소아과 등록 경로를 찾아내 아이가 진료를 받는다. Cesare가 평소와 달리 조용히 커피를 마신다. | G12: STP 코드(d.lgs. 286/1998 제35조), 미성년자 소아과 등록, 진료 의뢰서(impegnativa) | H12: Giulia, Marco, Sofia, Rosa, 가족(가상) | I12: S2 | J12: =턴_설계!$B$5
A13: 1 | B13: 9 | C13: 사건5 도입 | D13: La vedova del quinto piano | E13: 5층의 미망인 | F13: [사건5 도입] 가짜 투자에 저축을 잃은 노년의 이웃 Iolanda(가상)가 찾아온다. Alessandro가 장부를 살피는 동안, 양복 입은 낯선 남자 Francesco가 나타나 은행 쪽 흐름을 봐 주겠다고 하면서도 자기 이야기는 하지 않는다. Galileo가 '관찰 대상'이라며 기웃거린다. | G13: 저축·투자 사기, 은행 계좌 기초 어휘 | H13: Alessandro, Francesco, Galileo, Sofia, Rosa, Iolanda(가상) | I13: E3 | J13: =턴_설계!$B$5
A14: 1 | B14: 10 | C14: 사건5 해결 | D14: Segui il denaro | E14: 돈을 따라가라 | F14: [사건5 해결] Francesco의 계좌 흐름 추적과 Alessandro의 장부 대조로 사기 계좌를 찾아 돈 일부를 되찾는다. Francesco는 설명 없이 떠나고, Alessandro는 «Banca Adriatica»라는 이름에 말없이 굳는다. | G14: 자금 흐름 추적, 계좌·송금(bonifico) 어휘 | H14: Alessandro, Francesco, Sofia, Rosa, Iolanda(가상) | I14: E3 | J14: =턴_설계!$B$5
A15: 1 | B15: 11 | C15: 사건6 도입 | D15: Una carta di anni fa | E15: 수년 전 서류 | F15: [사건6 도입] Fatima의 남편 Karim(가상)이 수십 년 전 다른 건물에서 받은 낡은 퇴거 서류를 들고 온다. 당장 급한 사안은 아니지만 오래된 절차 오류가 보인다. Galileo가 «증거가 두 개면 기사가 된다»며 흥미를 보인다. | G15: 오래된 서류 판독, 절차 하자 | H15: Marco, Galileo, Sofia, Rosa, Karim(가상) | I15: E1 | J15: =턴_설계!$B$5
A16: 1 | B16: 12 | C16: 사건6 해결(훅) | D16: La firma | E16: 서명 | F16: [사건6 해결·훅] 절차 오류를 바로잡아 오래된 기록을 정정하지만, 진짜 충격은 서류 맨 아래: Marco의 옛 로펌 «Ferrari & Colombo»의 서명이다. Marco가 얼어붙고 Rosa가 «Sedetevi, che vi porto qualcosa.»로 분위기를 잇는다. 금요일에는 Marco의 이야기가 시작된다. | G16: 서명·기록 정정, 이름 확인 | H16: Marco, Rosa, Sofia, Cesare, Machiavelli, Karim(가상) | I16: E1 | J16: =턴_설계!$B$5
A17: 2 | B17: 1 | C17: 발단 | D17: Venerdì di storie | E17: 금요일의 이야기 | F17: (프레임) Rosa의 식탁에서 금요일마다 한 사람이 과거를 이야기하는 규칙이 시작된다. Sofia가 Marco에게 왜 로펌을 그만뒀느냐고 묻고 Marco는 «Andiamo con ordine.»로 시작한다. | G17: 격식체(Lei)와 tu의 대비, 과거 이야기 도입 | H17: Sofia, Marco, Rosa, Cesare | I17: E1 | J17: =턴_설계!$B$5
A18: 2 | B18: 2 | C18: 발단 | D18: Un lunedì in Prati | E18: 프라티의 월요일 | F18: (과거) 승소율 100%의 파트너 후보 Marco의 하루. 새벽 편의점에서 계산대에 선 채 『신곡』을 중얼거리는 야간 점원 Dante와 마주친다. 상사 Colombo(가상)가 파트너 승진을 암시한다. | G18: 로펌 어휘: socio, parcella, portafoglio clienti | H18: Marco, Dante, Colombo(가상) | J18: =턴_설계!$B$5
A19: 2 | B19: 3 | C19: 발단 | D19: Il cliente d'oro | E19: VIP 고객 | F19: 대형 고객 Gruppo Meridiano의 회장 Santoro(가상)를 소개받는다. 회의석에는 고객 측 컨설턴트 Chiara와 매각 은행 지점장 Francesco가 있다. | G19: 인수합병 어휘: acquisizione, portafoglio, clausola | H19: Marco, Chiara, Francesco, Santoro(가상) | I19: E1 | J19: =턴_설계!$B$5
A20: 2 | B20: 4 | C20: 전개 | D20: Il portafoglio di Testaccio | E20: 테스타초 자산 포트폴리오 | F20: 실사(due diligence). 포트폴리오에 Testaccio 건물 12채가 들어 있다. 감사인 Alessandro가 «Questo non torna»를 흘리고, Piazza Borghese 고서 노점에서 등기 자료를 찾던 Marco에게 Gramsci가 «Cercalo tu.» | G20: 실사, 부동산 등기(Conservatoria dei Registri Immobiliari)·토지대장(Catasto), 임차인 명부 | H20: Marco, Alessandro, Gramsci | I20: E1 | J20: =턴_설계!$B$5
A21: 2 | B21: 5 | C21: 전개 | D21: Venerdì: la via di Rosa | E21: 금요일: Rosa의 거리 | F21: (프레임) 그 포트폴리오에 Rosa의 트라토리아가 있던 건물이 들어 있었음이 밝혀진다. Sofia는 놀라 Lei를 놓치고 Marco는 잠시 침묵한다. | G21: 감정 표현, 놀람 | H21: Rosa, Marco, Sofia | I21: E1 | J21: =턴_설계!$B$5
A22: 2 | B22: 6 | C22: 미드포인트 | D22: La clausola | E22: 조항 | F22: 임차인을 비우는 가장 '깨끗한' 방법으로 Marco가 «첫 만기 때 리모델링을 이유로 갱신을 거절하는(diniego di rinnovo per ristrutturazione)» 조항 전략을 설계한다. Chiara의 재무 모델이 이를 뒷받침한다. | G22: 갱신 거절 사유(legge 431/1998 제3조), 리모델링 사유, 통지 요건(만기 6개월 전) | H22: Marco, Chiara, Colombo(가상) | I22: E1 | J22: =턴_설계!$B$5
A23: 2 | B23: 7 | C23: 위기 | D23: L'assemblea degli inquilini | E23: 세입자 총회 | F23: 세입자들이 총회를 연다. 노조 출신 Paolo가 이끌고, 응급실 의사 Giulia가 공황을 일으킨 노인을 돌본다. Marco는 78세 Assunta(가상)를 만난다. | G23: 총회·발언·동의, 항의 표현 | H23: Marco, Paolo, Giulia, Assunta(가상) | I23: E1 | J23: =턴_설계!$B$5
A24: 2 | B24: 8 | C24: 위기 | D24: Il processo | E24: 재판 | F24: 심리(udienza)와 판결. Marco가 승소한다. 방청석의 Galileo가 «È orgoglioso?»라고 묻는다. 감사인 Alessandro는 고객의 장부를 보고 고개를 젓는다. | G24: 소송: citazione, udienza, sentenza, spese processuali | H24: Marco, Galileo, Alessandro, 판사(가상) | I24: E1·P3 | J24: =턴_설계!$B$5
A25: 2 | B25: 9 | C25: 위기 | D25: Venerdì: continua | E25: 금요일: 계속해 | F25: (프레임) Marco가 말을 잇지 못하자 Cesare가 «Quando Cesare era in Gallia…»로 시간을 벌어 주고 Rosa가 «Continua.»라고 한다. Sofia는 «E lei?»라고 묻는다. Machiavelli는 말없이 메모한다. | G25: 위로·재촉 표현 | H25: Marco, Cesare, Rosa, Sofia, Machiavelli | J25: =턴_설계!$B$5
A26: 2 | B26: 10 | C26: 절정 | D26: Una cena ai Parioli | E26: 파리올리의 저녁 | F26: 승소 축하 만찬. 파트너들이 건배하는 동안 Santoro가 다음 포트폴리오를 건넨다. Marco의 휴대전화가 울린다. | G26: 고급 식당 표현, 건배·축하(brindisi) | H26: Marco, Colombo(가상), Santoro(가상), Alessandro | J26: =턴_설계!$B$5
A27: 2 | B27: 11 | C27: 절정 | D27: La nipote di Assunta | E27: Assunta의 손녀 | F27: Assunta가 퇴거 석 달 뒤 세상을 떠났다는 소식. 손녀 Marina(가상)가 사무실로 찾아와 조용히 묻는다: «Ha vinto Lei?» | G27: 조의·항의, 문서 vs 사람 | H27: Marco, Marina(가상) | I27: E1 | J27: =턴_설계!$B$5
A28: 2 | B28: 12 | C28: 결말·훅 | D28: Venerdì: le dimissioni | E28: 금요일: 사직 | F28: (프레임+과거) Marco가 다음 포트폴리오 서명을 거부하고 사직서를 낸다. 짐 상자를 든 채 응급실 대기실에서 쓰러지고 Giulia가 그를 진료한다. Sofia는 여전히 Lei를 쓴다. | G28: 사직·거절 표현, 접속법(congiuntivo) | H28: Marco, Giulia, Sofia, Rosa | J28: =턴_설계!$B$5
A29: 3 | B29: 1 | C29: 발단 | D29: Venerdì: i nomi | E29: 금요일: 이름들 | F29: (프레임) Giulia가 «Questa non è una statistica, è una persona.»라며 이야기를 시작한다. Cesare가 계단을 오르내리다 숨을 고르는 것을 Giulia가 흘끗 본다. | G29: 의학 어휘 도입 | H29: Giulia, Sofia, Cesare, Rosa | J29: =턴_설계!$B$5
A30: 3 | B30: 2 | C30: 발단 | D30: Turno di notte | E30: 야간 근무 | F30: (과거) San Camillo 응급실(가상 설정)의 야간 근무. 분류(triage), 병상, 간호사 Loredana(가상)와의 호흡. 가슴 통증으로 실려 온 Marco를 진료한다. | G30: triage(긴급도 코드 1~5), parametri vitali, barella, box | H30: Giulia, Loredana(가상), Marco | J30: =턴_설계!$B$5
A31: 3 | B31: 3 | C31: 발단 | D31: L'ondata di calore | E31: 폭염 | F31: 폭염 경보(bollino rosso)에 고령 환자가 몰려 응급실이 넘친다. 산소·수액·얼음. Giulia는 밤새 환자 이름을 외운다. | G31: 열사병(colpo di calore), 탈수, 고령 환자 | H31: Giulia, Loredana(가상) | I31: S4·S3 | J31: =턴_설계!$B$5
A32: 3 | B32: 4 | C32: 전개 | D32: Un contratto che nessuno legge | E32: 읽히지 않는 계약 | F32: 병원이 검사·병상 관리를 Meridiano Salute에 외주한다고 발표한다. 원장 회의에서 컨설턴트 Chiara가 '효율' 발표를 한다. | G32: 외주(esternalizzazione)·민간 위탁, 예산, 입찰(gara d'appalto) | H32: Giulia, 원장(가상), Chiara | I32: S3 | J32: =턴_설계!$B$5
A33: 3 | B33: 5 | C33: 전개 | D33: Venerdì: la lista | E33: 금요일: 명단 | F33: (프레임) Sofia가 Giulia의 수첩 명단을 본다. Giulia는 «Ho visto di peggio in un martedì qualsiasi.»로 넘긴다. Cesare는 발목이 부었냐는 물음에 «Sono i calzari.» | G33: 명단·숫자 읽기 | H33: Giulia, Sofia, Cesare | J33: =턴_설계!$B$5
A34: 3 | B34: 6 | C34: 미드포인트 | D34: La prima della lista | E34: 명단의 첫 번째 | F34: 체류 서류 없는 20대 여성이 패혈증으로 실려 오지만 병상 배정이 아홉 시간 지연되어 숨진다. 외주 병상관리가 '비용 검토' 중이었다. Giulia가 수첩에 첫 이름을 쓴다. | G34: 패혈증(sepsi), 병상 관리(bed management), 서류 없는 환자의 접근권(STP 코드) | H34: Giulia, Loredana(가상), 원장(가상) | I34: S2·S3 | J34: =턴_설계!$B$5
A35: 3 | B35: 7 | C35: 위기 | D35: I numeri del direttore | E35: 원장의 숫자 | F35: 원장(direttore generale)이 '대기 시간 개선' 통계를 발표한다. 외주 업체의 재무를 자문하는 Alessandro가 배석한다. Giulia가 내부 사망 사례 보고서를 제출한다. | G35: 통계 읽기, 보고서 어휘 | H35: Giulia, 원장(가상), Alessandro | I35: P3 | J35: =턴_설계!$B$5
A36: 3 | B36: 8 | C36: 위기 | D36: Il procedimento | E36: 징계 절차 | F36: 보고서 유출 의혹으로 징계 절차가 시작된다. 취재하는 Galileo에게 Giulia가 «Questo non esce da qui.»라고 못 박는다. | G36: 징계(procedimento disciplinare), 비밀유지 | H36: Giulia, Galileo, 원장(가상) | I36: P3 | J36: =턴_설계!$B$5
A37: 3 | B37: 9 | C37: 위기 | D37: Venerdì: e come ti fa sentire? | E37: 금요일: 기분이 어때요? | F37: (프레임) Montessori가 Giulia에게 감정을 되묻는다. Giulia는 «Prima, respira.»로 받아친다. Sofia가 Montessori의 화법을 흉내 낸다. | G37: 감정 표현, 되받기 화법 | H37: Giulia, Montessori, Sofia | J37: =턴_설계!$B$5
A38: 3 | B38: 10 | C38: 절정 | D38: Una notte senza letti | E38: 병상 없는 밤 | F38: 버스 사고와 폭염이 겹친 밤. 병상이 없어 복도까지 환자가 찬다. Giulia가 즉흥으로 일곱 명을 살리고 한 명을 잃는다. | G38: 대량 환자(maxi-emergenza), 우선순위, 명령형(imperativo) | H38: Giulia, Loredana(가상) | I38: S4 | J38: =턴_설계!$B$5
A39: 3 | B39: 11 | C39: 절정 | D39: Le dimissioni della dottoressa | E39: 의사의 사직 | F39: 징계 통보와 마지막 근무. 수첩을 덮고 사직서를 낸다. Loredana가 «Dottoressa, non se ne vada.» | G39: 사직서, 작별 | H39: Giulia, Loredana(가상), 원장(가상) | J39: =턴_설계!$B$5
A40: 3 | B40: 12 | C40: 결말·훅 | D40: Venerdì: una firma | E40: 금요일: 한 사람의 서명 | F40: (프레임) Giulia가 «La relazione di revisione sul contratto aveva una firma.»라고 말한다. Alessandro가 조용히 «Tocca a me.» | G40: 서명·책임 표현 | H40: Giulia, Alessandro, Sofia, Cesare | J40: =턴_설계!$B$5
A41: 4 | B41: 1 | C41: 발단 | D41: Venerdì: ho firmato io | E41: 금요일: 내가 서명했다 | F41: (프레임) Alessandro가 «Fammi vedere le carte.»를 습관처럼 하다가 «Ho firmato io.»라고 시작한다. Sofia가 숫자를 못 읽어 질문한다. | G41: 회계 어휘 도입 | H41: Alessandro, Sofia, Giulia, Cesare | J41: =턴_설계!$B$5
A42: 4 | B42: 2 | C42: 발단 | D42: Chiusura di bilancio | E42: 결산 마감 | F42: (과거) Conti Revisori의 결산 감사 마감 주간. 표본추출(campionamento)과 중요성(significatività). Alessandro의 정확성과 냉소. | G42: 감사 절차 어휘 | H42: Alessandro, Bassi(가상), 후배 감사인(가상) | J42: =턴_설계!$B$5
A43: 4 | B43: 3 | C43: 발단 | D43: Il cliente che paga bene | E43: 돈 잘 주는 고객 | F43: Gruppo Meridiano가 회사 수임료의 15%를 차지한다. 독립성과 감사인 순환 규정이 문제가 된다. 대표 파트너 Bassi는 '관계'를 강조한다. | G43: 독립성, 수임료 집중, 감사인 순환(d.lgs. 39/2010) | H43: Alessandro, Bassi(가상) | J43: =턴_설계!$B$5
A44: 4 | B44: 4 | C44: 전개 | D44: Questo non torna | E44: 이건 안 맞아 | F44: 특수관계자 대출이 룩셈부르크 지주회사로 흘러간 흔적. 은행 자료를 보내 준 Francesco가 «Segui il denaro.» | G44: 특수관계자 거래(parti correlate), 조세 회피처 | H44: Alessandro, Francesco | J44: =턴_설계!$B$5
A45: 4 | B45: 5 | C45: 전개 | D45: Venerdì: il padre di Alessandro | E45: 금요일: Alessandro의 아버지 | F45: (프레임) 정직한 장부를 지키다 해고된 아버지 이야기. «Mostrami i numeri e ti dirò chi sei.»의 기원. | G45: 가족 이야기, 과거 | H45: Alessandro, Sofia, Rosa | J45: =턴_설계!$B$5
A46: 4 | B46: 6 | C46: 미드포인트 | D46: La riunione dei soci | E46: 파트너 회의 | F46: Alessandro가 '한정 의견(giudizio con rilievi)'을 주장하자 파트너들이 승진과 고객 유지를 들어 설득한다. Alessandro는 리스크 위원회로 사안을 올린다. | G46: 의견 종류: senza rilievi, con rilievi, negativo, impossibilità di esprimere un giudizio | H46: Alessandro, Bassi(가상), 파트너들 | J46: =턴_설계!$B$5
A47: 4 | B47: 7 | C47: 위기 | D47: Il comitato rischi | E47: 리스크 위원회 | F47: GM의 변호사 서한이 도착한다(고객 측 변호사는 Marco의 옛 동료). 위원회는 '증거 불충분'으로 결정한다. | G47: 변호사 서한(lettera dei legali), 충분한 증거 | H47: Alessandro, 위원회(가상) | I47: P3 | J47: =턴_설계!$B$5
A48: 4 | B48: 8 | C48: 위기 | D48: Un pranzo ai Parioli | E48: 파리올리의 점심 | F48: Santoro가 Alessandro에게 점심을 산다. 정중한 위협과 제안: 파트너 승진과 개인 자문 계약. 뉴스레터 «Nuncius»를 쓰는 Galileo의 전화가 온다. | G48: 완곡한 압박, 접속법·조건법 | H48: Alessandro, Santoro(가상), Galileo | J48: =턴_설계!$B$5
A49: 4 | B49: 9 | C49: 위기 | D49: Venerdì: e hai firmato? | E49: 금요일: 서명했어요? | F49: (프레임) Sofia가 묻고 Alessandro는 «Aspetta.»라고 한다. Cesare가 «Tutti, prima o poi, firmiamo qualcosa.»라고 말하고 Giulia가 눈을 감는다. | G49: 재촉·회피 | H49: Alessandro, Sofia, Cesare, Giulia | J49: =턴_설계!$B$5
A50: 4 | B50: 10 | C50: 절정 | D50: La firma | E50: 서명 | F50: Alessandro가 '적정(senza rilievi)' 의견서에 서명한다. 서명 후 그는 복사본 USB를 챙긴다. | G50: 서명, 감사보고서(relazione di revisione), 책임 | H50: Alessandro, Bassi(가상) | J50: =턴_설계!$B$5
A51: 4 | B51: 11 | C51: 절정 | D51: Dopo la firma | E51: 서명 이후 | F51: 그 의견서로 병원 외주 계약이 확정되고(3부의 계약) 구조조정 컨설팅이 시작된다는 통보를 받는다. Alessandro는 사직하고 다시는 서명하지 않겠다고 다짐한다. | G51: 결과·책임, 사직 | H51: Alessandro, Bassi(가상), Chiara | J51: =턴_설계!$B$5
A52: 4 | B52: 12 | C52: 결말·훅 | D52: Venerdì: la lista di Chiara | E52: 금요일: Chiara의 명단 | F52: (프레임) Alessandro가 USB를 꺼내지 않은 채 식탁에 놓고, Chiara가 «La lista la facevo io.»라고 말한다. | G52: 고백 | H52: Alessandro, Chiara, Sofia, Rosa | J52: =턴_설계!$B$5
A53: 5 | B53: 1 | C53: 발단 | D53: Venerdì: in una matrice | E53: 금요일: 매트릭스로 | F53: (프레임) Chiara가 «Mettiamolo in una matrice.»로 시작하다 Sofia에게 제지당한다. | G53: 경영 어휘 도입, 쉬운 말로 바꾸기 | H53: Chiara, Sofia, Cesare | J53: =턴_설계!$B$5
A54: 5 | B54: 2 | C54: 발단 | D54: Zenit, 32° piano | E54: Zenit, 32층 | F54: (과거) EUR 오피스 타워의 컨설팅 회사 문화: up-or-out, 야근, 영어가 섞인 이탈리아어(itanglese). Chiara의 초고속 승진. | G54: allineare, scalabile, impatto, stakeholder | H54: Chiara, 파트너(가상) | J54: =턴_설계!$B$5
A55: 5 | B55: 3 | C55: 발단 | D55: La bottega dei Ruggeri | E55: Ruggeri 가족의 공방 | F55: 영세 가족 제조업체 컨설팅. Chiara의 '규모 키우기' 권고가 현실과 맞지 않아 실패한다. 생산성은 조언이 아니라 구조의 문제임을 처음 본다. | G55: 영세·가족 기업, 생산성, 규모의 경제 | H55: Chiara, Ruggeri(가상) | I55: E2 | J55: =턴_설계!$B$5
A56: 5 | B56: 4 | C56: 전개 | D56: Progetto Icaro | E56: 이카로 프로젝트 | F56: GM이 Zenit에 '비용 18% 절감'을 의뢰한다. 킥오프 회의. | G56: 프로젝트 관리, 목표, 절감 | H56: Chiara, 파트너(가상), GM 임원(가상) | J56: =턴_설계!$B$5
A57: 5 | B57: 5 | C57: 전개 | D57: Venerdì: un Excel | E57: 금요일: 엑셀 한 장 | F57: (프레임) Chiara가 «Io non licenziavo nessuno; spostavo celle.»라고 말한다. Sofia가 «E quante celle?» | G57: 질문·죄책 표현 | H57: Chiara, Sofia, Alessandro | J57: =턴_설계!$B$5
A58: 5 | B58: 6 | C58: 미드포인트 | D58: La cella C47 | E58: C47 셀 | F58: 모델이 완성되고 승인이 난다. 셀 하나가 412개 일자리다. 팀은 스푸만테를 딴다. | G58: 모델, 시나리오, 인원 감축 | H58: Chiara, 팀(가상) | I58: S1 | J58: =턴_설계!$B$5
A59: 5 | B59: 7 | C59: 위기 | D59: Il tavolo della trattativa | E59: 협상 테이블 | F59: 집단해고 협의 절차. 노조 대표 Paolo가 «Dietro ogni cella c'è una persona.» | G59: 집단해고(licenziamento collettivo, legge 223/1991), 노조 협의 45일 + 행정 단계 30일, 노조 대표(RSU) | H59: Chiara, Paolo, 노무 담당(가상) | I59: S1 | J59: =턴_설계!$B$5
A60: 5 | B60: 8 | C60: 위기 | D60: La mail sbagliata | E60: 잘못 보낸 이메일 | F60: Chiara가 이름이 든 파일을 잘못 보낸다. 기간제·청년이 먼저 잘려 있다. 번아웃 상담에서 Montessori를 만난다. | G60: 기간제 계약, 청년 우선 해고, 죄책감 | H60: Chiara, Montessori | I60: S1 | J60: =턴_설계!$B$5
A61: 5 | B61: 9 | C61: 위기 | D61: Venerdì: quattrocentododici | E61: 금요일: 412 | F61: (프레임) «Quattrocentododici.» Sofia가 말을 잃고 Cesare가 «Almeno lo dice senza slide.» | G61: 숫자 낭독 | H61: Chiara, Sofia, Cesare | J61: =턴_설계!$B$5
A62: 5 | B62: 10 | C62: 절정 | D62: Lo sciopero | E62: 파업 | F62: 파업이 벌어지고 Paolo가 해고되어 블랙리스트에 오른다. Chiara는 유리창 너머로 그것을 본다. | G62: 파업권(헌법 제40조), 해고, 블랙리스트 | H62: Chiara, Paolo | I62: S1 | J62: =턴_설계!$B$5
A63: 5 | B63: 11 | C63: 절정 | D63: L'ultima riunione | E63: 마지막 회의 | F63: 보너스 지급 회의. Chiara가 '이카로 2'를 거절하고 사직한다. | G63: 보너스, 거절, 사직 | H63: Chiara, 파트너(가상) | J63: =턴_설계!$B$5
A64: 5 | B64: 12 | C64: 결말·훅 | D64: Venerdì: un martedì al Quarticciolo | E64: 금요일: 콰르티촐로의 화요일 | F64: (프레임) 네 명이 같은 강당에 모이게 된 화요일을 Rosa가 설명하며 6부를 예고한다. | G64: 다음 이야기 예고 | H64: Chiara, Rosa, Marco, Giulia, Alessandro | J64: =턴_설계!$B$5
A65: 6 | B65: 1 | C65: 발단 | D65: Un martedì al Quarticciolo | E65: 콰르티촐로의 화요일 | F65: 네 사람이 각자 다른 이유로 같은 세입자 총회에 도착한다. 옛 공공주택 매각분을 사들인 민간 블록이다. 손녀 Marina(가상)와 23세 세입자 Sofia가 맞이한다. | G65: 총회 공고, 자기소개 | H65: Marco, Giulia, Alessandro, Chiara, Marina(가상), Sofia | I65: E1 | J65: =턴_설계!$B$5
A66: 6 | B66: 2 | C66: 발단 | D66: Quattro sconosciuti | E66: 네 명의 낯선 사람 | F66: 서로 아는 척하지 않는다. Marco와 Alessandro는 서로의 명함 «Ferrari & Colombo», «Conti Revisori»에서 흠칫한다. | G66: 긴장 대화, Lei | H66: Marco, Giulia, Alessandro, Chiara, Sofia | J66: =턴_설계!$B$5
A67: 6 | B67: 3 | C67: 발단 | D67: Il lotto quattordici | E67: 14번 동 | F67: 건물을 돌아본다. 22가구, 물이 새는 벽, 동네 진료소 폐쇄. 이웃 Paolo와 '계단 반장' Garibaldi가 안내한다. | G67: 건물·거주 표현 | H67: Marco, Giulia, Alessandro, Chiara, Paolo, Garibaldi, Sofia | I67: E1 | J67: =턴_설계!$B$5
A68: 6 | B68: 4 | C68: 전개 | D68: La notte delle scale | E68: 계단의 밤 | F68: 새벽 퇴거 집행 소문에 함께 밤샘한다. Rosa의 음식과 Cesare의 커피 불평. 처음으로 조금씩 속내를 꺼낸다. | G68: 밤샘 대화, 위로 | H68: Marco, Giulia, Alessandro, Chiara, Rosa, Cesare, Garibaldi | J68: =턴_설계!$B$5
A69: 6 | B69: 5 | C69: 전개 | D69: Le carte di Alessandro | E69: Alessandro의 서류 | F69: Alessandro가 USB를 꺼내 Fondo Cardinale – Gruppo Meridiano – Meridiano Salute의 연결을 보여 준다. 변호사가 필요하다. | G69: 서류 브리핑, 지분 구조 | H69: Alessandro, Marco, Sofia, Machiavelli | J69: =턴_설계!$B$5
A70: 6 | B70: 6 | C70: 미드포인트 | D70: Uno stesso nome | E70: 같은 이름 | F70: Marco의 퇴거, Giulia의 외주, Alessandro의 감사, Chiara의 구조조정이 모두 Gruppo Meridiano였다. 각자 «il mio cliente / il mio contratto / la mia relazione / il mio piano.» | G70: 책임 표현, 접속법 | H70: Marco, Giulia, Alessandro, Chiara | I70: E1 | J70: =턴_설계!$B$5
A71: 6 | B71: 7 | C71: 위기 | D71: Rimproveri | E71: 서로에 대한 비난 | F71: 공모라고 서로를 몰아세운다. Marco가 나가 버리고 Giulia가 막아선다. | G71: 다툼, 비난·사과 | H71: Marco, Giulia, Alessandro, Chiara, Sofia | J71: =턴_설계!$B$5
A72: 6 | B72: 8 | C72: 위기 | D72: Ora zero | E72: 영시 | F72: 퇴거 집행 날 새벽. 서로의 전문성을 처음 합친다: Marco는 집행 정지 신청, Alessandro는 서류, Chiara는 동선, Giulia는 취약계층 진단서. Galileo가 기록하고 Gramsci가 서류 위치를 알려 준다. | G72: 집행 정지(sospensione dell'esecuzione), 진단서 | H72: Marco, Giulia, Alessandro, Chiara, Galileo, Gramsci, Garibaldi | I72: E1·S2 | J72: =턴_설계!$B$5
A73: 6 | B73: 9 | C73: 위기 | D73: La prima sospensione | E73: 첫 정지 | F73: 법원이 집행을 정지한다. Dante의 서툰 첫 연설이 군중을 울리고 Montessori가 아이들을 달랜다. Fatima 가족이 인사한다. | G73: 안도·감사 표현 | H73: Marco, Giulia, Alessandro, Chiara, Dante, Montessori, Sofia, Fatima(가상) | I73: S2·E1 | J73: =턴_설계!$B$5
A74: 6 | B74: 10 | C74: 절정 | D74: Un locale a Testaccio | E74: 테스타초의 가게 | F74: 사무실 자리를 찾는다. 소규모 집주인이 월세를 낮춰 주고 Rosa의 트라토리아가 1층에서 다시 문을 연다. Francesco가 계좌 도움을 자청한다. | G74: 임대 협상, 협약 임대료(canone concordato), 소규모 임대인 | H74: Marco, Giulia, Alessandro, Chiara, Rosa, Francesco | I74: E1 | J74: =턴_설계!$B$5
A75: 6 | B75: 11 | C75: 절정 | D75: Le regole del tavolo | E75: 식탁의 규칙 | F75: 규칙을 정한다: 가난한 사람에게는 수임료 없음, 금요일마다 한 명씩 과거를 이야기함. Sofia가 «Posso restare?» Cesare는 '청하지 않은 고문', Machiavelli는 '청하지 않은 전략가'를 자처한다. | G75: 규칙, 약속 표현 | H75: 전원 | I75: S1 | J75: =턴_설계!$B$5
A76: 6 | B76: 12 | C76: 결말·훅 | D76: L'insegna | E76: 간판 | F76: 간판이 걸린다. Rosa가 «Domani, alle cinque.» 원이 닫히며 1부 1화로 이어진다. | G76: 시간 표현, 마무리 | H76: 전원 | J76: =턴_설계!$B$5
A77: 7 | B77: 1 | C77: 발단 | D77: Un anno dopo | E77: 1년 후 | F77: 사무소가 커졌다. Rosa가 팀 이름을 호명하며 역할을 소개한다: Garibaldi 로지스틱스, Gramsci 출처, Galileo 공론화·검증, Montessori 상담, Paolo 현장, Dante 글, Francesco 자금, Machiavelli 전략. | G77: 역할·업무 분담 | H77: 전원 | J77: =턴_설계!$B$5
A78: 7 | B78: 2 | C78: 발단 | D78: La fila sulle scale | E78: 계단 위의 줄 | F78: 의뢰인 줄이 계단까지 이어진다. 접수·분류 창구(sportello)를 세우고 Chiara의 매트릭스가 처음으로 쓸모 있어진다. | G78: 접수·분류, 순서 | H78: Chiara, Sofia, Garibaldi, Rosa | I78: S1·E1 | J78: =턴_설계!$B$5
A79: 7 | B79: 3 | C79: 발단 | D79: Il tempo che ha punito la vittima | E79: 피해자를 벌한 시간 | F79: 성폭력 피해자 사건. 재판이 늘어지는 동안 공소시효가 다가오고, 폭력·위협 입증을 중심으로 한 현행 조항 때문에 피해자가 다시 심문대에 선다. Marco와 Montessori가 피해자를 돕는다. '동의(consenso)' 기준을 명문화하자는 쪽과 절차부터 고치자는 쪽이 사무실 안에서도 갈린다. | G79: 형법 제609-bis조(성폭력), 공소시효(prescrizione), '자유롭고 현재적인 동의' 개정 논의 | H79: Marco, Montessori, Alessandro, Galileo | I79: N4 | J79: =턴_설계!$B$5
A80: 7 | B80: 4 | C80: 전개 | D80: Senza documenti | E80: 서류 없는 사람들 | F80: Karim이 체류허가(permesso di soggiorno) 갱신과 축소된 특별보호(protezione speciale) 문제를 들고 온다. Paolo는 노동, Giulia는 의료 접근을 이야기하고 수용의 한계를 두고 의견이 갈린다. | G80: permesso di soggiorno, protezione speciale, 이민 쿼터(decreto flussi) | H80: Marco, Paolo, Giulia, Karim(가상) | I80: S2 | J80: =턴_설계!$B$5
A81: 7 | B81: 5 | C81: 전개 | D81: La segnalazione di Francesco | E81: Francesco의 제보 | F81: 전 은행 지점장이 내부 자료를 들고 나온다. 내부고발자 보호법과 신고 채널을 검토한다. | G81: 내부고발자 보호(d.lgs. 24/2023), 내부 신고 채널, ANAC 외부 신고 | H81: Francesco, Marco, Alessandro, Galileo | I81: P3 | J81: =턴_설계!$B$5
A82: 7 | B82: 6 | C82: 미드포인트 | D82: Il fascicolo | E82: 사건 파일 | F82: Alessandro·Francesco의 자금 경로 + Gramsci의 공개 출처 + Giulia의 사망 사례. Marco가 로마 검찰(Procura della Repubblica)에 고발장(esposto-denuncia)을 쓰고, 피해 주민 단체의 민사 당사자 참여(parte civile)를 준비한다. | G82: esposto, denuncia, parte civile, Procura, ANAC | H82: Marco, Alessandro, Francesco, Gramsci, Giulia | I82: P3 | J82: =턴_설계!$B$5
A83: 7 | B83: 7 | C83: 위기 | D83: Rappresaglie | E83: 보복 | F83: 명예훼손 고소(querela per diffamazione)가 Galileo에게, 위생 점검(NAS)이 Rosa의 트라토리아에 날아온다. 익명의 협박이 이어진다. | G83: 명예훼손(형법 제595조), 괴롭히기 소송(querela temeraria·SLAPP), 협박 | H83: Galileo, Rosa, Marco, Garibaldi | I83: P3 | J83: =턴_설계!$B$5
A84: 7 | B84: 8 | C84: 위기 | D84: Il microfono nella lampada | E84: 전등 속 마이크 | F84: Gramsci가 도청기를 찾아낸다 — 평생 정치경찰에게 감시당했던 사람의 감각이다. 되쏘자는 Gramsci와 합법 경로만 쓰자는 Marco가 충돌한다. | G84: 사용할 수 없는 증거(prove inutilizzabili, 형사소송법 제191조), 통신의 비밀(헌법 제15조) | H84: Gramsci, Marco, Garibaldi, Montessori | I84: P3 | J84: =턴_설계!$B$5
A85: 7 | B85: 9 | C85: 위기 | D85: La guardia del quartiere | E85: 동네의 보초 | F85: 사무소 앞에 이웃들이 교대로 서서 지킨다. Paolo가 조직하고 Dante가 벽에 문구를 쓴다. | G85: 연대·조직 표현 | H85: Paolo, Dante, Rosa, Garibaldi | J85: =턴_설계!$B$5
A86: 7 | B86: 10 | C86: 절정 | D86: Il decreto del GIP | E86: 예비수사판사의 결정 | F86: 로마의 예비수사판사(GIP)가 압수수색과 수사 연장을 승인하고, 검찰이 GM 임원 세 명에게 피의자 통지(avviso di garanzia)를 보낸다. 사무실이 환호한다. | G86: GIP, avviso di garanzia, interrogatorio | H86: Marco, Alessandro, Galileo, Francesco | I86: P3 | J86: =턴_설계!$B$5
A87: 7 | B87: 11 | C87: 절정 | D87: La legge che viene | E87: 다가오는 법 | F87: GM과 가까운 의원들이 공직자 범죄를 축소하고 도청을 제한하는 법안을 낸다. 통과되면 임원들의 혐의 일부가 소급해 사라진다(형법 제2조 2항). Cesare: «Le sentenze si vincono; le leggi si scrivono.» | G87: 입법 발의, 범죄 폐지의 소급(abolitio criminis) | H87: Cesare, Marco, Chiara, Paolo, Machiavelli | I87: P1·P3 | J87: =턴_설계!$B$5
A88: 7 | B88: 12 | C88: 결말·훅 | D88: Una sedia a San Giovanni | E88: 산 조반니의 의자 | F88: Paolo가 Piazza San Giovanni에서 모이자고 제안한다. Rosa가 식탁의 의자를 든다. Marco가 «Dobbiamo cambiare la legge.» | G88: 결단, 제안 | H88: 전원 | I88: P1 | J88: =턴_설계!$B$5
A89: 8 | B89: 1 | C89: 발단 | D89: La piazza di San Giovanni | E89: 산 조반니 광장의 집회 | F89: 사무소를 거쳐 간 의뢰인 수백 명이 광장에 모인다. Paolo와 Garibaldi가 조직하고, 집회 신고를 두고 Marco와 Garibaldi가 실랑이한다(«천 명을 이끌고 시칠리아에 상륙할 때 신고 같은 건 안 했소!»). | G89: 공공장소 집회는 3일 전 경찰청장(Questore)에게 사전 통지(헌법 제17조, TULPS 제18조) | H89: Paolo, Garibaldi, Marco | I89: E1·S2 | J89: =턴_설계!$B$5
A90: 8 | B90: 2 | C90: 발단 | D90: Dal caso alla legge | E90: 사건에서 법으로 | F90: Marco가 수십 건의 사건에서 같은 조항이 반복되는 것을 짚는다. 법을 바꿔야 한다. Machiavelli가 '가장 빠른 길과 가장 오래가는 길'을 구분한다. | G90: 법을 바꾸는 길: 정부 법안(disegno di legge), 의원 발의(proposta di legge), 국민 발의(5만 서명), 폐지 국민투표(50만 서명) | H90: Marco, Sofia, Machiavelli | J90: =턴_설계!$B$5
A91: 8 | B91: 3 | C91: 발단 | D91: Cinquecentomila firme | E91: 50만 서명 | F91: 7부의 '공직자 범죄 축소법'을 없애는 폐지 국민투표 서명 운동. Rosa의 트라토리아가 서명 접수처가 되고 온라인 서명도 받는다. | G91: 폐지 국민투표 50만 서명(헌법 제75조, legge 352/1970), 전자 서명 플랫폼 | H91: Rosa, Paolo, Sofia | I91: P3·S1 | J91: =턴_설계!$B$5
A92: 8 | B92: 4 | C92: 전환점 | D92: Il quorum | E92: 정족수 | F92: 헌법재판소가 국민투표를 허용하지만, 투표율이 유권자 과반에 못 미쳐 무효가 된다. 개표 방송 앞의 시민들. | G92: 폐지 국민투표는 유권자 과반 투표 시에만 유효(헌법 제75조), 헌법재판소 허용 심사(ammissibilità) | H92: Marco, Galileo, Machiavelli | J92: =턴_설계!$B$5
A93: 8 | B93: 5 | C93: 미드포인트 | D93: Nasce un partito | E93: 정당의 탄생 | F93: 이름을 정한다: «Casa Comune» — Rosa의 식탁에서 나온 이름. 공증인 앞에서 설립 문서와 정관에 서명한다. | G93: 정당은 법인격 없는 사단(헌법 제49조, 민법 제36조), 국가 정당 등록부 등록(d.l. 149/2013) | H93: Rosa, Dante, Marco | J93: =턴_설계!$B$5
A94: 8 | B94: 6 | C94: 위기 | D94: Lo statuto | E94: 정관 | F94: 당원 자격, 윤리 강령, 후보 경선 방식을 둘러싼 토론. Chiara의 조직도 vs Paolo의 총회. | G94: 등록 정당 정관의 민주적 절차 요건(d.l. 149/2013 제3조), 헌법 제49조 '민주적 방법' | H94: Chiara, Paolo, Machiavelli | I94: P1 | J94: =턴_설계!$B$5
A95: 8 | B95: 7 | C95: 위기 | D95: Il denaro pulito | E95: 깨끗한 돈 | F95: 소액 후원 원칙과 회계 공개. 은행이 계좌 개설을 미룬다. Francesco의 노하우. | G95: 정치 후원 공개 의무(legge 3/2019), 2x1000 기부, 정당 회계 감독위원회(Commissione di garanzia) | H95: Alessandro, Francesco | J95: =턴_설계!$B$5
A96: 8 | B96: 8 | C96: 위기 | D96: Le candidature | E96: 후보 명부 | F96: Alessandro는 로마 시장 후보, Giulia는 라치오 주의회 명부 1번. 명부 순서를 둘러싼 갈등. | G96: 성별 균형(명부 내 한 성별 2/3 초과 금지·선호투표 성별 교차), 명부 제출 서명 | H96: Alessandro, Giulia, Sofia | I96: N4·S1 | J96: =턴_설계!$B$5
A97: 8 | B97: 9 | C97: 위기 | D97: La campagna nei quartieri | E97: 골목길 캠페인 | F97: Rosa의 트라토리아에서 시작해 Quarticciolo·Tor Bella Monaca 골목을 도는 유세. Dante의 첫 연설 문구. | G97: 선거운동 규칙, 방송 균등 노출(par condicio, legge 28/2000), AGCOM 감독 | H97: Dante, Rosa, Garibaldi | I97: E1·E2·S2 | J97: =턴_설계!$B$5
A98: 8 | B98: 10 | C98: 절정 | D98: L'attacco della stampa | E98: 언론의 공격 | F98: 왜곡 기사가 나온다. Galileo가 반박하고 정정을 청구한다. | G98: 정정권(legge 47/1948 제8조), AGCOM 제소 | H98: Galileo, Marco | J98: =턴_설계!$B$5
A99: 8 | B99: 11 | C99: 절정 | D99: Il silenzio elettorale | E99: 선거 침묵 | F99: 선거 전날, 마지막 유세의 유혹을 접고 정적. Montessori의 되받기가 처음으로 위로가 된다. | G99: 선거 전날·당일 선거운동 금지(legge 212/1956), 마지막 15일 여론조사 공표 금지(legge 28/2000) | H99: Montessori, Chiara | J99: =턴_설계!$B$5
A100: 8 | B100: 12 | C100: 결말·훅 | D100: La notte dello spoglio | E100: 개표의 밤 | F100: Assemblea Capitolina 48석 중 5석, 라치오 주의회 진출 (가상 수치). 시장 후보 Alessandro는 3위로 결선에 오르지 못한다. | G100: 시장 직선·결선투표(ballottaggio), 시장 연합 과반 보너스, 명부 문턱 3% | H100: 전원 | J100: =턴_설계!$B$5
A101: 9 | B101: 1 | C101: 발단 | D101: L'insediamento | E101: 시의회 개원 | F101: 2주 뒤 결선투표에서 다른 당 후보가 시장이 된다. 낙선한 시장 후보 Alessandro는 규정에 따라 시의원이 되어 첫 회의에서 자리에 앉는다. | G101: 시장 직선·결선(TUEL 제72조), 낙선 시장 후보의 의석(TUEL 제73조, 확인) | H101: Alessandro, Marco | J101: =턴_설계!$B$5
...

Sheet 복선_회수
A1: 복선 설치와 회수 (Setup → Payoff)
A2: 설치 부와 회수 부의 간격(부 수)은 수식으로 계산됩니다. 간격이 클수록 오래 기다린 복선이라 낭독 시 기억에 남습니다.
A4: No | B4: 복선(설치) | C4: 유형 | D4: 설치 부 | E4: 설치 위치 | F4: 회수 부 | G4: 간격(부) | H4: 회수 위치와 효과 | I4: 관련 인물
A5: 1 | B5: Cesare의 «Questo sarà il mio ultimo inverno» 반복 | C5: 대사 | D5: 1 | E5: 1부 1화 | F5: 11 | G5: =F5-D5 | H5: 11부 12화 — 양치기 소년 개그가 진짜 (두 번째) 죽음이 되는 낙차 | I5: Cesare
A6: 2 | B6: Cesare가 Sofia에게 우산을 물려준다고 말한다 | C6: 소품 | D6: 1 | E6: 1부 1화 | F6: 13 | G6: =F6-D6 | H6: 13부 2화 — 유언장에서 우산이 진짜 유산으로 돌아옴 | I6: Cesare, Sofia
A7: 3 | B7: Cesare의 부은 발목·숨참 («Sono i calzari.») | C7: 설정 | D7: 3 | E7: 3부 1·5화 | F7: 11 | G7: =F7-D7 | H7: 11부 4~6화 — Giulia가 진단을 알고도 침묵한 이유가 드러남 | I7: Giulia, Cesare
A8: 4 | B8: Cesare의 최고 칭찬 «Niente male.» | C8: 대사 | D8: 1 | E8: 1부 7화(Dante에게 1회) | F8: 11 | G8: =F8-D8 | H8: 11부 12화 — Sofia에게 처음이자 마지막 칭찬, 브뤼셀 승리 직후라 더 무겁다 | I8: Cesare, Sofia
A9: 5 | B9: Sofia의 1차 폭발 | C9: 사건 | D9: 1 | E9: 1부 6화 | F9: 9 | G9: =F9-D9 | H9: 9부 6화 — 몰라서 화내던 Sofia → 알아서 화내는 Sofia | I9: Sofia
A10: 6 | B10: Sofia의 Lei (Cesare에게) | C10: 호칭 | D10: 1 | E10: 1부 1화 | F10: 12 | G10: =F10-D10 | H10: 12부 1화 — 조사에서 처음 tu — 호칭 전환이 곧 애도 | I10: Sofia, Cesare
A11: 7 | B11: Gramsci의 카드 #1과 «Cercalo tu.» | C11: 대사 | D11: 1 | E11: 1부 2화 | F11: 13 | G11: =F11-D11 | H11: 13부 10화 — 끝까지 결론을 말하지 않던 그가 처음 답을 말함 | I11: Gramsci, Sofia
A12: 8 | B12: Marco의 «갱신 거절(diniego di rinnovo)» 조항 | C12: 사건 | D12: 2 | E12: 2부 6화 | F12: 11 | G12: =F12-D12 | H12: 11부 3화 — 자기가 쓰던 조항 전략을 국정에서 봉쇄 | I12: Marco
A13: 9 | B13: Alessandro의 «Questo non torna» | C13: 대사 | D13: 2 | E13: 2부 4화 | F13: 4 | G13: =F13-D13 | H13: 4부 4화 — 감사인의 눈이 처음 이상을 발견한 순간의 원점 | I13: Alessandro
A14: 10 | B14: Alessandro의 복사본 USB | C14: 소품 | D14: 4 | E14: 4부 10화 | F14: 7 | G14: =F14-D14 | H14: 7부 5~6화 — 서명의 죄가 고발의 증거로 바뀜 | I14: Alessandro, Marco
A15: 11 | B15: Alessandro의 «다시는 서명하지 않는다» | C15: 인물 | D15: 4 | E15: 4부 11화 | F15: 11 | G15: =F15-D15 | H15: 11부 10화 — «Io firmo solo ciò che ho verificato.» — 브뤼셀 합의문 서명으로 회수 | I15: Alessandro
A16: 12 | B16: Chiara의 C47 셀 | C16: 소품 | D16: 5 | E16: 5부 6화 | F16: 11 | G16: =F16-D16 | H16: 11부 9화 — 사람을 지우던 셀이 해고 없는 통합 모델로 | I16: Chiara
... A32: 28 | B32: Galileo의 «Mi servono due fonti indipendenti» | C32: 대사 | D32: 1 | E32: 1부 11화 | F32: 9 | G32: =F32-D32 | H32: 9부 8화 — 폭로 기사에서 두 개의 독립 출처를 갖추는 장면 | I32: Galileo, Gramsci
B34: 평균 간격(부) | G34: =AVERAGE(G5:G32)
B35: 가장 긴 복선(부) | G35: =MAX(G5:G32)
B36: 복선 개수 | G36: =COUNTA(B5:B32)

Sheet 현안_배치
A1: 이탈리아 현안 18개 배치표
A2: 현재 이탈리아의 쟁점을 이야기 곳곳에 녹이는 계획. 현실의 정당·정치인·참사 희생자는 특정하지 않고 가상 설정으로 각색하며, 제도와 통계만 현실 기준으로 쓴다.
A4: ID | B4: 분야 | C4: 현안 | D4: 이탈리아어 키워드 | E4: 이야기 속 가상 설정 | F4: 주요 배치 (전용 화) | G4: 곁가지 배치 | H4: 주요 인물 | I4: 권한 소재 | J4: 관련 제도·법 | K4: 낭독 어휘 | L4: 균형·민감도 유의 | M4: 현실 기준값·확인
A5: P1 | B5: 정치 | C5: 정부 불안정과 연정 협상 | D5: governo, fiducia, maggioranza, rimpasto, crisi di governo | E5: 어떤 정당도 과반이 안 되는 의회. 법안마다 협상 비용이 든다. Casa Comune도 연립 정부로 표결마다 파트너의 이탈을 걱정해야 한다. 공화국 역사상 짧은 정부 수명이 '이탈리아식 불안정'으로 대사에 등장한다. | F5: 9부 5화 불편한 동맹, 10부 8화 탐색 위임, 12부 7화 모자란 불신임안 | G5: 7부 11화, 8부 6화(왜 새 정당인가: 거대 정당 피로), 11부 1화, 12부 9화 | H5: Chiara, Marco, Paolo, Machiavelli | I5: 하원·상원·시의회 | J5: 헌법 제88·92·94조, 연정 협약 | K5: maggioranza, fiducia, crisi di governo, rimpasto, voto di sfiducia | L5: 특정 실존 정당·인물을 비난하는 대사 금지. 가상 정당(CC·UCN·PPS·IU·TA·TB)으로만. | M5: 현실은 2022년 이후 우파 연립 다수 정부(2026-09 기준). 이야기에는 쓰지 않음
A6: P2 | B6: 정치 | C6: 남북 격차와 차등 자치 | D6: autonomia differenziata, LEP, Mezzogiorno, questione meridionale, residuo fiscale | E6: 북부 주 연합 TB가 지지의 대가로 차등 자치(더 많은 권한과 세수 이양) 가속을 요구한다. 남부의 필수 공공서비스 수준(LEP)은 어떻게 보장하나. 나라를 통일한 Garibaldi가 가장 예민하게 반응한다. | F6: 10부 11화 연정 협상 | G6: 10부 3화(TV 토론 공격), 12부 7화(불신임안에서 TB의 기권) | H6: Garibaldi, Marco, Paolo, Chiara | I6: 의회, 헌법재판소, 주 | J6: 헌법 제116조 3항·제117조, legge 86/2024(차등 자치), 헌법재판소 2024년 판결 192호 | K6: autonomia differenziata, LEP, perequazione, Mezzogiorno, coesione | L6: 가장 민감. 북부의 효율 논거와 남부의 형평 논거를 각 인물이 나눠 말하게 하고 결론은 열어 둔다(Marco는 헌법 우려, Garibaldi는 통일의 가치, Chiara는 현실 협상). | M6: 헌법재판소가 2024년 legge 86/2024 일부를 위헌 판단. 이후 입법·협상 진행 상황은 반영 전 확인
A7: P3 | B7: 정치 | C7: 사법 개혁과 정치적 대립 | D7: separazione delle carriere, CSM, prescrizione, intercettazioni, lentezza della giustizia | E7: 사법 개혁과 도청 제한을 둘러싼 대립 속에 스캔들 수사가 표류한다. 재판 지연과 공소시효가 사무소의 고발을 무력하게 만든다. | F7: 7부(고발·GIP 결정·보복), 9부 9화 고발장 | G7: 2부 8화(재판), 3부(징계·외주), 4부 7화, 8부 3~4화(국민투표), 10부 11화(협상 조건), 12부 7화 | H7: Marco, Galileo, Gramsci | I7: 의회, 사법 최고회의(CSM), 사법부 | J7: 헌법 제104~112조, 형사소송법, 형법 제2조 | K7: CSM, magistratura, prescrizione, intercettazioni, abolitio criminis | L7: 여야 모두가 사법부를 압박한다는 비판을 각각 담는다. 실제 재판 결과를 단정하지 않는다. | M7: 검사·판사 경력 분리 개헌은 2026년 3월 국민투표에서 부결(반대 약 53.6%, 투표율 약 58.9%). 이후 논의는 반영 전 확인
A8: E1 | B8: 경제 | C8: 주거난과 단기 관광 임대 | D8: emergenza abitativa, affitti brevi, sfratto, canone concordato, overtourism | E8: 로마 중심가 월세가 임금보다 빨리 오르고 단기 관광 임대가 동네를 비운다. 소규모 임대인의 입장(Rosa의 친구)도 대사에 넣는다. | F8: 2부 6화(조항 설계), 6부 1·3·8·10화(Quarticciolo), 9부 6화(임대료 보조 삭감·단기임대 조항), 11부 2·3화 | G8: 1부 1·2·11·12화(Fatima), 8부 1·9화, 13부 | H8: Rosa, Sofia, Alessandro, Marco | I8: 국가(임대차 기본법·세제), 주(관광·주거 정책), 시(도시계획·인허가) | J8: legge 431/1998, 단기임대 CIN 코드(d.l. 145/2023), 비귀책 체납 기금 | K8: affitti brevi, sfratto, canone, piccolo proprietario, CIN | L8: 임차인만 피해자로 그리지 않는다. 소규모 임대인·대형 보유자(펀드)를 구분해서 말한다. | M8: 단기임대 규제와 로마 시 조치의 세부는 반영 전 확인
A9: E2 | B9: 경제 | C9: 저생산성과 영세·가족 기업 구조 | D9: microimpresa, PMI, produttività, impresa familiare, passaggio generazionale | E9: Chiara가 컨설팅한 규모의 경제 없는 가족 공방들: 해고 없이 살릴 길을 못 찾았던 과거. 11부에서 영세 기업 통합·R&D 전환 사업을 설계한다. | F9: 5부 3화 Ruggeri 공방 | G9: 8부 9화(골목 상권), 11부 9화, 13부 | H9: Chiara, Rosa, Paolo | I9: 국가·주 | J9: R&D 세액공제, 기업 지원 제도(확인), 집단해고법 | K9: produttività, scalare, aggregazione, ricerca e sviluppo | L9: '영세 기업이 문제'라는 식의 낙인 대신 구조 문제로 설명한다. | M9: 통계 수치는 반영 전 확인
A10: E3 | B10: 경제 | C10: 국가 부채와 재정 건전성 | D10: debito pubblico, spread, deficit, procedura per deficit eccessivo, pensioni | E10: GDP의 130%를 넘는 부채, 과도한 재정적자 절차, 연금 지출 증가 사이의 줄타기. Alessandro가 숫자로 설명하고 Sofia가 되묻는다. | F10: 11부 10화(EU 재정규칙), 12부 11~12화(예산안) | G10: 12부 3화, 13부 7화 | H10: Alessandro, Cesare(메모), Francesco | I10: 국가·EU | J10: EU 재정규칙과 중기 재정구조계획, TFUE 제126조, 헌법 제81조 | K10: debito, deficit, spread, sostenibilità, pensioni | L10: 긴축 vs 확대 양쪽 논거를 모두 숫자로 제시한다. | M10: 부채 GDP 대비 137.1%(2025년 말, ISTAT), 2025년 적자 3.1%로 과도한 재정적자 절차 조기 졸업 불발
A11: S1 | B11: 사회 | C11: 청년 고용 불안과 두뇌 유출 | D11: tirocinio, contratto a termine, NEET, salario minimo, fuga dei cervelli | E11: 무급·저임금 인턴과 기간제 계약으로 청년의 자립이 늦어지고, 많은 청년이 해외로 떠난다. 법정 최저임금이 없는 나라에서 Sofia가 그 당사자이자 질문자다. | F11: 11부 6화, 13부 5·6화 | G11: 1부 5·6화(Davide), 5부(Chiara의 인력 감축), 7부 2화, 8부, 10부 3화 | H11: Sofia, Paolo, Chiara | I11: 국가(노동법)·단체협약·주(인턴 규율) | J11: 사회적 대화, 단체협약, 인턴 규율(주별 지침) | K11: tirocinio, contratto, salario minimo, precariato, NEET | L11: 청년 vs 기성세대 구도로 몰지 않는다(Paolo도 Cesare도 청년의 편에서 돕는다). | M11: 청년(15~24세) 실업률 18.9%, 전체 5.8% (2026년 7월, ISTAT 잠정)
A12: S2 | B12: 사회 | C12: 이민·난민과 수용 분담 | D12: permesso di soggiorno, protezione speciale, accoglienza, MSNA, cittadinanza | E12: Testaccio·Esquilino는 다국적 동네다. 서류 없는 이웃, 체류허가 사건, 람페두사 도착과 수용 과부하, 보호자 없는 미성년자 비용을 둘러싼 떠넘기기. | F12: 6부 8·9화(퇴거 저지·서류 없는 이웃), 7부 4화(체류허가), 11부 5화 분담 | G12: 1부 7·8화, 3부 6화(서류 없는 환자), 8부(투표권 없는 이웃), 10부 3화 | H12: Rosa, Giulia, Marco, Paolo, Montessori | I12: 국가(이민·국경·수용), 지자체(SAI·아동 보호) | J12: d.lgs. 286/1998, legge 47/2017, 수용 체계(CAS·SAI) | K12: permesso di soggiorno, accoglienza, minore non accompagnato, richiesta d'asilo, cittadinanza | L12: 반이민 여론(IU)과 수용 부담 지역의 실제 어려움을 함께 담고, 이주민을 배경이 아닌 화자로 세운다. | M12: 알바니아 수용 시설 협정, 시민권 요건 국민투표(2025년 정족수 미달) 등 최신 상황은 반영 전 확인
A13: S3 | B13: 사회 | C13: 고령화와 내륙 과소지역(aree interne) | D13: spopolamento, aree interne, denatalità, guardia medica, piccoli comuni | E13: 내륙 마을의 야간 진료소가 문을 닫고 주는 병원 외주를 늘린다(9부). Garibaldi가 말년을 보낸 사르데냐 일대의 과소 마을을 캠페인이 지나며 일자리·의료·연금 문제가 되풀이된다(10부). | F13: 9부 7화 주의회에서의 보건 | G13: 3부(응급실 고령 환자), 10부 2화(사르데냐 내륙), 11부 4화, 13부 | H13: Garibaldi, Giulia, Sofia | I13: 주·시·국가 | J13: 내륙 지역 국가 전략(SNAI), 주 보건서비스 | K13: spopolamento, invecchiamento, natalità, guardia medica | L13: '텅 빈 마을'을 동정하지 않고 마을 사람들이 직접 말하게 한다. | M13: 출생률·인구 통계는 반영 전 확인
A14: S4 | B14: 사회 | C14: 가뭄·폭염과 에너지 전환 부담 | D14: siccità, ondata di calore, bollino rosso, bollette, transizione energetica | E14: 폭염 경보에 응급실이 넘치고(3부), 저수지가 마른 남부 마을을 지나며(10부), 횡재세 재원을 전환 비용과 전기요금에 쓸지 논쟁한다(11부). | F14: 3부 3·10화(폭염 응급실) | G14: 10부 2화, 11부 4·8화, 12부 8화 | H14: Giulia, Garibaldi, Alessandro | I14: 국가·주·유역 관리 기구 | J14: 폭염 경보 체계, 수자원 관리(확인) | K14: siccità, ondata di calore, bollino rosso, bolletta, transizione energetica | L14: 기후를 정치적 구호로 쓰지 않고 현장 사건으로 보여 준다. | M14: 최신 가뭄·폭염 통계 확인
A15: N1 | B15: 재난 | C15: 홍수와 수리·지반 취약성 | D15: alluvione, allerta rossa, IT-alert, Protezione Civile, dissesto idrogeologico | E15: 가상의 중부 지방에 집중호우와 하천 범람이 덮친다. 경보·대피 지연, 주–중앙정부 책임 공방, 국가 비상사태 선포, 민방위·군 투입, 복구와 보상. | F15: 12부 8화 L'alluvione | G15: 13부(복구 결산) | H15: Garibaldi, Giulia, Marco, Galileo, Dante | I15: 주·시(1차 대응), 국가(비상사태·민방위 국), EU | J15: d.lgs. 1/2018(민방위법), EU 연대기금 | K15: protezione civile, allerta rossa, stato di emergenza, sfollati | L15: 실제 참사와 희생자를 연상시키므로 추모의 톤을 지키고, 특정 정치인 비난 없이 제도의 공백을 보여 준다. | M15: 실제 홍수(에밀리아로마냐 2023 등) 후속 조치는 반영 전 확인
... A22: N8 | B22: 사회 | C22: 청년 정신건강 위기 | D22: salute mentale, ansia, liste d'attesa, bonus psicologo, CSM | E22: 청년 정신건강 상담 대기가 몇 달씩 밀린다. Montessori가 현장에서, Sofia가 자신의 불안을 처음 인정하며 함께 부딪힌다. | F22: 12부 6화 Le liste d'attesa | G22: 1부(Sofia의 폭발과 연결 가능, 곁가지) | H22: Montessori, Sofia, Giulia | I22: 주(정신건강 서비스)·국가(지원 예산) | J22: 공공 심리 지원(bonus psicologo), 지역 정신건강센터 | K22: salute mentale, ansia, terapia, lista d'attesa | L22: 청년 정신건강을 극적 소재로만 소비하지 않는다. 낙인 없이, 도움을 구하는 것이 자연스럽다는 톤으로. | M22: 청년 불안장애·상담 대기 증가는 이탈리아에서 널리 보도된 추세. 최신 통계는 확인 필요
A24: 현실 기준값 (확인일 2026-09-24)
A25: No | B25: 구분 | C25: 항목 | D25: 값 | E25: 출처·비고
A26: 1 | B26: 경제 | C26: 정부 부채 / GDP | D26: 137.1% (2025년 말), 2025년 적자 3.1% | E26: ISTAT 2026년 1차 EU 통보. 과도한 재정적자 절차(2024~)는 2027년 졸업 전망 보도.
A27: 2 | B27: 사회 | C27: 청년(15~24세) 실업률 | D27: 18.9% (2026년 7월), 전체 5.8% | E27: ISTAT 월간 잠정치(트레이딩이코노믹스 인용 포함). 청년 실업은 전체의 약 3.3배.
A28: 3 | B28: 정치 | C28: 현 정부 형태 | D28: 우파 연립 다수 정부(2022~) | E28: 이야기에는 실존 정당·인물을 쓰지 않는다. 이야기 속은 '연립 정부'와 '소수 야당'.
A29: 4 | B29: 확인 필요 | C29: 변동이 잦은 항목 | D29: 차등 자치 입법, 사법 개혁 후속, NATO 경로, 이민 협정, PNRR 결산, '동의' 기준 개정 | E29: 교재에 넣기 직전 최신 상태를 확인한다. (확인일 2026-09-24)

Sheet 현안_분포
A1: 현안 분포표 (부 × 현안)
A2: ● = 그 화의 주된 사건(전용 화), ○ = 곁가지(대사·서브플롯). 기호를 바꾸면 아래 집계가 자동 갱신됩니다.
A4: ID | B4: 현안 | C4: 1부 | D4: 2부 | E4: 3부 | F4: 4부 | G4: 5부 | H4: 6부 | I4: 7부 | J4: 8부 | K4: 9부 | L4: 10부 | M4: 11부 | N4: 12부 | O4: 13부 | P4: ● 수 | Q4: ○ 수
A5: P1 | B5: 정부 불안정·연정 협상 | I5: ○ | J5: ○ | K5: ● | L5: ● | M5: ○ | N5: ● | P5: =COUNTIF(C5:O5,"●") | Q5: =COUNTIF(C5:O5,"○")
A6: P2 | B6: 남북 격차·차등 자치 | L6: ● | N6: ○ | P6: =COUNTIF(C6:O6,"●") | Q6: =COUNTIF(C6:O6,"○")
A7: P3 | B7: 사법 개혁·정치 대립 | D7: ○ | E7: ○ | F7: ○ | I7: ● | J7: ○ | K7: ● | L7: ○ | N7: ○ | P7: =COUNTIF(C7:O7,"●") | Q7: =COUNTIF(C7:O7,"○")
A8: E1 | B8: 주거난·단기 관광 임대 | C8: ○ | D8: ● | H8: ● | J8: ○ | K8: ● | M8: ● | O8: ○ | P8: =COUNTIF(C8:O8,"●") | Q8: =COUNTIF(C8:O8,"○")
A9: E2 | B9: 저생산성·영세 기업 | G9: ● | J9: ○ | M9: ○ | O9: ○ | P9: =COUNTIF(C9:O9,"●") | Q9: =COUNTIF(C9:O9,"○")
A10: E3 | B10: 부채·재정·연금 | M10: ● | N10: ● | O10: ○ | P10: =COUNTIF(C10:O10,"●") | Q10: =COUNTIF(C10:O10,"○")
A11: S1 | B11: 청년 고용·두뇌 유출 | C11: ○ | G11: ○ | I11: ○ | J11: ○ | L11: ○ | M11: ● | O11: ● | P11: =COUNTIF(C11:O11,"●") | Q11: =COUNTIF(C11:O11,"○")
A12: S2 | B12: 이민·난민·수용 분담 | C12: ○ | E12: ○ | H12: ● | I12: ● | J12: ○ | L12: ○ | M12: ● | P12: =COUNTIF(C12:O12,"●") | Q12: =COUNTIF(C12:O12,"○")
A13: S3 | B13: 고령화·내륙 과소지역 | E13: ○ | K13: ● | L13: ○ | M13: ○ | O13: ○ | P13: =COUNTIF(C13:O13,"●") | Q13: =COUNTIF(C13:O13,"○")
A14: S4 | B14: 가뭄·폭염·에너지 전환 | E14: ● | L14: ○ | M14: ○ | N14: ○ | P14: =COUNTIF(C14:O14,"●") | Q14: =COUNTIF(C14:O14,"○")
A15: N1 | B15: 홍수·지반 취약성 | N15: ● | O15: ○ | P15: =COUNTIF(C15:O15,"●") | Q15: =COUNTIF(C15:O15,"○")
A16: N2 | B16: PNRR 집행 | K16: ● | M16: ○ | N16: ○ | P16: =COUNTIF(C16:O16,"●") | Q16: =COUNTIF(C16:O16,"○")
A17: N3 | B17: 국방비·NATO | L17: ○ | M17: ● | N17: ● | O17: ○ | P17: =COUNTIF(C17:O17,"●") | Q17: =COUNTIF(C17:O17,"○")
A18: N4 | B18: 성폭력 법·재판 지연 | I18: ● | J18: ○ | L18: ○ | P18: =COUNTIF(C18:O18,"●") | Q18: =COUNTIF(C18:O18,"○")
A19: N5 | B19: 녹색 대 녹색 | L19: ● | M19: ○ | O19: ○ | P19: =COUNTIF(C19:O19,"●") | Q19: =COUNTIF(C19:O19,"○")
A20: N6 | B20: 플랫폼 노동(라이더) | G20: ○ | N20: ● | P20: =COUNTIF(C20:O20,"●") | Q20: =COUNTIF(C20:O20,"○")
A21: N7 | B21: 스파이웨어·정보기관 감시 | I21: ○ | N21: ● | P21: =COUNTIF(C21:O21,"●") | Q21: =COUNTIF(C21:O21,"○")
A22: N8 | B22: 청년 정신건강 | C22: ○ | N22: ● | P22: =COUNTIF(C22:O22,"●") | Q22: =COUNTIF(C22:O22,"○")
B23: 부별 ● 수 | C23: =COUNTIF(C5:C22,"●") | D23: =COUNTIF(D5:D22,"●") | E23: =COUNTIF(E5:E22,"●") | F23: =COUNTIF(F5:F22,"●") | G23: =COUNTIF(G5:G22,"●") | H23: =COUNTIF(H5:H22,"●") | I23: =COUNTIF(I5:I22,"●") | J23: =COUNTIF(J5:J22,"●") | ... O23: =COUNTIF(O5:O22,"●") | P23: =SUM(P5:P22)
B24: 부별 ○ 수 | C24: =COUNTIF(C5:C22,"○") | D24: =COUNTIF(D5:D22,"○") | E24: =COUNTIF(E5:E22,"○") | F24: =COUNTIF(F5:F22,"○") | G24: =COUNTIF(G5:G22,"○") | H24: =COUNTIF(H5:H22,"○") | I24: =COUNTIF(I5:I22,"○") | J24: =COUNTIF(J5:J22,"○") | ... O24: =COUNTIF(O5:O22,"○") | Q24: =SUM(Q5:Q22)
A26: 읽는 법: 1~5부는 곁가지 중심이라 B1~B2 난이도를 지키고, 9~12부에서 전용 화가 몰린다. 화당 전용 현안은 1개(+곁가지 1~2개)로 제한해 낭독 분량을 지킨다. N6~N8은 12부의 신규 현안으로 각 1개 전용 화를 받는다.
A27: 현안 ID와 설명은 '현안_배치' 시트, 화별 반영은 '화별목차_전체'의 '반영 현안' 열을 참고.

Sheet 정치제도
A1: 현실 정치 제도 기준표 (이탈리아)
A2: 8~12부에 반영한 실제 제도. 정당·정치인은 전부 가상이며 실존 정치인의 대사는 쓰지 않는다. '검색 확인' 표시는 2026-09-24 기준 자료로 확인한 항목.
A4: 영역 | B4: 제도·규칙 | C4: 핵심 내용 | D4: 근거 | E4: 이야기 반영 | F4: 낭독 어휘 | G4: 확인 상태
A5: 정당·선거 | B5: 정당 설립 | C5: 이탈리아 정당은 대개 법인격 없는 사단(associazione non riconosciuta)으로, 공증인 앞에서 설립 문서(atto costitutivo)와 정관(statuto)을 작성해 만든다. 국가 정당 등록부에 등록하면 2x1000 기부 등 혜택 자격을 얻는다. | D5: 헌법 제49조, 민법 제36조, d.l. 149/2013 제4조 | E5: 8부 5화 | F5: atto costitutivo, statuto, iscrizione, associazione | G5: 기획 시점 지식 — Normattiva 확인 필요
A6: 정당·선거 | B6: 정당의 민주적 내부 운영 | C6: 시민은 '민주적 방법으로' 국가 정책 결정에 참여하기 위해 정당을 결성한다. 등록 정당의 정관은 기관 구성·당원 권리·후보 선출 절차 등을 명시해야 한다. | D6: 헌법 제49조, d.l. 149/2013 제3조 | E6: 8부 6화 | F6: metodo democratico, statuto, iscritto, organi | G6: 기획 시점 지식 — Normattiva 확인 필요
A7: 정당·선거 | B7: 정당 재정 | C7: 공적 직접 보조금은 폐지되고(2013~), 개인의 2x1000 세금 기부와 공개 의무가 있는 후원으로 운영된다. 정당 회계는 독립 위원회(Commissione di garanzia)가 감독한다. | D7: d.l. 149/2013, legge 3/2019 | E7: 8부 7화 | F7: finanziamento, 2x1000, donazione, rendiconto | G7: 기획 시점 지식 — Normattiva 확인 필요
A8: 정당·선거 | B8: 집회 신고 | C8: 공공장소 집회는 최소 3일 전 경찰청장(Questore)에게 통지한다. 허가가 아니라 통지이며, 공공질서·안전을 이유로만 금지할 수 있다. | D8: 헌법 제17조, TULPS 제18조 | E8: 8부 1화 | F8: preavviso, manifestazione, Questura, piazza | G8: 기획 시점 지식 — Normattiva 확인 필요
A9: 정당·선거 | B9: 국민 발의와 폐지 국민투표 | C9: 국민 5만 명 서명으로 법안을 발의할 수 있다(의회 심의 의무는 약함). 유권자 50만 명 서명(또는 주의회 5곳)으로 법률 폐지 국민투표를 청구하며, 헌법재판소 허용 심사를 거친다. 유권자 과반이 투표해야 유효하다. | D9: 헌법 제71·75조, legge 352/1970 | E9: 8부 2~4화 | F9: iniziativa popolare, referendum abrogativo, quorum, ammissibilità | G9: 기획 시점 지식 — Normattiva 확인 필요
A10: 정당·선거 | B10: 총선 제도 | C10: 하원 400석·상원 200석(선출). 약 3/8은 소선거구 단순다수, 나머지는 비례(해외 선거구 별도). 명부 문턱 3%, 연합 문턱 10%. 하원 과반 201석. | D10: legge 165/2017 (Rosatellum), 헌법 제56·57조(2020 의석 축소 개헌) | E10: 10부 | F10: collegio uninominale, proporzionale, soglia di sbarramento, seggio | G10: 기획 시점 지식 — Normattiva 확인 필요
A11: 정당·선거 | B11: 명부 제출 서명 요건 | C11: 의회에 교섭단체가 없는 정당은 선거구마다 일정 수의 유권자 서명을 받아야 명부를 낼 수 있다(전자 서명 허용 확대 중). 지방선거도 인구 규모에 따라 서명이 필요하다. | D11: legge 165/2017, 지방선거법 | E11: 9부 12화, 10부 1화 | F11: raccolta firme, presentazione delle liste, sottoscrittori | G11: 서명 수·면제 요건 확인 필요
A12: 정당·선거 | B12: 선거 일정 | C12: 해산 후 70일 안에 선거, 새 의회는 선거 후 20일 안에 소집. 선거 전날·당일은 선거운동 금지(silenzio elettorale), 마지막 15일은 여론조사 공표 금지. 방송 노출은 균등 원칙(par condicio)과 AGCOM 감독. | D12: 헌법 제61조, legge 212/1956, legge 28/2000 | E12: 8부 11화, 10부 | F12: campagna elettorale, silenzio elettorale, sondaggio, par condicio | G12: 기획 시점 지식 — Normattiva 확인 필요
A13: 정당·선거 | B13: 로마 시의회·라치오 주의회 선거 | C13: 로마 시장은 직선제이며 과반 득표자가 없으면 2주 뒤 결선(ballottaggio). 시의회(Assemblea Capitolina)는 48석, 당선 시장 연합에 과반 보너스. 라치오 주지사도 직선제, 주의회는 약 50석. | D13: TUEL(d.lgs. 267/2000) 제71~73조, 라치오 주 선거법 | E13: 8부 12화, 9부 | F13: sindaco, ballottaggio, consigliere, premio di maggioranza | G13: 의석 수·문턱·동시 선거 여부 확인 필요
A14: 정당·선거 | B14: 낙선 시장 후보의 의석 | C14: 결선에 오르지 못한 시장 후보라도 연계 명부가 의석을 얻으면 시의원으로 선출될 수 있다. | D14: TUEL 제73조 | E14: 9부 1화 | F14: candidato sindaco, consigliere, proclamazione | G14: 조항 세부 확인 필요
A15: 정당·선거 | B15: 선거 분쟁 | C15: 명부 제출·접수는 선거 사무국(Ufficio elettorale)이 심사하고, 거부 결정은 행정법원(TAR) 등으로 다툰다. 방송 불공정은 AGCOM에 제소. | D15: 선거법, 행정소송법 | E15: 8부 10~11화, 10부 | F15: ricorso, TAR, AGCOM, esclusione della lista | G15: 기획 시점 지식 — Normattiva 확인 필요
... A53: 정부 | B53: 연금 | C53: 노령 연금 수급 연령과 조기 퇴직 제도(Quota 등)가 매년 예산안 논쟁의 중심이다. 연금 지출은 GDP 대비 EU 최고 수준. | D53: legge 214/2011 (Fornero), 매년 예산법 | E53: 12부 11~12화 | F53: pensioni, età pensionabile, Quota | G53: 기획 시점 지식 — Normattiva 확인 필요
A55: ※ 법령 번호·조항은 교재에 넣기 전에 Normattiva(normattiva.it)의 현행 통합본(testo vigente)으로 반드시 확인하세요. '검색 확인'은 공개 자료에서 교차 확인한 항목이며, 나머지는 기획 시점 지식입니다.

Sheet 정치경로_의석
A1: 정치 경로와 가상 의석 시뮬레이션
A2: 창당에서 총리까지의 경로를 이탈리아 현실 제도에 맞춰 단계화했다. 정당·의석 수는 전부 가상의 교육용 수치이며, 파란 숫자·표결 값은 수정하면 결과가 자동 갱신된다. 표결 값: Sì(찬성) / No(반대) / Astenuto(기권) / Assente(불참).
A4: 1. 정치 경로 (창당 → 총리)
A5: 단계 | B5: 부·화 | C5: 이야기 사건 | D5: 제도·규칙 | E5: 확인 상태
A6: 1 | B6: 8부 1~4화 | C6: San Giovanni 집회 → 폐지 국민투표 서명 50만 → 정족수 미달로 무효 | D6: 집회 사전 통지(3일), 헌법 제75조, 헌법재판소 허용 심사 | E6: 기획 지식
A7: 2 | B7: 8부 5~7화 | C7: 정당 «Casa Comune» 창당 | D7: 공증인 앞 설립 문서·정관, 국가 정당 등록부(d.l. 149/2013), 후원 공개(legge 3/2019) | E7: 기획 지식
A8: 3 | B8: 8부 8~12화 | C8: 첫 로마 시의회·라치오 주의회 선거, 시의회 48석 중 5석·주의회 진출 (가상 수치) | D8: 시장 직선·결선, 과반 보너스, 문턱 3%, 성별 균형 명부, 정정권 | E8: 의석·문턱 확인 필요
A9: 4 | B9: 9부 1화 | C9: 결선에서 다른 당 시장 당선, 낙선 시장 후보 Alessandro는 시의원으로 | D9: TUEL 제72·73조 | E9: 조항 확인 필요
A10: 5 | B10: 9부 2~11화 | C10: Alessandro는 시의회(예산·계약), Giulia는 주의회(보건)에서 활동. 스캔들 폭로, 검찰 고발 | D10: 보건·도시계획은 국가–주 공동 권한(헌법 제117조), d.lgs. 24/2023, 형사소송법 제191조 | E10: 기획 지식
A11: 6 | B11: 9부 12화 | C11: UCN 정부가 예산 신임 투표에서 패배 → 대통령이 해산 | D11: 해산: 대통령이 양원 의장 의견 청취 후(헌법 제88조). 명부 제출 서명 필요 | E11: 기획 지식
A12: 7 | B12: 10부 1~4화 | C12: 총선 1차: 캠페인, TV 토론, 결과 CC 하원 70석 3위 (아래 A블록) | D12: 해산 후 70일 이내 선거, 하원 400석·상원 200석, 문턱 3% | E12: 기획 지식
A13: 8 | B13: 10부 5화 | C13: 개원, 양원 의장 선출, CC 교섭단체 구성 | D13: 교섭단체 최소 인원 (CC 70석이라 충족) | E13: 인원 요건 확인 필요
A14: 9 | B14: 10부 6~7화 | C14: 대통령 협의 → UCN 지도자 조각 위임 → 선서 → 하원 신임 부결 (A블록) | D14: 헌법 제92~94조: 선서 후 10일 안에 양원 신임, 찬성>반대 | E14: 검색 확인 (선례)
A15: 10 | B15: 10부 8화 | C15: 탐색 위임(상원의장) → 다수파 불성립, 부결된 정부는 일상 업무만 | D15: 헌정 관행, 사퇴 정부의 affari correnti | E15: 기획 지식
A16: 11 | B16: 10부 9~10화 | C16: 재해산과 재선거: CC 하원 130석 1당이지만 과반 아님 (B블록) | D16: 하원 과반 201석 미달 → 연정 협상 | E16: 가상 수치
... A24: 19 | B24: 13부 | C24: 임기 후반, 사무소를 재단으로 전환 | D24: 정부 구성원 이해충돌(legge 215/2004) | E24: 기획 지식
A26: 2. 가상 정당 (실존 정당·정치인 사용 금지)
A27: 약칭 | B27: 정당명 (가상) | C27: 성격 | D27: 이야기 속 역할
A28: CC | B28: Casa Comune | C28: 주인공 정당. Rosa의 식탁에서 나온 이름 | D28: 시민 정당. 창당 → 지방 → 총선 → 총리
A29: UCN | B29: Unione Civica Nazionale | C29: 거대 보수 정당 | D29: 현직 총리 배출, 1차 총선 1당, 첫 정부가 하원 신임 부결
A30: PPS | B30: Partito del Progresso Sociale | C30: 거대 중도좌파 정당 | D30: 재선거에서 52석으로 추락, Marco 정부의 연정 파트너
A31: IU | B31: Italia Unita | C31: 민족주의 성향 소수당 | D31: UCN과 함께 반대·불신임안 지지
A32: TA | B32: Coalizione Territoriale A | C32: 남부·섬 지역정당 연합 | D32: 조건부 친여 (필수 급부 수준 보장 요구)
A33: TB | B33: Coalizione Territoriale B | C33: 북부 자치주의 지역정당 연합 | D33: 캐스팅보트: 차등 자치 가속을 조건으로 하원 기권·상원 반대 (협상의 열쇠)
A35: 3-A. 총선 1차 결과와 UCN 정부의 하원 신임 투표 (가상, 10부 7화)
A36: 정당 | B36: 의석 | C36: 표결 | E36: 비고
A37: UCN | B37: 145 | C37: Sì
A38: PPS | B38: 105 | C38: No
A39: CC | B39: 70 | C39: No
A40: IU | B40: 40 | C40: Sì
A41: TA | B41: 15 | C41: No
A42: TB | B42: 25 | C42: Astenuto
A43: 총 의석 | B43: =SUM(B37:B42) | E43: =IF(B43=400,"400석 OK","400석과 불일치")
A44: 절대다수 (참고) | B44: =INT(B43/2)+1
A45: 찬성 (Sì) | C45: =SUMIF(C37:C42,"Sì",$B$37:$B$42)
A46: 반대 (No) | C46: =SUMIF(C37:C42,"No",$B$37:$B$42)
A47: 기권 (Astenuto) | C47: =SUMIF(C37:C42,"Astenuto",$B$37:$B$42)
A48: 불참 (Assente) | C48: =SUMIF(C37:C42,"Assente",$B$37:$B$42)
A49: 결과 | C49: =IF(C45>C46,"신임 가결","신임 부결") | E49: 찬성 > 반대이면 가결 (단순다수)
A50: 해석: UCN 정부는 찬성 185 대 반대 190으로 하원 신임을 얻지 못한다(TB 기권 25). 신임 없는 정부는 사퇴하고 일상 업무만 처리한다. 대통령은 탐색 위임을 시도하지만 다수파가 나오지 않자 양원 의장의 의견을 들어 해산한다(헌법 제88조). 첫 정부가 신임 투표에서 부결된 실제 선례가 있다(1987년 등).
A52: 3-B. 재선거 결과와 Marco 정부의 양원 신임 투표 (가상, 10부 12화)
A53: 정당 | B53: 하원 의석 | C53: 하원 표결 | D53: 상원 의석 | E53: 상원 표결
A54: CC | B54: 130 | C54: Sì | D54: 64 | E54: Sì
A55: UCN | B55: 122 | C55: No | D55: 62 | E55: No
A56: PPS | B56: 52 | C56: Sì | D56: 26 | E56: Sì
A57: IU | B57: 38 | C57: No | D57: 19 | E57: No
A58: TA | B58: 20 | C58: Sì | D58: 10 | E58: Sì
A59: TB | B59: 38 | C59: Astenuto | D59: 19 | E59: No
A60: 종신 상원의원 (찬성) | D60: 2 | E60: Sì
A61: 종신 상원의원 (반대) | D61: 1 | E61: No
A62: 종신 상원의원 (불참) | D62: 2 | E62: Assente
A63: 선출 의석 합계 | B63: =SUM(B54:B62) | C63: =IF(B63=400,"하원 400석 OK","400석과 불일치") | D63: =SUM(D54:D59) | E63: =IF(D63=200,"상원 선출 200석 OK","200석과 불일치")
A64: 종신 상원의원 | B64: — | D64: =SUM(D60:D62) | E64: 투표권 있음 (가상 5명)
A65: 찬성 (Sì) | C65: =SUMIF(C54:C62,"Sì",$B$54:$B$62) | E65: =SUMIF(E54:E62,"Sì",$D$54:$D$62)
A66: 반대 (No) | C66: =SUMIF(C54:C62,"No",$B$54:$B$62) | E66: =SUMIF(E54:E62,"No",$D$54:$D$62)
A67: 기권 (Astenuto) | C67: =SUMIF(C54:C62,"Astenuto",$B$54:$B$62) | E67: =SUMIF(E54:E62,"Astenuto",$D$54:$D$62)
A68: 불참 (Assente) | C68: =SUMIF(C54:C62,"Assente",$B$54:$B$62) | E68: =SUMIF(E54:E62,"Assente",$D$54:$D$62)
A69: 결과 | C69: =IF(C65>C66,"하원 신임 가결","하원 신임 부결") | E69: =IF(E65>E66,"상원 신임 가결","상원 신임 부결")
A70: 상원 표 차 | E70: =E65-E66
A71: 해석: 하원은 CC·PPS·TA의 202표로 여유 있게 통과(TB 기권). 상원에서는 TB가 차등 자치 조건을 이유로 반대로 돌아서 선출 의원만으로는 100 대 100 동수 — 종신 상원의원 두 명의 찬성과 한 명의 반대로 102 대 101, 1표 차로 신임이 가결된다. 종신 상원의원의 표가 정부의 운명을 가른 실제 사례(2006년 등)가 있다.
A73: 3-C. 야당의 불신임안 (가상, 12부 7화, 하원)
A74: 정당 | B74: 의석 | C74: 표결 | E74: 비고
A75: UCN | B75: 122 | C75: Sì
A76: IU | B76: 38 | C76: Sì
A77: TB | B77: 38 | C77: Astenuto
A78: CC | B78: 130 | C78: No
A79: PPS | B79: 52 | C79: No
A80: TA | B80: 20 | C80: No
A81: 총 의석 | B81: =SUM(B75:B80) | E81: =IF(B81=400,"400석 OK","400석과 불일치")
A82: 절대다수 (참고) | B82: =INT(B81/2)+1
A83: 찬성 (Sì) | C83: =SUMIF(C75:C80,"Sì",$B$75:$B$80)
A84: 반대 (No) | C84: =SUMIF(C75:C80,"No",$B$75:$B$80)
A85: 기권 (Astenuto) | C85: =SUMIF(C75:C80,"Astenuto",$B$75:$B$80)
A86: 불참 (Assente) | C86: =SUMIF(C75:C80,"Assente",$B$75:$B$80)
A87: 결과 | C87: =IF(C83>C84,"불신임 가결","불신임 부결") | E87: 찬성 > 반대이면 가결 (대안 후보 불필요)
A88: 발의 필요 서명 (1/10) | C88: =ROUNDUP(B81/10,0) | E88: =IF(B75>=C88,"UCN 단독으로 서명 충족","미달")
A89: 해석: 발의 요건(40명)은 UCN 단독으로 충족하지만, 찬성 160 대 반대 202로 부결(TB 기권 38). 제출 후 3일이 지나야 토론할 수 있고 호명 투표로 표결한다. PPS(52석)가 돌아서면 찬성 212 대 반대 150으로 가결될 수 있다는 긴장이 이 화의 서스펜스.
A91: 4. 이야기 속 엑스트라 화자 (전부 가상)
A92: PRESIDENTE DELLA CAMERA / PRESIDENTE DEL SENATO(표결 결과를 낭독), SINDACO / SINDACA(가상), PRESIDENTE DEL CONSIGLIO USCENTE(UCN, 가상), MODERATRICE(TV 토론), NOTAIO(13부 유언장). 대통령(Presidente della Repubblica)은 직접 대사를 주지 않고, 협의·조각 위임 결과는 대통령실 사무총장의 발표문(가상)이나 인물들의 대사로 전달한다. 실존 정치인·정당명은 쓰지 않는다.

Sheet 호칭규칙
A1: 호칭 규칙 (tu / Lei / voi / Loro)
A2: 표준 이탈리아어 기준. 격식 복수 Loro는 현대 구어에서 거의 쓰지 않으므로 Cesare의 고풍 캐릭터 장치로만 사용. 2~5부 '사무소 프레임 장면'은 1부와 같은 규칙을 따른다.
A4: 화자 → 청자 | B4: 1부 (현재) | C4: 2~5부 (각자의 과거) | D4: 6부 이후 | E4: 비고
A5: 주력 4인 상호 | B5: tu | C5: Lei (만나기 전이라) | D5: tu | E5: 6부 만남을 기점으로 전환 — «Diamoci del tu.» 같은 전환 순간을 대사로 드러낼 것
A6: 주력 4인 → Sofia | B6: tu | C6: tu (프레임 장면) | D6: tu
A7: Sofia → 주력 4인 | B7: Lei | C7: Lei (프레임 장면) | D7: tu (제안) | E7: 6부에서는 이웃 사이라 tu, 인턴이 되면서(1부) Lei로 바뀐다 — 1부 1화 대본에서 «Al Quarticciolo mi davi del tu.»로 대사 설명. 이후 tu로 돌아갈 시점은 미확정
A8: Sofia → Cesare | B8: Lei | C8: Lei | D8: Lei 유지 → 12부 1화 조사에서 처음 tu | E8: 7부에서 Cesare가 «Puoi darmi del tu.»라고 허락해도 Sofia는 습관 때문에 끝내 Lei. 폭발 중에도 Lei (예: «Proprio Lei non mi chiami stolta!»). 폭발 중 tu 실수 금지 — 장례식 전환의 복선.
A9: Sofia → Garibaldi, Francesco | B9: Lei | C9: 해당 없음 | D9: Lei (전환 시점 미정)
A10: Cesare → Sofia | B10: tu («ragazza») | C10: 해당 없음 | D10: tu | E10: 처음부터 tu — 욕(stolta)도 Sofia에게만
A11: Cesare → 여럿(집단) | B11: Loro (고풍 격식 복수) | C11: Loro | D11: Loro | E11: 사무소 안에서도 일부러 거리를 두는 심술. 현대 이탈리아어에서는 거의 쓰지 않는 격식 복수 Loro를 다른 인물의 voi와 비교 학습. 3인칭 자기 지칭(«Cesare pensa…»)과 함께.
A12: Cesare → 개인 (Sofia 외) | B12: Lei | C12: Lei | D12: 소수에게만 tu
A13: Garibaldi → 후배들 | B13: tu (명령조) | C13: tu / Lei 혼용 | D13: 정치 무대에서는 Lei | E13: 의용군 지휘관의 버릇으로 모두를 '동지'처럼 부른다
A14: Gramsci → 전원 | B14: tu | C14: tu | D14: tu | E14: 모두에게 tu — 그래서 더 단호하다. «Cercalo tu.»
A15: Rosa, Paolo → 전원 | B15: tu | C15: tu | D15: tu | E15: Rosa는 'amore/tesoro', 로마 사투리 한두 마디(«daje», «che te serve?»)
A16: Galileo → 취재·관찰 대상 | B16: Lei (취재 시) | C16: Lei | D16: 친해지면 tu
A17: Machiavelli, Dante, Montessori → 전원 | B17: Lei | C17: Lei | D17: 가까운 사람에게만 tu | E17: 부활자들은 격식이 기본. Dante는 가끔 옛 존칭 voi를 한 사람에게 써서 웃음을 준다(옛 이탈리아어의 존칭 voi).
A18: 집단 대화 (사무소 안) | B18: voi | C18: voi | D18: voi | E18: 예: «Sedetevi, che vi porto qualcosa.»
A19: 공식 연설·의회 | B19: — | C19: — | D19: voi / Loro, «Onorevoli colleghi» | E19: 8부 이후 대중 연설, 9부 이후 시의회·주의회·양원 토론
A20: 하원·상원 | B20: — | C20: — | D20: «Signor Presidente / Signora Presidente»(의장), «onorevole»(하원의원), «senatore/senatrice», «signor Ministro / signora Ministra» | E20: 의원끼리는 «collega», 총리는 «Presidente del Consiglio»로 부른다. 발언은 의장을 향해 3인칭
A21: 시의회 (Assemblea Capitolina) | B21: — | C21: — | D21: «Signor Sindaco / Signora Sindaca», «Presidente», «consigliera / consigliere» | E21: 발언은 Lei, 회의 밖 동료끼리는 tu로 돌아간다
A22: 대통령 | B22: — | C22: — | D22: «Signor Presidente della Repubblica» | E22: 대통령은 직접 대사를 주지 않는다. 절차와 결과는 공식 발표문(가상)이나 인물의 대사로 전달
A24: 부활 인물 직접 호칭 규칙 (2부~7부 집필 중 확정, 2026-09-25)
A25: 다른 인물이 부활자를 이름/성으로 직접 부를 때(2인칭, vocative)는 역할·직함 + 이름의 정식 호칭을 쓴다. 3인칭 언급, 자기지칭(Cesare), tu 관계의 편한 호칭은 이름만 써도 된다.
A27: 약칭 | B27: 직접 호칭 시 정식 표현 | C27: 한국어 번역
A28: Cesare | B28: Console Cesare | C28: 체사레 집정관님
A29: Gramsci | B29: Segretario Gramsci | C29: 그람시 서기장님
A30: Machiavelli | B30: Segretario Machiavelli | C30: 마키아벨리 서기관
A31: Garibaldi | B31: Generale Garibaldi | C31: 가리발디 장군님
A32: Dante | B32: Poeta Dante | C32: 단테 시인님
A33: Galileo | B33: Professor Galileo | C33: 갈릴레오 교수님
A34: Montessori | B34: Dottoressa Montessori | C34: 몬테소리 박사님
A36: 예외: 1년 이상 함께한 친한 동료 사이의 격의없는 장면(7부 이후)에서는 직함 없이 이름만 써도 무방하다. Cesare는 본인 성격상 항상 공식적이어야 하므로 이 예외에서 제외.

Sheet Sofia_폭발과욕
A1: Sofia의 폭발 (Lo Sfogo) 과 욕 배정
A2: 폭발은 총 2회. 희소성이 가치다. 폭발 뒤에는 반드시 쉬운 말로 다시 설명하는 어휘 교습 장면이 이어진다.
A4: 1. 폭발 배치 (총 2회)
A5: 회차 | B5: 위치 | C5: 성격 | D5: 단계 구성 | E5: 특기 사항
A6: 1차 폭발 | B6: 1부 6화 «Basta!» (사건3 위장 인턴·임금 체불 해결 화, Chiara의 경영 용어가 협상을 막는 장면) | C6: 코미디 — 「몰라서 화내는 Sofia」 | D6: 1단계 → 2단계 → 3단계 전부 노출 | E6: 인물별 고정 반응 패턴을 여기서 한 번에 보여 준다. Garibaldi·Rosa·Gramsci가 이 화에 함께 등장 — Paolo의 욕은 9부 2차 폭발로 이관해 과밀을 피함.
A7: 2차 폭발 | B7: 9부 6화 (시의회 예산 심의) | C7: 역전 — 「알아서 화내는 Sofia」. 이번엔 Sofia가 옳다. | D7: 1단계에서 곧바로 3단계로 (2단계 생략: '이번엔 참지 않는다') | E7: 관료 전문 용어 속에 서민 예산을 깎는 조항이 숨어 있었고 Sofia가 짚어 낸다. Cesare가 선을 넘는 말을 하고 Garibaldi·Rosa가 나무란다.
A8: 사이 구간 | B8: 2~8부 | C8: 폭발 없음 | D8: 1단계 질문만 일상 장치로 반복 | E8: 어휘 학습의 핵심은 1단계 질문. 폭발은 정점 이벤트일 뿐.
A10: 2. 3단계 계단
A11: 단계 | B11: 대사 (IT) | C11: 한국어 | D11: 분위기 | E11: 사용
A12: 1단계 | B12: Scusi, cosa significa? | C12: 실례지만, 그게 무슨 뜻이에요? | D12: 정중한 질문 | E12: 상시 (매 화 가능)
A13: 2단계 | B13: Me lo spiega come se avessi cinque anni? | C13: 다섯 살한테 설명하듯 해 주실래요? | D13: 슬슬 짜증 | E13: 1차 폭발에서만
A14: 3단계 | B14: BASTA! Non capisco niente! | C14: 그만! 하나도 모르겠다고요! | D14: 폭발 | E14: 1차 · 2차(9부)
A16: 3. 폭발 직후 고정 반응 (전부 대사로 처리 — 지문 폐기)
A17: 인물 | B17: 반응 대사 (IT) | C17: 한국어 | D17: 기존 지문 (폐기) | E17: 비고
A18: Giulia | B18: Prima, respira. | C18: 우선, 숨 쉬어요. | D18: — | E18: Sofia: «Non mi dica "respira"!»로 받는다
A19: Rosa | B19: Uh. Poso 'sto piatto sul tavolo prima che voli. | C19: 어이쿠. 접시 날아가기 전에 식탁에 내려놔야겠네. | D19: 말없이 접시를 내려놓음 | E19: 정적의 순간을 웃음으로 대신한다. 'sto = questo (로마 구어)
A20: Garibaldi | B20: Nulla da segn… No. Meglio che stia zitto. | C20: 이상 없… 아니. 입 다무는 게 낫겠군. | D20: «Nulla da segnalare»를 하려다 입을 다묾
A21: Gramsci | B21: Io non ho detto niente. | C21: 나는 아무 말도 안 했어. | D21: 아무 말도 하지 않아 오히려 가장 긴장됨 | E21: 침묵 설정을 폐지하고 시그니처 대사로 대체
A23: 4. 욕 배정 (폭발 장면 한정 — 교재용 순한 표현만)
A24: 인물 | B24: 표현 | C24: 뉘앙스 | D24: 사용 규칙 | E24: 비고
A25: Cesare | B25: Stolta / Testa di rapa | C25: 고풍스럽고 격식 있는 욕 — 우아하게 기분 나쁨 (라틴어 stulta의 후손) | D25: 1차·2차 폭발에서만, Sofia에게만 | E25: 11부 12화 마지막에 «stolta» 대신 «Niente male.»이 나올 때 낙차가 커진다.
A26: Garibaldi | B26: Recluta! / Pivella | C26: 의용군식 신병 취급 | D26: 1차에서 1회 | E26: 1부 6화(폭발 화)에 카메오로 함께 있으므로 여기서 1회 (확정)
A27: Paolo | B27: Zuccona / Testona | C27: 시장통식 직설 | D27: 2차(9부)에서 1회 | E27: 1차 폭발 화의 카메오 과밀을 피해 이관 (확정)
A28: Rosa | B28: Svampita / Scemotta + «amore» | C28: 애정이 섞여 욕인 줄 모름 (로마 할머니 화법) | D28: 1차에서 1회
A29: Gramsci | B29: 욕하지 않음 | C29: 대신 출처를 가리킨다 | D29: — | E29: «Cercalo tu.»
A31: 5. 유지 규칙
A32: 1. Sofia가 옳은 경우가 있어야 한다. 2차(9부)에서는 관료 용어에 숨은 삭감 조항을 짚어 낸다. 1차에서도 Chiara의 용어(sinergie, scalabile)가 알맹이 없었음이 드러난다. Sofia는 '어려운 말로 숨는 어른들'을 드러내는 인물이다.
A33: 2. 폭발 직후에는 누군가 쉬운 말로 다시 설명한다 (전문 표현 → 쉬운 표현 짝 학습). 1차 담당: Alessandro — «Traduco io. Vuol dire: licenziare gente per risparmiare.»
A34: 3. 욕과 괴롭힘의 선: 별도 에피소드를 만들지 않고 2차 폭발에 합친다. Cesare가 정말 아픈 말을 하고 Garibaldi·Rosa가 나무라며, 사과는 «Ritiro quello che ho detto… in parte.» 정도로 삐딱하게.
A35: 4. 욕설 수위: cazzo, vaffanculo 등은 교재에서 제외. 필요하면 각주로 '실제로는 더 거칠게 말한다'고만 알려 준다. 로마 사투리 욕도 순한 것만.

Sheet Cesare_죽음
A1: Cesare — 부활한 독재관, 협상 승리 직후 두 번째 죽음
A2: 10부 동안 매 겨울 '마지막'이라고 외치는 양치기 소년 → 11부에서 2천 년 만에 다시 협상가가 되어 브뤼셀에서 승리하고, 그 직후 12화에서 진짜로(두 번째로) 죽는다.
A4: 1. 기본 설정
A5: 항목 | B5: 내용
A6: 나이 | B6: ="1부 "&INDEX(캐릭터!$E$5:$E$19,MATCH("Cesare",캐릭터!$D$5:$D$19,0))&"세 → 11부 약 "&INDEX(캐릭터!$F$5:$F$19,MATCH("Cesare",캐릭터!$D$5:$D$19,0))&"세 (부활 시점 나이 = 암살 당시 55세, 경과 연수 가정 "&개요!$C$11&"년)"
A7: 성격 | B7: 정중하게 독을 뿌리는 심술 영감. 예의를 지키며 비꼬는 화법이라 Paolo·Garibaldi의 큰 소리 화법과 구분된다. 자기 자신을 3인칭(«Cesare pensa…»)으로 부른다. 낭독하면 '정중한데 기분 나쁜' 억양 연습이 된다.
A8: 심술 패턴 | B8: 커피가 맛없다고 매일 불평(«Che modo di rovinare un buon caffè.»). Chiara를 «quella delle slide», Dante의 원고를 «le mille bozze»라고 놀림. 모든 것이 «Ai miei tempi»(기원전!)보다 못하다.
A9: 반복 개그 | B9: 매 겨울 «Questo sarà il mio ultimo inverno.» 선언, 유언장을 계속 고쳐 씀 (Sofia에게 우산을 물려주겠다 등). 입버릇 «Lo scrivano nel mio testamento.»(고풍 격식 복수 Loro). 모두 '또 시작이네' 하며 웃어넘긴다.
A10: 가짜 병 | B10: 무릎, 소화, 불면 — 전부 엄살. 부은 발목은 «Sono i calzari.»(샌들 탓). 소란스러운 엄살이 진짜 병의 위장이 된다.
A11: 진짜 병 | B11: 만성 심부전 (insufficienza cardiaca cronica). 이것만 숨긴다.
A12: Giulia의 딜레마 | B12: Giulia는 진단을 알지만 의사의 비밀유지(segreto professionale)를 지킨다. Cesare가 «Dottoressa, questo resta tra noi.»라고 못 박았기 때문. 시청자가 뒤늦게 'Giulia가 왜 조용했는지' 깨닫는 구조.
A13: 최고의 칭찬 | B13: «Niente male.» — 극히 드물게 쓰는 표현. Sofia에게는 11부 12화(사망 직전)가 사실상 처음이어야 낙차가 산다.
A14: 호칭·욕 | B14: 여럿에게는 Loro, Sofia에게는 tu(«ragazza»). 욕(«stolta»)은 Sofia에게만, 폭발 장면 2회 한정.
A15: 죽음 이후 | B15: La Vecchia Guardia는 Garibaldi + Gramsci + Machiavelli + 빈 의자. 12부 10화 'Il vuoto nella Vecchia Guardia'에서 정면으로 다룬다.
A17: 2. 복선·사망 타임라인 (전부 대사로 처리)
A18: 부·화 | B18: 사건 | C18: 대화문 처리 방식 | D18: 대사 예시 (IT) | E18: 학습 어휘
A19: 1~10부 (매 겨울) | B19: '마지막 겨울' 선언과 유언장 수정. 1부 1화(개소 1개월 시점)부터 이미 반복되어 온 농담으로 등장한다. | C19: 본인이 선언하고 주변이 «Di nuovo…»로 받는다. | D19: Questo sarà il mio ultimo inverno. Lo scrivano nel mio testamento. | E19: testamento, lasciare in eredità, inverno
A20: 1~11부 | B20: 가짜 병 (무릎·소화·불면) | C20: Giulia가 «Non ha niente.»로 넘긴다. | D20: Mi fa male il ginocchio. È la fine. | E20: ginocchio, digestione, insonnia, acciacco
A21: 7부 | B21: «Puoi darmi del tu.» 허락 — Sofia는 습관 때문에 Lei 유지 | C21: 허락과 거절이 모두 대사로 나온다. | D21: Puoi darmi del tu, ragazza. / Mi scusi, è l'abitudine. | E21: dare del tu, abitudine
A22: 9부 | B22: Sofia 2차 폭발에서 Cesare가 선을 넘음 → Garibaldi·Rosa가 나무람 | C22: 선을 넘는 말과 사과 모두 대사로. | D22: Ritiro quello che ho detto… in parte. | E22: ritirare, scusarsi
A23: 11부 6화 | B23: 청년 고용 협상에서 좋은 조언을 하지만 계단에서 숨이 가쁜 게 처음으로 드러남 (죽음은 아직 아님) | C23: «Non ha niente»가 아니라 «Sto bene, sono solo le scale»로 처음 균열. | D23: Sto bene. Sono solo le scale, ragazza. | E23: scale, fiato, affanno, stanchezza
A24: 11부 9화 | B24: 브뤼셀行 자원(«Cesare andrà.»). Dante에게 짐을 싸며 두 지도자를 특징으로만 묘사 — 건물에 금박 이름을 새긴 사업가 출신과, 정보기관 출신으로 이웃 나라 땅을 가져간 인물. 이름·국가는 끝내 말하지 않는다. | C24: 실명 대신 행동·이력의 특징만 나열. 실존 인물 실명 미사용. | D24: Uno ha scritto il suo nome in lettere d'oro sui suoi palazzi. Ora vende dazi allo stesso modo, urlando. / Somiglierà a chi vuole Lei, giovanotto. Io descrivo solo il paesaggio. | E24: dazi, servizi segreti, regime, discrezione diplomatica
A25: 11부 10화 | B25: 직접 협상. 상대의 과장·거짓 주장을 합의문의 날짜·조항으로 정확히 반박. 벨가이 인용으로 긴장을 푼다. | C25: «Mi permetta di correggerLa»로 시작하는 반박 대사. | D25: Horum omnium fortissimi sunt Belgae. / Cesare ricorda le date meglio dei vostri archivi, giovanotto. Li rilegga con più attenzione. | E25: correggere, archivio, precisione diplomatica
A26: 11부 11화 | B26: 타결. 귀국길에 피로를 숨기고 Alessandro에게 메모를 남기라고 지시 | C26: 직접 증상을 말하지 않고 '메모를 남기라'는 명령으로 암시. | D26: Per sicurezza, annota anche questo, Alessandro. | E26: per sicurezza, eredità, istruzione
A27: 11부 12화 (사망) | B27: 귀국 직후 Testaccio 자택에서 심부전으로 두 번째 죽음. Sofia가 서명을 받으러 왔다가 발견 | C27: 사망은 지문 없이 호명과 확인 대사로: Sofia가 부르고 Giulia가 «Non c'è più.»라고 말한다. | D27: Niente male. / Cesare? — Non c'è più, Sofia. | E27: polso, arresto cardiaco, rianimazione, morire
A28: 12부 1화 | B28: 장례식이 첫 화. Trattoria da Rosa에 빈자리, Rosa가 커피 한 잔을 계속 내놓음. Sofia가 조사에서 처음으로 tu 사용 | C28: 장소·상황은 Rosa·Sofia의 대사로. | D28: Un caffè per Cesare. Come sempre. / Per te, "niente male" era il complimento più grande. | E28: veglia funebre, funerale, condoglianze, elogio funebre
A29: 12부 2~3화 | B29: 유작 메모 발견 → 2차 브뤼셀 협상에서 Dante가 다듬은 그의 문장을 인용 | C29: Dante가 메모를 소리 내어 읽고 Alessandro가 협상장에서 그 문장을 인용한다. | D29: Mi permettano un'ultima precisazione: non è stato niente male. | E29: promemoria, eredità, precisazione, ECOFIN
... A32: 12부 (선택) | B32: Montessori의 애도 상담 | C32: 다들 질색하던 «E questo come ti fa sentire?»가 처음으로 진지하게 쓰인다. | D32: E questo come ti fa sentire? | E32: lutto, perdita, dolore

Sheet Gramsci_출처
A1: Gramsci — 결론 대신 출처를 가리키는 사람
A2: 직접 답하지 않고 '어디를 찾을지'만 알려 준다. 감옥에서 노트(Quaderni)로 세상을 읽던 사람의 논리: 정보의 대부분은 공개 출처에 있다. 평생 정치경찰에게 감시당해 감시의 흔적도 알아본다.
A4: 1. 설정 변경
A5: 항목 | B5: 내용
A6: 답하는 방식 | B6: 침묵 → 결론은 말하지 않고 출처만 가리킨다.
A7: 시그니처 | B7: «Io non ho detto niente. Ma guarda in…» / «Non te lo dico. Ti dico dov'è.» / «Quasi tutto è nelle fonti aperte. Basta saper leggere.»
A8: 도구 (대화문 처리) | B8: 책을 꺼내 건네거나 카드에 적어 주는 행동은 지문 대신 대사로 말한다: «Terzo ripiano, a sinistra.» / «Annota. Cerca: …»
A9: 호칭 | B9: 전원에게 tu — «Cercalo tu.»가 명령조라 더 단호하다.
A10: Sofia와의 관계 | B10: Sofia가 «Dimmi la risposta!» 하면 서가 위치만 말한다. 짜증 나지만 정답을 떠먹이지 않는 이 교재의 태도와 같다.
A11: 현실 요소 | B11: Piazza Borghese의 고서·판화 노점(Mercato delle stampe), 일요일 Porta Portese 벼룩시장의 헌책 좌판, 국립중앙도서관(Biblioteca Nazionale Centrale di Roma, Castro Pretorio)을 단골 출처로. 학습자가 실제 로마에서 따라 걸어 볼 수 있다. 국립중앙문서고(Archivio Centrale dello Stato, EUR)에는 그 자신의 감시 파일도 있다.
A12: 서점 원칙 | B12: 손님이 찾던 답이 든 책일 때만 값을 받지 않는다.
A14: 2. 그의 서가 4칸
A15: 칸 | B15: 내용 | C15: 대표 출처
A16: 법령칸 | B16: 법과 조문 | C16: Normattiva(normattiva.it), 관보(gazzettaufficiale.it), 헌법, 각 법률
A17: 문서칸 | B17: 기록과 자료 | C17: 국립중앙문서고(ACS)의 정치범 기록(Casellario Politico Centrale), 로마 시 역사 문서고(Archivio Storico Capitolino), 양원 속기록(resoconti stenografici)
A18: 신문칸 | B18: 과거 기사 | C18: 국립중앙도서관 디지털 신문 자료, 신문사 온라인 아카이브(예: La Stampa 역사 아카이브)
A19: 사전칸 | B19: 용어 | C19: Treccani(treccani.it) 사전·백과, Accademia della Crusca 언어 상담
A21: 3. 주제별 출처표 (기획한 에피소드 기준)
A22: 상황 | B22: 관련 부·화 | C22: Gramsci의 대사 (IT) | D22: 찾을 곳 | E22: 검색어·키워드 | F22: 서가칸
A23: 정보기관 통제 | B23: 12부 5화 (스파이웨어) | C23: Comincia dalla legge che li ha creati. | D23: legge 124/2007 (정보기관 체계·국가 기밀), COPASIR 연례 보고서 — Normattiva·의회 사이트에서 검색 | E23: legge 124/2007; COPASIR relazione annuale | F23: 법령칸
A24: 도청의 합법성 | B24: 7부 8화, 11부 7화 | C24: Una prova vietata non vale. Cercalo. | D24: 헌법 제15조(통신의 비밀), 형사소송법 제191조(사용할 수 없는 증거)·제266조 이하(감청) | E24: intercettazioni, autorizzazione del GIP, catena di custodia, prove inutilizzabili | F24: 법령칸
A25: 국가 기밀과 공개 | B25: 스파이웨어 관련 | C25: C'è un segreto di Stato, e c'è una legge che lo limita. | D25: legge 124/2007 제39조 이하(국가 기밀), d.lgs. 33/2013·97/2016(정보공개 FOIA) | E25: segreto di Stato, accesso civico generalizzato | F25: 법령칸
A26: 의사의 비밀유지 | B26: 11부 4~6화 (Cesare 복선) | C26: Chiedi alla dottoressa cosa dice il suo codice. | D26: 형법 제622조(직업상 비밀 누설), 의사 윤리강령(FNOMCeO Codice di deontologia medica) | E26: segreto professionale, cartella clinica | F26: 법령칸
A27: 자금 세탁 | B27: 4부, 11부 (주거·금융 전투) | C27: Ogni denaro ha una legge che lo sorveglia. Cercala. | D27: d.lgs. 231/2007 (자금세탁방지), 금융정보분석원(UIF, Banca d'Italia 소속), 기업 등록부 | E27: riciclaggio, titolare effettivo, paradiso fiscale | F27: 문서칸·법령칸
A28: 주거·퇴거 | B28: 1·2·11부 | C28: Confronta quello che dicono con quello che esiste. | D28: legge 431/1998(주거 임대차), 민사소송법 제657조 이하(퇴거 확인 절차), d.l. 145/2023(단기임대 CIN) | E28: sfratto, locazione, diniego di rinnovo | F28: 법령칸
A29: 가격 담합 | B29: 11부 7화 | C29: Guarda nella Concorrenza. | D29: legge 287/1990(경쟁법), 공정거래위원회(AGCM, agcm.it)의 제재 결정 | E29: cartello, istruttoria, concorrenza | F29: 법령칸·문서칸
A30: 횡재세 | B30: 11부 8화 | C30: Non l'hai inventato tu. È già stato fatto. | D30: d.l. 104/2023(은행 특별 부담금), d.l. 21/2022(에너지 기업 특별 부담금)와 관련 헌법재판소 판결 | E30: contributo straordinario, extraprofitti | F30: 법령칸
A31: EU 긴축 압박 | B31: 11부 9~10화 | C31: Quell'articolo non dice quello che ti hanno detto. | D31: 유럽연합기능조약(TFUE) 제126조(과도한 재정적자 절차), EUR-Lex(eur-lex.europa.eu) | E31: procedura per deficit eccessivo | F31: 법령칸
A32: 과거 감시 스캔들 | B32: 6~7부 | C32: Gli archivi ricordano quello che la gente dimentica. | D32: 국립중앙문서고의 정치범 기록(Casellario Politico Centrale), 신문 아카이브 | E32: 'fascicoli SIFAR'로 검색, Casellario Politico Centrale | F32: 신문칸·문서칸
A33: 의회 발언 확인 | B33: 9부 | C33: Tutto quello che si è detto in aula è scritto. | D33: 양원 속기록(camera.it, senato.it), 로마 시의회 회의록 | E33: resoconto stenografico, intervento | F33: 문서칸
... A41: 모르는 단어 | B41: 전 부 | C41: Se non sai la parola, non sai la legge. | D41: Treccani, Accademia della Crusca | E41: — | F41: 사전칸
A42: ※ 법령 번호와 조항은 기획 시점 지식으로 정리한 것입니다. 교재에 넣기 전에 Normattiva(normattiva.it)의 현행 통합본(testo vigente)으로 반드시 확인하세요. 참고 도서 제목은 지어낼 위험이 있어 제외하고 검색어만 적었습니다.
A44: 4. 카드(FICHA) 구술 템플릿 — 지문 없이 대사로만
A45: 화자 | B45: 기능 | C45: 대사 (IT) | D45: 한국어
A46: GRAMSCI | B46: 검색어 (Cerca) | C46: Annota. Cerca: «prove inutilizzabili». | D46: 적어. 찾을 것: «사용할 수 없는 증거».
A47: SOFIA | B47: 질문으로 다음 항목을 끌어냄 | C47: Va bene. Dove? | D47: 알겠어요. 어디서요?
A48: GRAMSCI | B48: 출처 (Dove) | C48: Normattiva. Codice di procedura penale, articolo 191. | D48: 노르마티바. 형사소송법 제191조.
A49: SOFIA | B49: 질문 | C49: E che parole cerco? | D49: 그럼 어떤 단어를 찾죠?
A50: GRAMSCI | B50: 키워드 (Parole chiave) | C50: Intercettazioni. Autorizzazione del giudice. Catena di custodia. | D50: 감청. 판사의 허가. 증거 보관 연속성.
A51: SOFIA | B51: Sofia의 조급함 | C51: E la risposta? | D51: 그럼 답은요?
A52: GRAMSCI | B52: 시그니처 + 서가 위치 (손짓 지문 대체) | C52: Io non ho detto niente. Terzo ripiano, a sinistra. | D52: 나는 아무 말도 안 했어. 세 번째 선반, 왼쪽이야.
A53: 카드는 3줄(검색어·출처·키워드)과 마지막 시그니처로 짧게 유지한다. 이 카드가 모이면 교재 전체의 이탈리아어 자료 색인이 된다(Gramsci의 '수첩'). 카드를 넣을 화의 범위(전 화 vs Gramsci 등장 화)는 미결사항 참고.

Sheet 대화문규칙
A1: 대화문 규칙 — 모든 것은 대화문으로 풀어간다
A2: 이전 안(상황 30% + 대화 70%)을 폐기하고, 전 화를 「화자명: 대사」만으로 구성한다.
A4: 1. 원칙
A5: No | B5: 규칙 | C5: 내용 | D5: 예시
A6: 1 | B6: 전 화 100% 대화문 | C6: 지문(narrazione)은 0%. 각 화는 화자명 + 대사로만 구성한다. | D6: ROSA: Sono le cinque. Comincia la riunione.
A7: 2 | B7: 화 머리 표기 | C7: 부·화 번호, 제목, 장소·날짜는 낭독하지 않는 표기 전용 한 줄(메타). 낭독 본문에는 넣지 않는다. | D7: [11부 4화 · Pronto soccorso al collasso]
A8: 3 | B8: 괄호 무대지시 금지 | C8: 행동·표정·침묵은 괄호 지문이 아니라 대사로 표현한다. | D8: (Rosa posa il piatto) → ROSA: Poso 'sto piatto prima che voli.
A9: 4 | B9: 장소·시간 소개 | C9: 지정 화자가 대사로 알린다: Rosa(식사·장소), Sofia(질문), Garibaldi(보고). | D9: ROSA: Sono le cinque. Riunione al mio tavolo.
A10: 5 | B10: 시간 경과·장면 전환 | C10: 인물이 말로 알린다. 전환은 화자 교체 + 장소 언급으로. | D10: GALILEO: Sono passati tre mesi dallo sfratto, vero?
A11: 6 | B11: 문서·기사·메모 | C11: 소리 내어 읽는다: Marco=조항, Galileo=기사·뉴스레터, Dante=초고·메모, Gramsci=카드. | D11: MARCO: Articolo 3: «Tutti i cittadini hanno pari dignità sociale…»
A12: 7 | B12: 무거운 장면 (죽음·침묵) | C12: 짧은 호명·확인 대사로 처리한다. | D12: SOFIA: Cesare? / GIULIA: Non c'è più, Sofia.
A13: 8 | B13: 내면·감정 | C13: 독백은 '소리 내어 하는 말'로만 허용. 감정 노출은 Montessori의 되받기 화법을 활용. | D13: MONTESSORI: Allora ti senti sola. È così?
A14: 9 | B14: 문장 길이 | C14: 1부(B1): 대사 한 줄 15단어 이내. Cesare·Marco의 격식체는 한두 줄만 '어른들 말투 맛보기'. 부가 올라갈수록 인물별 허용 길이 확대. Sofia의 질문은 끝까지 짧게. | D14: 1부 1화 대본(1부1화_Un_altra_lettera.docx)으로 한 줄 15단어 이내 점검
A15: 10 | B15: 화당 분량 = 120턴 | C15: 한 화는 대화 120턴(화자 교대 1회 = 1턴)으로 구성한다. 한 턴은 1부 15단어 이내, 연설·조항·기사 낭독은 긴 턴 1개로 세되 화당 3개까지. 화 유형별 도입·장면·절정·마무리 배분과 화자 점유율은 '턴_설계' 시트. | D15: 120턴 중 장면 전환·시간·장소 안내 5~10턴, Sofia 질문→재설명 6~12턴
A16: 11 | B16: 시그니처 표현 | C16: 화자 식별 장치이자 반복 학습 문장. 한 화에 화자당 1~2회까지.
A17: 12 | B17: Sofia의 질문 장치 | C17: 어려운 용어 뒤에는 Sofia의 질문 → 쉬운 재설명이 온다 (전문 표현 → 쉬운 표현 짝). | D17: SOFIA: Scusi, cosa significa?
A18: 13 | B18: Gramsci의 카드 | C18: 카드는 구술로 처리한다 (Gramsci_출처 시트 템플릿). | D18: GRAMSCI: Annota. Cerca: …
A19: 14 | B19: 욕설 수위 | C19: cazzo, vaffanculo 등은 교재 제외. 순한 표현만 (Sofia_폭발과욕 시트).
A20: 15 | B20: 호칭 전환 | C20: tu/Lei 전환은 대사로 명시한다 (호칭규칙 시트). | D20: CESARE: Puoi darmi del tu.
A21: 16 | B21: 가상 정치 세계 | C21: 정당·정치인은 전부 가상. 실존 정치인·정당명을 쓰지 않고, 대통령은 직접 대사를 주지 않는다 (절차 결과는 양원 의장 대사나 공식 발표문으로). | D21: PRESIDENTE DEL SENATO: Favorevoli: centodue. Contrari: centouno.
A22: 17 | B22: 현안을 다루는 법 | C22: 시사 현안은 가상 설정으로 각색하고 실존 인물·참사 희생자를 특정하지 않는다. 찬반 양측이 각자의 가장 강한 논거를 말하게 하고, 결론은 화 안에서 제도의 결과(표결·판결·협약)로만 닫는다. 수치는 Gramsci의 카드로 출처를 안내한다. | D22: SOFIA: Scusi, cosa sono gli «affitti brevi»? / ALESSANDRO: Case affittate ai turisti per pochi giorni.
A23: 18 | B23: 화자 표기 | C23: 화자명은 대문자 + 콜론. 이탈리아어 본문과 한국어 번역은 열(또는 파일)을 분리해 낭독 시 번역이 섞이지 않게 한다. | D23: SOFIA: BASTA!
A24: 19 | B24: 고전 인용 | C24: 인물마다 다른 이탈리아 고전 출처를 맡겨 화마다 1~2명이 짧게 인용한다. 부활한 인물은 주로 자기 자신의 글을 인용한다(자기 인용 개그). 전부 저작권 만료 공유 저작물만 쓰고, 원문을 정확히 인용한다 (배정표는 아래 3번). | D24: DANTE: Fatti non foste a viver come bruti, ma per seguir virtute e canoscenza.
A26: 2. 지문 → 대사 대체표
A27: No | B27: 기존 지문 | C27: 대사 처리 (IT) | D27: 담당 화자
A28: 1 | B28: (Silenzio.) 폭발 직후 정적 | C28: «Uh.» — 정적 대신 짧은 감탄으로 멈춤을 표현 | D28: Rosa
A29: 2 | B29: (Posa il piatto.) 행동 | C29: «Poso 'sto piatto prima che voli.» | D29: Rosa
A30: 3 | B30: 장소 도입 | C30: «Sono le cinque. Riunione al mio tavolo.» | D30: Rosa
A31: 4 | B31: 보고·상황 정리 | C31: «Nulla da segnalare.» / «C'è da segnalare.»(12부 8화) | D31: Garibaldi
A32: 5 | B32: 서류를 건넴 | C32: «Terzo ripiano, a sinistra.» | D32: Gramsci
A33: 6 | B33: 숫자 제시 | C33: «Tre milioni duecentomila, in quattordici bonifici.» | D33: Alessandro, Francesco
A34: 7 | B34: 감정 드러내기 | C34: «Allora ti senti arrabbiata. È così?» | D34: Montessori
A35: 8 | B35: 시간 경과 | C35: «Sono passati tre mesi dallo sfratto, vero?» | D35: Galileo (질문 형태)
A36: 9 | B36: 신문 기사 삽입 | C36: Galileo가 뉴스레터 «Nuncius» 첫 문단을 소리 내어 읽는다 | D36: Galileo
A37: 10 | B37: 연설문 초고 삽입 | C37: Dante가 초고를 읽고 Marco가 고친다 | D37: Dante, Marco
A38: 11 | B38: 투표 결과 전광판·자막 | C38: 양원 의장이 표결 결과를 낭독한다: «Presenti: quattrocento. Votanti… Favorevoli…» | D38: PRESIDENTE DELLA CAMERA / DEL SENATO
A39: 12 | B39: 대통령 협의·선서 | C39: 대통령은 대사 없이, 협의 결과는 공식 발표문으로 전달하고 Marco가 선서 문구(«Giuro di essere fedele alla Repubblica…»)를 말한다 | D39: 발표문(가상), Marco
A41: 3. 고전 인용 배정 (화마다 1~2명)
A42: 인물마다 다른 출처를 맡겨 반복되지 않게 하고, Rosa가 거의 전 화에 등장하므로 로테이션 캐스트인 1부에서도 대부분의 화가 커버된다. 전부 저작권 만료 공유 저작물(단테·마키아벨리·갈릴레이·베카리아·만초니 등은 수백 년 전, 그람시는 1937년·몬테소리는 1952년 사망으로 사후 70년 경과)과 헌법 조문만 쓰고, 원문을 정확히 인용한다. 출처가 불확실한 '명언'(예: 가리발디의 «Qui si fa l'Italia o si muore»는 전언)은 '전해지는 말'임을 대사로 밝히거나 쓰지 않는다.
A43: 인물 | B43: 출처 | C43: 쓰는 방식 | D43: 실제 인용 예시 (IT·라틴어) | E43: 등장 부
A44: Rosa | B44: 로마·이탈리아 속담(proverbi) | C44: 인용이 아니라 그냥 말버릇처럼 자연스럽게 섞인다. 따뜻하고 실용적. 로마 사투리 버전도 가끔. | D44: Roma non fu fatta in un giorno. / Chi va piano va sano e va lontano. | E44: 거의 전 화
A45: Cesare | B45: 자신의 『갈리아 전기』, 수에토니우스가 전한 말 | C45: 정중하게 비꼬는 코미디로(평소), 죽음 앞에서는 무겁게(11부). 자기 책을 인용하며 3인칭으로 자랑한다. | D45: Gallia est omnis divisa in partes tres. / Horum omnium fortissimi sunt Belgae. (De bello Gallico I, 1) | E45: 1부, 11부
A46: Gramsci | B46: 자신의 글(『옥중수고』·『옥중서간』, 1917년 기사 등) | C46: 감정으로 낭송하지 않고 서지 정보처럼 인용한다 — 「몇 번째 선반」식 습관과 같은 화법. | D46: Odio gli indifferenti. (La città futura, 1917) / Istruitevi, perché avremo bisogno di tutta la vostra intelligenza. (L'Ordine Nuovo, 1919) | E46: 1·2·6·11·12·13부
A47: Dante | B47: 자신의 『신곡』 | C47: 자기 글이 부끄러운 척하며 결국 인용으로 도피한다. 시적이고 머뭇거리는 톤. | D47: Nel mezzo del cammin di nostra vita… (Inf. I) / Fatti non foste a viver come bruti, ma per seguir virtute e canoscenza. (Inf. XXVI) | E47: 6부 이후
A48: Marco | B48: 베카리아 『범죄와 형벌』, 이탈리아 헌법 | C48: 총리가 되어 가며 연설에 섞어 쓴다. | D48: È meglio prevenire i delitti che punirgli. (Beccaria, cap. XLI) / Costituzione, art. 3: «Tutti i cittadini hanno pari dignità sociale…» | E48: 8~13부
A49: Machiavelli | B49: 자신의 『군주론』 | C49: 현실 분석의 근거로 건조하게 인용하고, 오독에 대해 투덜댄다. | D49: …è molto più sicuro essere temuto che amato, quando si abbia a mancare dell'uno de' dua. (Il Principe, XVII) | E49: 7부 이후
A50: Galileo | B50: 자신의 『시금석(Il Saggiatore)』 | C50: 관찰과 증거를 강조할 때 한 줄. | D50: La filosofia è scritta in questo grandissimo libro che continuamente ci sta aperto innanzi a gli occhi (io dico l'universo)… (Il Saggiatore) | E50: 1부 이후
A51: Garibaldi | B51: 자신의 전보·회고록 | C51: 짧고 군인답게. «Obbedisco»(1866년 전보)는 명령에 따를 때의 개그로. | D51: Obbedisco. (1866) | E51: 전 부

Sheet 변경이력_미결
A1: 변경 이력과 미결 사항
A3: 1. 변경 이력
A4: No | B4: 항목 | C4: 이전 | D4: 이후 | E4: 반영 시트
A5: 1 | B5: 인원 | C5: 13인 (내각) | D5: 15인 — 주력 4인 + 부활 7인 + 서민·청년 3인 + 금융 1인. 15인 모두가 장관은 아니므로 '내각'보다 핵심 그룹(Il Cerchio di Testaccio) 개념 사용 | E5: 개요, 캐릭터
A6: 2 | B6: 부활자 설정 | C6: 현대 인물만의 원로 그룹 | D6: 각자의 시대에 죽었다가 이유 없이 현재 로마에 되살아난 역사 인물 7인(Cesare·Machiavelli·Garibaldi·Dante·Gramsci·Galileo·Montessori). 부활의 이유는 끝내 설명하지 않는다 | E6: 캐릭터
A7: 3 | B7: 가상 상호명 | C7: 실존 로펌·회계법인명 | D7: Ferrari & Colombo Studio Legale / Conti Revisori / Zenit Consulting (가상) | E7: 캐릭터
A8: 4 | B8: 기관 실명 | C8: 실존 은행·병원명 | D8: Banca Adriatica(가상), San Camillo 응급실은 '가상 설정'으로 운영·인물 모두 허구 (이야기 속에서 부패와 얽히기 때문) | E8: 캐릭터
A9: 5 | B9: Cesare | C9: 우아한 원로 | D9: 가장 까칠한 심술 영감 + 시한부 (11부 12화 두 번째 죽음). 가짜 병은 엄살, 진짜 병은 만성 심부전 | E9: Cesare_죽음
A10: 6 | B10: Sofia 폭발 | C10: 자주 폭발하는 인물 (안) | D10: 폭발은 1부·9부 딱 2회. 욕은 폭발 장면 한정 | E10: Sofia_폭발과욕
A11: 7 | B11: Gramsci | C11: 침묵으로 대답 | D11: 결론 대신 출처(서가 위치·법령·검색어)를 가리킴 — 『옥중수고』의 수첩 습관 | E11: Gramsci_출처
A12: 8 | B12: Gramsci 대사 | C12: «Segui il denaro. E la legge che lo sorveglia.» | D12: «Ogni denaro ha una legge che lo sorveglia. Cercala.» — Francesco의 시그니처 «Segui il denaro.»와 중복 방지 | E12: Gramsci_출처
A13: 9 | B13: 형식 | C13: 상황 설명 30% + 대화 70% | D13: 전 화 100% 대화문 (지문 없음) | E13: 대화문규칙
A14: 10 | B14: 1부 시범 장면 | C14: 괄호 지문 포함 | D14: 모든 지문을 대사로 대체. 이후 '1부_시범대사' 시트는 삭제하고 1부 1화 전체 대본(1부1화_Un_altra_lettera.docx)으로 대체 (2026-09-25) | E14: 1부 1화 대본
A15: 11 | B15: 부 수 | C15: 11부작 (132화) → 12부작 (144화) | D15: 13부작 (156화). 11부를 '국정 I'과 '국정 II'로 분리하고 귀환 부를 13부로 | E15: 개요, 13부_구성, 아크_구성계획, 화별목차_전체
... A34: 30 | B34: 현안_분포 재집계 | C34: 화별 목차와 어긋난 기호 배치 | D34: 현안_배치의 주요(●)·곁가지(○) 배치를 기준으로 부별 기호를 다시 채움 | E34: 현안_분포
A36: 2. 미결 사항 (확정 필요)
A37: No | B37: 항목 | C37: 내용 | D37: 제안 | E37: 관련 시트
A38: 1 | B38: 부활의 규칙 | C38: 부활자 7인의 신분(서류·국적·나이)과 부활 이유를 어디까지 설명할지. | D38: 끝까지 설명하지 않고 개그로만 처리(공증인의 곤혹, 선거 출마 자격 등은 피해 간다) | E38: 캐릭터
A39: 2 | B39: Gramsci 카드의 범위 | C39: 카드를 전 화(156화)에 넣을지, Gramsci 등장 화에만 넣을지. | D39: 등장 화에만 넣고, 미등장 화는 Sofia가 사전(Treccani)을 찾는 짧은 대사로 대체 | E39: Gramsci_출처
A40: 3 | B40: Sofia → 주력 4인 호칭 전환 | C40: Cesare에게만 12부 1화에서 tu로 전환한다는 것 외에, 다른 인물에게 언제 tu로 넘어가는지 미정. | D40: 6부 만남 이후 자연스럽게 tu (Cesare·Garibaldi·Francesco는 Lei 유지) | E40: 호칭규칙
A41: 4 | B41: 경과 연수 가정 | C41: 1부→11부 6년 가정(Cesare 55→61세). 13부는 그 이후 시점. | D41: 확정 시 개요!C11만 수정 | E41: 개요
A42: 5 | B42: 정치 직책 | C42: 15인의 직책은 제안 단계. Galileo(정부 대변인)·Montessori(청년 정신건강) 역할을 캐릭터 시트에 반영함. | D42: 부활자는 정식 장관보다 '자문'으로 두는 안 유지 (Garibaldi만 장관) | E42: 캐릭터
A43: 6 | B43: 법령·조항 확인 | C43: 출처표·제도표의 법령 번호·조항은 기획 시점 지식 기준. | D43: 교재 반영 전 Normattiva 현행 통합본으로 확인. 선거 서명 요건·교섭단체 인원·TUEL 제73조는 특히 확인 | E43: Gramsci_출처, 정치제도
A44: 7 | B44: 대화량 실측 교정 | C44: 화당 120턴은 확정. 화자 점유율·평균 단어/턴·낭독 속도(130단어/분)는 가정값이다. 이탈리아어는 스페인어와 단어 길이가 비슷해 기존 값 유지. | D44: 1부 1~3화 대본을 쓴 뒤 실제 턴·단어를 재서 '턴_설계'의 파란 값을 교정 | E44: 턴_설계
A45: 8 | B45: Montessori·Galileo 비중 보강 | C45: 가장 얇은 조연. | D45: 3·5부 상담 장면 확대, 12부 애도 상담·스파이웨어 검증 배정 | E45: 등장비중, Cesare_죽음
A46: 9 | B46: 정부 형태 | C46: CC 주도 연립(PPS·TA) + TB 사안별 지지 (현재 설정) | D46: PPS 장관 포함 여부와 연정 협약 문서의 대사화 결정 | E46: 정치경로_의석
A47: 10 | B47: 겸직 규정 확인 | C47: Alessandro는 시의원, Giulia는 주의원으로 직책을 분리하고 Marco만 하원에 출마시키는 설정. 이후 장관 임명 시 지방 의원직 처리. | D47: 지방 의원과 국회의원·장관의 겸직 불가 규정을 확인한 뒤 사퇴 장면을 넣을지 결정 | E47: 정치제도
A48: 11 | B48: 가상 수치 | C48: 의석 수(70·130 등)와 상원 1표 차 설정은 교육용 가상 수치. | D48: 드라마 효과에 맞춰 조정 가능 (정치경로_의석의 파란 셀) | E48: 정치경로_의석
... A59: 22 | B59: 로마 사투리 비율 | C59: Rosa·Paolo의 romanesco를 어느 정도 쓸지. | D59: B1 부(1·13부)는 화당 1~2마디, 표준어 병기 | E59: 대화문규칙
A61: 3. 진행 상황 반영 (2026-09-25, 이탈리아판 대본 집필 진행 중)
A63: No | B63: 항목 | C63: 내용 | D63: 결과 | E63: 관련 시트
A64: 1 | B64: 1~7부 대본 완성 | C64: 1부~7부 각 12화, 총 84화 실제 대본 완성 (100% 대화문, 화자별 색상 구분 docx) | D64: 완료 | E64: 제작현황
A65: 2 | B65: 8부 부분 완성 | C65: 8부 1~3화 완성 (광장 집회·입법 경로 설명·서명운동 도입). 4~12화는 미착수 | D65: 부분 완료 | E65: 제작현황
A66: 3 | B66: 미결 #3 해결: Sofia → 주력 4인 호칭 전환 | C66: 6부에서는 Sofia가 23세 이웃(tu). 주력 4인은 6부 4화 밤새움 장면에서 명시적으로 tu로 전환(«Diamoci del tu, ormai.»). Sofia가 인턴이 되는 1부부터는 Lei로 다시 전환, Cesare에게만은 6부도 계속 Lei 유지 | D66: 해결됨 | E66: 호칭규칙
A67: 4 | B67: 미결 #15 해결: 가상 인물 목록 | C67: 1~8부(부분) 집필 중 등장한 모든 가상 인물을 이름·최초 등장·역할 기준으로 정리. 이름 중복 5건 발견·개명(Iolanda→Pina/Federica/Valeria, Davide→Ottavio/Matteo) | D67: 해결됨 | E67: 가상인물_등록부
A68: 5 | B68: 미결 #17 해결: 7부 3화 톤 | C68: 선정적 묘사 금지, 피해사실 자체는 상세히 다루지 않고 절차·제도(형법 609-bis조, 공소시효)와 인물들의 존엄 있는 태도에만 집중. '동의' 명문화 vs 절차 개혁, 양쪽 모두 선의로 그림 | D68: 해결됨 | E68: 7부 3화 대본
A69: 6 | B69: 부활 인물 직접 호칭 규칙 신설 | C69: Console Cesare / Segretario Gramsci / Segretario Machiavelli / Generale Garibaldi / Poeta Dante / Professor Galileo / Dottoressa Montessori — 사용자 지시로 새로 확정 | D69: 신규 | E69: 호칭규칙
A70: 7 | B70: 연속성 오류 수정: Chiara의 Zenit 상사 | C70: 5부 2화에서 잘못 쓴 이름 Vergani를 4/6/11화와 동일하게 Moretti로 통일 | D70: 수정됨 | E70: 5부2화
A71: 8 | B71: 2~5부(과거) 구조 확정 | C71: 금요일 프레임(1·5·9·12화)이 현재·과거 장면을 감싸고, 일반 화는 전부 과거로 진행. B2~C1, 20단어 제한(1부 B1 15단어보다 완화) | D71: 확정 | E71: 2~5부 전체
A72: 9 | B72: 6부 구조 확정 | C72: 프레임 없는 12화 연속 서사, B2, 18단어 제한. 12화 마지막 대사가 1부 1화 첫 대사와 정확히 맞물려 원형 구조 완성 | D72: 확정 | E72: 6부 전체
A73: 10 | B73: 7~8부 구조 확정 | C73: 프레임 없음. 7부는 1부의 연속(개소 1년 후), 8부는 7부의 연속. 둘 다 B2~C1, 20단어 제한 | D73: 확정 | E73: 7~8부

Sheet 제작현황
A1: Roma 이탈리아어 낭독 교재 — 제작 현황 (2026-09-25 기준)
A2: 1부에서 8부 3화까지 실제 대본이 완성되었습니다. 이후 화는 미착수 상태입니다.
A4: 부 | B4: 화 | C4: 제목 (IT) | D4: 제목 (한국어) | E4: 상태 | F4: 파일명 | G4: 턴 수
A5: 1 | B5: 1 | C5: Un'altra lettera | D5: 또 다른 편지 | E5: 완료 | F5: 1부1화_Un_altra_lettera.docx | G5: 119
A6: 1 | B6: 2 | C6: La clausola che non sale | D6: 오르지 않는 조항 | E6: 완료 | F6: 1부2화_La_clausola_che_non_sale.docx | G6: 120
A7: 1 | B7: 3 | C7: L'avviso delle otto | D7: 여덟 시의 통지 | E7: 완료 | F7: 1부3화_Lavviso_delle_otto.docx | G7: 120
A8: 1 | B8: 4 | C8: Il furgone che non arrivò | D8: 오지 않은 트럭 | E8: 완료 | F8: 1부4화_Il_furgone_che_non_arrivò.docx | G8: 120
A9: 1 | B9: 5 | C9: Lo stagista della fabbrica | D9: 공장의 인턴 | E9: 완료 | F9: 1부5화_Lo_stagista_della_fabbrica.docx | G9: 120
A10: 1 | B10: 6 | C10: Basta! | D10: 그만! | E10: 완료 | F10: 1부6화_Basta.docx | G10: 120
A11: 1 | B11: 7 | C11: La bambina con la febbre | D11: 열이 나는 아이 | E11: 완료 | F11: 1부7화_La_bambina_con_la_febbre.docx | G11: 120
A12: 1 | B12: 8 | C12: Un codice per tutti | D12: 모두를 위한 코드 | E12: 완료 | F12: 1부8화_Un_codice_per_tutti.docx | G12: 120
A13: 1 | B13: 9 | C13: La vedova del quinto piano | D13: 5층의 미망인 | E13: 완료 | F13: 1부9화_La_vedova_del_quinto_piano.docx | G13: 120
A14: 1 | B14: 10 | C14: Segui il denaro | D14: 돈을 따라가라 | E14: 완료 | F14: 1부10화_Segui_il_denaro.docx | G14: 120
A15: 1 | B15: 11 | C15: Una carta di anni fa | D15: 수년 전 서류 | E15: 완료 | F15: 1부11화_Una_carta_di_anni_fa.docx | G15: 120
A16: 1 | B16: 12 | C16: La firma | D16: 서명 | E16: 완료 | F16: 1부12화_La_firma.docx | G16: 122
... A91: 8 | B91: 3 | C91: Cinquecentomila firme | D91: 50만 서명 | E91: 완료 | F91: 8부3화_Cinquecentomila_firme.docx | G91: 120
A92: 8 | B92: 4 | E92: 미착수
A93: 8 | B93: 5 | E93: 미착수
A94: 8 | B94: 6 | E94: 미착수
A95: 8 | B95: 7 | E95: 미착수
A96: 8 | B96: 8 | E96: 미착수
A97: 8 | B97: 9 | E97: 미착수
A98: 8 | B98: 10 | E98: 미착수
A99: 8 | B99: 11 | E99: 미착수
A100: 8 | B100: 12 | E100: 미착수
A101: 9 | B101: 1 | E101: 미착수
A102: 9 | B102: 2 | E102: 미착수
A103: 9 | B103: 3 | E103: 미착수
... A160: 13 | B160: 12 | E160: 미착수
A162: 진행률 | B162: 87 / 156화 완료 (55.8%)

Sheet 가상인물_등록부
A1: 가상 인물 등록부 (이름 중복 방지용 캐릭터 설정 자료)
A2: '변경이력_미결' 시트 미결사항 #15가 요구한 부록. 새 가상 인물을 만들 때는 이 목록과 겹치지 않는지 먼저 확인할 것.
A4: 이름 | B4: 최초 등장 | C4: 역할/설명 | D4: 비고
A5: AMINA | B5: 1부 7화 (La bambina con la febbre) | C5: (가상) 체류 서류가 없는 엄마
A6: ASSUNTA | B6: 2부 7화 (L'assemblea degli inquilini) | C6: (가상) 78세 세입자, 이 건물에서 평생을 산 인물
A7: BASSI | B7: 4부 3화 (Il cliente che paga bene) | C7: (가상) Conti Revisori 대표 파트너 / (가상) Conti Revisori 대표 파트너, Alessandro의 상사 / Conti Revisori 대표 파트너 (가상) / Conti Revisori 대표 파트너, Alessandro의 상사 (가상)
A8: CANCELLIERE | B8: 1부 4화 (Il furgone che non arrivò) | C8: 법원 서기 (가상)
A9: COLOMBO | B9: 2부 2화 (Un lunedì in Prati) | C9: (가상) Marco의 상사, 로펌 대표 파트너 / 로펌 대표 파트너 (가상, 과거)
A10: DAVIDE | B10: 1부 5화 (Lo stagista della fabbrica) | C10: 공장 인턴 (가상, 22세)
A11: DIRETTORE | B11: 3부 4화 (Un contratto che nessuno legge) | C11: San Camillo 병원장 (가상) / San Camillo 병원장 (가상, 과거)
A12: FATIMA | B12: 1부 2화 (La clausola che non sale) | C12: (가상) 세입자 이웃 — 감사 인사를 전하러 가족과 함께 찾아온다 / 임차인, 소피아의 옛 이웃(가상)
A13: FEDERICA | B13: 5부 6화 (La cella C47) | C13: (가상) 팀 동료 컨설턴트 | D13: 원래 Iolanda로 초고했다가 1부 Iolanda와 겹쳐 개명
A14: GIUDICE | B14: 2부 8화 (Il processo) | C14: (가상) 심리를 주재하는 판사
A15: IDA | B15: 1부 3화 (L'avviso delle otto) | C15: 테레사의 어머니, 거동이 불편한 고령자 (가상)
A16: IMPIEGATO | B16: 1부 4화 (Il furgone che non arrivò) | C16: 구청 직원 (가상)
A17: IOLANDA | B17: 1부 9화 (La vedova del quinto piano) | C17: 5층 이웃, 투자 사기 피해자(가상)
A18: KARIM | B18: 1부 11화 (Una carta di anni fa) | C18: 가상, Fatima의 남편, 의뢰인 / 파티마의 남편 (가상)
A19: LOREDANA | B19: 3부 2화 (Turno di notte) | C19: Giulia와 손발을 맞추는 간호사 (가상) / 간호사, Giulia와 손발을 맞추는 동료 (가상)
A20: MARINA | B20: 2부 11화 (La nipote di Assunta) | C20: Assunta의 손녀 (가상, 과거) / 세입자 총회를 안내하는 이웃 (가상)
A21: MARTINA | B21: 4부 2화 (Chiusura di bilancio) | C21: (가상) Alessandro와 함께 일하는 후배 감사인 / (가상) 후배 감사인, 이번이 첫 결산 마감이다 / Alessandro와 함께 일하는 후배 감사인 (가상)
A22: MATTEO | B22: 5부 4화 (Progetto Icaro) | C22: Chiara와 함께 일하는 동료 컨설턴트 | D22: 원래 Davide로 초고했다가 1부 Davide와 겹쳐 개명
A23: MORETTI | B23: 5부 2화 (Zenit, 32° piano) | C23: (가상) Zenit Consulting의 파트너, Chiara의 상사 / (가상) Zenit 파트너, Chiara의 상사 / (가상) Zenit의 파트너, Chiara의 상사 / 가상, Zenit Consulting 파트너, Chiara의 상사 | D23: 5부 2화에서는 Vergani로 잘못 쓰였다가 4/6/11화와 통일(Chiara의 Zenit 상사)
A24: NOA | B24: 1부 7화 (La bambina con la febbre) | C24: (가상) 열이 나는 아이, 4세
A25: RICCI | B25: 4부 6화 (La riunione dei soci) | C25: (가상) 시니어 파트너
A26: RUGGERI | B26: 5부 3화 (La bottega dei Ruggeri) | C26: (가상) 3대째 이어온 가족 공방의 사장
A27: SANTORO | B27: 2부 3화 (Il cliente d'oro) | C27: (가상) Gruppo Meridiano 회장 — 2·4부에도 등장한 그 고객사 / (가상) 그루포 메리디아노 회장 / Gruppo Meridiano 회장 (가상) / Gruppo Meridiano 회장 (가상, 과거)
A28: SIRAGUSA | B28: 4부 7화 (Il comitato rischi) | C28: 시니어 파트너, 리스크 위원회 위원 (가상)
A29: TERESA | B29: 1부 3화 (L'avviso delle otto) | C29: 퇴거 위기의 세입자 (가상)
A30: UFFICIALE | B30: 1부 4화 (Il furgone che non arrivò) | C30: 집행관(ufficiale giudiziario) (가상)
A31: VALENTINI | B31: 4부 6화 (La riunione dei soci) | C31: (가상) 시니어 파트너
A32: VALERIA | B32: 7부 3화 (Il tempo che ha punito la vittima) | C32: 의뢰인 (가상) | D32: 원래 Iolanda로 초고했다가 1부 Iolanda와 겹쳐 개명 (7부 3화 민감 소재 상 특히 주의)
A33: VALLI | B33: 5부 7화 (Il tavolo della trattativa) | C33: 가상, Gruppo Meridiano 측 담당 임원
