Workbook

Sheet 개요
A1: Paris 프랑스어 낭독 교재 — 캐릭터 바이블 (부활자 특별편)
A2: v1.0 · 파리 배경 13부작 옴니버스(156화) · 부활 7인 = Napoléon·Voltaire·Olympe·Jeanne·Sartre·Curie·Hugo
B4: 기본 설정
B5: 부 수 | C5: 13 | D5: 1 사무소(Belleville, 개소 1개월 후, 6사건×2화) → 2~5 각자의 과거 → 6 만남 → 7 전면전 → 8 창당·파리 시의회 선거 → 9 파리 시의회(Hôtel de Ville) → 10 대선·대통령 취임·총선(Élysée) → 11 국정 I(EU 협상·Napoléon 사망) → 12 국정 II(장례·유작 메모 승계) → 13 귀환(원형 구조)
B6: 부당 화 수 | C6: 12 | D6: 각 부 12화
B7: 총 화 수 | C7: =C5*C6 -> 156 | D7: 부 수 × 부당 화 수 (자동 계산)
B8: 등장인물 수 | C8: =COUNTA(캐릭터!$D$5:$D$19) -> 15 | D8: 캐릭터 시트의 약칭 개수
B9: 남성 인물 수 | C9: =COUNTIF(캐릭터!$G$5:$G$19,"남") -> 8 | D9: 음색이 다양할수록 화자 구분이 쉬워 남 8 : 여 7로 배분 (Olympe 포함)
B10: 여성 인물 수 | C10: =COUNTIF(캐릭터!$G$5:$G$19,"여") -> 7
B11: 1부→11부 경과 연수 (가정) | C11: 6 | D11: 가정값: Napoléon이 1부 51세(부활 시 외형 나이) → 11부 약 57세가 되도록 잡음. 확정 시 이 셀만 수정하면 캐릭터 시트의 나이가 자동 갱신. (캐릭터 시트 '나이(11부)' 열)
B12: 배경·언어 | C12: 파리 (벨빌) | D12: 표준 프랑스어: 친한 사이 tu, 공식 석상은 vous/공식 호칭.
B13: 형식 | C13: 전 화 100% 대화문, 화당 120턴 | D13: ="지문(didascalies) 없음. 화당 "&턴_설계!$B$5&"턴 × "&C7&"화 = "&TEXT(C7*턴_설계!$B$5,"#,##0")&"턴. 상세는 '대화문규칙'·'턴_설계' 시트." -> 지문(didascalies) 없음. 화당 120턴 × 156화 = 18,720턴. 상세는 '대화문규칙'·'턴_설계' 시트.
B15: 그룹별 인원
B16: 주력 4인 | C16: =COUNTIF(캐릭터!$B$5:$B$19,B16) -> 4 | D16: Nicolas(변호사)·Camille(의사)·Julien(회계사)·Léa(컨설턴트)
B17: 부활 7인 | C17: =COUNTIF(캐릭터!$B$5:$B$19,B17) -> 7 | D17: Napoléon(전 황제)·Voltaire(계몽사상가)·Olympe(여성인권가)·Jeanne(전사)·Sartre(철학자)·Curie(과학자)·Hugo(문호) ※ 각자의 시대에 죽었다가 이유 없이 현재 파리에 되살아나 사무소에 합류 (부활 시점은 인물마다 다름 — 2~5부 과거 장면에 카메오로 나오는 인물은 그때 이미 파리에 살고 있음)
B18: 서민·청년 | C18: =COUNTIF(캐릭터!$B$5:$B$19,B18) -> 3 | D18: Monique(비스트로 사장)·Karim(노조위원장)·Manon(인턴)
B19: 금융 | C19: =COUNTIF(캐릭터!$B$5:$B$19,B19) -> 1 | D19: Philippe(전 은행 지점장)
B22: 시트 안내 (클릭하면 이동)
B23: 캐릭터 | C23: 기준표 | D23: 14인의 이름·나이·결핍·말투·시그니처·낭독 포인트·대화문 장치·직책·현안 담당
B24: 등장비중 | C24: 기준표 | D24: 13부 배분표, 합계·비중·등급(수식), 조연 단독 중심 화 목표
B25: 턴_설계 | C25: 기준표 | D25: 화당 120턴 설계: 부별 화자 점유율(턴 기준), 평균 단어/턴, 화당 단어·낭독 시간(수식), 화 유형별 턴 구성, 집필 규칙
B26: 13부_구성 | C26: 구조 | D26: 13부 한눈에 보기: 배경·핵심 내용·난이도(CEFR)·반영 제도
B27: 아크_구성계획 | C27: 구성 계획 | D27: 1~13부 아크별 구성 계획: 서사 기능·로그라인·비트·인물 아크·복선·현안·언어 설계
B28: 화별목차_전체 | C28: 목차 | D28: 1~13부 156화의 서사 기능·제목(FR)·핵심 사건·반영 제도·인물·현안 (필터 가능)
B29: 복선_회수 | C29: 구성 계획 | D29: 복선 설치→회수 28건과 간격(부)을 수식으로 계산
B30: 현안_배치 | C30: 현안 | D30: 프랑스 현안 18개를 어느 화에 어떻게 녹일지 배치, 균형 유의, 현실 기준값
B31: 현안_분포 | C31: 현안 | D31: 부 × 현안 분포표: 전용 화(●)와 곁가지(○)를 수식으로 집계
B32: 정치제도 | C32: 현실 제도 | D32: 제5공화국 제도 기준표: 정당·선거·대통령·의회·정부·지방자치·사법·EU (확인 상태 표시)
B33: 정치경로_의석 | C33: 현실 제도 | D33: 창당→대통령 경로와 가상 득표·의석·표결 시뮬레이션(수식): 대선 1차·결선, 총선 577석, 불신임안(motion de censure)
B34: 호칭규칙 | C34: 규칙 | D34: tu / vous(단수 존칭) / vous(복수), 의회·대통령·시의회 공식 호칭
... B40: 변경이력_미결 | C40: 관리 | D40: 지금까지의 변경 이력과 확정이 필요한 미결 사항
B42: 범례
B43: 파란 글씨 | C43: 직접 입력한 값 (수정 가능)
B44: 노란 배경 | C44: 가정 · 확정이 필요한 값
B45: 검정 글씨 | C45: 수식으로 계산되는 값 (직접 수정하지 말 것)
B47: 주의: 성별·나이·기관명은 기획용 가상 설정입니다. 법령 번호·조항은 교재에 넣기 전에 Légifrance(legifrance.gouv.fr)의 현행 텍스트(version en vigueur)로 확인하세요.

Sheet 캐릭터
A1: 캐릭터 바이블 — 15인 (Paris 프랑스어 낭독 교재 — 캐릭터 바이블 (부활자 특별편))
A2: v1.0 · 파리 배경 13부작 옴니버스(156화) · 부활 7인 = Napoléon·Voltaire·Olympe·Jeanne·Sartre·Curie·Hugo
A4: No | B4: 그룹 | C4: 이름 | D4: 약칭 | E4: 나이 (1부) | F4: 나이 (11부) | G4: 성별 | H4: 직업·신분 | I4: 전 소속 (가상) | J4: 결핍 (Blessure) | K4: 말투 | L4: 시그니처 표현 | M4: 낭독 포인트 | N4: 대화문 장치 (지문 대체) | O4: 정치 직책 (8~13부, 제안) | P4: 1부 등장 방식 | Q4: 등장 화 수 | R4: 등급 | S4: 현안 담당 (ID)
A5: 1 | B5: 주력 4인 | C5: Nicolas Lefevre | D5: Nicolas | E5: 39 | F5: =E5+개요!$C$11 -> 45 | G5: 남 | H5: 변호사 (기업·규제 전문) | I5: Vasseur & Delorme Avocats (전 파트너 후보) | J5: 승소율은 높지만, 강제퇴거 소송에서 이긴 사건 하나가 계속 마음에 걸린다. | K5: 문장이 완결되고 격식체(접속법 사용). 초반엔 차갑게 조항을 인용, 후반엔 연설가로 성장. | L5: Procédons dans l'ordre.\nAvec tout le respect que je vous dois, ce n'est pas ce que dit la loi.\n(후반) Je ne vous demande pas de me croire. Je vous demande de lire le texte. | M5: 또박또박, 중저음. | N5: 법조문을 소리 내어 읽어 상황을 설명한다. | O5: 당 대표(8부) → 대선 후보(9부 12화) → 대통령(10부 8화 취임) | P5: 본격 | Q5: =INDEX(등장비중!$O$5:$O$19,MATCH($D5,등장비중!$A$5:$A$19,0)) -> 108 | R5: =INDEX(등장비중!$Q$5:$Q$19,MATCH($D5,등장비중!$A$5:$A$19,0)) -> 주연 | S5: P1·P3·E1
A6: 2 | B6: 주력 4인 | C6: Camille Girard | D6: Camille | E6: 41 | F6: =E6+개요!$C$11 -> 47 | G6: 여 | H6: 응급의학과 전문의 | I6: Hôpital Saint-Bernard 응급실 (가상) | J6: 살리지 못한 환자의 이름을 전부 외우고 있다. | K6: 짧고 명령형, 블랙유머. | L6: Ce n'est pas une statistique, c'est une personne.\nD'abord, respire.\nJ'ai vu pire un mardi ordinaire. | M6: 빠른 템포, 짧은 호흡. | N6: 명령형으로 행동을 말하며 진행한다. | O6: 파리 시의원·AP-HP 감독위원(9부) → 보건부 장관(11부~) | P6: 본격 | Q6: =INDEX(등장비중!$O$5:$O$19,MATCH($D6,등장비중!$A$5:$A$19,0)) -> 98 | R6: =INDEX(등장비중!$Q$5:$Q$19,MATCH($D6,등장비중!$A$5:$A$19,0)) -> 준주연 | S6: S3·S4·N8
A7: 3 | B7: 주력 4인 | C7: Julien Moreau | D7: Julien | E7: 37 | F7: =E7+개요!$C$11 -> 43 | G7: 남 | H7: 공인회계사 (감사) | I7: Bertin & Roux Audit (가상, 전 시니어 파트너) | J7: 부정을 발견하고도 서명했던 기억. | K7: 건조하고 정확, 비꼬는 유머. | L7: Montrez-moi les documents.\nÇa ne colle pas.\nMontrez-moi les chiffres, je vous dirai qui vous êtes. | M7: 일정한 속도, 결론에서 톤을 낮춘다. | N7: 숫자를 소리 내어 읽는다. | O7: 파리 시의원·예산 담당(9부) → 경제·재정부 장관(Bercy, 11부~) | P7: 본격 | Q7: =INDEX(등장비중!$O$5:$O$19,MATCH($D7,등장비중!$A$5:$A$19,0)) -> 110 | R7: =INDEX(등장비중!$Q$5:$Q$19,MATCH($D7,등장비중!$A$5:$A$19,0)) -> 주연 | S7: E3·N2
A8: 4 | B8: 주력 4인 | C8: Léa Dubois | D8: Léa | E8: 36 | F8: =E8+개요!$C$11 -> 42 | G8: 여 | H8: 전략 컨설턴트 | I8: Zénith Consulting (가상, La Défense) | J8: 구조조정 표 한 칸이 수백 명의 해고였음을 뒤늦게 안다. | K8: 영어식 경영 용어가 섞인 빠른 말투, 후반 쉬운 말로 성장. | L8: Mettons ça dans une matrice.\n(후반) Bon, sans slides : de quoi tu as vraiment besoin ? | M8: 초반 숨 가쁜 톤, 후반 솔직한 톤. | N8: 프레젠테이션식 브리핑. | O8: 선거캠프 총괄 참모(8~10부) → 엘리제궁 비서실장(secrétaire générale de l'Élysée) | P8: 본격 | Q8: =INDEX(등장비중!$O$5:$O$19,MATCH($D8,등장비중!$A$5:$A$19,0)) -> 101 | R8: =INDEX(등장비중!$Q$5:$Q$19,MATCH($D8,등장비중!$A$5:$A$19,0)) -> 준주연 | S8: E2·P1
A9: 5 | B9: 부활 7인 | C9: Napoléon Bonaparte | D9: Napoléon | E9: 51 | F9: =E9+개요!$C$11 -> 57 | G9: 남 | H9: 부활한 황제·전략가 (1769–1821) | I9: 프랑스 제1제국 황제, 세인트헬레나 유배지에서 사망 | J9: 자신의 몰락까지 전략적으로 복기하는 버릇이 있다 — 패배조차 전술적으로 설명하려 든다. 세인트헬레나에서 자신을 죽인 위(胃)의 병이 되살아났다는 것만은 숨긴다. | K9: 단호하고 명령조, 짧고 강한 문장. 자신의 전투를 예시로 모든 걸 설명한다. | L9: Impossible n'est pas français — enfin, plus maintenant, apparemment.\n(현대 용어 오해) Un « serveur » ? Un valet qui ne dort jamais. Très impérial.\n« Pare-feu » ? Nous appelions ça un siège. | M9: 짧고 단호한 톤, 명령형. | N9: 자신의 옛 전투와 현재 상황을 비교해 설명한다. | O9: 대통령 특사(외교·안보) — 11부 9~11화 브뤼셀 협상, 11부 12화 두 번째 죽음 | P9: 준본격 (겨울 복선) | Q9: =INDEX(등장비중!$O$5:$O$19,MATCH($D9,등장비중!$A$5:$A$19,0)) -> 65 | R9: =INDEX(등장비중!$Q$5:$Q$19,MATCH($D9,등장비중!$A$5:$A$19,0)) -> 핵심 조연 | S9: N3·E3
A10: 6 | B10: 부활 7인 | C10: Voltaire | D10: Voltaire | E10: 83 | F10: =E10+개요!$C$11 -> 89 | G10: 남 | H10: 부활한 계몽사상가·풍자가 (1694–1778) | I10: 『캉디드』 저자, 바스티유 투옥 경험 | J10: 자신이 그렇게 싸운 관용과 이성이 오늘날에도 여전히 부족하다는 걸 매일 확인하며 냉소로 버틴다. | K10: 신랄하고 재치 있는 풍자, 팜플렛 문체. | L10: (고전 인용) Il faut cultiver notre jardin.\n(현대 용어 재해석) « Fake news » ? Nous appelions ça la censure royale — au moins, aujourd'hui, tout le monde peut mentir également. | M10: 빠르고 재치있는 톤. | N10: 현재 사안을 풍자적 우화로 요약해 설명한다. | O10: 엘리제궁 공보·메시지 자문 | P10: 카메오 | Q10: =INDEX(등장비중!$O$5:$O$19,MATCH($D10,등장비중!$A$5:$A$19,0)) -> 63 | R10: =INDEX(등장비중!$Q$5:$Q$19,MATCH($D10,등장비중!$A$5:$A$19,0)) -> 핵심 조연 | S10: P3·N7
A11: 7 | B11: 부활 7인 | C11: Olympe de Gouges | D11: Olympe | E11: 45 | F11: =E11+개요!$C$11 -> 51 | G11: 여 | H11: 부활한 여성인권 운동가 (1748–1793) | I11: 『여성과 여성시민의 권리선언』 저자, 단두대에서 처형 | J11: 자신이 요구한 권리들이 200년이 지나서야 겨우 이뤄지는 걸 보며 조급해한다 — '이번엔 기다리지 않는다'. | K11: 열정적이고 논리적, 선언문 낭독하듯 말한다. | L11: La femme a le droit de monter à l'échafaud, elle doit avoir également celui de monter à la tribune.\n(현대 용어 오해) « Cancel culture » ? Enfin — qui déchoit-on en premier ? | M11: 빠르고 격정적, 선언문 낭독조. | N11: 선언문 형식으로 상황과 요구사항을 정리해 전달한다. | O11: 창당 전략가(8부) → 총리(Première ministre, 10부 11화 임명) | P11: 7부 1화 합류 (1부 미등장) | Q11: =INDEX(등장비중!$O$5:$O$19,MATCH($D11,등장비중!$A$5:$A$19,0)) -> 59 | R11: =INDEX(등장비중!$Q$5:$Q$19,MATCH($D11,등장비중!$A$5:$A$19,0)) -> 조연 | S11: N4·P2
A12: 8 | B12: 부활 7인 | C12: Jeanne d'Arc | D12: Jeanne | E12: 19 | F12: =E12+개요!$C$11 -> 25 | G12: 여 | H12: 부활한 전사·신비주의자 (1412–1431) | I12: 백년전쟁 프랑스군 지휘, 화형으로 처형 | J12: 아무도 믿어주지 않았던 목소리를 들었던 소녀 — 지금도 자기 확신을 의심받으면 참지 못한다. | K12: 단순하고 확신에 찬 문장, 나이답지 않게 단호하다. | L12: (현대 용어 오해) Une notification sur le téléphone ? Est-ce... une nouvelle voix ?\nJ'ai déjà mené une armée à dix-neuf ans. Une réunion, je peux gérer. | M12: 맑고 단호한 톤, 어린 목소리지만 흔들림 없다. | N12: 확신에 찬 짧은 선언으로 상황을 정리한다. | O12: 현장 조직(7부) → 대선 캠프 로지스틱스 총괄(10부) → 대통령 특별참모(위기 대응) | P12: 카메오 | Q12: =INDEX(등장비중!$O$5:$O$19,MATCH($D12,등장비중!$A$5:$A$19,0)) -> 56 | R12: =INDEX(등장비중!$Q$5:$Q$19,MATCH($D12,등장비중!$A$5:$A$19,0)) -> 조연 | S12: S3·N1
A13: 9 | B13: 부활 7인 | C13: Jean-Paul Sartre | D13: Sartre | E13: 74 | F13: =E13+개요!$C$11 -> 80 | G13: 남 | H13: 부활한 실존주의 철학자 (1905–1980) | I13: 레지스탕스 참여, 『존재와 무』 저자 | J13: 자유가 무겁다는 걸 누구보다 잘 알아서, 선택을 회피하는 사람을 보면 참지 못한다. | K13: 낮고 분석적, 인간의 자유와 책임으로 모든 상황을 재해석한다. | L13: (고전 인용) L'homme est condamné à être libre.\n(현대 용어 재해석) « Algorithme » ? Une nouvelle mauvaise foi — on choisit, mais on prétend que la machine a choisi. | M13: 느리고 낮은 톤, 담배 연기처럼 여운이 길다. | N13: 상황을 '누가 자유를 회피하고 있는가'로 짚어 설명한다. | O13: 사회·문화 정책 자문 (청년 정신건강 담당) | P13: 카메오 (카페 단골) | Q13: =INDEX(등장비중!$O$5:$O$19,MATCH($D13,등장비중!$A$5:$A$19,0)) -> 45 | R13: =INDEX(등장비중!$Q$5:$Q$19,MATCH($D13,등장비중!$A$5:$A$19,0)) -> 조연 | S13: N8·S2
A14: 10 | B14: 부활 7인 | C14: Marie Curie | D14: Curie | E14: 66 | F14: =E14+개요!$C$11 -> 72 | G14: 여 | H14: 부활한 물리·화학자 (1867–1934) | I14: 노벨상 2회 수상, 방사선 연구 중 피폭으로 사망 | J14: 자신을 죽인 바로 그 연구를 후회하지 않는다는 게 주변을 불편하게 한다 — 위험을 대수롭지 않게 여긴다. | K14: 차분하고 정확, 겸손하지만 권위에 굴하지 않는다. | L14: (현대 용어 오해) « Radiation Wi-Fi » ? Non, non — laissez-moi vous expliquer la vraie radioactivité.\nOn n'a rien à craindre dans la vie, il faut seulement comprendre. | M14: 차분하고 신중한 톤. | N14: 정확한 데이터와 실험으로 상황을 설명한다. | O14: 과학·교육 정책 자문 (12부 사찰 스캔들 기술 검증) | P14: 카메오 | Q14: =INDEX(등장비중!$O$5:$O$19,MATCH($D14,등장비중!$A$5:$A$19,0)) -> 64 | R14: =INDEX(등장비중!$Q$5:$Q$19,MATCH($D14,등장비중!$A$5:$A$19,0)) -> 핵심 조연 | S14: N7·N5
A15: 11 | B15: 서민·청년 | C15: Monique Rousseau | D15: Monique | E15: 63 | F15: =E15+개요!$C$11 -> 69 | G15: 여 | H15: 비스트로 사장 (Chez Monique, 30년 운영) | I15: Chez Monique, Belleville → 사무소 1층으로 이전 | J15: 임대료 폭등으로 가게를 잃었다. | K15: 파리 서민 구어체, 누구에게나 tu, 'mon/ma petit(e)'. | L15: Asseyez-vous, je vous apporte quelque chose.\nLe ventre vide, on ne réfléchit pas bien.\nC'est la maison qui offre. | M15: 따뜻하고 넉넉한 톤. | N15: 시간·장소·식사를 말로 알린다. | O15: 소상공인 정책 자문 (비공식) | P15: 본격 | Q15: =INDEX(등장비중!$O$5:$O$19,MATCH($D15,등장비중!$A$5:$A$19,0)) -> 69 | R15: =INDEX(등장비중!$Q$5:$Q$19,MATCH($D15,등장비중!$A$5:$A$19,0)) -> 핵심 조연 | S15: E1·S2
A16: 12 | B16: 서민·청년 | C16: Karim Belkacem | D16: Karim | E16: 55 | F16: =E16+개요!$C$11 -> 61 | G16: 남 | H16: 전 대중교통 노조위원장 | I16: RATP 버스 노조 → 노선 경쟁 입찰로 이관된 Méridien Mobilité(가상) 노조 대표, 파업 책임으로 해고 | J16: 파업 책임으로 해고되어 블랙리스트에 올랐지만 후회하지 않는다. | K16: 거칠고 직설적, 구호형 문장. | L16: Ici, personne ne se rend !\nÇa se règle dans la rue.\nÇa suffit, là. | M16: 큰 볼륨, 강한 억양. | N16: 구호와 함성으로 현장 분위기를 전달한다. | O16: 사회적 대화 자문 | P16: 카메오 | Q16: =INDEX(등장비중!$O$5:$O$19,MATCH($D16,등장비중!$A$5:$A$19,0)) -> 58 | R16: =INDEX(등장비중!$Q$5:$Q$19,MATCH($D16,등장비중!$A$5:$A$19,0)) -> 조연 | S16: S1·N6
... A19: 15 | B19: 부활 7인 | C19: Victor Hugo | D19: Hugo | E19: 83 | F19: =E19+개요!$C$11 -> 89 | G19: 남 | H19: 부활한 문호 (1802–1885) | I19: 『레미제라블』 저자, 망명 경험 | J19: 자신이 그린 빈곤과 불의가 150년 뒤에도 형태만 바뀐 채 그대로라는 걸 보며 분노를 감추지 못한다. | K19: 장엄하고 도덕적 열변, 사회정의 이야기만 나오면 톤이 올라간다. | L19: (고전 인용) Rien n'est plus puissant qu'une idée dont le temps est venu.\n(현대 용어 오해) « Influenceur » ? On dirait un nouveau vendeur d'indulgences — j'en ai déjà mis un dans mes romans. | M19: 느리고 웅장한 톤, 감정이 격해지면 목소리가 커진다. | N19: 사회 부조리를 목격한 이야기로 현재 상황을 은유한다. | O19: 연설·메시지 자문 (대통령 연설문 담당) | P19: 카메오 | Q19: =INDEX(등장비중!$O$5:$O$19,MATCH($D19,등장비중!$A$5:$A$19,0)) -> 58 | R19: =INDEX(등장비중!$Q$5:$Q$19,MATCH($D19,등장비중!$A$5:$A$19,0)) -> 조연 | S19: N5·N1

Sheet 등장비중
A1: 인물별 등장 비중 (부별 등장 화 수)
A2: 등장 화 = 대사가 있는 화 수 (기획용 초안). 파란 숫자는 직접 입력값이며 수정하면 합계·비중·등급이 자동 갱신됩니다.
A4: 인물 (약칭) | B4: 1부 사무소 | C4: 2부 Nicolas | D4: 3부 Camille | E4: 4부 Julien | F4: 5부 Léa | G4: 6부 만남 | H4: 7부 전면전 | I4: 8부 창당 | J4: 9부 파리 시의회 | K4: 10부 대선·대통령 | L4: 11부 국정 I | M4: 12부 국정 II | N4: 13부 귀환 | O4: 합계 | P4: 비중 | Q4: 등급 | R4: 검증 (≤부당 화 수) | S4: 단독 중심 화 목표 (조연)
A5: Nicolas | B5: 7 | C5: 12 | D5: 3 | E5: 3 | F5: 3 | G5: 12 | H5: 11 | I5: 12 | J5: 11 | K5: 11 | L5: 10 | M5: 3 | N5: 10 | O5: =SUM(B5:N5) -> 108 | P5: =O5/개요!$C$7 -> 0.69230769 | Q5: =IF(P5>=$B$23,"주연",IF(P5>=$B$24,"준주연",IF(P5>=$B$25,"핵심 조연","조연"))) -> 주연 | R5: =IF(MAX(B5:N5)<=개요!$C$6,"OK","확인") -> OK | S5: —
A6: Camille | B6: 6 | C6: 3 | D6: 12 | E6: 3 | F6: 3 | G6: 12 | H6: 10 | I6: 10 | J6: 8 | K6: 10 | L6: 10 | M6: 2 | N6: 9 | O6: =SUM(B6:N6) -> 98 | P6: =O6/개요!$C$7 -> 0.62820513 | Q6: =IF(P6>=$B$23,"주연",IF(P6>=$B$24,"준주연",IF(P6>=$B$25,"핵심 조연","조연"))) -> 준주연 | R6: =IF(MAX(B6:N6)<=개요!$C$6,"OK","확인") -> OK | S6: —
A7: Julien | B7: 8 | C7: 3 | D7: 3 | E7: 12 | F7: 3 | G7: 12 | H7: 11 | I7: 10 | J7: 10 | K7: 11 | L7: 10 | M7: 8 | N7: 9 | O7: =SUM(B7:N7) -> 110 | P7: =O7/개요!$C$7 -> 0.70512821 | Q7: =IF(P7>=$B$23,"주연",IF(P7>=$B$24,"준주연",IF(P7>=$B$25,"핵심 조연","조연"))) -> 주연 | R7: =IF(MAX(B7:N7)<=개요!$C$6,"OK","확인") -> OK | S7: —
A8: Léa | B8: 6 | C8: 3 | D8: 3 | E8: 3 | F8: 12 | G8: 12 | H8: 10 | I8: 11 | J8: 10 | K8: 10 | L8: 9 | M8: 3 | N8: 9 | O8: =SUM(B8:N8) -> 101 | P8: =O8/개요!$C$7 -> 0.6474359 | Q8: =IF(P8>=$B$23,"주연",IF(P8>=$B$24,"준주연",IF(P8>=$B$25,"핵심 조연","조연"))) -> 준주연 | R8: =IF(MAX(B8:N8)<=개요!$C$6,"OK","확인") -> OK | S8: —
A9: Napoléon | B9: 4 | C9: 2 | D9: 2 | E9: 2 | F9: 2 | G9: 7 | H9: 9 | I9: 7 | J9: 9 | K9: 9 | L9: 9 | M9: 0 | N9: 3 | O9: =SUM(B9:N9) -> 65 | P9: =O9/개요!$C$7 -> 0.41666667 | Q9: =IF(P9>=$B$23,"주연",IF(P9>=$B$24,"준주연",IF(P9>=$B$25,"핵심 조연","조연"))) -> 핵심 조연 | R9: =IF(MAX(B9:N9)<=개요!$C$6,"OK","확인") -> OK | S9: —
A10: Voltaire | B10: 2 | C10: 1 | D10: 1 | E10: 3 | F10: 1 | G10: 5 | H10: 10 | I10: 7 | J10: 8 | K10: 8 | L10: 7 | M10: 3 | N10: 7 | O10: =SUM(B10:N10) -> 63 | P10: =O10/개요!$C$7 -> 0.40384615 | Q10: =IF(P10>=$B$23,"주연",IF(P10>=$B$24,"준주연",IF(P10>=$B$25,"핵심 조연","조연"))) -> 핵심 조연 | R10: =IF(MAX(B10:N10)<=개요!$C$6,"OK","확인") -> OK | S10: —
A11: Olympe | B11: 0 | C11: 0 | D11: 1 | E11: 0 | F11: 0 | G11: 3 | H11: 8 | I11: 9 | J11: 6 | K11: 9 | L11: 9 | M11: 8 | N11: 6 | O11: =SUM(B11:N11) -> 59 | P11: =O11/개요!$C$7 -> 0.37820513 | Q11: =IF(P11>=$B$23,"주연",IF(P11>=$B$24,"준주연",IF(P11>=$B$25,"핵심 조연","조연"))) -> 조연 | R11: =IF(MAX(B11:N11)<=개요!$C$6,"OK","확인") -> OK | S11: —
A12: Jeanne | B12: 3 | C12: 1 | D12: 2 | E12: 1 | F12: 2 | G12: 4 | H12: 7 | I12: 8 | J12: 6 | K12: 7 | L12: 6 | M12: 2 | N12: 7 | O12: =SUM(B12:N12) -> 56 | P12: =O12/개요!$C$7 -> 0.35897436 | Q12: =IF(P12>=$B$23,"주연",IF(P12>=$B$24,"준주연",IF(P12>=$B$25,"핵심 조연","조연"))) -> 조연 | R12: =IF(MAX(B12:N12)<=개요!$C$6,"OK","확인") -> OK | S12: —
A13: Sartre | B13: 1 | C13: 1 | D13: 1 | E13: 2 | F13: 1 | G13: 4 | H13: 6 | I13: 6 | J13: 5 | K13: 6 | L13: 6 | M13: 1 | N13: 5 | O13: =SUM(B13:N13) -> 45 | P13: =O13/개요!$C$7 -> 0.28846154 | Q13: =IF(P13>=$B$23,"주연",IF(P13>=$B$24,"준주연",IF(P13>=$B$25,"핵심 조연","조연"))) -> 조연 | R13: =IF(MAX(B13:N13)<=개요!$C$6,"OK","확인") -> OK | S13: —
A14: Curie | B14: 3 | C14: 1 | D14: 1 | E14: 1 | F14: 1 | G14: 6 | H14: 8 | I14: 9 | J14: 8 | K14: 8 | L14: 7 | M14: 4 | N14: 7 | O14: =SUM(B14:N14) -> 64 | P14: =O14/개요!$C$7 -> 0.41025641 | Q14: =IF(P14>=$B$23,"주연",IF(P14>=$B$24,"준주연",IF(P14>=$B$25,"핵심 조연","조연"))) -> 핵심 조연 | R14: =IF(MAX(B14:N14)<=개요!$C$6,"OK","확인") -> OK | S14: —
A15: Monique | B15: 12 | C15: 2 | D15: 2 | E15: 2 | F15: 2 | G15: 5 | H15: 8 | I15: 6 | J15: 4 | K15: 5 | L15: 8 | M15: 3 | N15: 10 | O15: =SUM(B15:N15) -> 69 | P15: =O15/개요!$C$7 -> 0.44230769 | Q15: =IF(P15>=$B$23,"주연",IF(P15>=$B$24,"준주연",IF(P15>=$B$25,"핵심 조연","조연"))) -> 핵심 조연 | R15: =IF(MAX(B15:N15)<=개요!$C$6,"OK","확인") -> OK | S15: —
A16: Karim | B16: 2 | C16: 1 | D16: 2 | E16: 1 | F16: 3 | G16: 5 | H16: 9 | I16: 8 | J16: 6 | K16: 6 | L16: 7 | M16: 2 | N16: 6 | O16: =SUM(B16:N16) -> 58 | P16: =O16/개요!$C$7 -> 0.37179487 | Q16: =IF(P16>=$B$23,"주연",IF(P16>=$B$24,"준주연",IF(P16>=$B$25,"핵심 조연","조연"))) -> 조연 | R16: =IF(MAX(B16:N16)<=개요!$C$6,"OK","확인") -> OK | S16: —
... A19: Hugo | B19: 1 | C19: 1 | D19: 1 | E19: 1 | F19: 1 | G19: 4 | H19: 6 | I19: 9 | J19: 7 | K19: 9 | L19: 7 | M19: 4 | N19: 7 | O19: =SUM(B19:N19) -> 58 | P19: =O19/개요!$C$7 -> 0.37179487 | Q19: =IF(P19>=$B$23,"주연",IF(P19>=$B$24,"준주연",IF(P19>=$B$25,"핵심 조연","조연"))) -> 조연 | R19: =IF(MAX(B19:N19)<=개요!$C$6,"OK","확인") -> OK | S19: —
A20: 부별 연인원 (합계) | B20: =SUM(B5:B19) -> 69 | C20: =SUM(C5:C19) -> 36 | D20: =SUM(D5:D19) -> 39 | E20: =SUM(E5:E19) -> 41 | F20: =SUM(F5:F19) -> 39 | G20: =SUM(G5:G19) -> 104 | H20: =SUM(H5:H19) -> 131 | I20: =SUM(I5:I19) -> 127 | ... O20: =SUM(O5:O19) -> 1109 | S20: =SUM(S5:S19) -> 0
A23: 주연 | B23: 0.69 | C23: ← 기준값은 제안값입니다. 인원 재배정(총리 Olympe 신설) 후 등급은 수식이 자동 계산합니다.
A24: 준주연 | B24: 0.6
A25: 핵심 조연 | B25: 0.4
A26: 조연 | B26: 그 미만
A28: 배분 원칙
A29: 1. 1부는 개소 1개월 후 시점: Manon·Monique가 전 화에, 주력 4인은 사건별로 2~3인씩 교대 등장(전원 겹치지 않음). Napoléon 4화, Curie 3화(1·2·6화)로 자주 얼굴을 비추고 '이번 겨울이 마지막' 복선을 1화부터 깐다. 나머지는 사건마다 다른 조합으로 카메오.
A30: 2. 2~5부: 각 주인공이 자기 부 12화 전부에 나오고, 다른 주력 3인은 3화씩 스쳐 지나가며 6부 만남을 예고. Manon은 4화씩 '사무소에서 이야기를 듣는 프레임'으로 등장해 회상을 잇는다.
A31: 3. 조연은 과거와 겹치는 곳에만 배치: Karim-5부(Léa의 구조조정 현장), Philippe·Voltaire-4부(Julien의 감사 사건), Sartre-3부·5부(카페에서의 되묻기).
A32: 4. 조연 본격 비중은 7~10부에서 최고치: 7부 Voltaire·Karim·Olympe(공론화·현장 조직·피해자 사건), 8부 Hugo·Sartre·Jeanne·Olympe(선언문·메시지·캠프·창당), 10부 Hugo·Voltaire·Curie(취임 연설·공보·출처).
A33: 5. 11부(국정 I)는 Napoléon이 9~12화에서 브뤼셀 직접 협상을 이끌며 최고치(9화)를 찍고 12화에서 사망한다. Philippe는 앞선 주거·금융 국내 현안 화에서 정점. 총리 Olympe는 11~12부 내내 의회 전선을 맡는다.
A34: 6. 12부(국정 II)는 Napoléon 사후: 1화 장례식에서 Jeanne·Curie·Camille가 몰리고, Julien·Hugo가 유작 메모를 이어받는 3화에서 비중이 오른다.
A35: 7. 13부(귀환)는 원형 구조: Manon 12화 전부, Monique 10화. Napoléon은 유언장·회상으로 3화, Nicolas·Camille·Julien·Léa는 사무소의 손님으로 9~10화 등장.
A36: 8. Napoléon은 11부 12화(브뤼셀 승리 직후)에서 사망한다. 12부 1화 장례식, 2·3화 유작 메모 승계, 13부 2화 유언장까지 이어진다.
A37: 9. 등장 화 수와 대사량은 다르다: Manon은 등장이 많지만 문장이 짧아 대사량은 Nicolas의 절반 이하가 되게 하고, Napoléon·Hugo는 화당 대사가 길어도 된다.
A38: 10. 조연은 화 전체의 중심이 되는 에피소드를 각자 2개 이상 배정(S열 목표). 자기 이야기가 한 번도 없으면 얇은 인물이 된다.
A39: 11. Sartre가 가장 얇다: 3·5부 카페 장면을 늘리거나, 12부 Napoléon 애도 장면을 맡겨 서사를 넓히는 안을 검토.

Sheet 턴_설계
A1: 대화량 설계: 화당 120턴
A2: 한 화 = 대화 120턴, 전체 156화 = 18,720턴. 점유율·평균 단어/턴·배율·낭독 속도는 가정값(파란 숫자)이며 수정하면 아래 표가 자동 갱신됩니다.
A4: 1. 기본 설정
A5: 화당 대화 턴 | B5: 120
A6: 낭독 속도 (단어/분, 가정) | B6: 130
A7: 총 화 수 | B7: =개요!$C$7 -> 156
A8: 총 대화 턴 | B8: =B5*B7 -> 18720
A9: 턴 정의 | B9: 화자 표기 한 줄 = 1턴 (화자가 바뀌면 새 턴). 연설·조항·기사 낭독처럼 긴 발화도 1턴으로 센다.
A11: 2. 부별 화자 점유율 (턴 기준, 각 부의 합 = 100%)
A12: 인물 | B12: 평균 단어/턴 | C12: 1부 | D12: 2부 | E12: 3부 | F12: 4부 | G12: 5부 | H12: 6부 | I12: 7부 | J12: 8부 | K12: 9부 | L12: 10부 | M12: 11부 | N12: 12부 | O12: 13부
A13: Nicolas | B13: 13 | C13: 0.13 | D13: 0.48 | E13: 0.03 | F13: 0.02 | G13: 0.02 | H13: 0.13 | I13: 0.14 | J13: 0.11 | K13: 0.08 | L13: 0.15 | M13: 0.11 | N13: 0.11 | O13: 0.06
A14: Camille | B14: 8 | C14: 0.12 | D14: 0.03 | E14: 0.46 | F14: 0.04 | G14: 0.03 | H14: 0.12 | I14: 0.07 | J14: 0.08 | K14: 0.11 | L14: 0.06 | M14: 0.09 | N14: 0.09 | O14: 0.06
A15: Julien | B15: 11 | C15: 0.12 | D15: 0.04 | E15: 0.04 | F15: 0.46 | G15: 0.04 | H15: 0.12 | I15: 0.1 | J15: 0.09 | K15: 0.15 | L15: 0.08 | M15: 0.11 | N15: 0.13 | O15: 0.07
A16: Léa | B16: 12 | C16: 0.12 | D16: 0.05 | E16: 0.03 | F16: 0.03 | G16: 0.46 | H16: 0.12 | I16: 0.06 | J16: 0.09 | K16: 0.08 | L16: 0.11 | M16: 0.08 | N16: 0.08 | O16: 0.07
A17: Napoléon | B17: 14 | C17: 0.08 | D17: 0.04 | E17: 0.04 | F17: 0.04 | G17: 0.04 | H17: 0.04 | I17: 0.06 | J17: 0.05 | K17: 0.04 | L17: 0.06 | M17: 0.04 | N17: 0 | O17: 0.02
A18: Olympe | B18: 11 | C18: 0 | D18: 0 | E18: 0.01 | F18: 0 | G18: 0 | H18: 0.02 | I18: 0.05 | J18: 0.05 | K18: 0.03 | L18: 0.06 | M18: 0.06 | N18: 0.06 | O18: 0.03
A19: Jeanne | B19: 7 | C19: 0.02 | D19: 0.01 | E19: 0.01 | F19: 0.01 | G19: 0.01 | H19: 0.05 | I19: 0.06 | J19: 0.06 | K19: 0.04 | L19: 0.08 | M19: 0.07 | N19: 0.07 | O19: 0.06
A20: Curie | B20: 9 | C20: 0.02 | D20: 0.01 | E20: 0.01 | F20: 0.01 | G20: 0.01 | H20: 0.03 | I20: 0.06 | J20: 0.03 | K20: 0.04 | L20: 0.03 | M20: 0.05 | N20: 0.05 | O20: 0.08
A21: Voltaire | B21: 10 | C21: 0.02 | D21: 0.01 | E21: 0.03 | F21: 0.04 | G21: 0.01 | H21: 0.03 | I21: 0.08 | J21: 0.06 | K21: 0.07 | L21: 0.05 | M21: 0.06 | N21: 0.06 | O21: 0.05
A22: Sartre | B22: 9 | C22: 0.01 | D22: 0.01 | E22: 0.04 | F22: 0.01 | G22: 0.04 | H22: 0.03 | I22: 0.05 | J22: 0.06 | K22: 0.04 | L22: 0.05 | M22: 0.04 | N22: 0.04 | O22: 0.05
A23: Monique | B23: 9 | C23: 0.12 | D23: 0.04 | E23: 0.03 | F23: 0.03 | G23: 0.03 | H23: 0.05 | I23: 0.04 | J23: 0.05 | K23: 0.03 | L23: 0.04 | M23: 0.04 | N23: 0.04 | O23: 0.13
A24: Karim | B24: 10 | C24: 0.01 | D24: 0.02 | E24: 0.01 | F24: 0.01 | G24: 0.09 | H24: 0.05 | I24: 0.06 | J24: 0.08 | K24: 0.08 | L24: 0.06 | M24: 0.05 | N24: 0.05 | O24: 0.05
... A28: 엑스트라(가상) | B28: 10 | C28: 0.03 | D28: 0.15 | E28: 0.16 | F28: 0.13 | G28: 0.12 | H28: 0.05 | I28: 0.02 | J28: 0.02 | K28: 0.02 | L28: 0.02 | M28: 0.02 | N28: 0.02 | O28: 0.02
A29: 합계 | C29: =SUM(C13:C28) -> 1 | D29: =SUM(D13:D28) -> 1 | E29: =SUM(E13:E28) -> 1 | F29: =SUM(F13:F28) -> 1 | G29: =SUM(G13:G28) -> 1 | H29: =SUM(H13:H28) -> 1 | I29: =SUM(I13:I28) -> 1 | J29: =SUM(J13:J28) -> 1 | ... O29: =SUM(O13:O28) -> 1
A30: 검증 | C30: =IF(ROUND(C29,4)=1,"OK","확인") -> OK | D30: =IF(ROUND(D29,4)=1,"OK","확인") -> OK | E30: =IF(ROUND(E29,4)=1,"OK","확인") -> OK | F30: =IF(ROUND(F29,4)=1,"OK","확인") -> OK | G30: =IF(ROUND(G29,4)=1,"OK","확인") -> OK | H30: =IF(ROUND(H29,4)=1,"OK","확인") -> OK | I30: =IF(ROUND(I29,4)=1,"OK","확인") -> OK | J30: =IF(ROUND(J29,4)=1,"OK","확인") -> OK | ... O30: =IF(ROUND(O29,4)=1,"OK","확인") -> OK
A32: 3. 부별 턴·단어·낭독 시간 (수식)
A33: 부 | B33: 난이도 배율 | C33: 화당 턴 | D33: 부 총 턴 | E33: 평균 단어/턴 | F33: 화당 단어 | G33: 부 총 단어 | H33: 화당 낭독 (분) | I33: 부 총 낭독 (시간)
A34: 1부 | B34: 0.8 | C34: =$B$5 -> 120 | D34: =C34*개요!$C$6 -> 1440 | E34: =SUMPRODUCT(C$13:C$28,$B$13:$B$28)*B34 -> 8.128 | F34: =C34*E34 -> 975.36 | G34: =F34*개요!$C$6 -> 11704.32 | H34: =F34/$B$6 -> 7.5027692 | I34: =H34*개요!$C$6/60 -> 1.5005538
A35: 2부 | B35: 1 | C35: =$B$5 -> 120 | D35: =C35*개요!$C$6 -> 1440 | E35: =SUMPRODUCT(D$13:D$28,$B$13:$B$28)*B35 -> 11.39 | F35: =C35*E35 -> 1366.8 | G35: =F35*개요!$C$6 -> 16401.6 | H35: =F35/$B$6 -> 10.513846 | I35: =H35*개요!$C$6/60 -> 2.1027692
A36: 3부 | B36: 1 | C36: =$B$5 -> 120 | D36: =C36*개요!$C$6 -> 1440 | E36: =SUMPRODUCT(E$13:E$28,$B$13:$B$28)*B36 -> 9.12 | F36: =C36*E36 -> 1094.4 | G36: =F36*개요!$C$6 -> 13132.8 | H36: =F36/$B$6 -> 8.4184615 | I36: =H36*개요!$C$6/60 -> 1.6836923
A37: 4부 | B37: 1 | C37: =$B$5 -> 120 | D37: =C37*개요!$C$6 -> 1440 | E37: =SUMPRODUCT(F$13:F$28,$B$13:$B$28)*B37 -> 10.44 | F37: =C37*E37 -> 1252.8 | G37: =F37*개요!$C$6 -> 15033.6 | H37: =F37/$B$6 -> 9.6369231 | I37: =H37*개요!$C$6/60 -> 1.9273846
A38: 5부 | B38: 1 | C38: =$B$5 -> 120 | D38: =C38*개요!$C$6 -> 1440 | E38: =SUMPRODUCT(G$13:G$28,$B$13:$B$28)*B38 -> 10.8 | F38: =C38*E38 -> 1296 | G38: =F38*개요!$C$6 -> 15552 | H38: =F38/$B$6 -> 9.9692308 | I38: =H38*개요!$C$6/60 -> 1.9938462
A39: 6부 | B39: 1 | C39: =$B$5 -> 120 | D39: =C39*개요!$C$6 -> 1440 | E39: =SUMPRODUCT(H$13:H$28,$B$13:$B$28)*B39 -> 10.18 | F39: =C39*E39 -> 1221.6 | G39: =F39*개요!$C$6 -> 14659.2 | H39: =F39/$B$6 -> 9.3969231 | I39: =H39*개요!$C$6/60 -> 1.8793846
A40: 7부 | B40: 1 | C40: =$B$5 -> 120 | D40: =C40*개요!$C$6 -> 1440 | E40: =SUMPRODUCT(I$13:I$28,$B$13:$B$28)*B40 -> 10.4 | F40: =C40*E40 -> 1248 | G40: =F40*개요!$C$6 -> 14976 | H40: =F40/$B$6 -> 9.6 | I40: =H40*개요!$C$6/60 -> 1.92
A41: 8부 | B41: 1.1 | C41: =$B$5 -> 120 | D41: =C41*개요!$C$6 -> 1440 | E41: =SUMPRODUCT(J$13:J$28,$B$13:$B$28)*B41 -> 11.418 | F41: =C41*E41 -> 1370.16 | G41: =F41*개요!$C$6 -> 16441.92 | H41: =F41/$B$6 -> 10.539692 | I41: =H41*개요!$C$6/60 -> 2.1079385
A42: 9부 | B42: 1.1 | C42: =$B$5 -> 120 | D42: =C42*개요!$C$6 -> 1440 | E42: =SUMPRODUCT(K$13:K$28,$B$13:$B$28)*B42 -> 11.187 | F42: =C42*E42 -> 1342.44 | G42: =F42*개요!$C$6 -> 16109.28 | H42: =F42/$B$6 -> 10.326462 | I42: =H42*개요!$C$6/60 -> 2.0652923
A43: 10부 | B43: 1.2 | C43: =$B$5 -> 120 | D43: =C43*개요!$C$6 -> 1440 | E43: =SUMPRODUCT(L$13:L$28,$B$13:$B$28)*B43 -> 12.708 | F43: =C43*E43 -> 1524.96 | G43: =F43*개요!$C$6 -> 18299.52 | H43: =F43/$B$6 -> 11.730462 | I43: =H43*개요!$C$6/60 -> 2.3460923
A44: 11부 | B44: 1.2 | C44: =$B$5 -> 120 | D44: =C44*개요!$C$6 -> 1440 | E44: =SUMPRODUCT(M$13:M$28,$B$13:$B$28)*B44 -> 12.252 | F44: =C44*E44 -> 1470.24 | G44: =F44*개요!$C$6 -> 17642.88 | H44: =F44/$B$6 -> 11.309538 | I44: =H44*개요!$C$6/60 -> 2.2619077
A45: 12부 | B45: 1.2 | C45: =$B$5 -> 120 | D45: =C45*개요!$C$6 -> 1440 | E45: =SUMPRODUCT(N$13:N$28,$B$13:$B$28)*B45 -> 12.132 | F45: =C45*E45 -> 1455.84 | G45: =F45*개요!$C$6 -> 17470.08 | H45: =F45/$B$6 -> 11.198769 | I45: =H45*개요!$C$6/60 -> 2.2397538
A46: 13부 | B46: 0.8 | C46: =$B$5 -> 120 | D46: =C46*개요!$C$6 -> 1440 | E46: =SUMPRODUCT(O$13:O$28,$B$13:$B$28)*B46 -> 7.616 | F46: =C46*E46 -> 913.92 | G46: =F46*개요!$C$6 -> 10967.04 | H46: =F46/$B$6 -> 7.0301538 | I46: =H46*개요!$C$6/60 -> 1.4060308
A47: 전체 | D47: =SUM(D34:D46) -> 18720 | E47: =G47/D47 -> 10.597769 | F47: =AVERAGE(F34:F46) -> 1271.7323 | G47: =SUM(G34:G46) -> 198390.24 | H47: =AVERAGE(H34:H46) -> 9.7825562 | I47: =SUM(I34:I46) -> 25.434646
A48: ※ 난이도 배율: 1·13부(B1~B2)는 짧게 0.8, 10~12부(C1~C2)는 길게 1.2. 화당 단어는 '평균 단어/턴 × 120턴', 낭독 시간은 낭독 속도로 환산한 추정치.
A50: 4. 화 유형별 턴 구성 (합계 = 화당 120턴)
A51: 화 유형 | B51: 도입 | C51: 장면 1 | D51: 장면 2 | E51: 절정·전환 | F51: 마무리 | G51: 합계 | H51: 검증 | I51: 적용
A52: 일반 화 | B52: 15 | C52: 35 | D52: 30 | E52: 25 | F52: 15 | G52: =SUM(B52:F52) -> 120 | H52: =IF(G52=$B$5,"OK","확인") -> OK | I52: 발단·전개·위기 화 대부분
A53: 프레임 화 | B53: 15 | C53: 30 | D53: 30 | E53: 25 | F53: 20 | G53: =SUM(B53:F53) -> 120 | H53: =IF(G53=$B$5,"OK","확인") -> OK | I53: 2~5부 1·5·9·12화: 금요일 프레임(도입·마무리)과 과거 장면
A54: 폭발·감정 정점 화 | B54: 15 | C54: 30 | D54: 25 | E54: 35 | F54: 15 | G54: =SUM(B54:F54) -> 120 | H54: =IF(G54=$B$5,"OK","확인") -> OK | I54: 1부 6화, 9부 6화 등 인물의 감정이 터지는 화
A55: 표결·절차 화 | B55: 15 | C55: 30 | D55: 25 | E55: 35 | F55: 15 | G55: =SUM(B55:F55) -> 120 | H55: =IF(G55=$B$5,"OK","확인") -> OK | I55: 10부 4·7화 개표·결과 선포, 10부 12화·12부 7화 불신임안 (하원의장의 결과 낭독 포함)
A56: 재난·추도 화 | B56: 10 | C56: 30 | D56: 30 | E56: 40 | F56: 10 | G56: =SUM(B56:F56) -> 120 | H56: =IF(G56=$B$5,"OK","확인") -> OK | I56: 11부 12화(Napoléon 죽음), 12부 1화(장례), 12부 8화(남부 급류 재난)
A57: 원형·회고 화 | B57: 20 | C57: 25 | D57: 25 | E57: 25 | F57: 25 | G57: =SUM(B57:F57) -> 120 | H57: =IF(G57=$B$5,"OK","확인") -> OK | I57: 13부 1·11·12화: 1부 대사를 되풀이하고 마무리를 길게
A59: 5. 집필 규칙
A60: 1. 1부는 한 턴 15단어 이내를 지킨다. 연설·조항·기사·카드처럼 긴 낭독은 예외로 두되 1턴으로 세고, 화당 최대 3개까지만 쓴다.
A61: 2. 지문이 없으므로 장소·시간·행동을 알리는 턴이 화당 5~10턴 필요하다 (Monique의 시간 안내, Jeanne의 보고, 하원의장의 결과 낭독 등).
A62: 3. Manon의 질문 → 쉬운 재설명 짝은 화당 3~6쌍(6~12턴)을 기본으로 한다. 어려운 용어를 도입할 때 반드시 사용한다.
A63: 4. 시그니처 표현은 화자당 1~2회. 120턴 안에서 같은 시그니처가 반복되지 않게 배분한다.
A64: 5. 화자 점유율은 턴 수 기준이다. Manon처럼 턴은 많지만 짧게 말하는 인물은 평균 단어/턴을 낮게 잡았다. 옛 마드리드판 점유율을 인물 대응표(변경이력 참고)대로 옮기고 Olympe(총리)를 신설했다.
A65: 6. 표의 파란 숫자는 가정값이다. 1부 1~3화 대본을 쓴 뒤 실제 턴·단어 수를 재서 점유율과 평균 단어/턴을 교정한다.

Sheet 13부_구성
A1: 13부 구성 (13부 × 12화 = 156화)
A2: 정치 파트(8~12부)는 프랑스 제5공화국 제도에 맞춰 재설계했습니다. 화별 목차는 '화별목차_전체', 제도 근거는 '정치제도' 시트.
A4: 부 | B4: 제목 (FR) | C4: 한국어 | D4: 배경 | E4: 핵심 내용 | F4: 난이도 (CEFR) | G4: 반영 제도·전문 영역 | H4: 시점
A5: 1 | B5: Le Cabinet de Belleville | C5: 벨빌 사무소 | D5: Belleville의 작은 사무실 (1층은 Monique의 비스트로), 개소 1개월 후 | E5: 이미 한 달째 좌충우돌 중인 팀이 이웃들의 사건 6개를 2화씩(도입→해결) 풀어 간다. 자기소개 대신 '이 사람들이 어쩌다 이렇게 됐지?' 하는 궁금증(in medias res)으로 시작. | F5: B1 | G5: 생활 법률·노동·의료·금융 기초 어휘, 반복되는 말다툼, Manon 1차 폭발(6화) | H5: 현재(개소 후 1개월)
A6: 2 | B6: L'Avocat | C6: 변호사 | D6: 8구 avenue George-V의 대형 로펌 | E6: 승소율 100%의 이면: 강제퇴거 사건이 Nicolas의 결핍이 된다. | F6: B2~C1 | G6: 임대차(1989년 법), 퇴거 절차, 소송(assignation, audience, jugement) | H6: 과거
A7: 3 | B7: La Médecin | C7: 의사 | D7: Hôpital Saint-Bernard 응급실 (가상) | E7: 예산 압박과 컨설팅·외주 속에서 치료받지 못하는 환자들. Camille의 이름 목록. | F7: B2~C1 | G7: 응급의학·병원 행정, ARS·AP-HP 체계, 병원 외주(externalisation)와 컨설팅 계약 | H7: 과거
A8: 4 | B8: L'Auditeur | C8: 회계감사인 | D8: Bertin & Roux Audit (가상) | E8: 룩셈부르크 지주회사를 통한 탈세·자금세탁 정황을 발견하지만 조직의 묵인 압박. 다시는 서명하지 않겠다는 다짐의 기원. | F8: B2~C1 | G8: 법정감사(commissaire aux comptes), 자금세탁방지(TRACFIN), 감사인 독립성(H2A) | H8: 과거
A9: 5 | B9: La Consultante | C9: 컨설턴트 | D9: Zénith Consulting (가상), La Défense 32층 | E9: 구조조정 엑셀 한 칸이 수백 명의 실직이었음을 깨닫는다. Karim과의 첫 접점. | F9: B2~C1 | G9: 경영 전략, 고용보호계획(PSE), 노동법(Code du travail) | H9: 과거
A10: 6 | B10: La Rencontre | C10: 운명적 만남 | D10: Saint-Denis의 서민 주거 단지(cité), 작은 카페 | E10: 강제퇴거와 의료 방치가 한 건으로 얽힌 사건에서 네 사람이 만나 사무소를 차리기로 한다. | F10: B2 | G10: 협상·설득 구어체 | H10: 현재로 수렴
A11: 7 | B11: Le Réseau de résistance | C11: 사무소 2탄: 전면전 | D11: 법원, 시청 앞, 파리 전역 | E11: 부당 해고·의료 사고·탈세 대기업 상대 집단 대응. 내부고발자를 보호하고 반부패 단체의 사소(私訴, partie civile)로 고소한다. | F11: B2~C1 | G11: plainte avec constitution de partie civile, 국가금융검찰(PNF), 내부고발자 보호(Sapin II·2022년 법) | H11: 과거→현재
A12: 8 | B12: L'Éveil citoyen | C12: 정치적 각성과 창당 | D12: Place de la République, 시민 집회 | E12: 하원 시민청원이 본회의 토론에서 멈추자 스스로 정당 «Maison Commune»을 창당해 파리 시의회 선거(municipales)에 나선다. | F12: B2~C1 | G12: 시위 사전 신고, 하원 시민청원(pétition), 정당 결성(1901년 결사법·1988년 정치자금법), 선거운동 규칙 | H12: 정치
A13: 9 | B13: À l'Hôtel de Ville | C13: 파리 시의회 | D13: Hôtel de Ville(파리 시청), Conseil de Paris, AP-HP 감독위원회 | E13: Julien은 예산을, Camille는 보건(시립 보건센터·AP-HP)을 파고든다. 스캔들 폭로와 Manon의 2차 폭발. 마지막 화에서 Nicolas가 대선 출마를 선언한다. | F13: C1 | G13: Conseil de Paris, 예산·결산(CFU), 공공조달(Code de la commande publique), 지방재정감사원(CRC) | H13: 정치
A14: 10 | B14: Vers l'Élysée | C14: 대선에서 대통령 취임까지 | D14: Conseil constitutionnel, TV 토론 스튜디오, Élysée, Assemblée nationale | E14: 추천서 500장 → 1차 투표 2위 → 결선 승리 → 취임 → 국회 해산·총선(상대다수) → 총리 Olympe 임명 → 불신임안 1표 차 부결. | F14: C1~C2 | G14: 대선 2회 투표제(헌법 제6·7조), 추천서(parrainages), 해산(제12조), 총리 임명(제8조), 불신임안(제49조) | H14: 정치
A15: 11 | B15: La Grande Bataille sociale I | C15: 사회 현안 전투 I | D15: Élysée, Matignon, 국무회의(Conseil des ministres), 브뤼셀 | E15: 상대다수 정부로 주거·보건·이민·청년·물가 국내 현안을 돌파한 뒤, Napoléon이 대통령 특사로 브뤼셀 협상(NATO 방위비·EU 재정규칙)에 나서 승리하고 귀국 직후 사망한다. | F15: C1~C2 | G15: 국무회의(수요일), 대통령–총리 권한 분담, NATO 방위비 목표(2025 헤이그 합의), EU 과도한 적자 절차 | H15: 정치
A16: 12 | B16: La Grande Bataille sociale II | C16: 사회 현안 전투 II | D16: Élysée, Matignon, 브뤼셀, 재난 현장 | E16: 장례식으로 열고 Napoléon의 유작 메모로 브뤼셀 후속 협상을 마무리한다. 플랫폼 노동·정보기관 사찰·청년 정신건강 등 새 현안과 불신임안 방어, 남부 급류 재난, 예산안까지. | F16: C1~C2 | G16: 메모 승계, 법률 vs 명령(ordonnance·décret), 헌법재판소(Conseil constitutionnel), 불신임안, ORSEC 재난 체계, 예산(제47조) | H16: 정치
A17: 13 | B17: Retour à Belleville | C17: 귀환 | D17: Belleville, Chez Monique | E17: 1부 1화와 같은 대사로 시작해 원을 닫는다. Napoléon의 유언장(이각모), 새 인턴, 이제 설명하는 쪽이 된 Manon. | F17: B1~B2 | G17: 유언(notaire, exécuteur testamentaire), 고위공직 겸직 제한(HATVP), 재단 전환, 원형 구조 | H17: 귀환
A19: 흐름: 현재(1) → 과거(2~5) → 교차(6) → 전면전(7) → 정치(8 창당·시의회 선거 → 9 파리 시의회 → 10 대선·대통령·총선) → 정부(11~12) → 귀환(13, 원형 구조). 난이도는 B1 → C1/C2 → B1~B2로 올라갔다 내려와 마무리가 부드럽고, 13부에서 1부 장면을 다시 읽으면 낭독 실력의 성장을 스스로 확인할 수 있다.

Sheet 아크_구성계획
A1: 아크별 구성 계획 (1~13부)
A2: 각 부(아크)의 서사 기능, 변화, 비트(발단→결말), 인물 아크, 복선, 현안·제도, 언어 설계를 한 블록으로 정리. 화별 세부는 '화별목차_전체', 복선 추적은 '복선_회수'.
A4: 1부 | B4: Le Cabinet de Belleville — 벨빌 사무소 | 난이도 B1 | 사무소 개소 1개월 후(6부 12화로부터 약 4주). Belleville 사무소와 1층 Monique의 비스트로.
A5: 서사 기능 | B5: 독자 진입 장치. 이미 굴러가는(그러나 여전히 좌충우돌하는) 사무소를 보여 주어 '이 사람들이 어쩌다 이렇게 됐지?' 하는 궁금증을 만든다. 자기소개 대신 여섯 사건을 통해 인물의 습관과 리듬을 익히게 한다.
A6: 로그라인 | B6: 개소 한 달째, 여전히 순서 하나 못 정하고 매번 다투는 네 전문가와 팀이 그래도 이웃들의 사건 여섯 개를 하나씩 해결해 나가지만, 마지막 사건의 서류에서 Nicolas의 옛 로펌 이름이 튀어나온다.
A7: 변화 (시작 → 끝) | B7: '한 달이나 됐는데 아직도 이 모양' → 그래도 매번 어떻게든 해결하는 팀이라는 신뢰. 그러나 각자의 과거는 여전히 미해결이고, 옛 로펌 이름이 도착한다.
A8: 핵심 갈등 | B8: 전문가의 말투 vs 이웃의 삶 / 여전히 못 정한 방법 / 각자 숨기는 과거
A9: 비트 1 | B9: 사건1 임대료 인상, 1~2화(Fatima): 도입에서 여전히 자리 못 잡은 한 달 차 팀의 말다툼을 보여 주고, 해결에서 Curie의 카드 #1(1989년 임대차법·IRL)로 부당 인상을 막는다.
A10: 비트 2 | B10: 사건2 퇴거 집행, 3~4화: 겨울 퇴거 유예가 끝나는 밤의 급보 → 아침 집행 저지. Jeanne·Karim 첫 카메오, 넷의 역할 분담(서류·건강·숫자·동선)이 처음으로 손발이 맞는다.
A11: 비트 3 | B11: 사건3 임금 체불, 5~6화: Léa의 컨설팅 용어가 청년 노동자를 지치게 하고, 협상 중 Manon이 1차 폭발한다. 폭발 후 쉬운 말로 다시 협상해 해결.
A12: 비트 4 | B12: 사건4 의료 접근, 7~8화: 서류 없는 가족의 아이가 진료를 못 받는다. Sartre·Hugo 카메오, Napoléon의 가짜 무릎 통증이 진짜 아픈 아이 앞에서 조용해지는 대비.
A13: 비트 5 | B13: 사건5 금융 사기, 9~10화: 저축을 잃은 이웃을 두고 Julien이 장부를, 낯선 Philippe가 계좌 흐름을 추적한다. Voltaire 카메오. Philippe는 설명 없이 사라지고 Julien은 은행 이름에 말없이 굳는다.
A14: 비트 6 | B14: 사건6 오래된 서류·훅, 11~12화: 수십 년 전 퇴거 서류의 절차 하자를 바로잡다가 서명란에서 Nicolas의 옛 로펌 이름을 발견한다. Nicolas가 얼어붙고 금요일 이야기(2부)가 예고된다.
A15: 인물 아크 | B15: Manon=독자의 대리인(질문), 한 달이 지나도 Nicolas에게 vous 유지. Napoléon=심술과 복선(매년 하는 소리라는 게 드러남). Monique=정서적 중심. 카메오는 사건별로 분산: Curie(1·2·6화), Jeanne·Karim(3·4화), Sartre·Hugo(7화), Philippe·Voltaire(9·10·11화). 폭발 화(6화)에는 Jeanne·Monique·Curie의 고정 반응만 남기고 Karim의 욕은 9부 2차 폭발로 이관해 과밀을 해소.
... A19: 언어 설계 | B19: B1. 한 줄 15단어 이내, 현재·명령형·복합과거(passé composé). tu·vous 대비 중심. 낭독: 빠른 티키타카로 입 풀기. Nicolas·Napoléon의 격식체는 한두 줄 맛보기. 매 사건 2화(도입→해결) 리듬을 반복해 구조를 익히게 한다.
A20: 대화량 (화당 120턴) | B20: ="화당 "&턴_설계!$B$5&"턴 · 부 총 "&TEXT(턴_설계!D34,"#,##0")&"턴 · 화당 약 "&TEXT(턴_설계!F34,"#,##0")&"단어 · 낭독 약 "&TEXT(턴_설계!H34,"0.0")&"분 (평균 "&TEXT(턴_설계!E34,"0.0")&"단어/턴)" -> 화당 120턴 · 부 총 1,440턴 · 화당 약 975단어 · 낭독 약 7.5분 (평균 8.1단어/턴)
A21: Manon 질문·Curie 카드 | B21: Manon: 임대·노동·의료·금융 기초 용어(dépôt de garantie, CDD, domiciliation, compte bancaire). 카드: 1989년 7월 6일 법, 사전(아카데미 프랑세즈 사전·CNRTL).
A22: 다음 부 연결 | B22: 2부: 금요일마다 한 명씩 과거를 이야기하는 규칙 — 첫 번째는 Nicolas.
A24: 2부 | B24: L'Avocat — 변호사 | 난이도 B2~C1 | 프레임: 1부와 같은 첫 겨울의 금요일 밤. 과거: 약 5년 전, 8구 avenue George-V의 대형 로펌.
A25: 서사 기능 | B25: 첫 과거 회상. 공동 악역 Groupe Méridien을 도입하고 '법을 잘 쓰는 것과 옳은 것은 다르다'는 이 이야기의 첫 질문을 던진다. 프레임(Monique의 식탁)과 과거를 오가는 구조 실험.
A26: 로그라인 | B26: 승소율 100%의 파트너 후보가 대형 고객의 주택 포트폴리오를 비우는 조항을 설계해 재판에서 이기고, 그 승리가 한 노인의 죽음이 되었음을 알게 된다.
A27: 변화 (시작 → 끝) | B27: 자랑스러운 승자 → 자기 승리에 사직서를 낸 사람.
A28: 핵심 갈등 | B28: 잘 쓰는 법 vs 옳은 것 / 파트너 승진 vs 양심
A29: 비트 1 | B29: 발단(1~3화): 금요일 프레임, 조르주5세 거리의 월요일, VIP 고객 Verdier.
A30: 비트 2 | B30: 전개(4~5화): 실사에서 Belleville 건물 발견 / 프레임에서 그곳이 Monique의 거리였음이 드러남.
A31: 비트 3 | B31: 미드포인트(6화): 조항 설계 — Nicolas가 스스로 함정을 만든다.
A32: 비트 4 | B32: 위기(7~9화): 세입자 총회(Madeleine), 재판 승소, 프레임에서 Nicolas의 말이 막힘.
A33: 비트 5 | B33: 절정(10~11화): 16구 축하 만찬 중 부고, 손녀 Chloé의 방문.
... A39: 언어 설계 | B39: B2~C1. 접속법 현재·과거, 수동태, 법률 문어체. 과거 장면은 격식 문어, 프레임 장면은 B1로 두어 톤을 대비. 발성: 또박또박, 중저음.
A40: 대화량 (화당 120턴) | B40: ="화당 "&턴_설계!$B$5&"턴 · 부 총 "&TEXT(턴_설계!D35,"#,##0")&"턴 · 화당 약 "&TEXT(턴_설계!F35,"#,##0")&"단어 · 낭독 약 "&TEXT(턴_설계!H35,"0.0")&"분 (평균 "&TEXT(턴_설계!E35,"0.0")&"단어/턴)" -> 화당 120턴 · 부 총 1,440턴 · 화당 약 1,367단어 · 낭독 약 10.5분 (평균 11.4단어/턴)
A41: Manon 질문·Curie 카드 | B41: Manon: assignation·jugement·clause 등 법률 용어. 카드: 부동산 공시(service de la publicité foncière), 1989년 임대차법, 민사집행법전(CPCE)의 퇴거 절차.
A42: 다음 부 연결 | B42: 3부: 응급실에서 쓰러진 Nicolas — 다음 금요일은 Camille의 이야기.
A44: 3부 | B44: La Médecin — 의사 | 난이도 B2~C1 | 프레임: 금요일 밤. 과거: 약 4년 전, Hôpital Saint-Bernard(가상) 응급실.
A45: 서사 기능 | B45: 인간의 생명과 공공 보건이라는 정서적 무게. Groupe Méridien의 두 번째 얼굴(병원 외주·컨설팅)을 보여 주고, 폭염·고령 환자·서류 없는 환자 등 현안을 응급실에서 체감하게 한다.
A46: 로그라인 | B46: 응급의가 예산 압박과 병원 외주 속에서 환자를 잃기 시작하고, 이름을 적어 두다가 내부 보고를 올리지만 징계로 돌아온다.
A47: 변화 (시작 → 끝) | B47: 시스템을 믿는 의사 → 이름 명단만 든 사직자.
A48: 핵심 갈등 | B48: 의료 윤리 vs 관리 효율 / 침묵하는 동료들
A49: 비트 1 | B49: 발단(1~3화): 금요일 프레임, 야간 근무(Nicolas 진료), 폭염 환자 폭증.
A50: 비트 2 | B50: 전개(4~5화): 병원 외주 발표(컨설턴트 Léa 등장), 프레임에서 수첩 명단과 Napoléon이 움켜쥐는 배.
A51: 비트 3 | B51: 미드포인트(6화): '명단의 첫 번째' — 서류 없는 환자가 병상 지연으로 들것 위에서 숨진다.
A52: 비트 4 | B52: 위기(7~9화): 원장의 통계, 징계 절차, 프레임에서 Sartre의 되묻기.
A53: 비트 5 | B53: 절정(10~11화): 병상 없는 밤(백색 계획), 사직.
... A59: 언어 설계 | B59: B2~C1. 의학 어휘, 짧은 명령형, 긴박한 호흡. 발성: 빠른 템포와 짧은 호흡.
A60: 대화량 (화당 120턴) | B60: ="화당 "&턴_설계!$B$5&"턴 · 부 총 "&TEXT(턴_설계!D36,"#,##0")&"턴 · 화당 약 "&TEXT(턴_설계!F36,"#,##0")&"단어 · 낭독 약 "&TEXT(턴_설계!H36,"0.0")&"분 (평균 "&TEXT(턴_설계!E36,"0.0")&"단어/턴)" -> 화당 120턴 · 부 총 1,440턴 · 화당 약 1,094단어 · 낭독 약 8.4분 (평균 9.1단어/턴)
A61: Manon 질문·Curie 카드 | B61: Manon: tri·constantes·sepsis 등 의학 용어. 카드: 공중보건법전(Code de la santé publique), 2002년 3월 4일 환자권리법, AP-HP.
A62: 다음 부 연결 | B62: 4부: Julien — «À moi.» 그 서명의 주인.
A64: 4부 | B64: L'Auditeur — 회계감사인 | 난이도 B2~C1 | 프레임: 금요일 밤. 과거: 약 3년 전, Bertin & Roux Audit(가상).
A65: 서사 기능 | B65: 돈의 흐름과 '서명의 책임'. 부패의 공모가 일상 업무의 얼굴로 온다는 것을 보여 주고, 이후 아크의 결정적 증거(USB)를 만든다.
A66: 로그라인 | B66: 시니어 파트너가 최대 고객의 이상 거래를 발견하지만, 압박과 승진 앞에서 결국 '깨끗한' 의견서에 서명하고 그 서명이 다른 사람의 죽음과 해고에 쓰인다.
A67: 변화 (시작 → 끝) | B67: 정확함을 자랑하던 감사인 → '서명한 사람'. 다시는 서명하지 않겠다는 다짐.
A68: 핵심 갈등 | B68: 감사인의 독립성 vs 수임료 / 정확함 vs 생존
A69: 비트 1 | B69: 발단(1~3화): '내가 서명했다' 프레임, 결산 마감, 돈 잘 주는 고객.
A70: 비트 2 | B70: 전개(4~5화): '이건 안 맞아' — 특수관계자 대출 발견 / 프레임에서 아버지 이야기.
A71: 비트 3 | B71: 미드포인트(6화): 파트너 회의 — 한정 의견 주장, 리스크 위원회로 에스컬레이션.
A72: 비트 4 | B72: 위기(7~9화): 위원회의 '증거 불충분', 16구의 점심(위협), 프레임 '서명했나요?'.
A73: 비트 5 | B73: 절정(10~11화): 서명, 그리고 서명 이후 — 계약 확정과 구조조정 통보, 사직.
... A79: 언어 설계 | B79: B2~C1. 숫자 낭독, 수동태·조건법, 감사 보고서체. 발성: 일정한 속도, 결론 문장에서 톤 낮춤.
A80: 대화량 (화당 120턴) | B80: ="화당 "&턴_설계!$B$5&"턴 · 부 총 "&TEXT(턴_설계!D37,"#,##0")&"턴 · 화당 약 "&TEXT(턴_설계!F37,"#,##0")&"단어 · 낭독 약 "&TEXT(턴_설계!H37,"0.0")&"분 (평균 "&TEXT(턴_설계!E37,"0.0")&"단어/턴)" -> 화당 120턴 · 부 총 1,440턴 · 화당 약 1,253단어 · 낭독 약 9.6분 (평균 10.4단어/턴)
A81: Manon 질문·Curie 카드 | B81: Manon: bilan·compte de résultat·seuil de signification 등 회계 용어. 카드: 상법전 법정감사 편, H2A, 상업등기소(Infogreffe).
A82: 다음 부 연결 | B82: 5부: Léa — 그 의견서 이후 시작된 구조조정 명단의 주인.
A84: 5부 | B84: La Consultante — 컨설턴트 | 난이도 B2~C1 | 프레임: 금요일 밤. 과거: 약 2년 전, Zénith Consulting(가상) La Défense 32층.
A85: 서사 기능 | B85: 효율의 이름으로 사람이 숫자가 되는 순간. 노동(Karim), 청년 고용(S1), 영세 기업·탈산업화(E2)를 도입하고 Léa의 말투 변화를 예고한다.
A86: 로그라인 | B86: 전략 컨설턴트가 영세 기업을 살리려던 낙관에서 출발해, 대형 고객 구조조정 모델의 셀 하나가 412명의 해고임을 알게 된다.
A87: 변화 (시작 → 끝) | B87: '스케일'을 믿던 사람 → 사람을 숫자로 본 죄책감을 인정하는 사람(프레젠테이션 톤에서 솔직한 톤으로 가는 시작).
A88: 핵심 갈등 | B88: 효율 vs 사람 / 조직 충성 vs 양심
A89: 비트 1 | B89: 발단(1~3화): 매트릭스 프레임, Zénith 32층, Garnier 공방(영세 기업의 실패).
A90: 비트 2 | B90: 전개(4~5화): 이카로스 프로젝트 킥오프 / 프레임 '엑셀 한 장'.
A91: 비트 3 | B91: 미드포인트(6화): C47 셀 — 412개 일자리, 샴페인.
A92: 비트 4 | B92: 위기(7~9화): 협상 테이블에서 Karim과 대면, 잘못 보낸 메일과 카페의 Sartre, 프레임 '412'.
A93: 비트 5 | B93: 절정(10~11화): 파업과 Karim의 해고, 마지막 회의에서 사직.
... A99: 언어 설계 | B99: B2~C1. 경영 외래어(aligner, scalable, livrable), 프레젠테이션 톤. 발성: 숨 가쁜 톤에서 느린 솔직한 톤으로.
A100: 대화량 (화당 120턴) | B100: ="화당 "&턴_설계!$B$5&"턴 · 부 총 "&TEXT(턴_설계!D38,"#,##0")&"턴 · 화당 약 "&TEXT(턴_설계!F38,"#,##0")&"단어 · 낭독 약 "&TEXT(턴_설계!H38,"0.0")&"분 (평균 "&TEXT(턴_설계!E38,"0.0")&"단어/턴)" -> 화당 120턴 · 부 총 1,440턴 · 화당 약 1,296단어 · 낭독 약 10.0분 (평균 10.8단어/턴)
A101: Manon 질문·Curie 카드 | B101: Manon: parties prenantes·scaler·synergie·KPI 등 경영 용어. 카드: 노동법전 경제적 해고 편.
A102: 다음 부 연결 | B102: 6부: 생드니 — 네 사람이 같은 총회에.
A104: 6부 | B104: La Rencontre — 운명적 만남 | 난이도 B2 | 약 1년 전(1부보다 앞). Saint-Denis '14동' → Belleville 사무소 개소.
A105: 서사 기능 | B105: 퍼즐 완성. 네 개의 과거가 하나의 이름(Groupe Méridien)으로 수렴하고 팀이 결성된다. 1부의 '왜?'에 대한 대답이자 시간의 고리를 닫는 아크.
A106: 로그라인 | B106: 각자 무너진 네 사람이 같은 건물을 지키려고 모였다가 자기들이 서로 다른 얼굴의 같은 회사를 도왔음을 알게 되고, 서로를 비난한 끝에 처음으로 함께 이긴다.
A107: 변화 (시작 → 끝) | B107: 혼자 무너진 네 사람 → 서로의 죄를 아는 팀.
A108: 핵심 갈등 | B108: 서로에 대한 책임(공모) vs 함께 속죄
A109: 비트 1 | B109: 발단(1~3화): 생드니의 화요일, 낯선 넷, 14동.
A110: 비트 2 | B110: 전개(4~5화): 계단의 밤(첫 속내), Julien의 서류.
A111: 비트 3 | B111: 미드포인트(6화): '같은 이름' — 네 개의 과거가 Méridien 하나로 이어진다.
A112: 비트 4 | B112: 위기(7~9화): 서로에 대한 비난, 퇴거 아침 영시의 협업, 첫 정지 승리.
A113: 비트 5 | B113: 절정(10~11화): 벨빌의 가게, 식탁의 규칙(금요일 이야기 전통).
... A119: 언어 설계 | B119: B2. 감정 폭발·설득 구어체, 다툼과 화해. 발성: 소리 높임과 회복의 대비. vous → tu 전환(tutoiement)의 시작.
A120: 대화량 (화당 120턴) | B120: ="화당 "&턴_설계!$B$5&"턴 · 부 총 "&TEXT(턴_설계!D39,"#,##0")&"턴 · 화당 약 "&TEXT(턴_설계!F39,"#,##0")&"단어 · 낭독 약 "&TEXT(턴_설계!H39,"0.0")&"분 (평균 "&TEXT(턴_설계!E39,"0.0")&"단어/턴)" -> 화당 120턴 · 부 총 1,440턴 · 화당 약 1,222단어 · 낭독 약 9.4분 (평균 10.2단어/턴)
A121: Manon 질문·Curie 카드 | B121: Manon: « C'est quoi, un fonds vautour ? » 등 소유 구조 용어. 카드: 상업등기소, 퇴거 유예 규정(민사집행법전).
A122: 다음 부 연결 | B122: 1부 1화 — 원이 닫힌다. 그리고 7부로.
A124: 7부 | B124: Le Réseau de résistance — 전면전 | 난이도 B2~C1 | 사무소 개소 1년 후. 법원, 시청 앞, 파리 전역.
A125: 서사 기능 | B125: 전문 능력이 결합되어 첫 결정적 승리를 얻지만, 법원 결정이 법 앞에서 무력할 수 있음을 배운다. 정치의 필요성을 낳는 아크.
A126: 로그라인 | B126: 사무소가 사소 고소·내부고발·보도를 결합해 Groupe Méridien을 상대로 전면전을 벌이고 예심판사의 입건 결정을 얻지만, 그 승리를 뒤집을 법이 준비되고 있음을 알게 된다.
A127: 변화 (시작 → 끝) | B127: 사건을 푸는 사무소 → 법을 바꿔야 한다는 결론.
A128: 핵심 갈등 | B128: 합법 vs 효율(도청기) / 승리의 지속 가능성
A129: 비트 1 | B129: 발단(1~3화): 1년 후(Olympe 합류), 계단 위의 줄, 불기소된 피해자 사건(N4).
A130: 비트 2 | B130: 전개(4~5화): 서류 없는 사람들(S2), Philippe의 제보.
A131: 비트 3 | B131: 미드포인트(6화): 사건 파일 — 인가 반부패 단체와 함께 사소 고소장 제출.
A132: 비트 4 | B132: 위기(7~9화): 보복(봉쇄 소송), 전등 속 마이크(증거 적법성 논쟁), 동네의 보초.
A133: 비트 5 | B133: 절정(10~11화): 예심판사의 입건 결정 / 다가오는 법(반부패 단체 사소권 제한 법안).
... A139: 언어 설계 | B139: B2~C1. 집단 소송·성명서·인터뷰 어휘. 발성: 긴박한 대화와 기자회견 톤.
A140: 대화량 (화당 120턴) | B140: ="화당 "&턴_설계!$B$5&"턴 · 부 총 "&TEXT(턴_설계!D40,"#,##0")&"턴 · 화당 약 "&TEXT(턴_설계!F40,"#,##0")&"단어 · 낭독 약 "&TEXT(턴_설계!H40,"0.0")&"분 (평균 "&TEXT(턴_설계!E40,"0.0")&"단어/턴)" -> 화당 120턴 · 부 총 1,440턴 · 화당 약 1,248단어 · 낭독 약 9.6분 (평균 10.4단어/턴)
...

Sheet 화별목차_전체
A1: 전체 화별 목차 (1~13부, 156화)
A2: 프랑스 제5공화국 제도와 현안(ID는 '현안_배치' 시트)을 반영한 초안. 득표율·의석 수·결과는 가상 수치. 모든 화는 지문 없이 대화문으로만 진행한다.
A4: 부 | B4: 화 | C4: 서사 기능 | D4: 제목 (FR) | E4: 한국어 | F4: 핵심 사건 | G4: 반영 제도·전문 영역 | H4: 주요 인물 | I4: 반영 현안 (ID) | J4: 턴 수
A5: 1 | B5: 1 | C5: 사건1 도입 | D5: Encore une lettre | E5: 또 한 통의 편지 | F5: 사무소 개소 1개월 후. 다섯 시, 여전히 방법을 못 정한 채 매일 다투는 팀. Fatima가 두 번째로 찾아와 새 임대료 인상 통지서를 보인다. Manon은 여전히 Nicolas에게 vous를 쓴다. Curie가 지나가며 «날짜를 세어 보라»는 힌트만 던지고, 임대차 계약서가 없어 다음 날로 미뤄진다. | G5: 생활 법률 구어체, 반복되는 말다툼 (B1) | H5: Monique, Nicolas, Camille, Julien, Léa, Manon, Napoléon, Fatima, Curie | I5: E1 | J5: =턴_설계!$B$5 -> 120
A6: 1 | B6: 2 | C6: 사건1 해결 | D6: La clause qui n'augmente pas | E6: 오르지 않는 조항 | F6: [사건1 해결] Fatima와 Manon이 계약서를 가져온다. Curie의 카드 #1(1989년 임대차법 제17-1조, 임대료 기준지수 IRL)로 인상률이 부당함을 확인하고, 기한 안에 등기우편(lettre recommandée)으로 답장을 쓴다. 사무소의 첫 번째 규칙(가난한 이웃에겐 돈을 받지 않는다)이 확인된다. | G6: 임대차(1989년 7월 6일 법), 임대료 기준지수(IRL), 파리 임대료 상한(encadrement des loyers) | H6: Nicolas, Julien, Léa, Fatima, Curie, Manon, Monique | I6: E1 | J6: =턴_설계!$B$5 -> 120
A7: 1 | B7: 3 | C7: 사건2 도입 | D7: La fin de la trêve | E7: 겨울 휴전의 끝 | F7: [사건2 도입] 3월 31일 밤, 겨울 퇴거 유예(trêve hivernale)가 끝나는 다음 날 아침으로 퇴거 집행이 잡혔다는 급보가 온다. Jeanne이 주민을 조직하고 Karim이 이웃들을 모은다. 네 사람이 각자 서류·건강·숫자·동선을 맡아 밤새 준비하지만 승산은 불투명하다. | G7: 겨울 퇴거 유예(11월 1일~3월 31일), 퇴거 명령(commandement de quitter les lieux), 이웃 조직 | H7: Nicolas, Camille, Julien, Léa, Jeanne, Karim, Manon, Monique | I7: S1 | J7: =턴_설계!$B$5 -> 120
A8: 1 | B8: 4 | C8: 사건2 해결 | D8: Le fourgon qui n'est pas venu | E8: 오지 않은 경찰 승합차 | F8: [사건2 해결] 집행 당일 아침. Nicolas의 긴급 가처분(référé)과 유예 기간 신청, Camille의 취약성 진단서, Julien의 채무 계산, Léa의 동선 배치가 맞물리고, 도청(préfecture)이 경찰 지원(concours de la force publique)을 미뤄 집행이 연기된다. Jeanne의 «Rien à signaler.» 보고로 마무리된다. | G8: 보호소송 판사(juge des contentieux de la protection), 유예 기간, 경찰 지원 거부와 국가 배상 | H8: Nicolas, Camille, Julien, Léa, Jeanne, Karim, Manon, Monique | I8: S1 | J8: =턴_설계!$B$5 -> 120
A9: 1 | B9: 5 | C9: 사건3 도입 | D9: Le stagiaire de l'usine | E9: 공장의 인턴 | F9: [사건3 도입] 임금 체불과 부당한 초과근무에 지친 청년 노동자 Théo(가상)가 찾아온다. Léa가 컨설팅 용어로 상황을 분석하려 하고 Manon이 통역하듯 애쓰지만 Théo는 점점 지쳐 간다. | G9: 기간제 계약(CDD), 초과근무, 경영 용어의 벽 | H9: Léa, Manon, Julien, Monique, Théo(가상) | I9: S1 | J9: =턴_설계!$B$5 -> 120
A10: 1 | B10: 6 | C10: 사건3 해결(폭발) | D10: Ça suffit ! | E10: 그만! | F10: [사건3 해결] 협상 자리에서 Léa의 용어가 한 시간째 이어지자 Manon이 폭발한다(1차 폭발). Camille·Jeanne·Monique·Curie의 고정 반응, Napoléon의 «Bécasse… Demande.», Julien의 «Je traduis.» 이후 쉬운 말로 다시 협상해 노동법원(prud'hommes)에 가기 전에 밀린 임금 지급에 합의한다. | G10: 감정 표현, 전문 용어 → 쉬운 말, 임금 체불 합의(노동법원 전 화해) | H10: Manon, Léa, Julien, Camille, Napoléon, Jeanne, Monique, Curie, Théo(가상) | I10: S1 | J10: =턴_설계!$B$5 -> 120
A11: 1 | B11: 7 | C11: 사건4 도입 | D11: La petite qui a de la fièvre | E11: 열이 나는 아이 | F11: [사건4 도입] 체류 서류가 없어 소아과 예약을 못 잡는 가족이 찾아온다. Camille가 나서고 Sartre가 카페에서 건너와 «Et toi, qu'est-ce que tu choisis ?»를 처음 선보인다. 마침 들른 Hugo는 Napoléon에게 원고를 놀림받다 «Pas mal.»이라는 최고의 칭찬을 듣는다. 정작 진짜 아픈 아이 앞에서 Napoléon은 자기 무릎 타령을 멈춘다. | G11: 서류 없는 가족의 의료 접근(국가의료지원 AME, 모자보건센터 PMI), 증상 표현 | H11: Camille, Sartre, Napoléon, Hugo, Manon, Monique, 가족(가상) | I11: S2 | J11: =턴_설계!$B$5 -> 120
A12: 1 | B12: 8 | C12: 사건4 해결 | D12: L'AME pour Amina | E12: Amina를 위한 AME | F12: [사건4 해결] Nicolas와 Camille가 행정 거주지 등록(domiciliation, CCAS) 경로를 찾아내고, 미성년자는 3개월 거주 요건 없이 AME를 받을 수 있음을 확인해 아이가 진료를 받는다. Napoléon이 평소와 달리 조용히 커피를 마신다. | G12: 행정 거주지 등록(domiciliation), AME의 미성년자 특례, 진료 의뢰 | H12: Camille, Nicolas, Manon, Monique, 가족(가상) | I12: S2 | J12: =턴_설계!$B$5 -> 120
A13: 1 | B13: 9 | C13: 사건5 도입 | D13: La veuve du cinquième | E13: 5층의 미망인 | F13: [사건5 도입] 가짜 적금 상품(faux livret)에 저축을 잃은 노년의 이웃 Josette(가상)가 찾아온다. Julien이 장부를 살피는 동안, 양복 입은 낯선 남자 Philippe가 나타나 은행 쪽 흐름을 봐 주겠다고 하면서도 자기 이야기는 하지 않는다. Voltaire가 냄새를 맡고 기웃거린다. | G13: 투자 사기(arnaque aux faux placements), 은행 계좌 기초 어휘 | H13: Julien, Philippe, Voltaire, Manon, Monique, Josette(가상) | I13: E3 | J13: =턴_설계!$B$5 -> 120
A14: 1 | B14: 10 | C14: 사건5 해결 | D14: Suivez l'argent | E14: 돈을 따라가라 | F14: [사건5 해결] Philippe의 계좌 흐름 추적과 Julien의 장부 대조로 사기 계좌를 찾아 은행에 이의 제기를 하고 돈 일부를 되찾는다. Philippe는 설명 없이 떠나고, Julien은 «Banque Atlantique»라는 이름에 말없이 굳는다. | G14: 자금 흐름 추적, 무권한 송금 이의 제기, 계좌·송금 어휘 | H14: Julien, Philippe, Manon, Monique, Josette(가상) | I14: E3 | J14: =턴_설계!$B$5 -> 120
A15: 1 | B15: 11 | C15: 사건6 도입 | D15: Un papier d'il y a des années | E15: 수년 전 서류 | F15: [사건6 도입] Fatima의 남편 Rachid가 수십 년 전 다른 건물에서 받은 낡은 퇴거 서류를 들고 온다. 당장 급한 사안은 아니지만 오래된 절차 하자가 보인다. Voltaire가 풍자 기사 각도로 흥미를 보인다. | G15: 오래된 서류 판독, 절차 하자 | H15: Nicolas, Voltaire, Manon, Monique, Rachid(가상) | I15: E1 | J15: =턴_설계!$B$5 -> 120
A16: 1 | B16: 12 | C16: 사건6 해결(훅) | D16: La Signature | E16: 서명 | F16: [사건6 해결·훅] 절차 하자를 바로잡아 오래된 기록을 정정하지만, 진짜 충격은 서류 맨 아래: Nicolas의 옛 로펌 «Vasseur & Delorme»의 서명이다. Nicolas가 얼어붙고 Monique가 «Asseyez-vous, je vous apporte quelque chose.»로 분위기를 잇는다. 금요일에는 Nicolas의 이야기가 시작된다. | G16: 서명·기록 정정, 이름 확인 | H16: Nicolas, Monique, Manon, Napoléon, Rachid(가상) | I16: E1 | J16: =턴_설계!$B$5 -> 120
A17: 2 | B17: 1 | C17: 발단 | D17: Les histoires du vendredi | E17: 금요일의 이야기 | F17: (프레임) Monique의 식탁에서 금요일마다 한 사람이 과거를 이야기하는 규칙이 시작된다. Manon이 Nicolas에게 왜 로펌을 그만뒀느냐고 묻고 Nicolas는 «Procédons dans l'ordre.»로 시작한다. | G17: 존칭 vous와 tu의 대비, 과거 이야기 도입(passé composé·imparfait) | H17: Manon, Nicolas, Monique, Napoléon | I17: E1 | J17: =턴_설계!$B$5 -> 120
A18: 2 | B18: 2 | C18: 발단 | D18: Un lundi avenue George-V | E18: 조르주5세 거리의 월요일 | F18: (과거) 승소율 100%의 파트너 후보 Nicolas의 하루. 새벽 편의점에서 영수증 뒷면에 시를 쓰는 야간 점원 Hugo와 마주친다. 상사 Delorme(가상)이 파트너 승진을 암시한다. | G18: 로펌 어휘: associé, honoraires, portefeuille de clients | H18: Nicolas, Hugo, Delorme(가상) | J18: =턴_설계!$B$5 -> 120
A19: 2 | B19: 3 | C19: 발단 | D19: Le client vedette | E19: VIP 고객 | F19: 대형 고객 Groupe Méridien의 회장 Verdier(가상)를 소개받는다. 회의석에는 고객 측 컨설턴트 Léa와 매각 은행 지점장 Philippe가 있다. | G19: 인수합병 어휘: acquisition, portefeuille, clause | H19: Nicolas, Léa, Philippe, Verdier(가상) | I19: E1 | J19: =턴_설계!$B$5 -> 120
A20: 2 | B20: 4 | C20: 전개 | D20: Le portefeuille de Belleville | E20: 벨빌 자산 포트폴리오 | F20: 실사(due diligence). 포트폴리오에 Belleville 건물 12채가 들어 있다. 감사인 Julien이 «Ça ne colle pas.»를 흘리고, 센 강변 헌책방(bouquinistes)에서 부동산 등기 자료를 찾던 Nicolas에게 Curie가 «Cherche toi-même.» | G20: 실사, 부동산 공시(service de la publicité foncière), 임차인 명부 | H20: Nicolas, Julien, Curie | I20: E1 | J20: =턴_설계!$B$5 -> 120
A21: 2 | B21: 5 | C21: 전개 | D21: Vendredi : la rue de Monique | E21: 금요일: Monique의 거리 | F21: (프레임) 그 포트폴리오에 Monique의 가게가 있던 건물이 들어 있었음이 밝혀진다. Manon은 놀라 vous를 놓치고 Nicolas는 잠시 침묵한다. | G21: 감정 표현, 놀람 | H21: Monique, Nicolas, Manon | I21: E1 | J21: =턴_설계!$B$5 -> 120
A22: 2 | B22: 6 | C22: 미드포인트 | D22: La Clause | E22: 조항 | F22: 임차인을 비우는 가장 '깨끗한' 방법으로 Nicolas가 '대규모 에너지 리노베이션'을 '정당하고 중대한 사유(motif légitime et sérieux)'로 삼는 해지 조항을 설계한다. Léa의 재무 모델이 이를 뒷받침한다. | G22: 임대인의 해지 통지(congé), 정당하고 중대한 사유, 에너지 성능 진단(DPE) | H22: Nicolas, Léa, Delorme(가상) | I22: E1 | J22: =턴_설계!$B$5 -> 120
A23: 2 | B23: 7 | C23: 위기 | D23: L'assemblée des locataires | E23: 세입자 총회 | F23: 세입자들이 총회를 연다. 버스 노조 출신 Karim이 이끌고, 응급실 의사 Camille가 공황을 일으킨 노인을 돌본다. Nicolas는 78세 Madeleine(가상)을 만난다. | G23: 총회·발언·동의, 항의 표현 | H23: Nicolas, Karim, Camille, Madeleine(가상) | I23: E1 | J23: =턴_설계!$B$5 -> 120
A24: 2 | B24: 8 | C24: 위기 | D24: Le Procès | E24: 재판 | F24: 심리(audience)와 판결. Nicolas가 승소한다. 풍자 칼럼을 쓰던 Voltaire가 «Vous êtes fier ?»라고 묻는다. 감사인 Julien은 고객의 장부를 보고 고개를 젓는다. | G24: 소송: assignation, audience, jugement, dépens | H24: Nicolas, Voltaire, Julien, 판사(가상) | I24: E1·P3 | J24: =턴_설계!$B$5 -> 120
A25: 2 | B25: 9 | C25: 위기 | D25: Vendredi : continue | E25: 금요일: 계속해 | F25: (프레임) Nicolas가 말을 잇지 못하자 Napoléon이 «Quand j'étais empereur…»로 시간을 벌어 주고 Monique가 «Continue.»라고 한다. Manon은 «Et elle ?»라고 묻는다. | G25: 위로·재촉 표현 | H25: Nicolas, Napoléon, Monique, Manon | J25: =턴_설계!$B$5 -> 120
A26: 2 | B26: 10 | C26: 절정 | D26: Un dîner dans le 16e | E26: 16구의 저녁 | F26: 승소 축하 만찬. 파트너들이 건배하는 동안 Verdier가 다음 포트폴리오를 건넨다. Nicolas의 휴대전화가 울린다. | G26: 고급 식당 표현, 건배·축하 | H26: Nicolas, Delorme(가상), Verdier(가상), Julien | J26: =턴_설계!$B$5 -> 120
A27: 2 | B27: 11 | C27: 절정 | D27: La petite-fille de Madeleine | E27: Madeleine의 손녀 | F27: Madeleine이 퇴거 석 달 뒤 세상을 떠났다는 소식. 손녀 Chloé(가상)가 사무실로 찾아와 조용히 묻는다: «Vous avez gagné ?» | G27: 조의·항의, 문서 vs 사람 | H27: Nicolas, Chloé(가상) | I27: E1 | J27: =턴_설계!$B$5 -> 120
A28: 2 | B28: 12 | C28: 결말·훅 | D28: Vendredi : la démission | E28: 금요일: 사직 | F28: (프레임+과거) Nicolas가 다음 포트폴리오 서명을 거부하고 사직서를 낸다. 짐 상자를 든 채 응급실 대기실에서 쓰러지고 Camille가 그를 진료한다. Manon은 여전히 vous를 쓴다. | G28: 사직·거절 표현, 접속법(subjonctif) | H28: Nicolas, Camille, Manon, Monique | J28: =턴_설계!$B$5 -> 120
A29: 3 | B29: 1 | C29: 발단 | D29: Vendredi : les noms | E29: 금요일: 이름들 | F29: (프레임) Camille가 «Ce n'est pas une statistique, c'est une personne.»라며 이야기를 시작한다. Napoléon이 식사를 거르고 배를 움켜쥐는 것을 Camille가 흘끗 본다. | G29: 의학 어휘 도입 | H29: Camille, Manon, Napoléon, Monique | J29: =턴_설계!$B$5 -> 120
A30: 3 | B30: 2 | C30: 발단 | D30: Garde de nuit | E30: 야간 근무 | F30: (과거) Saint-Bernard 응급실의 야간 근무. 분류 간호사(IOA)의 트리아주, 들것(brancard), 간호사 Sandrine(가상)과의 호흡. 가슴 통증으로 실려 온 Nicolas를 진료한다. | G30: tri, constantes, brancard, box | H30: Camille, Sandrine(가상), Nicolas | J30: =턴_설계!$B$5 -> 120
A31: 3 | B31: 3 | C31: 발단 | D31: La Canicule | E31: 폭염 | F31: 폭염에 고령 환자가 몰려 응급실이 넘친다. 산소·수액·얼음. Camille는 밤새 환자 이름을 외운다. | G31: 열사병(coup de chaleur), 탈수, 고령 환자, 폭염 경보 계획(plan canicule) | H31: Camille, Sandrine(가상) | I31: S4·S3 | J31: =턴_설계!$B$5 -> 120
A32: 3 | B32: 4 | C32: 전개 | D32: Un contrat que personne ne lit | E32: 아무도 읽지 않는 계약 | F32: 병원이 병상 관리·검사 물류를 Méridien Santé에 외주하고 컨설팅 회사에 '효율화'를 맡긴다고 발표한다. 원장 회의에서 컨설턴트 Léa가 '효율' 발표를 한다. | G32: 외주(externalisation), 공공조달, 공공부문 컨설팅 계약 논란 | H32: Camille, 원장(가상), Léa | I32: S3 | J32: =턴_설계!$B$5 -> 120
A33: 3 | B33: 5 | C33: 전개 | D33: Vendredi : la liste | E33: 금요일: 명단 | F33: (프레임) Manon이 Camille의 수첩 명단을 본다. Camille는 «J'ai vu pire un mardi ordinaire.»로 넘긴다. Napoléon은 배가 아프냐는 물음에 «C'est la cuisine anglaise. Sainte-Hélène m'a laissé des souvenirs.» | G33: 명단·숫자 읽기 | H33: Camille, Manon, Napoléon | J33: =턴_설계!$B$5 -> 120
A34: 3 | B34: 6 | C34: 미드포인트 | D34: La première de la liste | E34: 명단의 첫 번째 | F34: 서류 없는 20대 여성이 패혈증으로 실려 오지만 병상 배정이 아홉 시간 지연되어 들것 위에서 숨진다. 외주 병상관리가 '비용 검토' 중이었다. Camille가 수첩에 첫 이름을 쓴다. | G34: 패혈증(sepsis), 병상 관리, 들것 위의 사망, 서류 없는 환자의 응급 진료권 | H34: Camille, Sandrine(가상), 원장(가상) | I34: S2·S3 | J34: =턴_설계!$B$5 -> 120
A35: 3 | B35: 7 | C35: 위기 | D35: Les chiffres du directeur | E35: 원장의 숫자 | F35: 원장이 '대기 시간 개선' 통계를 발표한다. 외주 업체의 재무를 자문하는 Julien이 배석한다. Camille가 내부 사망 사례 보고서(déclaration d'événement indésirable grave)를 제출한다. | G35: 통계 읽기, 중대 부작용 사례 보고 | H35: Camille, 원장(가상), Julien | I35: P3 | J35: =턴_설계!$B$5 -> 120
A36: 3 | B36: 8 | C36: 위기 | D36: La Procédure disciplinaire | E36: 징계 절차 | F36: 보고서 유출 의혹으로 징계 절차가 시작된다. 취재하러 온 Voltaire에게 Camille가 «Ça ne sort pas d'ici.»라고 못 박는다. | G36: 공무원 징계(procédure disciplinaire), 직업상 비밀 유지 | H36: Camille, Voltaire, 원장(가상) | I36: P3 | J36: =턴_설계!$B$5 -> 120
A37: 3 | B37: 9 | C37: 위기 | D37: Vendredi : et qu'est-ce que tu choisis ? | E37: 금요일: 그래서 넌 뭘 선택하지? | F37: (프레임) Sartre가 Camille에게 «Et toi, qu'est-ce que tu choisis ?»라고 되묻는다. Camille는 «D'abord, respire.»로 받아친다. Manon이 Sartre의 화법을 흉내 낸다. | G37: 선택·책임 표현, 되받기 화법 | H37: Camille, Sartre, Manon | J37: =턴_설계!$B$5 -> 120
A38: 3 | B38: 10 | C38: 절정 | D38: Une nuit sans lits | E38: 병상 없는 밤 | F38: 버스 사고와 폭염이 겹친 밤. 백색 계획(plan blanc)이 발동되지만 병상이 없어 복도까지 환자가 찬다. Camille가 즉흥으로 일곱 명을 살리고 한 명을 잃는다. | G38: 대량 환자, 백색 계획(plan blanc), 우선순위, 명령형 | H38: Camille, Sandrine(가상) | I38: S4 | J38: =턴_설계!$B$5 -> 120
A39: 3 | B39: 11 | C39: 절정 | D39: La démission de la docteure | E39: 의사의 사직 | F39: 징계 통보와 마지막 근무. 수첩을 덮고 사직서를 낸다. Sandrine이 «Docteure, ne partez pas.» | G39: 사직서, 작별 | H39: Camille, Sandrine(가상), 원장(가상) | J39: =턴_설계!$B$5 -> 120
A40: 3 | B40: 12 | C40: 결말·훅 | D40: Vendredi : une signature | E40: 금요일: 한 사람의 서명 | F40: (프레임) Camille가 «Le rapport d'audit du contrat portait une signature.»라고 말한다. Julien이 조용히 «À moi.» | G40: 서명·책임 표현 | H40: Camille, Julien, Manon, Napoléon | J40: =턴_설계!$B$5 -> 120
A41: 4 | B41: 1 | C41: 발단 | D41: Vendredi : j'ai signé | E41: 금요일: 내가 서명했다 | F41: (프레임) Julien이 «Montrez-moi les documents.»를 습관처럼 하다가 «J'ai signé.»라고 시작한다. Manon이 숫자를 못 읽어 질문한다. | G41: 회계 어휘 도입 | H41: Julien, Manon, Camille, Napoléon | J41: =턴_설계!$B$5 -> 120
A42: 4 | B42: 2 | C42: 발단 | D42: Clôture de l'exercice | E42: 결산 마감 | F42: (과거) Bertin & Roux의 결산 감사 마감 주간. 표본추출(échantillonnage)과 중요성 기준(seuil de signification). Julien의 정확성과 냉소. | G42: 감사 절차 어휘 | H42: Julien, Bertin(가상), 후배 감사인(가상) | J42: =턴_설계!$B$5 -> 120
A43: 4 | B43: 3 | C43: 발단 | D43: Le client qui paie bien | E43: 돈 잘 주는 고객 | F43: Groupe Méridien이 회사 수임료의 15%를 차지한다. 감사인 독립성과 교체(rotation) 규정이 문제가 된다. Bertin은 '관계'를 강조한다. | G43: 독립성, 수임료 집중, 법정감사인 교체 | H43: Julien, Bertin(가상) | J43: =턴_설계!$B$5 -> 120
A44: 4 | B44: 4 | C44: 전개 | D44: Ça ne colle pas | E44: 이건 안 맞아 | F44: 특수관계자 대출이 룩셈부르크 지주회사로 흘러간 흔적. 은행 자료를 보내 준 Philippe가 «Suivez l'argent.» | G44: 특수관계자 거래, 조세 회피처 | H44: Julien, Philippe | J44: =턴_설계!$B$5 -> 120
A45: 4 | B45: 5 | C45: 전개 | D45: Vendredi : le père de Julien | E45: 금요일: Julien의 아버지 | F45: (프레임) 정직한 장부를 지키다 해고된 아버지 이야기. «Montrez-moi les chiffres, je vous dirai qui vous êtes.»의 기원. | G45: 가족 이야기, 과거 | H45: Julien, Manon, Monique | J45: =턴_설계!$B$5 -> 120
A46: 4 | B46: 6 | C46: 미드포인트 | D46: La réunion des associés | E46: 파트너 회의 | F46: Julien이 '한정 의견(certification avec réserve)'을 주장하자 파트너들이 승진과 고객 유지를 들어 설득한다. Julien은 리스크 위원회로 사안을 올린다. | G46: 감사 의견: sans réserve, avec réserve, refus de certifier, impossibilité de certifier | H46: Julien, Bertin(가상), 파트너들 | J46: =턴_설계!$B$5 -> 120
A47: 4 | B47: 7 | C47: 위기 | D47: Le comité des risques | E47: 리스크 위원회 | F47: GM의 변호사 서한이 도착한다(고객 측 변호사는 Nicolas의 옛 동료). 위원회는 '증거 불충분'으로 결정한다. | G47: 변호사 서한, 충분한 감사 증거 | H47: Julien, 위원회(가상) | I47: P3 | J47: =턴_설계!$B$5 -> 120
A48: 4 | B48: 8 | C48: 위기 | D48: Un déjeuner dans le 16e | E48: 16구의 점심 | F48: Verdier가 Julien에게 점심을 산다. 정중한 위협과 제안: 파트너 승진과 개인 자문 계약. Voltaire의 전화가 온다. | G48: 완곡한 압박, 조건법(conditionnel) | H48: Julien, Verdier(가상), Voltaire | J48: =턴_설계!$B$5 -> 120
A49: 4 | B49: 9 | C49: 위기 | D49: Vendredi : et vous avez signé ? | E49: 금요일: 서명했나요? | F49: (프레임) Manon이 묻고 Julien은 «Attends.»라고 한다. Napoléon이 «Nous avons tous signé quelque chose un jour. Moi, une abdication. Deux fois.»라고 말하고 Camille가 눈을 감는다. | G49: 재촉·회피 | H49: Julien, Manon, Napoléon, Camille | J49: =턴_설계!$B$5 -> 120
A50: 4 | B50: 10 | C50: 절정 | D50: Certifié sans réserve | E50: 무한정 적정 의견 | F50: Julien이 '적정' 의견서에 서명한다. 서명 후 그는 복사본 USB를 챙긴다. | G50: 서명, 감사 보고서, 책임 | H50: Julien, Bertin(가상) | J50: =턴_설계!$B$5 -> 120
A51: 4 | B51: 11 | C51: 절정 | D51: Après la signature | E51: 서명 이후 | F51: 그 의견서로 병원 외주 계약이 확정되고(3부의 계약) 구조조정 컨설팅이 시작된다는 통보를 받는다. Julien은 사직하고 다시는 서명하지 않겠다고 다짐한다. | G51: 결과·책임, 사직 | H51: Julien, Bertin(가상), Léa | J51: =턴_설계!$B$5 -> 120
A52: 4 | B52: 12 | C52: 결말·훅 | D52: Vendredi : la liste de Léa | E52: 금요일: Léa의 명단 | F52: (프레임) Julien이 USB를 꺼내지 않은 채 식탁에 놓고, Léa가 «C'est moi qui faisais la liste.»라고 말한다. | G52: 고백 | H52: Julien, Léa, Manon, Monique | J52: =턴_설계!$B$5 -> 120
A53: 5 | B53: 1 | C53: 발단 | D53: Vendredi : dans une matrice | E53: 금요일: 매트릭스로 | F53: (프레임) Léa가 «Mettons ça dans une matrice.»로 시작하다 Manon에게 제지당한다. | G53: 경영 어휘 도입, 쉬운 말로 바꾸기 | H53: Léa, Manon, Napoléon | J53: =턴_설계!$B$5 -> 120
A54: 5 | B54: 2 | C54: 발단 | D54: Zénith, 32e étage | E54: Zénith, 32층 | F54: (과거) La Défense 컨설팅 회사의 문화: up-or-out, 야근, 영어가 섞인 프랑스어(franglais). Léa의 초고속 승진. | G54: aligner, scalable, impact, parties prenantes | H54: Léa, 파트너(가상) | J54: =턴_설계!$B$5 -> 120
A55: 5 | B55: 3 | C55: 발단 | D55: L'atelier des Garnier | E55: Garnier 가족의 공방 | F55: 영세 제조업체(TPE) 컨설팅. Léa의 '규모 키우기' 권고가 현실과 맞지 않아 실패한다. 생산성은 조언이 아니라 구조의 문제임을 처음 본다. | G55: 영세 기업, 생산성, 탈산업화 | H55: Léa, Garnier(가상) | I55: E2 | J55: =턴_설계!$B$5 -> 120
A56: 5 | B56: 4 | C56: 전개 | D56: Projet Icare | E56: 이카로스 프로젝트 | F56: GM이 RATP에서 넘겨받은 버스 노선 운영사 Méridien Mobilité의 '비용 18% 절감'을 Zénith에 의뢰한다. 킥오프 회의. | G56: 프로젝트 관리, 목표, 절감, 버스 노선 경쟁 입찰 | H56: Léa, 파트너(가상), GM 임원(가상) | J56: =턴_설계!$B$5 -> 120
A57: 5 | B57: 5 | C57: 전개 | D57: Vendredi : un Excel | E57: 금요일: 엑셀 한 장 | F57: (프레임) Léa가 «Je ne licenciais personne ; je déplaçais des cellules.»라고 말한다. Manon이 «Et combien de cellules ?» | G57: 질문·죄책 표현 | H57: Léa, Manon, Julien | J57: =턴_설계!$B$5 -> 120
A58: 5 | B58: 6 | C58: 미드포인트 | D58: La cellule C47 | E58: C47 셀 | F58: 모델이 완성되고 승인이 난다. 셀 하나가 412개 일자리다. 팀은 샴페인을 딴다. | G58: 모델, 시나리오, 인원 감축 | H58: Léa, 팀(가상) | I58: S1 | J58: =턴_설계!$B$5 -> 120
A59: 5 | B59: 7 | C59: 위기 | D59: La table de négociation | E59: 협상 테이블 | F59: 고용보호계획(PSE) 정보·협의 절차. 노조 대표 Karim이 «Derrière chaque cellule, il y a une personne.» | G59: PSE, 사회경제위원회(CSE) 협의, 노조 대표 | H59: Léa, Karim, 인사 담당(가상) | I59: S1 | J59: =턴_설계!$B$5 -> 120
A60: 5 | B60: 8 | C60: 위기 | D60: Le mauvais mail | E60: 잘못 보낸 메일 | F60: Léa가 이름이 든 파일을 잘못 보낸다. 기간제·파견·청년이 먼저 잘려 있다. 번아웃으로 쉬던 날 Café de Flore에서 Sartre를 만난다. | G60: 기간제·파견 계약, 청년 우선 감축, 죄책감 | H60: Léa, Sartre | I60: S1 | J60: =턴_설계!$B$5 -> 120
A61: 5 | B61: 9 | C61: 위기 | D61: Vendredi : quatre cent douze | E61: 금요일: 412 | F61: (프레임) «Quatre cent douze.» Manon이 말을 잃고 Napoléon이 «Au moins, elle le dit sans slides.» | G61: 숫자 낭독 | H61: Léa, Manon, Napoléon | J61: =턴_설계!$B$5 -> 120
A62: 5 | B62: 10 | C62: 절정 | D62: La Grève | E62: 파업 | F62: 파업이 벌어지고 보호 근로자인 Karim이 근로감독관의 해고 승인을 거쳐 해고되고 블랙리스트에 오른다. Léa는 유리창 너머로 그것을 본다. | G62: 파업권, 보호 근로자(salarié protégé) 해고, 블랙리스트 | H62: Léa, Karim | I62: S1 | J62: =턴_설계!$B$5 -> 120
A63: 5 | B63: 11 | C63: 절정 | D63: La dernière réunion | E63: 마지막 회의 | F63: 보너스 지급 회의. Léa가 '이카로스 2'를 거절하고 사직한다. | G63: 보너스, 거절, 사직 | H63: Léa, 파트너(가상) | J63: =턴_설계!$B$5 -> 120
A64: 5 | B64: 12 | C64: 결말·훅 | D64: Vendredi : un mardi à Saint-Denis | E64: 금요일: 생드니의 화요일 | F64: (프레임) 네 명이 같은 강당에 모이게 된 화요일을 Monique가 설명하며 6부를 예고한다. | G64: 다음 이야기 예고 | H64: Léa, Monique, Nicolas, Camille, Julien | J64: =턴_설계!$B$5 -> 120
A65: 6 | B65: 1 | C65: 발단 | D65: Un mardi à Saint-Denis | E65: 생드니의 화요일 | F65: 네 사람이 각자 다른 이유로 같은 세입자 총회에 도착한다. 손녀 Chloé(가상)와 23세 세입자 Manon이 맞이한다. | G65: 총회 공고, 자기소개 | H65: Nicolas, Camille, Julien, Léa, Chloé(가상), Manon | I65: E1 | J65: =턴_설계!$B$5 -> 120
A66: 6 | B66: 2 | C66: 발단 | D66: Quatre inconnus | E66: 네 명의 낯선 사람 | F66: 서로 아는 척하지 않는다. Nicolas와 Julien은 서로의 이름 «Vasseur & Delorme», «Bertin & Roux»에서 흠칫한다. | G66: 긴장 대화, vous | H66: Nicolas, Camille, Julien, Léa, Manon | J66: =턴_설계!$B$5 -> 120
A67: 6 | B67: 3 | C67: 발단 | D67: Le bâtiment 14 | E67: 14동 | F67: 건물을 돌아본다. 22가구, 물이 새는 벽, 동네 보건센터 폐쇄. 이웃 Karim과 '계단 반장' Jeanne이 안내한다. | G67: 건물·거주 표현 | H67: Nicolas, Camille, Julien, Léa, Karim, Jeanne, Manon | I67: E1 | J67: =턴_설계!$B$5 -> 120
A68: 6 | B68: 4 | C68: 전개 | D68: La nuit de l'escalier | E68: 계단의 밤 | F68: 야간 퇴거 소문에 함께 밤샘한다. Monique의 음식과 Napoléon의 커피 불평. 처음으로 조금씩 속내를 꺼낸다. | G68: 밤샘 대화, 위로 | H68: Nicolas, Camille, Julien, Léa, Monique, Napoléon, Jeanne | J68: =턴_설계!$B$5 -> 120
A69: 6 | B69: 5 | C69: 전개 | D69: Les papiers de Julien | E69: Julien의 서류 | F69: Julien이 USB를 꺼내 Fonds Cardinal – Groupe Méridien – Méridien Santé의 연결을 보여 준다. 변호사가 필요하다. | G69: 서류 브리핑, 지분 구조 | H69: Julien, Nicolas, Manon | J69: =턴_설계!$B$5 -> 120
A70: 6 | B70: 6 | C70: 미드포인트 | D70: Un même nom | E70: 같은 이름 | F70: Nicolas의 퇴거, Camille의 외주, Julien의 감사, Léa의 구조조정이 모두 Groupe Méridien이었다. 각자 «mon client / mon contrat / mon rapport / mon plan.» | G70: 책임 표현, 접속법 | H70: Nicolas, Camille, Julien, Léa | I70: E1 | J70: =턴_설계!$B$5 -> 120
A71: 6 | B71: 7 | C71: 위기 | D71: Reproches | E71: 서로에 대한 비난 | F71: 공모라고 서로를 몰아세운다. Nicolas가 나가 버리고 Camille가 막아선다. | G71: 다툼, 비난·사과 | H71: Nicolas, Camille, Julien, Léa, Manon | J71: =턴_설계!$B$5 -> 120
A72: 6 | B72: 8 | C72: 위기 | D72: Heure zéro | E72: 영시 | F72: 퇴거 집행 날 새벽. 서로의 전문성을 처음 합친다: Nicolas는 긴급 가처분(référé), Julien은 서류, Léa는 동선, Camille는 취약성 진단서. Voltaire가 기사를 쓰고 Curie가 서류가 있는 곳을 알려 준다. | G72: 긴급 가처분(référé), 유예 기간, 진단서 | H72: Nicolas, Camille, Julien, Léa, Voltaire, Curie, Jeanne | I72: E1·S2 | J72: =턴_설계!$B$5 -> 120
A73: 6 | B73: 9 | C73: 위기 | D73: La première suspension | E73: 첫 정지 | F73: 판사가 집행을 정지한다. Hugo의 서툰 첫 연설이 군중을 울리고 Sartre가 아이들에게 말을 건다. Fatima 가족이 인사한다. | G73: 안도·감사 표현 | H73: Nicolas, Camille, Julien, Léa, Hugo, Sartre, Manon, Fatima(가상) | I73: S2·E1 | J73: =턴_설계!$B$5 -> 120
A74: 6 | B74: 10 | C74: 절정 | D74: Un local à Belleville | E74: 벨빌의 가게 | F74: 사무실 자리를 찾는다. 소규모 집주인이 월세를 낮춰 주고 Monique의 새 비스트로가 1층에 들어선다. Philippe가 계좌 도움을 자청한다. | G74: 상가 임대 협상, 소규모 임대인 | H74: Nicolas, Camille, Julien, Léa, Monique, Philippe | I74: E1 | J74: =턴_설계!$B$5 -> 120
A75: 6 | B75: 11 | C75: 절정 | D75: Les règles de la table | E75: 식탁의 규칙 | F75: 규칙을 정한다: 가난한 사람에게는 수임료 없음, 금요일마다 한 명씩 과거를 이야기함. Manon이 «Je peux rester ?» Napoléon은 '아무도 청하지 않은 참모'를 자처한다. | G75: 규칙, 약속 표현 | H75: 전원 | I75: S1 | J75: =턴_설계!$B$5 -> 120
A76: 6 | B76: 12 | C76: 결말·훅 | D76: L'Enseigne | E76: 간판 | F76: 간판이 걸린다. Monique가 «Demain, à cinq heures.» 원이 닫히며 1부 1화로 이어진다. | G76: 시간 표현, 마무리 | H76: 전원 | J76: =턴_설계!$B$5 -> 120
A77: 7 | B77: 1 | C77: 발단 | D77: Un an après | E77: 1년 후 | F77: 사무소가 커졌다. Monique가 팀 이름을 호명하며 역할을 소개한다: Jeanne 로지스틱스, Curie 출처, Voltaire 공론화, Sartre 되묻기, Karim 현장, Hugo 글, Philippe 자금, 그리고 새로 합류한 Olympe 권리 전략. | G77: 역할·업무 분담 | H77: 전원 | J77: =턴_설계!$B$5 -> 120
A78: 7 | B78: 2 | C78: 발단 | D78: La queue dans l'escalier | E78: 계단 위의 줄 | F78: 의뢰인 줄이 계단까지 이어진다. 접수·분류 체계를 세우고 Léa의 매트릭스가 처음으로 쓸모 있어진다. | G78: 접수·분류, 순서 | H78: Léa, Manon, Jeanne, Monique | I78: S1·E1 | J78: =턴_설계!$B$5 -> 120
A79: 7 | B79: 3 | C79: 발단 | D79: Classée sans suite | E79: 불기소 처분 | F79: 성폭력 피해자 사건. 고소가 '증거 불충분'으로 불기소(classement sans suite)되자 Olympe와 Nicolas가 검찰총장 이의와 사소 고소(plainte avec constitution de partie civile)로 피해자를 돕는다. 형법상 강간 정의에 '비동의'를 넣은 개정의 적용을 두고 사무실 안에서도 의견이 갈린다. | G79: 불기소와 이의(형사소송법 제40-1조), 사소 고소, 동의(consentement) 개념 | H79: Olympe, Nicolas, Sartre, Julien, Voltaire | I79: N4 | J79: =턴_설계!$B$5 -> 120
A80: 7 | B80: 4 | C80: 전개 | D80: Sans papiers | E80: 서류 없는 사람들 | F80: Rachid가 예외적 체류 허가(admission exceptionnelle au séjour)와 노동 서류 문제를 들고 온다. Karim은 노동, Camille는 의료 접근을 이야기하고 수용의 한계를 두고 의견이 갈린다. | G80: 체류증(titre de séjour), 인력난 직종, 예외적 체류 허가 | H80: Nicolas, Karim, Camille, Rachid(가상) | I80: S2 | J80: =턴_설계!$B$5 -> 120
A81: 7 | B81: 5 | C81: 전개 | D81: Le signalement de Philippe | E81: Philippe의 제보 | F81: 전 은행 지점장이 내부 자료를 들고 나온다. 내부고발자 보호법과 신고 채널, 권리보호관(Défenseur des droits)의 역할을 검토한다. | G81: 내부고발자 보호(Sapin II법·2022년 개정), 신고 채널 | H81: Philippe, Nicolas, Julien, Voltaire | I81: P3 | J81: =턴_설계!$B$5 -> 120
A82: 7 | B82: 6 | C82: 미드포인트 | D82: Le Dossier | E82: 사건 파일 | F82: Julien·Philippe의 자금 경로 + Curie의 공개 출처 + Camille의 사망 사례. Nicolas가 인가받은 반부패 단체를 통해 사소 고소장을 쓴다. | G82: 사소 고소, 인가 반부패 단체(형사소송법 제2-23조), 국가금융검찰(PNF) | H82: Nicolas, Julien, Philippe, Curie, Camille | I82: P3 | J82: =턴_설계!$B$5 -> 120
A83: 7 | B83: 7 | C83: 위기 | D83: Représailles | E83: 보복 | F83: 명예훼손 소송(procédure-bâillon)이 Voltaire에게, 위생 점검이 Monique의 비스트로에 날아온다. 익명의 협박이 이어진다. | G83: 명예훼손(1881년 언론자유법), 전략적 봉쇄 소송, 보복 | H83: Voltaire, Monique, Nicolas, Jeanne | I83: P3 | J83: =턴_설계!$B$5 -> 120
A84: 7 | B84: 8 | C84: 위기 | D84: Le micro dans la lampe | E84: 전등 속 마이크 | F84: Curie가 전파 측정기로 도청기를 찾아낸다. 도청기로 되갚자는 Curie와 합법 경로만 쓰자는 Nicolas가 충돌한다. | G84: 사생활 침해(형법 제226-1조), 증거의 적법성, 통신 비밀 | H84: Curie, Nicolas, Jeanne, Sartre | I84: P3 | J84: =턴_설계!$B$5 -> 120
A85: 7 | B85: 9 | C85: 위기 | D85: La garde du quartier | E85: 동네의 보초 | F85: 사무소 앞에 이웃들이 교대로 서서 지킨다. Karim이 조직하고 Hugo가 벽에 문구를 쓴다. | G85: 연대·조직 표현 | H85: Karim, Hugo, Monique, Jeanne | J85: =턴_설계!$B$5 -> 120
A86: 7 | B86: 10 | C86: 절정 | D86: L'Ordonnance | E86: 예심판사의 결정 | F86: 파리 금융 전담 예심판사가 수사를 개시하고 GM 임원 세 명을 피의자로 입건(mise en examen)한다. 사무실이 환호한다. | G86: 예심(instruction), 입건(mise en examen), 출석 | H86: Nicolas, Julien, Voltaire, Philippe | I86: P3 | J86: =턴_설계!$B$5 -> 120
A87: 7 | B87: 11 | C87: 절정 | D87: La loi qui vient | E87: 다가오는 법 | F87: GM과 가까운 의원들이 반부패 단체의 인가와 사소 고소권을 제한하는 법안을 낸다. Napoléon: «Les jugements se gagnent ; les lois s'écrivent. Moi, j'ai écrit un Code.» | G87: 의원 발의 법안(proposition de loi), 단체 인가 제한 | H87: Napoléon, Nicolas, Léa, Karim | I87: P1·P3 | J87: =턴_설계!$B$5 -> 120
A88: 7 | B88: 12 | C88: 결말·훅 | D88: Une chaise à République | E88: 레퓌블리크 광장의 의자 | F88: Karim이 레퓌블리크 광장에서 모이자고 제안한다. Monique가 식탁의 의자를 든다. Nicolas가 «Il faut changer la loi.» | G88: 결단, 제안 | H88: 전원 | I88: P1 | J88: =턴_설계!$B$5 -> 120
A89: 8 | B89: 1 | C89: 발단 | D89: L'assemblée à République | E89: 레퓌블리크 광장의 집회 | F89: 사무소를 거쳐 간 의뢰인 수백 명이 레퓌블리크 광장에 모인다. Karim과 Jeanne이 조직하고, 시위 사전 신고를 두고 Nicolas와 Jeanne이 실랑이. | G89: 시위는 파리 경찰청(Préfecture de police)에 사전 신고(국내안전법전 L.211-1조 이하) | H89: Karim, Jeanne, Nicolas | I89: E1·S2 | J89: =턴_설계!$B$5 -> 120
A90: 8 | B90: 2 | C90: 발단 | D90: De l'affaire à la loi | E90: 사건에서 법으로 | F90: Nicolas가 수십 건의 사건에서 같은 조항이 반복되는 것을 짚는다. 법을 바꿔야 한다. | G90: 법을 바꾸는 길: 정부 법안(projet de loi), 의원 법안(proposition de loi), 시민청원, 공동발의 국민투표(RIP) | H90: Nicolas, Manon | J90: =턴_설계!$B$5 -> 120
A91: 8 | B91: 3 | C91: 발단 | D91: Cinq cent mille signatures | E91: 50만 서명 | F91: 하원 전자 청원 서명 운동. Monique의 비스트로가 노인들의 온라인 서명(FranceConnect 로그인)을 돕는 접수처가 된다. | G91: 하원 청원: 50만 명 이상이면 본회의 토론 가능 (하원 의사규칙 제148조, 확인) | H91: Monique, Karim, Manon | I91: S1·S2 | J91: =턴_설계!$B$5 -> 120
A92: 8 | B92: 4 | C92: 전환점 | D92: Un débat sans vote | E92: 표결 없는 토론 | F92: 청원이 50만을 넘어 본회의 토론이 열리지만, 표결도 법 개정도 없이 끝난다. 방청석의 시민들. | G92: 의장단 회의(Conférence des présidents), 청원은 입법권이 아니다 | H92: Nicolas, Voltaire | J92: =턴_설계!$B$5 -> 120
A93: 8 | B93: 5 | C93: 미드포인트 | D93: Naissance d'un parti | E93: 정당의 탄생 | F93: 이름을 정한다: «Maison Commune» — Monique의 식탁에서 나온 이름. 창립 정관에 서명하고 정치자금 수탁 단체를 세운다. | G93: 정당은 1901년 결사법상 단체로 설립, 정치자금 수탁자(mandataire financier)·CNCCFP 승인 (1988년 정치자금투명성법) | H93: Monique, Hugo, Nicolas, Olympe | J93: =턴_설계!$B$5 -> 120
A94: 8 | B94: 6 | C94: 위기 | D94: Les Statuts | E94: 정관 | F94: 당원 자격, 윤리 강령, 후보 선출 방식을 둘러싼 토론. Léa의 조직도 vs Karim의 총회. Olympe가 남녀 동수 원칙을 정관에 넣는다. | G94: 헌법 제4조(정당 활동의 자유·다원주의), 내부 민주주의는 법적 의무가 아닌 선택 | H94: Léa, Karim, Olympe | I94: P1 | J94: =턴_설계!$B$5 -> 120
A95: 8 | B95: 7 | C95: 위기 | D95: L'argent propre | E95: 깨끗한 돈 | F95: 소액 후원 원칙과 회계 공개. 은행이 계좌 개설을 미루자 Philippe가 프랑스은행의 계좌 개설권(droit au compte) 절차를 안다. | G95: 개인 후원 연 7,500유로 상한·법인 후원 금지, CNCCFP 감독, 계좌 개설권 | H95: Julien, Philippe | J95: =턴_설계!$B$5 -> 120
A96: 8 | B96: 8 | C96: 위기 | D96: Les Listes | E96: 후보 명부 | F96: Julien·Camille를 파리 시의회 명부 상위에 올린다. 남녀 교대(파리테) 명부 순서를 둘러싼 갈등. | G96: 남녀 교대 명부(2000년 파리테법), 파리 시의회 선거 방식(2025년 개정, 확인) | H96: Julien, Camille, Manon, Olympe | I96: N4·S1 | J96: =턴_설계!$B$5 -> 120
A97: 8 | B97: 9 | C97: 위기 | D97: La campagne dans les quartiers | E97: 골목길 캠페인 | F97: Monique의 비스트로에서 시작해 Belleville·Ménilmontant 골목을 도는 유세. Hugo의 첫 연설 문구. | G97: 공식 선거운동 기간, 선거비용 계정(compte de campagne) | H97: Hugo, Monique, Jeanne | I97: E1·E2·S2 | J97: =턴_설계!$B$5 -> 120
A98: 8 | B98: 10 | C98: 절정 | D98: L'attaque de la presse | E98: 언론의 공격 | F98: 왜곡 기사가 나온다. Voltaire가 반박하고 반론권을 행사한다. | G98: 반론권(droit de réponse, 1881년 법 제13조), 선거 중 허위정보 금지 가처분(2018년 법) | H98: Voltaire, Nicolas | J98: =턴_설계!$B$5 -> 120
A99: 8 | B99: 11 | C99: 절정 | D99: La veille du scrutin | E99: 투표 전날 | F99: 선거 전날, 마지막 유세의 유혹을 접고 침묵. Sartre의 되묻기가 처음으로 위로가 된다. | G99: 선거 전날·당일 선거운동 금지(réserve électorale), 여론조사 공표 금지 | H99: Sartre, Léa | J99: =턴_설계!$B$5 -> 120
A100: 8 | B100: 12 | C100: 결말·훅 | D100: La nuit des urnes | E100: 개표의 밤 | F100: 파리 시의회 163석 중 12석 (가상 수치). 시장 선출은 다른 당의 몫. | G100: 2회 투표 명부제, 결선 진출 10%·연합 5% 문턱, 다수파 보너스 | H100: 전원 | J100: =턴_설계!$B$5 -> 120
A101: 9 | B101: 1 | C101: 발단 | D101: L'installation du Conseil | E101: 시의회 개원 | F101: 선거 후 첫 회의에서 파리 시장을 뽑는다. Maison Commune은 Julien에게 투표하지만 3차 투표에서 상대다수로 다른 당 후보가 선출된다. | G101: 시장 선출: 1·2차 절대다수, 3차 상대다수 (지방자치법전 L.2122-7조) | H101: Julien, Nicolas | J101: =턴_설계!$B$5 -> 120
...

Sheet 복선_회수
A1: 복선 설치와 회수 (Setup → Payoff)
A2: 설치 부와 회수 부의 간격(부 수)은 수식으로 계산됩니다. 간격이 클수록 오래 기다린 복선이라 낭독 시 기억에 남습니다.
A4: No | B4: 복선(설치) | C4: 유형 | D4: 설치 부 | E4: 설치 위치 | F4: 회수 부 | G4: 간격(부) | H4: 회수 위치와 효과 | I4: 관련 인물
A5: 1 | B5: Napoléon의 «Cet hiver sera mon dernier» 반복 | C5: 대사 | D5: 1 | E5: 1부 1화 | F5: 11 | G5: =F5-D5 -> 10 | H5: 11부 12화 — 양치기 소년 개그가 진짜 죽음이 되는 낙차 | I5: Napoléon
A6: 2 | B6: Napoléon이 Manon에게 이각모(bicorne)를 물려준다고 말한다 | C6: 소품 | D6: 1 | E6: 1부 1화 | F6: 13 | G6: =F6-D6 -> 12 | H6: 13부 2화 — 유언장에서 이각모가 진짜 유산으로 돌아옴 | I6: Napoléon, Manon
A7: 3 | B7: Napoléon의 복통·식사 거름 | C7: 설정 | D7: 3 | E7: 3부 1·5화 | F7: 11 | G7: =F7-D7 -> 8 | H7: 11부 6~12화 — Camille가 진단을 알고도 침묵한 이유가 드러남 | I7: Camille, Napoléon
A8: 4 | B8: Napoléon의 최고 칭찬 «Pas mal.» | C8: 대사 | D8: 1 | E8: 1부 7화(Hugo에게 1회) | F8: 11 | G8: =F8-D8 -> 10 | H8: 11부 12화 — Manon에게 처음이자 마지막 칭찬, 브뤼셀 승리 직후라 더 무겁다 | I8: Napoléon, Manon
A9: 5 | B9: Manon의 1차 폭발 | C9: 사건 | D9: 1 | E9: 1부 6화 | F9: 9 | G9: =F9-D9 -> 8 | H9: 9부 6화 — 몰라서 화내던 Manon → 알아서 화내는 Manon | I9: Manon
A10: 6 | B10: Manon의 vous (Napoléon에게) | C10: 호칭 | D10: 1 | E10: 1부 1화 | F10: 12 | G10: =F10-D10 -> 11 | H10: 12부 1화 — 추도사에서 처음 tu — 호칭 전환이 곧 애도 | I10: Manon, Napoléon
A11: 7 | B11: Curie의 카드 #1과 «Cherche toi-même.» | C11: 대사 | D11: 1 | E11: 1부 2화 | F11: 13 | G11: =F11-D11 -> 12 | H11: 13부 10화 — 끝까지 결론을 말하지 않던 그녀가 처음 답을 말함 | I11: Curie, Manon
A12: 8 | B12: Nicolas의 '리노베이션 해지' 조항 | C12: 사건 | D12: 2 | E12: 2부 6화 | F12: 11 | G12: =F12-D12 -> 9 | H12: 11부 3화 — 자기가 만든 조항을 국정에서 폐지 | I12: Nicolas
A13: 9 | B13: Julien의 «Ça ne colle pas» | C13: 대사 | D13: 2 | E13: 2부 4화 | F13: 4 | G13: =F13-D13 -> 2 | H13: 4부 4화 — 감사인의 눈이 처음 이상을 발견한 순간의 원점 | I13: Julien
A14: 10 | B14: Julien의 복사본 USB | C14: 소품 | D14: 4 | E14: 4부 10화 | F14: 7 | G14: =F14-D14 -> 3 | H14: 7부 5~6화 — 서명의 죄가 고소의 증거로 바뀜 | I14: Julien, Nicolas
A15: 11 | B15: Julien의 «다시는 서명하지 않는다» | C15: 인물 | D15: 4 | E15: 4부 11화 | F15: 11 | G15: =F15-D15 -> 7 | H15: 11부 10화 — 브뤼셀에서 «Je ne signe que ce que j'ai vérifié» — 숫자 서명의 회수 | I15: Julien
A16: 12 | B16: Léa의 C47 셀 | C16: 소품 | D16: 5 | E16: 5부 6화 | F16: 11 | G16: =F16-D16 -> 6 | H16: 11부 6화 — 사람을 지우던 셀이 해고 없는 통합 모델로 | I16: Léa
... A32: 28 | B32: Voltaire의 «Il me faut deux sources.» | C32: 대사 | D32: 1 | E32: 1부 11화 | F32: 9 | G32: =F32-D32 -> 8 | H32: 9부 8화 — 폭로 기사에서 두 개의 출처를 갖추는 장면 | I32: Voltaire, Curie
B34: 평균 간격(부) | G34: =AVERAGE(G5:G32) -> 7.3928571
B35: 가장 긴 복선(부) | G35: =MAX(G5:G32) -> 12
B36: 복선 개수 | G36: =COUNTA(B5:B32) -> 28

Sheet 현안_배치
A1: 프랑스 현안 18개 배치표
A2: 현재 프랑스의 쟁점을 이야기 곳곳에 녹이는 계획. 현실의 정당·정치인·참사 희생자는 특정하지 않고 가상 설정으로 각색하며, 제도와 통계만 현실 기준으로 쓴다.
A4: ID | B4: 분야 | C4: 현안 | D4: 프랑스어 키워드 | E4: 이야기 속 가상 설정 | F4: 주요 배치 (전용 화) | G4: 곁가지 배치 | H4: 주요 인물 | I4: 권한 소재 | J4: 관련 제도·법 | K4: 낭독 어휘 | L4: 균형·민감도 유의 | M4: 현실 기준값·확인
A5: P1 | B5: 정치 | C5: 상대다수 의회와 정부 불안정 | D5: Assemblée fracturée, majorité relative, 49.3, motion de censure, coalition | E5: 2024년 조기 총선 이후처럼 어떤 진영도 과반이 없는 하원. 법안마다 협상 비용이 들고 불신임안이 상시 위협이다. Maison Commune 정부도 표결마다 다른 파트너를 찾아야 한다. | F5: 9부 5화 불편한 동맹, 10부 9~12화 해산·총선·불신임안, 12부 7화 두 번째 불신임안 | G5: 8부 6화(왜 새 정당인가: 정치 피로), 7부 12화, 11부 1화 | H5: Léa, Nicolas, Karim, Olympe | I5: 하원·파리 시의회 | J5: 헌법 제8·12·49조, 정당 간 협약 | K5: majorité relative, censure, compromis, blocage, 49.3 | L5: 특정 실존 정당·인물을 비난하는 대사 금지. 가상 정당(UCN·PPS·FS·AE·CT)으로만. | M5: 현실: 2024년 이후 하원은 3개 진영으로 분열, 2025년 9월 정부 신임 부결 뒤 Lecornu 정부(2026-09 확인). 이야기에는 쓰지 않음
A6: P2 | B6: 정치 | C6: 지역 자치 갈등(코르시카·누벨칼레도니) | D6: autonomie, Corse, Nouvelle-Calédonie, révision constitutionnelle | E6: 지역 정당 연합 CT가 지지의 대가로 코르시카 자치 개헌 협상 재개와 해외영토 협정 이행을 요구한다. 총리 인선과 첫 불신임안이 여기에 걸린다. | F6: 10부 11화 마티뇽 협상 | G6: 10부 3화(TV 토론 공격), 12부 7화(두 번째 불신임안에서 CT의 기권) | H6: Nicolas, Olympe, Karim, Léa | I6: 의회(개헌은 양원 동일 문안 + 양원합동회의 3/5 또는 국민투표), 헌법재판소 | J6: 헌법 제72·74·89조, 누벨칼레도니 관련 헌법 제13장 | K6: autonomie, unité de la République, statut, référendum | L6: 가장 민감. 찬성·반대 논거를 각 인물이 나눠 말하게 하고 결론은 열어 둔다(Nicolas는 공화국 불가분성 우려, Karim은 지역 형평, Léa는 현실 협상). | M6: 코르시카 자치 개헌안·누벨칼레도니 합의(2025) 진행 상황은 반영 전 확인
A7: P3 | B7: 정치 | C7: 사법부 독립과 정치적 대립 | D7: indépendance du parquet, CSM, PNF, attaques contre les juges, agrément anticorruption | E7: 검찰 인사 개혁은 개헌 교착으로 멈추고, 정치인 판결 뒤 판사를 향한 공격이 이어진다. 반부패 단체의 인가가 흔들리며 사무소의 고소가 표류한다. | F7: 7부(고소·예심·보복), 9부 9화 고소장 | G7: 2부 8화(재판), 3부(징계), 4부 7화, 10부 11화(협상 조건), 12부 7화(교착) | H7: Nicolas, Voltaire, Curie | I7: 사법부·최고사법관회의(CSM)·의회 | J7: 헌법 제64·65조, 형사소송법 제2-23조 | K7: indépendance, parquet, agrément, instruction, délais | L7: 여야 모두가 사법부를 압박한다는 비판을 각각 담는다. 실제 재판 결과를 단정하지 않는다. | M7: 검찰 독립 개헌·반부패 단체 인가 소송 최신 상황 확인
A8: E1 | B8: 경제 | C8: 주거난·임대료 상한·단기 관광 임대 | D8: logement, encadrement des loyers, meublé de tourisme, zone tendue, expulsion | E8: 월세가 임금보다 빨리 오르고 관광 단기임대가 동네를 비운다. 소규모 임대인의 입장(Monique의 친구)도 대사에 넣는다. | F8: 2부 6화(조항 설계), 6부 1·3·8·10화(Saint-Denis), 9부 6화(주거 보조 삭감·단기임대 조항), 11부 2·3화 | G8: 1부 1·2화(Fatima), 8부 1·9화, 13부 | H8: Monique, Manon, Julien, Nicolas | I8: 국가(임대차법·세제), 파리시(임대료 상한 신청·용도변경), 메트로폴 | J8: 1989년 임대차법, ELAN법(2018) 임대료 상한, 2024년 단기임대법(르뫼르법) | K8: meublé de tourisme, encadrement, petit propriétaire, trêve hivernale | L8: 임차인만 피해자로 그리지 않는다. 소규모 임대인·대형 보유자를 구분해서 말한다. | M8: 단기임대 규제 세부(연간 일수 상한 등)는 확인
A9: E2 | B9: 경제 | C9: 탈산업화와 영세 기업 구조 | D9: désindustrialisation, TPE, PME, productivité, réindustrialisation | E9: Léa가 컨설팅한 규모의 경제 없는 영세 제조업체들: 해고 없이 살릴 길을 못 찾았던 과거. 11부에서 영세 기업 통합·연구개발 전환 사업을 설계한다. | F9: 5부 3화 Garnier 공방 | G9: 8부 9화(골목 상권), 11부 6화, 13부 7화 | H9: Léa, Monique, Karim | I9: 국가·레지옹(경제 개발) | J9: 연구세액공제(CIR), 경제적 해고(PSE) | K9: productivité, scaler, consolidation, R&D | L9: '영세 기업이 문제'라는 식의 낙인 대신 구조 문제로 설명한다. | M9: 통계 수치는 반영 전 확인
A10: E3 | B10: 경제 | C10: 국가 부채·재정적자·연금 | D10: dette publique, déficit, procédure de déficit excessif, retraites | E10: 적자를 줄이라는 EU 절차와 연금·보건·국방 지출 증가 사이의 줄타기. Julien이 숫자로 설명하고 Manon이 되묻는다. | F10: 11부 10화(EU 재정규칙), 12부 11~12화(예산안) | G10: 10부 6화(결선 토론), 12부 3·9화, 13부 7화 | H10: Julien, Napoléon(메모), Philippe | I10: 국가·EU | J10: 헌법 제47조·LOLF, TFUE 제126조, 2023년 연금 개혁 | K10: dette, déficit, trajectoire, soutenabilité | L10: 긴축 vs 확대 양쪽 논거를 모두 숫자로 제시한다. | M10: 부채 GDP 대비 117.5% (2026년 1분기 말, INSEE). 2분기 수치는 2026-09-29 발표 예정
A11: S1 | B11: 사회 | C11: 청년 고용 불안 | D11: stage, CDD, intérim, apprentissage, précarité | E11: 기간제·인턴과 저임금으로 청년의 자립이 늦어진다. Manon이 그 당사자이자 질문자다. | F11: 1부 3~6화, 11부 6화, 13부 5·6화 | G11: 5부(Léa의 인력 감축), 6부, 7부, 8부, 10부 3화 | H11: Manon, Karim, Léa | I11: 국가(노동법)·사회적 대화 | J11: 노동법전, 인턴 수당(gratification), 견습 지원 | K11: stagiaire, contrat, SMIC, précarité | L11: 청년 vs 기성세대 구도로 몰지 않는다(Karim도 Napoléon도 청년의 편에서 돕는다). | M11: 15~24세 실업률 21.6%(2026 2분기), 전체 8.3%, 약 2.6배 (INSEE, 2026-09 확인)
A12: S2 | B12: 사회 | C12: 이민·난민과 수용 분담 | D12: titre de séjour, MNA, AME, asile, campement | E12: Belleville는 다국적 동네다. 서류 없는 이웃, 체류 자격 사건, 파리 북부 텐트촌과 보호자 없는 미성년 이주민을 둘러싼 도(département) 간 떠넘기기. | F12: 1부 7~8화(AME), 6부 8·9화, 7부 4화(체류 자격), 11부 5화 분담 | G12: 3부 6화(서류 없는 환자), 8부(투표권 없는 이웃), 10부 3화 | H12: Monique, Camille, Nicolas, Karim, Sartre | I12: 국가(체류·망명), 도(아동 보호 ASE) | J12: CESEDA, 2024년 이민법, EU 이민·망명 협약(2026 시행) | K12: titre de séjour, régularisation, mineur non accompagné, demande d'asile | L12: 반이민 여론(FS)과 수용 부담 지역의 실제 어려움을 함께 담고, 이주민을 배경이 아닌 화자로 세운다. | M12: 예외적 체류 허가 지침·EU 협약 시행 상태 확인
A13: S3 | B13: 사회 | C13: 고령화·농촌 공동화·의료 사막 | D13: désert médical, diagonale du vide, vieillissement, fermeture de services | E13: 시립 보건센터가 문을 닫고 파리 북동부·센생드니가 의료 사막이 된다(9부). Jeanne의 고향 근처 마을은 학교도 병원도 문을 닫았고, 추천서 순회가 그곳을 지나며 의료·일자리·연금 문제가 되풀이된다(10부). | F13: 9부 7화 시의회에서의 보건 | G13: 3부(응급실 고령 환자), 10부 2화(농촌 순회), 11부 4화, 13부 | H13: Jeanne, Camille, Manon | I13: 국가(ARS)·도·코뮌 | J13: 공중보건법전, 의사 배치 규제 논쟁 | K13: désert médical, vieillissement, maison de santé | L13: '시골'을 동정하지 않고 마을 사람들이 직접 말하게 한다. | M13: 인구·의사 밀도 통계는 반영 전 확인
A14: S4 | B14: 사회 | C14: 폭염·가뭄과 에너지 전환 부담 | D14: canicule, sécheresse, restrictions d'eau, transition énergétique | E14: 폭염에 응급실이 넘치고(3부), 저수지가 마른 마을을 지나며(10부), 초고액 자산 최저세 재원을 전환 비용에 쓸지 논쟁한다(11부). | F14: 3부 3·10화(폭염 응급실) | G14: 10부 2화, 11부 4·8화, 12부 8화 | H14: Camille, Jeanne, Julien | I14: 국가·도·유역기관 | J14: 폭염 경보 계획, 물 사용 제한 도지사 명령 | K14: canicule, sécheresse, Météo-France, transition énergétique | L14: 기후를 정치적 구호로 쓰지 않고 현장 사건으로 보여 준다. | M14: 최신 폭염·가뭄 통계 확인
A15: N1 | B15: 재난 | C15: 지중해성 폭우·급류와 방재 체계 | D15: épisode méditerranéen, crue éclair, vigilance rouge, FR-Alert, catastrophe naturelle | E15: 남부 해안 지방을 가상의 폭우와 급류가 덮친다. 경보·대피 명령을 둘러싼 도지사–시장 책임 공방, 자연재해 지정, 민방위 군부대 투입, 복구와 보험 보상. | F15: 12부 8화 L'Épisode méditerranéen | G15: 13부(복구 결산) | H15: Jeanne, Camille, Nicolas, Voltaire, Hugo | I15: 국가(도지사 ORSEC), 코뮌(시 보호계획), EU | J15: 국내안전법전, 자연재해 보상제도(CatNat), EU 연대기금 | K15: vigilance rouge, évacuation, sinistrés, catastrophe naturelle | L15: 실제 참사와 희생자를 연상시키므로 추모의 톤을 지키고, 특정 정치인 비난 없이 제도의 공백을 보여 준다. | M15: 실제 재난의 후속 조치·소송은 반영 전 확인
... A22: N8 | B22: 사회 | C22: 청년 정신건강 위기 | D22: santé mentale, anxiété, liste d'attente, Mon soutien psy, CMP | E22: 청년 정신건강 상담 대기가 몇 달씩 밀린다. Sartre가 카페의 청년들과, Manon이 자신의 불안을 처음 인정하며, Camille가 제도로 함께 부딪힌다. | F22: 12부 6화 Les Listes d'attente | G22: 1부(Manon의 폭발과 연결 가능, 곁가지) | H22: Sartre, Manon, Camille | I22: 국가(건강보험)·ARS | J22: 공공 심리상담 지원(Mon soutien psy), 의료심리센터(CMP) | K22: santé mentale, anxiété, psychologue, liste d'attente | L22: 청년 정신건강을 극적 소재로만 소비하지 않는다. 낙인 없이, 도움을 구하는 것이 자연스럽다는 톤으로. | M22: 정신건강은 2025년 '국가적 대의(grande cause nationale)'. 최신 통계 확인
A24: 현실 기준값 (확인일 2026-09-25)
A25: No | B25: 구분 | C25: 항목 | D25: 값 | E25: 출처·비고
A26: 1 | B26: 경제 | C26: 정부 부채 / GDP | D26: 117.5% (2026년 1분기 말) | E26: INSEE, 분기 부채 통계. 2분기 수치는 2026-09-29 발표 예정.
A27: 2 | B27: 사회 | C27: 15~24세 실업률 | D27: 21.6% (2026 2분기), 전체 8.3% | E27: INSEE 고용조사. 청년 실업은 전체의 약 2.6배.
A28: 3 | B28: 정치 | C28: 현 정부 형태 | D28: 과반 없는 하원(3개 진영) + 소수 정부 | E28: 이야기에는 실존 정당·인물을 쓰지 않는다. 표현은 '여소야대'가 아니라 '상대다수 정부'.
A29: 4 | B29: 확인 필요 | C29: 변동이 잦은 항목 | D29: 코르시카 자치 개헌, 누벨칼레도니 합의, 연금 개혁 유예, NATO 목표, EU 이민 협약 시행 | E29: 교재에 넣기 직전 최신 상태를 확인한다.

Sheet 현안_분포
A1: 현안 분포표 (부 × 현안)
A2: ● = 그 화의 주된 사건(전용 화), ○ = 곁가지(대사·서브플롯). 기호를 바꾸면 아래 집계가 자동 갱신됩니다.
A4: ID | B4: 현안 | C4: 1부 | D4: 2부 | E4: 3부 | F4: 4부 | G4: 5부 | H4: 6부 | I4: 7부 | J4: 8부 | K4: 9부 | L4: 10부 | M4: 11부 | N4: 12부 | O4: 13부 | P4: ● 수 | Q4: ○ 수
A5: P1 | B5: 상대다수 의회·정부 불안정 | I5: ○ | J5: ○ | K5: ● | L5: ● | M5: ○ | N5: ● | P5: =COUNTIF(C5:O5,"●") -> 3 | Q5: =COUNTIF(C5:O5,"○") -> 3
A6: P2 | B6: 지역 자치(코르시카·누벨칼레도니) | L6: ● | N6: ○ | P6: =COUNTIF(C6:O6,"●") -> 1 | Q6: =COUNTIF(C6:O6,"○") -> 1
A7: P3 | B7: 사법부 독립·정치 대립 | D7: ○ | E7: ○ | F7: ○ | I7: ● | K7: ● | L7: ○ | N7: ○ | P7: =COUNTIF(C7:O7,"●") -> 2 | Q7: =COUNTIF(C7:O7,"○") -> 5
A8: E1 | B8: 주거난·임대료 상한·단기임대 | C8: ● | D8: ● | H8: ● | J8: ○ | K8: ● | M8: ● | O8: ○ | P8: =COUNTIF(C8:O8,"●") -> 5 | Q8: =COUNTIF(C8:O8,"○") -> 2
A9: E2 | B9: 탈산업화·영세 기업 | G9: ● | J9: ○ | M9: ○ | O9: ○ | P9: =COUNTIF(C9:O9,"●") -> 1 | Q9: =COUNTIF(C9:O9,"○") -> 3
A10: E3 | B10: 부채·재정적자·연금 | L10: ○ | M10: ● | N10: ● | O10: ○ | P10: =COUNTIF(C10:O10,"●") -> 2 | Q10: =COUNTIF(C10:O10,"○") -> 2
A11: S1 | B11: 청년 고용 불안 | C11: ● | G11: ○ | H11: ○ | I11: ○ | J11: ○ | L11: ○ | M11: ● | O11: ● | P11: =COUNTIF(C11:O11,"●") -> 3 | Q11: =COUNTIF(C11:O11,"○") -> 5
A12: S2 | B12: 이민·난민·수용 분담 | C12: ● | E12: ○ | H12: ● | I12: ● | J12: ○ | L12: ○ | M12: ● | P12: =COUNTIF(C12:O12,"●") -> 4 | Q12: =COUNTIF(C12:O12,"○") -> 3
A13: S3 | B13: 고령화·농촌 공동화·의료 사막 | E13: ○ | K13: ● | L13: ○ | M13: ○ | O13: ○ | P13: =COUNTIF(C13:O13,"●") -> 1 | Q13: =COUNTIF(C13:O13,"○") -> 4
A14: S4 | B14: 폭염·가뭄·에너지 전환 | E14: ● | L14: ○ | M14: ○ | N14: ○ | P14: =COUNTIF(C14:O14,"●") -> 1 | Q14: =COUNTIF(C14:O14,"○") -> 3
A15: N1 | B15: 지중해성 폭우·방재 | N15: ● | O15: ○ | P15: =COUNTIF(C15:O15,"●") -> 1 | Q15: =COUNTIF(C15:O15,"○") -> 1
A16: N2 | B16: EU 회복기금 집행 | K16: ● | M16: ○ | O16: ○ | P16: =COUNTIF(C16:O16,"●") -> 1 | Q16: =COUNTIF(C16:O16,"○") -> 2
A17: N3 | B17: 국방비·NATO | L17: ○ | M17: ● | N17: ● | P17: =COUNTIF(C17:O17,"●") -> 2 | Q17: =COUNTIF(C17:O17,"○") -> 1
A18: N4 | B18: 성폭력·동의 개념 법 | I18: ● | J18: ○ | L18: ○ | P18: =COUNTIF(C18:O18,"●") -> 1 | Q18: =COUNTIF(C18:O18,"○") -> 2
A19: N5 | B19: 녹색 대 녹색 | L19: ● | M19: ○ | N19: ○ | O19: ○ | P19: =COUNTIF(C19:O19,"●") -> 1 | Q19: =COUNTIF(C19:O19,"○") -> 3
A20: N6 | B20: 플랫폼 노동 | G20: ○ | N20: ● | P20: =COUNTIF(C20:O20,"●") -> 1 | Q20: =COUNTIF(C20:O20,"○") -> 1
A21: N7 | B21: 정보기관 사찰 스캔들 | I21: ○ | N21: ● | P21: =COUNTIF(C21:O21,"●") -> 1 | Q21: =COUNTIF(C21:O21,"○") -> 1
A22: N8 | B22: 청년 정신건강 | C22: ○ | N22: ● | P22: =COUNTIF(C22:O22,"●") -> 1 | Q22: =COUNTIF(C22:O22,"○") -> 1
B23: 부별 ● 수 | C23: =COUNTIF(C5:C22,"●") -> 3 | D23: =COUNTIF(D5:D22,"●") -> 1 | E23: =COUNTIF(E5:E22,"●") -> 1 | F23: =COUNTIF(F5:F22,"●") -> 0 | G23: =COUNTIF(G5:G22,"●") -> 1 | H23: =COUNTIF(H5:H22,"●") -> 2 | I23: =COUNTIF(I5:I22,"●") -> 3 | J23: =COUNTIF(J5:J22,"●") -> 0 | ... O23: =COUNTIF(O5:O22,"●") -> 1 | P23: =SUM(P5:P22) -> 32
B24: 부별 ○ 수 | C24: =COUNTIF(C5:C22,"○") -> 1 | D24: =COUNTIF(D5:D22,"○") -> 1 | E24: =COUNTIF(E5:E22,"○") -> 3 | F24: =COUNTIF(F5:F22,"○") -> 1 | G24: =COUNTIF(G5:G22,"○") -> 2 | H24: =COUNTIF(H5:H22,"○") -> 1 | I24: =COUNTIF(I5:I22,"○") -> 3 | J24: =COUNTIF(J5:J22,"○") -> 6 | ... O24: =COUNTIF(O5:O22,"○") -> 7 | Q24: =SUM(Q5:Q22) -> 43
A26: 읽는 법: 1~5부는 곁가지 중심이라 B1~B2 난이도를 지키고, 9~12부에서 전용 화가 몰린다. 화당 전용 현안은 1개(+곁가지 1~2개)로 제한해 낭독 분량을 지킨다. N6~N8은 12부의 신규 현안으로 각 1개 전용 화를 받는다.
A27: 현안 ID와 설명은 '현안_배치' 시트, 화별 반영은 '화별목차_전체'의 '반영 현안' 열을 참고.

Sheet 정치제도
A1: 현실 정치 제도 기준표 (프랑스 제5공화국)
A2: 8~13부에 반영한 실제 제도. 정당·정치인은 전부 가상이며 실존 정치인의 대사는 쓰지 않는다. '검색 확인' 표시는 해당 날짜에 공개 자료로 확인한 항목.
A4: 영역 | B4: 제도·규칙 | C4: 핵심 내용 | D4: 근거 | E4: 이야기 반영 | F4: 낭독 어휘 | G4: 확인 상태
A5: 정당·선거 | B5: 정당 결성 | C5: 정당은 1901년 결사법상 단체로 자유롭게 결성한다(등록 의무 없음). 공적 보조·후원을 받으려면 정치자금 수탁 단체 또는 수탁자(mandataire financier)를 두고 CNCCFP 승인을 받아야 한다. | D5: 헌법 제4조, 1901년 7월 1일 법, 1988년 3월 11일 법(88-227) | E5: 8부 5화 | F5: association, statuts, mandataire financier, CNCCFP | G5: 기획 시점 지식 — Légifrance 확인 필요
A6: 정당·선거 | B6: 정당 내부 운영 | C6: 헌법은 정당의 자유·다원주의·남녀 동등 접근 기여만 규정하고, 내부 민주주의를 법적 의무로 두지 않는다(정관의 선택). | D6: 헌법 제4조 | E6: 8부 6화 | F6: pluralisme, adhérent, statuts | G6: 기획 시점 지식 — Légifrance 확인 필요
A7: 정당·선거 | B7: 정당 재정 | C7: 개인 후원은 1인당 연 7,500유로 상한(모든 정당 합산), 법인 후원은 금지. CNCCFP가 정당·선거 회계를 감독한다. | D7: 1988년 3월 11일 법 제11-4조 | E7: 8부 7화 | F7: don, plafond, comptes, CNCCFP | G7: 기획 시점 지식 — Légifrance 확인 필요
A8: 정당·선거 | B8: 계좌 개설권 | C8: 은행이 계좌 개설을 거부하면 프랑스은행(Banque de France)이 지정한 은행이 계좌를 열어 주어야 한다. | D8: 통화금융법전 L.312-1조 | E8: 8부 7화 | F8: droit au compte, Banque de France | G8: 기획 시점 지식 — Légifrance 확인 필요
A9: 정당·선거 | B9: 시위 사전 신고 | C9: 공공 도로 시위는 3일 전(최대 15일 전)까지 도청에 신고한다. 파리는 경찰청(Préfecture de police). | D9: 국내안전법전 L.211-1~L.211-4조 | E9: 8부 1화 | F9: déclaration préalable, manifestation, préfecture de police | G9: 기획 시점 지식 — Légifrance 확인 필요
A10: 정당·선거 | B10: 하원 시민청원 | C10: 하원 전자청원은 서명이 많으면 공개되고, 50만 명(여러 도·해외영토에 걸쳐) 이상이면 의장단 회의가 본회의 토론을 결정할 수 있다. 토론만 있고 표결·입법 효력은 없다. | D10: 하원 의사규칙 제147~148조 | E10: 8부 3~4화 | F10: pétition, Conférence des présidents, débat en séance | G10: 기획 시점 지식 — Légifrance 확인 필요
A11: 정당·선거 | B11: 공동발의 국민투표 (RIP) | C11: 의원 1/5 발의 + 유권자 1/10 지지로 국민투표를 열 수 있다. 문턱이 높아 실제 성립 사례가 없다. | D11: 헌법 제11조 | E11: 8부 2화 | F11: référendum d'initiative partagée, soutiens | G11: 기획 시점 지식 — Légifrance 확인 필요
A12: 정당·선거 | B12: 대통령 선거 | C12: 5년 임기 직선, 2회 투표. 1차에서 유효표 과반이 없으면 상위 2인이 14일 뒤 결선. 연속 2회 초과 연임 불가. | D12: 헌법 제6·7조, 1962년 11월 6일 법 | E12: 10부 | F12: élection présidentielle, premier tour, second tour, quinquennat | G12: 기획 시점 지식 — Légifrance 확인 필요
A13: 정당·선거 | B13: 추천서 (parrainages) | C13: 선출직(시장·의원 등) 500명 이상의 추천, 30개 이상의 도·해외영토에 걸쳐야 하고 한 도에서 10%를 넘을 수 없다. 헌법재판소가 받아 공개한다. | D13: 1962년 11월 6일 법 제3조 | E13: 9부 12화, 10부 1~2화 | F13: parrainage, élu, Conseil constitutionnel | G13: 기획 시점 지식 — Légifrance 확인 필요
A14: 정당·선거 | B14: 선거운동 규칙 | C14: 공식 선거운동 기간 방송 발언 시간 균등(Arcom). 투표 전날·당일 선거운동과 여론조사 공표 금지, 20시 투표 종료 전 결과 추정 공표 금지. | D14: 선거법전 L.49·L.52-2조, 1977년 7월 19일 법(여론조사) | E14: 8부 11화, 10부 3~4화 | F14: temps de parole, réserve électorale, sondage, estimation | G14: 기획 시점 지식 — Légifrance 확인 필요
A15: 정당·선거 | B15: 결과 선포와 취임 | C15: 헌법재판소가 대선의 적법성을 감시하고 결과를 선포한다. 취임식은 권한 이양식(passation de pouvoirs)이며 선서는 없다. | D15: 헌법 제58조 | E15: 10부 8화 | F15: proclamation, investiture, passation de pouvoirs | G15: 기획 시점 지식 — Légifrance 확인 필요
... A59: 사회 | B59: 플랫폼 노동 | C59: EU 플랫폼노동 지침(고용 추정·알고리즘 투명성, 2026년 12월까지 국내 이행)과 ARPE를 통한 플랫폼–노동자 대표 협상. | D59: EU 지침 2024/2831, 노동법전 L.7343-1조 이하 | E59: 12부 4화 | F59: plateforme, présomption de salariat, ARPE | G59: 기획 시점 지식 — Légifrance 확인 필요
A61: ※ 법령 번호·조항은 교재에 넣기 전에 Légifrance의 현행 텍스트(version en vigueur)로 반드시 확인하세요. '검색 확인'은 공개 자료에서 교차 확인한 항목이며, 나머지는 기획 시점 지식입니다.

Sheet 정치경로_의석
A1: 정치 경로와 가상 의석 시뮬레이션
A2: 창당에서 대통령까지의 경로를 프랑스 제5공화국 제도에 맞춰 단계화했다. 정당·득표율·의석 수는 전부 가상의 교육용 수치이며, 파란 숫자·표결 값은 수정하면 결과가 자동 갱신된다.
A4: 1. 정치 경로 (창당 → 대통령)
A5: 단계 | B5: 부·화 | C5: 이야기 사건 | D5: 제도·규칙 | E5: 확인 상태
A6: 1 | B6: 8부 1~4화 | C6: 레퓌블리크 집회 → 하원 청원 50만 서명이 표결 없는 본회의 토론으로 끝남 | D6: 시위 사전 신고, 하원 청원 50만·의장단 회의(의사규칙 제148조) | E6: 기획 지식
A7: 2 | B7: 8부 5~7화 | C7: 정당 «Maison Commune» 창당 | D7: 1901년 결사법상 단체 + 정치자금 수탁자·CNCCFP 승인(1988년 법), 개인 후원 연 7,500유로 상한 | E7: 기획 지식
A8: 3 | B8: 8부 8~12화 | C8: 파리 시의회 선거 출마, 163석 중 12석 (가상 수치) | D8: 2025년 PLM법: 시의회 별도 투표, 결선 진출 10%·연합 5%, 다수파 보너스 25%, 남녀 교대 명부 | E8: 검색 확인 (PLM법)
A9: 4 | B9: 9부 1화 | C9: 시의회 개원, 시장 선출은 다른 당의 몫 | D9: 1·2차 절대다수, 3차 상대다수 (지방자치법전 L.2122-7조) | E9: 기획 지식
A10: 5 | B10: 9부 2~11화 | C10: Julien은 예산, Camille는 보건(시립 보건센터·AP-HP 감독위원회)에서 활동. 스캔들 폭로, 사소 고소 | D10: 지방자치법전, 공공조달법전, Sapin II법, 형사소송법 제2-23조 | E10: 기획 지식
A11: 6 | B11: 9부 12화 | C11: 현직 대통령(UCN)이 연임 제한으로 불출마 → Nicolas 출마 선언, 추천서 수집 시작 | D11: 헌법 제6조(연속 2회 제한), 추천서 500장·30개 도·도별 10% 이하(1962년 법) | E11: 기획 지식
A12: 7 | B12: 10부 1~3화 | C12: 추천서 확보(농촌 시장 순회), 다자 TV 토론 | D12: 헌법재판소 추천서 접수·공개, 공식 선거운동 기간 발언 시간 균등(Arcom) | E12: 기획 지식
A13: 8 | B13: 10부 4화 | C13: 1차 투표: FS 후보 1위, Nicolas 2위로 결선 진출 (아래 A블록) | D13: 유효표 과반 없으면 상위 2인이 결선 (헌법 제7조) | E13: 기획 지식
A14: 9 | B14: 10부 5~7화 | C14: 결선까지의 2주: 지지 선언 협상, 결선 토론, 결선 승리 (A블록) | D14: 결선은 1차 14일 뒤 | E14: 기획 지식
A15: 10 | B15: 10부 8화 | C15: 헌법재판소 결과 선포, 엘리제 권한 이양식 | D15: 헌법 제58조. 프랑스 대통령은 선서하지 않는다 | E15: 기획 지식
A16: 11 | B16: 10부 9화 | C16: 하원에 의석이 없는 대통령 → 국회 해산 | D16: 헌법 제12조: 20~40일 내 총선, 총선 후 1년 내 재해산 불가 | E16: 기획 지식
A17: 12 | B17: 10부 10화 | C17: 총선: Maison Commune 198석 1당, 과반 289석에 91석 부족 (B블록) | D17: 577석 소선거구 2회 투표 | E17: 가상 수치
... A26: 21 | B26: 13부 | C26: 임기 후반, 사무소를 재단으로 전환 | D26: 각료 겸직 금지(헌법 제23조), HATVP 신고 | E26: 기획 지식
A28: 2. 가상 정당 (실존 정당·정치인 사용 금지)
A29: 약칭 | B29: 정당명 (가상) | C29: 성격 | D29: 이야기 속 역할
A30: CC | B30: Maison Commune | C30: 주인공 정당. Monique의 식탁에서 나온 이름 | D30: 시민 정당. 창당 → 파리 시의회 → 대선 승리 → 총선 1당(상대다수)
A31: UCN | B31: Union Civique Nationale | C31: 거대 보수 정당 | D31: 현직 대통령 배출(연임 제한으로 불출마), 대선 1차 3위, 총선 2당, 불신임안 주도
A32: FS | B32: France Souveraine | C32: 민족주의 성향 정당 | D32: 대선 1차 1위·결선 패배, 불신임안 찬성
A33: PPS | B33: Parti du Progrès Social | C33: 중도좌파 정당 | D33: 결선에서 Nicolas 지지 선언, 총선 후 법안별 조건부 지지
A34: AE | B34: Alliance Écologiste | C34: 환경 정당 | D34: 조건부 친여 (불신임안 불참)
A35: CT | B35: Coalition des Territoires | C35: 코르시카·해외영토 지역 정당 연합 | D35: 캐스팅보트: 10부 첫 불신임안에 찬성 → 12부 자치 협상 후 기권 (협상의 열쇠)
A37: 3-A. 대통령 선거 1차·결선 (가상, 10부 4·7화)
A38: 후보 (정당) | B38: 1차 득표율 | C38: 순위 | D38: 1차 결과 | E38: 결선 이동 비율 → Nicolas (CC) | F38: 결선 이동 비율 → FS 후보
A39: Nicolas (CC) | B39: 0.223 | C39: =RANK(B39,$B$39:$B$44) -> 2 | D39: =IF(C39<=2,"결선 진출","탈락") -> 결선 진출 | E39: 1 | F39: 0
A40: FS 후보 | B40: 0.241 | C40: =RANK(B40,$B$39:$B$44) -> 1 | D40: =IF(C40<=2,"결선 진출","탈락") -> 결선 진출 | E40: 0 | F40: 0.97
A41: UCN 후보 | B41: 0.215 | C41: =RANK(B41,$B$39:$B$44) -> 3 | D41: =IF(C41<=2,"결선 진출","탈락") -> 탈락 | E41: 0.3 | F41: 0.5
A42: PPS 후보 | B42: 0.152 | C42: =RANK(B42,$B$39:$B$44) -> 4 | D42: =IF(C42<=2,"결선 진출","탈락") -> 탈락 | E42: 0.7 | F42: 0.1
A43: AE 후보 | B43: 0.064 | C43: =RANK(B43,$B$39:$B$44) -> 6 | D43: =IF(C43<=2,"결선 진출","탈락") -> 탈락 | E43: 0.7 | F43: 0.05
A44: 기타 후보 합계 | B44: 0.105 | C44: =RANK(B44,$B$39:$B$44) -> 5 | D44: =IF(C44<=2,"결선 진출","탈락") -> 탈락 | E44: 0.25 | F44: 0.45
A45: 합계 | B45: =SUM(B39:B44) -> 1 | D45: =IF(ROUND(B45,4)=1,"100% OK","100%와 불일치") -> 100% OK
A46: 1차 당선 여부 | D46: =IF(MAX(B39:B44)>0.5,"1차 당선","결선 필요") -> 결선 필요
A47: 결선 득표 (1차 유효표 기준 환산) | E47: =SUMPRODUCT($B$39:$B$44,E39:E44) -> 0.46495 | F47: =SUMPRODUCT($B$39:$B$44,F39:F44) -> 0.40692
A48: 결선 득표율 (유효표) | E48: =E47/(E47+F47) -> 0.53327904 | F48: =F47/(E47+F47) -> 0.46672096
A49: 결선 결과 | E49: =IF(E48>0.5,"Nicolas 당선","FS 후보 당선") -> Nicolas 당선
A50: 기권·무효로 빠지는 몫 | E50: =1-E47-F47 -> 0.12813
A51: 해석: 1차는 FS 후보 24.1%, Nicolas 22.3%, UCN 21.5%로 3파전 — Nicolas는 0.8%p 차이로 결선에 오른다. 결선은 탈락 후보 지지층의 이동 비율(파란 셀, 가정값)로 환산하며, 기본값에서 Nicolas가 약 53%로 당선된다. UCN 지지층의 이동 비율이 10부 5화(결선까지의 2주) 협상의 서스펜스.
A53: 3-B. 총선 결과와 첫 불신임안 (가상, 10부 10·12화)
A54: 정당 | B54: 의석 | C54: 불신임안 표결 (찬성만 집계) | E54: 비고
A55: CC | B55: 198 | C55: —
A56: UCN | B56: 158 | C56: 찬성
A57: FS | B57: 96 | C57: 찬성
A58: PPS | B58: 71 | C58: —
A59: AE | B59: 20 | C59: —
A60: CT | B60: 34 | C60: 찬성
A61: 총 의석 | B61: =SUM(B55:B60) -> 577 | E61: =IF(B61=577,"577석 OK","577석과 불일치") -> 577석 OK
A62: 절대다수 (재적 과반) | B62: =INT(B61/2)+1 -> 289
A63: CC 과반까지 부족 의석 | B63: =MAX(B62-B55,0) -> 91
A64: 불신임안 찬성 | C64: =SUMIF(C55:C60,"찬성",$B$55:$B$60) -> 288
A65: 결과 | C65: =IF(C64>=$B$62,"가결 — 정부 총사퇴","부결 — 정부 존속") -> 부결 — 정부 존속 | E65: 찬성 ≥ 재적 과반이면 가결 (헌법 제49조 2항)
A66: 부족 표 | C66: =MAX($B$62-C64,0) -> 1
A67: 발의 필요 서명 (1/10) | C67: =ROUNDUP(B61/10,0) -> 58 | E67: =IF(B56>=C67,"UCN 단독 발의 가능","미달") -> UCN 단독 발의 가능
A68: 해석: Maison Commune은 198석으로 1당이지만 과반 289석에 91석 모자란 상대다수 정부다. 코르시카 자치 협상이 절반만 타결되자 CT가 불신임안에 찬성해 찬성은 UCN 158 + FS 96 + CT 34 = 288표 — 재적 과반 289에 딱 1표 부족해 부결된다. 불신임안은 찬성표만 세므로 반대·불참은 결과에 같은 효과를 낸다(표결 결과 낭독: 하원의장).
A70: 3-C. 두 번째 불신임안 (가상, 12부 7화 — 헌법 제49조 3항 사용 후)
A71: 정당 | B71: 의석 | C71: 불신임안 표결 (찬성만 집계) | E71: 비고
A72: CC | B72: =B55 -> 198 | C72: —
A73: UCN | B73: =B56 -> 158 | C73: 찬성
A74: FS | B74: =B57 -> 96 | C74: 찬성
A75: PPS | B75: =B58 -> 71 | C75: —
A76: AE | B76: =B59 -> 20 | C76: —
A77: CT | B77: =B60 -> 34 | C77: 기권 | E77: 코르시카 자치 협상 지속을 조건으로 기권
A78: 총 의석 | B78: =SUM(B72:B77) -> 577
A79: 절대다수 (재적 과반) | B79: =INT(B78/2)+1 -> 289
A80: 불신임안 찬성 | C80: =SUMIF(C72:C77,"찬성",$B$72:$B$77) -> 254
A81: 결과 | C81: =IF(C80>=$B$79,"가결 — 정부 총사퇴","부결 — 법안 채택") -> 부결 — 법안 채택
A82: 부족 표 | C82: =MAX($B$79-C80,0) -> 35
A83: 해석: 49조 3항으로 예산 조항을 표결 없이 통과시키자 야당이 불신임안을 내지만, CT가 기권으로 돌아서 찬성은 254표에 그친다. 불신임안이 부결되면 해당 조항은 채택된 것으로 본다. PPS가 등을 돌리면 가결도 가능하다는 긴장이 이 화의 서스펜스.
A85: 4. 이야기 속 엑스트라 화자 (전부 가상)
A86: PRÉSIDENTE DE L'ASSEMBLÉE NATIONALE(표결 결과 낭독), PRÉSIDENT DU CONSEIL CONSTITUTIONNEL(대선 결과 선포), MAIRE DE PARIS(다른 당, 가상), PRÉSIDENT SORTANT(UCN, 권한 이양식), MODÉRATRICE(TV 토론), 상대 후보들(FS·UCN, 가상), NOTAIRE(13부 유언장). 실존 정치인·정당명은 쓰지 않는다.

Sheet 호칭규칙
A1: 호칭 규칙 (tu / vous)
A2: 표준 프랑스어 기준. 스페인어의 tú/usted/vosotros/ustedes 4분 체계 대신 tu(친밀한 단수)와 vous(존칭 단수·모든 복수)의 2분 체계다. 집단에게는 누구나 vous를 쓰므로 호칭 전환의 드라마는 1:1 관계에서만 생긴다. 2~5부 프레임 장면은 1부 규칙을 따른다.
A4: 화자 → 청자 | B4: 1부 (현재) | C4: 2~5부 (각자의 과거) | D4: 6부 이후 | E4: 비고
A5: 주력 4인 상호 | B5: tu | C5: vous (만나기 전이라) | D5: tu | E5: 6부 만남을 기점으로 전환(«On se tutoie ?») — 전환 순간을 대사로 드러낼 것
A6: 주력 4인 → Manon | B6: tu | C6: tu (프레임 장면) | D6: tu
A7: Manon → 주력 4인 | B7: vous | C7: vous (프레임 장면) | D7: tu (제안) | E7: 6부에서는 이웃 사이라 tu, 인턴이 되면서(1부) vous로 바뀐다 — 1부 1화 대본에서 «À Saint-Denis, tu me tutoyais.»로 대사 설명. 이후 tu로 돌아갈 시점은 미확정
A8: Manon → Napoléon | B8: vous | C8: vous | D8: vous 유지 → 12부 1화 추도사에서 처음 tu | E8: 7부에서 Napoléon이 «Tu peux me tutoyer.»라고 허락해도 Manon은 습관 때문에 끝내 vous. 폭발 중에도 vous (예: «Vous, justement vous, ne me traitez pas de bécasse !»). 폭발 중 tu 실수 금지 — 장례식 전환의 복선.
A9: Manon → Philippe, Curie | B9: vous | C9: 해당 없음 | D9: vous (전환 시점 미정)
A10: Napoléon → Manon | B10: tu («petite», «soldat») | C10: 해당 없음 | D10: tu | E10: 처음부터 tu — 욕(bécasse)도 Manon에게만
A11: Napoléon → 여럿(집단) | B11: vous + «Messieurs, mesdames» | C11: 같음 | D11: 같음 | E11: 집단에는 누구나 vous이므로, Napoléon의 거리 두기는 호칭(«Messieurs», «Citoyens»)과 3인칭 화법으로 드러낸다. (스페인판의 ustedes 장치를 대체)
A12: Napoléon → 개인 (Manon 외) | B12: vous | C12: vous | D12: 소수에게만 tu | E12: Jeanne에게는 처음부터 tu — 옛 군인끼리
A13: Jeanne → 후배들 | B13: tu (명령조) | C13: tu / vous 혼용 | D13: 정치 무대에서는 vous
A14: Curie → 전원 | B14: tu | C14: tu | D14: tu | E14: 모두에게 tu — 그래서 더 위협적이다. «Cherche toi-même.»
A15: Monique, Karim → 전원 | B15: tu | C15: tu | D15: tu | E15: Monique는 'mon petit / ma petite'
A16: Voltaire → 취재 대상 | B16: vous (취재 시) | C16: vous | D16: 친해지면 tu
A17: 집단 대화 (사무소 안) | B17: vous (복수) | C17: vous (복수) | D17: vous (복수) | E17: 예: «Asseyez-vous, je vous apporte quelque chose.» 친한 사이여도 복수는 vous. 친밀한 집단 호칭은 «les amis», «les enfants».
A18: 공식 연설·의회 | B18: — | C18: — | D18: vous / «Mesdames et Messieurs» | E18: 8부 이후 대중 연설, 9부 이후 시의회·하원 토론
A19: 하원 (Assemblée nationale) | B19: — | C19: — | D19: «Madame la Présidente»(하원의장), «Madame la Première ministre», «Monsieur le ministre» | E19: 의원끼리는 «mon cher collègue / ma chère collègue». 대통령은 하원 토론에 나오지 않는다(양원합동회의 연설만 가능, 헌법 제18조).
A20: 시의회 (Conseil de Paris) | B20: — | C20: — | D20: «Madame la Maire / Monsieur le Maire», «Madame la conseillère» | E20: 발언은 vous, 회의 밖 동료끼리는 tu로 돌아간다
A21: 대통령 | B21: — | C21: — | D21: «Monsieur le Président» | E21: 대통령은 직접 대사를 준다(국왕 행 대체). 취임 뒤 사무소 식구들이 Nicolas를 tu로 부를지 «Monsieur le Président»으로 부를지가 13부의 작은 개그.

Sheet Manon_폭발과욕
A1: Manon의 폭발 (L'Explosion) 과 욕 배정
A2: 폭발은 총 2회. 희소성이 가치다. 폭발 뒤에는 반드시 쉬운 말로 다시 설명하는 어휘 교습 장면이 이어진다.
A4: 1. 폭발 배치 (총 2회)
A5: 회차 | B5: 위치 | C5: 성격 | D5: 단계 구성 | E5: 특기 사항
A6: 1차 폭발 | B6: 1부 6화 «Ça suffit !» (사건3 해결 화, Léa의 경영 용어가 협상을 막는 장면) | C6: 코미디 — 「몰라서 화내는 Manon」 | D6: 1단계 → 2단계 → 3단계 전부 노출 | E6: 인물별 고정 반응 패턴을 여기서 한 번에 보여 준다. Jeanne·Monique·Curie가 이 화에 함께 등장 — Karim의 욕은 9부 2차 폭발로 이관해 과밀을 피함.
A7: 2차 폭발 | B7: 9부 6화 (파리 시의회 예산 심의) | C7: 역전 — 「알아서 화내는 Manon」. 이번엔 Manon이 옳다. | D7: 1단계에서 곧바로 3단계로 (2단계 생략: '이번엔 참지 않는다') | E7: 행정 전문 용어 속에 서민 주거 보조를 깎는 조항이 숨어 있었고 Manon이 짚어 낸다. Napoléon이 선을 넘는 말을 하고 Jeanne·Monique가 나무란다.
A8: 사이 구간 | B8: 2~8부 | C8: 폭발 없음 | D8: 1단계 질문만 일상 장치로 반복 | E8: 어휘 학습의 핵심은 1단계 질문. 폭발은 정점 이벤트일 뿐.
A10: 2. 3단계 계단
A11: 단계 | B11: 대사 (FR) | C11: 한국어 | D11: 분위기 | E11: 사용
A12: 1단계 | B12: Pardon, ça veut dire quoi ? | C12: 실례지만, 그게 무슨 뜻이에요? | D12: 정중한 질문 | E12: 상시 (매 화 가능)
A13: 2단계 | B13: Vous pouvez m'expliquer comme si j'avais cinq ans ? | C13: 다섯 살한테 설명하듯 해 주실래요? | D13: 슬슬 짜증 | E13: 1차 폭발에서만
A14: 3단계 | B14: ÇA SUFFIT ! Je comprends rien ! | C14: 그만! 하나도 모르겠다고요! | D14: 폭발 | E14: 1차 · 2차(9부)
A16: 3. 폭발 직후 고정 반응 (전부 대사로 처리 — 지문 폐기)
A17: 인물 | B17: 반응 대사 (FR) | C17: 한국어 | D17: 기존 지문 (폐기) | E17: 비고
A18: Camille | B18: D'abord, respire. | C18: 우선, 숨 쉬어. | D18: — | E18: Manon: «Ne me dites pas “respire” !»로 받는다
A19: Monique | B19: Oh là. Je pose cette assiette avant qu'elle s'envole. | C19: 어이쿠. 접시 날아가기 전에 내려놔야겠네. | D19: 말없이 접시를 내려놓음 | E19: 정적의 순간을 웃음으로 대신한다
A20: Jeanne | B20: Rien à sig… Non. Je ferais mieux de me taire. | C20: 이상 없… 아니. 입 다무는 게 낫겠어. | D20: «Rien à signaler»를 하려다 입을 다묾
A21: Curie | B21: Je n'ai rien dit. | C21: 나는 아무 말도 안 했어. | D21: 아무 말도 하지 않아 오히려 가장 긴장됨 | E21: 침묵 설정을 폐지하고 시그니처 대사로 대체
A23: 4. 욕 배정 (폭발 장면 한정 — 교재용 순한 표현만)
A24: 인물 | B24: 표현 | C24: 뉘앙스 | D24: 사용 규칙 | E24: 비고
A25: Napoléon | B25: Bécasse / Tête de linotte | C25: 고풍스럽고 격식 있는 욕 — 우아하게 기분 나쁨 | D25: 1차·2차 폭발에서만, Manon에게만 | E25: 11부 12화 마지막에 «bécasse» 대신 «Pas mal.»이 나올 때 낙차가 커진다.
A26: Jeanne | B26: Recrue ! / Bleue ! | C26: 군대식 신병 취급 | D26: 1차에서 1회 | E26: 1부 6화(폭발 화)에 카메오로 함께 있으므로 여기서 1회 (확정)
A27: Karim | B27: Andouille / Patate | C27: 시장통식 직설 | D27: 2차(9부)에서 1회 | E27: 1차 폭발 화의 카메오 과밀을 피해 이관 (확정)
A28: Monique | B28: Nigaude / Cruche + «ma petite» | C28: 애정이 섞여 욕인 줄 모름 | D28: 1차에서 1회
A29: Curie | B29: 욕하지 않음 | C29: 대신 출처를 가리킨다 | D29: — | E29: «Cherche toi-même.»
A31: 5. 유지 규칙
A32: 1. Manon이 옳은 경우가 있어야 한다. 2차(9부)에서는 행정 용어에 숨은 삭감 조항을 짚어 낸다. 1차에서도 Léa의 용어(synergies, scalable)가 알맹이 없었음이 드러난다. Manon은 '어려운 말로 숨는 어른들'을 드러내는 인물이다.
A33: 2. 폭발 직후에는 누군가 쉬운 말로 다시 설명한다 (전문 표현 → 쉬운 표현 짝 학습). 1차 담당: Julien — «Je traduis. Ça veut dire : licencier des gens pour économiser.»
A34: 3. 욕과 괴롭힘의 선: 별도 에피소드를 만들지 않고 2차 폭발에 합친다. Napoléon이 정말 아픈 말을 하고 Jeanne·Monique가 나무라며, 사과는 «Je retire ce que j'ai dit… en partie.» 정도로 삐딱하게.
A35: 4. 욕설 수위: putain, merde 등은 교재에서 제외. 필요하면 각주로 '실제로는 더 거칠게 말한다'고만 알려 준다.

Sheet Napoléon_죽음
A1: Napoléon — 부활한 황제, 협상 승리 직후 두 번째 죽음
A2: 10부 동안 매 겨울 '마지막'이라고 외치는 양치기 소년 → 11부에서 대통령 특사가 되어 브뤼셀에서 승리하고, 그 직후 12화에서 진짜로(두 번째로) 죽는다.
A4: 1. 기본 설정
A5: 항목 | B5: 내용
A6: 나이 | B6: ="1부 "&INDEX(캐릭터!$E$5:$E$19,MATCH("Napoléon",캐릭터!$D$5:$D$19,0))&"세 → 11부 약 "&INDEX(캐릭터!$F$5:$F$19,MATCH("Napoléon",캐릭터!$D$5:$D$19,0))&"세 (부활 후 외형 나이, 경과 연수 가정 "&개요!$C$11&"년)" -> 1부 51세 → 11부 약 57세 (부활 후 외형 나이, 경과 연수 가정 6년)
A7: 성격 | B7: 정중하게 독을 뿌리는 심술 황제. 예의를 지키며 비꼬는 화법이라 Karim의 큰 소리 화법과 구분된다. 낭독하면 '정중한데 기분 나쁜' 억양 연습이 된다.
A8: 심술 패턴 | B8: 커피가 맛없다고 매일 불평(«Quelle façon de massacrer un bon café.»). Léa를 «la dame aux slides», Hugo의 원고를 «les mille brouillons»라고 놀림. 모든 것이 «De mon temps»보다 못하다 — 그의 시대가 1800년대라 더 우습다.
A9: 반복 개그 | B9: 매 겨울 «Cet hiver sera mon dernier.» 선언(«L'hiver ne m'a jamais réussi. Demandez à la Russie.»), 유언장을 계속 고쳐 씀 (Manon에게 이각모를 물려주겠다 등). 입버릇 «Notez-le dans mon testament.» 모두 '또 시작이네' 하며 웃어넘긴다.
A10: 가짜 병 | B10: 무릎, 불면, '세인트헬레나의 습기' 탓이라는 기침 — 전부 엄살. 소란스러운 엄살이 진짜 병의 위장이 된다.
A11: 진짜 병 | B11: 첫 번째 죽음과 같은 위(胃)의 병 (1821년 세인트헬레나의 사인). 이것만 숨긴다. 되살아난 몸이 같은 결말을 반복한다는 운명의 아이러니.
A12: Camille의 딜레마 | B12: 진단을 알지만 의사의 직업상 비밀(secret médical)을 지킨다. Napoléon이 «Docteure, ceci reste entre nous.»라고 못 박았기 때문. 시청자가 뒤늦게 'Camille가 왜 조용했는지' 깨닫는 구조.
A13: 최고의 칭찬 | B13: «Pas mal.» — 극히 드물게 쓰는 표현. Manon에게는 11부 12화(사망 직전)가 사실상 처음이어야 낙차가 산다.
A14: 호칭·욕 | B14: 여럿에게는 «Messieurs, mesdames» + vous, Manon에게는 tu(«petite», «soldat»). 욕(«bécasse»)은 Manon에게만, 폭발 장면 2회 한정.
A15: 죽음 이후 | B15: La Vieille Garde는 Jeanne + Curie + 빈 의자. 12부 10화 'Le vide dans la garde'에서 정면으로 다룬다. (La Vieille Garde는 실제 나폴레옹 근위대의 이름이기도 하다.)
A17: 2. 복선·사망 타임라인 (전부 대사로 처리)
A18: 부·화 | B18: 사건 | C18: 대화문 처리 방식 | D18: 대사 예시 (FR) | E18: 학습 어휘
A19: 1~10부 (매 겨울) | B19: '마지막 겨울' 선언과 유언장 수정. 1부 1화(개소 1개월 시점)부터 이미 반복되어 온 농담으로 등장한다. | C19: 본인이 선언하고 주변이 «Encore…»로 받는다. | D19: Cet hiver sera mon dernier. Notez-le dans mon testament. | E19: testament, léguer, hiver
A20: 1~11부 | B20: 가짜 병 (무릎·불면·기침) | C20: Camille가 «Vous n'avez rien.»으로 넘긴다. | D20: J'ai mal au genou. C'est la fin. | E20: genou, insomnie, toux, maux
A21: 7부 | B21: «Tu peux me tutoyer.» 허락 — Manon은 습관 때문에 vous 유지 | C21: 허락과 거절이 모두 대사로 나온다. | D21: Tu peux me tutoyer, petite. / Pardon, c'est l'habitude. | E21: tutoyer, vouvoyer, habitude
A22: 9부 | B22: Manon 2차 폭발에서 Napoléon이 선을 넘음 → Jeanne·Monique가 나무람 | C22: 선을 넘는 말과 사과 모두 대사로. | D22: Je retire ce que j'ai dit… en partie. | E22: retirer ses paroles, s'excuser
A23: 11부 6화 | B23: 청년 고용 협상에서 좋은 조언을 하지만 계단에서 배를 움켜쥐는 게 처음으로 드러남 (죽음은 아직 아님) | C23: «Je n'ai rien»이 아니라 «Ce n'est rien, c'est l'escalier»로 처음 균열. | D23: Ce n'est rien. C'est l'escalier, petite. | E23: escalier, souffle, douleur
A24: 11부 9화 | B24: 브뤼셀行 자원. Hugo에게 짐을 싸며 두 지도자를 특징으로만 묘사 — 건물에 금박 이름을 새긴 사업가 출신과, 정보기관 출신으로 이웃 나라 땅을 가져간 인물. 이름·국가는 끝내 말하지 않는다. | C24: 실명 대신 행동·이력의 특징만 나열. 실존 인물 실명 미사용. | D24: L'un a mis son nom en lettres dorées sur ses immeubles. Maintenant, il vend des droits de douane, en criant. / Cela ressemble à qui vous voulez, jeune homme. Moi, je décris le paysage. | E24: droits de douane, services secrets, régime, discrétion diplomatique
A25: 11부 10화 | B25: 직접 협상. 상대의 과장·거짓 주장을 밤새 읽은 기록의 날짜로 정확히 반박 | C25: «Permettez-moi de vous corriger»로 시작하는 반박 대사. | D25: J'ai lu les archives toute la nuit, jeune homme. Lisez-les avec plus d'attention. | E25: corriger, archives, précision diplomatique
A26: 11부 11화 | B26: 타결. 귀국길에 피로를 숨기고 Julien에게 메모를 남기라고 지시 | C26: 직접 증상을 말하지 않고 '메모를 남기라'는 명령으로 암시. | D26: Au cas où, notez ceci aussi, Julien. | E26: au cas où, héritage, instruction
A27: 11부 12화 (사망) | B27: 귀국 직후 자택에서 위의 병으로 사망. Manon이 서명을 받으러 왔다가 발견 | C27: 사망은 지문 없이 호명과 확인 대사로: Manon이 부르고 Camille가 «Il est parti.»라고 말한다. | D27: Pas mal. / Napoléon ? — Il est parti, Manon. | E27: pouls, arrêt cardiaque, réanimation, décéder
A28: 12부 1화 | B28: 장례식이 첫 화. Chez Monique에 빈자리, Monique가 커피 한 잔을 계속 내놓음. Manon이 추도사에서 처음으로 tu 사용 | C28: 장소·상황은 Monique·Manon의 대사로. | D28: Un café pour Napoléon. Comme d'habitude. / Pour toi, « pas mal », c'était le plus beau compliment. | E28: obsèques, enterrement, condoléances, éloge funèbre
A29: 12부 2~3화 | B29: 유작 메모 발견 → 2차 브뤼셀 협상에서 Hugo가 다듬은 그의 문장을 인용 | C29: Hugo가 메모를 소리 내어 읽고 Julien이 협상장에서 그 문장을 인용한다. | D29: Permettez-moi une dernière précision : ce n'était pas mal. | E29: mémorandum, héritage, précision, ECOFIN
... A32: 12부 (선택) | B32: Sartre의 애도 대화 | C32: 다들 질색하던 «Et toi, qu'est-ce que tu choisis ?»가 처음으로 진지하게 쓰인다. | D32: Et toi, qu'est-ce que tu choisis, maintenant qu'il n'est plus là ? | E32: deuil, perte, chagrin

Sheet Curie_출처
A1: Curie — 결론 대신 출처를 가리키는 사람
A2: 직접 답하지 않고 '어디를 찾을지'만 알려 준다. 과학자의 논리: 답은 측정과 원자료에 있고, 그 대부분은 공개 출처에 있다.
A4: 1. 설정 변경
A5: 항목 | B5: 내용
A6: 답하는 방식 | B6: 결론은 말하지 않고 출처만 가리킨다. 실험 노트처럼 정확하게.
A7: 시그니처 | B7: «Je n'ai rien dit. Mais regarde dans…» / «Je ne te le dis pas. Je te dis où c'est.» / «Presque tout est dans des sources ouvertes. Il suffit de savoir lire.»
A8: 도구 (대화문 처리) | B8: 책을 꺼내 건네거나 카드에 적어 주는 행동은 지문 대신 대사로 말한다: «Troisième rayon, à ta gauche.» / «Note. Cherche : …»
A9: 호칭 | B9: 전원에게 tu — «Cherche toi-même.»가 명령조라 더 섬뜩하다.
A10: Manon과의 관계 | B10: Manon이 «Dites-moi la réponse !» 하면 서가 위치만 말한다. 짜증 나지만 정답을 떠먹이지 않는 이 교재의 태도와 같다.
A11: 현실 요소 | B11: 센 강변 헌책방(bouquinistes des quais de Seine)과 프랑스 국립도서관(BnF, François-Mitterrand관), 5구 퀴리 박물관을 단골 출처로. 학습자가 실제 파리에서 따라 걸어 볼 수 있다.
A12: 서점 원칙 | B12: 강변 헌책방 친구의 상자 한 칸을 빌려 쓴다. 손님이 찾던 답이 든 책일 때만 값을 받지 않는다.
A14: 2. 그의 서가 4칸
A15: 칸 | B15: 내용 | C15: 대표 출처
A16: 법령칸 | B16: 법과 조문 | C16: Légifrance(legifrance.gouv.fr), 헌법, 각 법전(Code)
A17: 문서칸 | B17: 기록과 자료 | C17: 국립문서보관소(Archives nationales), 관보(Journal officiel), 하원 회의록(assemblee-nationale.fr)
A18: 신문칸 | B18: 과거 기사 | C18: BnF 디지털 도서관 Gallica, 신문 아카이브 RetroNews
A19: 사전칸 | B19: 용어 | C19: 아카데미 프랑세즈 사전(dictionnaire-academie.fr), CNRTL(TLFi), vie-publique.fr 용어 해설
A21: 3. 주제별 출처표 (기획한 에피소드 기준)
A22: 상황 | B22: 관련 부·화 | C22: Curie의 대사 (FR) | D22: 찾을 곳 | E22: 검색어·키워드 | F22: 서가칸
A23: 정보기관 통제 | B23: 12부 5화 | C23: Commence par la loi qui les encadre. | D23: 국내안전법전 L.801-1조 이하(2015년 정보법), CNCTR 연례 보고서 — Légifrance·cnctr.fr | E23: techniques de renseignement; CNCTR; contrôle a priori | F23: 법령칸
A24: 도청의 합법성 | B24: 7부 8화, 11부 7화 | C24: Une preuve volée reste une preuve… mais le voleur est puni. Cherche. | D24: 형법 제226-1조(사생활 침해), 형사소송법 제427조(증거의 자유), 파기원 판례(증거의 공정성) | E24: enregistrement clandestin, atteinte à la vie privée, preuve déloyale | F24: 법령칸
A25: 기밀 지정과 공개 | B25: 12부 5화 관련 | C25: Il y a un secret défense. Et une commission pour le lever. | D25: 형법 제413-9조 이하(국방기밀), 국방기밀자문위원회(CSDN), 행정문서공개위원회(CADA) | E25: secret de la défense nationale, déclassification | F25: 법령칸 (절차 최신본 확인)
A26: 의사의 비밀유지 | B26: 11부 6~12화 (Napoléon 복선) | C26: Demande à la docteure ce que dit son code. | D26: 공중보건법전 L.1110-4조, 형법 제226-13조, 의사윤리강령(Code de déontologie médicale) | E26: secret médical, dossier médical | F26: 법령칸
A27: 자금 세탁 | B27: 4부, 11부 2화 | C27: Tout argent a une loi qui le surveille. Cherche-la. | D27: 통화금융법전 L.561-1조 이하, TRACFIN(재무부 산하 금융정보기구), 실소유자 등록부 | E27: blanchiment, bénéficiaire effectif, paradis fiscal | F27: 문서칸·법령칸
A28: 주거·퇴거 | B28: 1·2·11부 | C28: Compare ce qu'ils disent avec ce qui existe. | D28: 1989년 7월 6일 법(임대차), 민사집행법전 L.412-1조 이하(퇴거·겨울 유예), 건설주거법전 | E28: expulsion, bail, congé, trêve hivernale | F28: 법령칸
A29: 가격 담합 | B29: 11부 7화 | C29: Regarde du côté de la Concurrence. | D29: 상법전 L.420-1조, 경쟁당국(autoritedelaconcurrence.fr) 제재 결정 | E29: entente, sanction, concurrence | F29: 법령칸·문서칸
A30: 초과이윤·고액자산 과세 | B30: 11부 8화 | C30: Tu ne l'as pas inventé. Ça a déjà été fait. | D30: 2023년 재정법의 전력 초과수익 부담금(contribution sur la rente inframarginale), 헌법 제34조 | E30: contribution exceptionnelle, rente inframarginale | F30: 법령칸
A31: EU 긴축 압박 | B31: 11부 10화 | C31: Cet article ne dit pas ce qu'on t'a dit. | D31: TFUE 제126조, EU 규칙 2024/1263, EUR-Lex(eur-lex.europa.eu) | E31: procédure de déficit excessif | F31: 법령칸
A32: 과거 스캔들 조사 | B32: 6~7부 | C32: Les journaux gardent ce que les gens oublient. | D32: Gallica·RetroNews | E32: 'écoutes de l'Élysée'로 검색 | F32: 신문칸
A33: 의회 발언 확인 (제안) | B33: 9부 | C33: Tout ce qui s'est dit à la tribune est écrit. | D33: 파리 시의회 공식 회의록(Bulletin officiel des débats), 하원 회의록 | E33: compte rendu, séance, intervention | F33: 문서칸
... A41: 모르는 단어 | B41: 전 부 | C41: Si tu ne connais pas le mot, tu ne connais pas la loi. | D41: 아카데미 프랑세즈 사전, CNRTL | E41: — | F41: 사전칸
A42: ※ 법령 번호와 조항은 기획 시점 지식으로 정리한 것입니다. 교재에 넣기 전에 Légifrance의 현행 텍스트(version en vigueur)로 반드시 확인하세요. 참고 도서 제목은 지어낼 위험이 있어 제외하고 검색어만 적었습니다.
A44: 4. 카드(FICHA) 구술 템플릿 — 지문 없이 대사로만
A45: 화자 | B45: 기능 | C45: 대사 (FR) | D45: 한국어
A46: CURIE | B46: 검색어 (Cherche) | C46: Note. Cherche : « preuve déloyale ». | D46: 적어. 찾을 것: «불공정하게 얻은 증거».
A47: MANON | B47: 질문으로 다음 항목을 끌어냄 | C47: D'accord. Où ? | D47: 알겠어요. 어디서요?
A48: CURIE | B48: 출처 (Où) | C48: Légifrance. Code pénal, article 226-1. | D48: 레지프랑스. 형법 제226-1조.
A49: MANON | B49: 질문 | C49: Et je cherche quels mots ? | D49: 그럼 어떤 단어를 찾죠?
A50: CURIE | B50: 키워드 (Mots-clés) | C50: Enregistrement clandestin. Vie privée. Loyauté de la preuve. | D50: 몰래 녹음. 사생활. 증거의 공정성.
A51: MANON | B51: Manon의 조급함 | C51: Et la réponse ? | D51: 그럼 답은요?
A52: CURIE | B52: 시그니처 + 서가 위치 (손짓 지문 대체) | C52: Je n'ai rien dit. Troisième rayon, à ta gauche. | D52: 나는 아무 말도 안 했어. 세 번째 선반, 왼쪽이야.
A53: 카드는 3줄(검색어·출처·키워드)과 마지막 시그니처로 짧게 유지한다. 이 카드가 모이면 교재 전체의 프랑스어 자료 색인이 된다. 카드를 넣을 화의 범위(전 화 vs Curie 등장 화)는 미결사항 참고.

Sheet 대화문규칙
A1: 대화문 규칙 — 모든 것은 대화문으로 풀어간다
A2: 이전 안(상황 30% + 대화 70%)을 폐기하고, 전 화를 「화자명: 대사」만으로 구성한다.
A4: 1. 원칙
A5: No | B5: 규칙 | C5: 내용 | D5: 예시
A6: 1 | B6: 전 화 100% 대화문 | C6: 지문(didascalies)은 0%. 각 화는 화자명 + 대사로만 구성한다. | D6: MONIQUE : Il est cinq heures. La réunion commence.
A7: 2 | B7: 화 머리 표기 | C7: 부·화 번호, 제목, 장소·날짜는 낭독하지 않는 표기 전용 한 줄(메타). 낭독 본문에는 넣지 않는다. | D7: [11부 4화 · Urgences saturées]
A8: 3 | B8: 괄호 무대지시 금지 | C8: 행동·표정·침묵은 괄호 지문이 아니라 대사로 표현한다. | D8: (Monique pose l'assiette) → MONIQUE : Je pose cette assiette avant qu'elle s'envole.
A9: 4 | B9: 장소·시간 소개 | C9: 지정 화자가 대사로 알린다: Monique(식사·장소), Manon(질문), Jeanne(보고). | D9: MONIQUE : Il est cinq heures. Réunion à ma table.
A10: 5 | B10: 시간 경과·장면 전환 | C10: 인물이 말로 알린다. 전환은 화자 교체 + 장소 언급으로. | D10: VOLTAIRE : Ça fait trois mois depuis l'expulsion, non ?
A11: 6 | B11: 문서·기사·메모 | C11: 소리 내어 읽는다: Nicolas=조항, Voltaire=기사, Hugo=초고·메모, Curie=카드. | D11: NICOLAS : Article premier : « La France est une République indivisible, laïque, démocratique et sociale. »
A12: 7 | B12: 무거운 장면 (죽음·침묵) | C12: 짧은 호명·확인 대사로 처리한다. | D12: MANON : Napoléon ? / CAMILLE : Il est parti, Manon.
A13: 8 | B13: 내면·감정 | C13: 독백은 '소리 내어 하는 말'로만 허용. 감정 노출은 Sartre의 되묻기 화법을 활용. | D13: SARTRE : Alors tu te sens seule. Et qu'est-ce que tu en fais ?
A14: 9 | B14: 문장 길이 | C14: 1부(B1): 대사 한 줄 15단어 이내. Napoléon·Nicolas의 격식체는 한두 줄만 '어른들 말투 맛보기'. 부가 올라갈수록 인물별 허용 길이 확대. Manon의 질문은 끝까지 짧게. | D14: '1부_시범대사' 시트에서 단어 수 자동 점검
A15: 10 | B15: 화당 분량 = 120턴 | C15: 한 화는 대화 120턴(화자 교대 1회 = 1턴)으로 구성한다. 한 턴은 1부 15단어 이내, 연설·조항·기사 낭독은 긴 턴 1개로 세되 화당 3개까지. 화 유형별 도입·장면·절정·마무리 배분과 화자 점유율은 '턴_설계' 시트. | D15: 120턴 중 장면 전환·시간·장소 안내 5~10턴, Manon 질문→재설명 6~12턴
A16: 11 | B16: 시그니처 표현 | C16: 화자 식별 장치이자 반복 학습 문장. 한 화에 화자당 1~2회까지.
A17: 12 | B17: Manon의 질문 장치 | C17: 어려운 용어 뒤에는 Manon의 질문 → 쉬운 재설명이 온다 (전문 표현 → 쉬운 표현 짝). | D17: MANON : Pardon, ça veut dire quoi ?
A18: 13 | B18: Curie의 카드 | C18: 카드는 구술로 처리한다 (Curie_출처 시트 템플릿). | D18: CURIE : Note. Cherche : …
A19: 14 | B19: 욕설 수위 | C19: putain, merde 등은 교재 제외. 순한 표현만 (Manon_폭발과욕 시트).
A20: 15 | B20: 호칭 전환 | C20: tu/vous 전환(tutoiement)은 대사로 명시한다 (호칭규칙 시트). | D20: NAPOLÉON : Tu peux me tutoyer.
A21: 16 | B21: 가상 정치 세계 | C21: 정당·정치인은 전부 가상. 실존 정치인·정당명을 쓰지 않는다. 공식 절차 문구는 하원의장(표결)·헌법재판소장(대선 결과) 대사로 전달한다. | D21: PRÉSIDENTE DE L'ASSEMBLÉE NATIONALE : Pour l'adoption : deux cent quatre-vingt-huit.
A22: 17 | B22: 현안을 다루는 법 | C22: 시사 현안은 가상 설정으로 각색하고 실존 인물·참사 희생자를 특정하지 않는다. 찬반 양측이 각자의 가장 강한 논거를 말하게 하고, 결론은 화 안에서 제도의 결과(표결·판결·협약)로만 닫는다. 수치는 Curie의 카드로 출처를 안내한다. | D22: MANON : Pardon, ça veut dire quoi, « encadrement des loyers » ? / JULIEN : Le loyer ne peut pas dépasser un plafond.
A23: 18 | B23: 화자 표기 | C23: 화자명은 대문자 + 공백 + 콜론(프랑스식 타이포그래피: ? ! : ; 앞에 공백). 프랑스어 본문과 한국어 번역은 열(또는 파일)을 분리해 낭독 시 번역이 섞이지 않게 한다. | D23: MANON : ÇA SUFFIT !
A24: 19 | B24: 고전 인용 | C24: 인물마다 다른 프랑스 고전 출처를 맡겨 화마다 1~2명이 짧게 인용한다. 공유 저작물(저자 사후 70년 경과)만 쓰고, 원문을 정확히 인용한다 (배정표는 아래 3번). 부활한 인물은 자기 글을 인용할 수 있다. | D24: HUGO : Ceux qui vivent, ce sont ceux qui luttent.
A26: 3. 고전 인용 배정 (화마다 1~2명)
A27: 인물마다 다른 출처를 맡겨 반복되지 않게 하고, Monique가 거의 전 화에 등장하므로 로테이션 캐스트인 1부에서도 대부분의 화가 커버된다. 공유 저작물(코르네유·라퐁텐·파스칼·볼테르·위고·1789년 인권선언 등)만 쓰고 원문을 정확히 인용한다. Sartre(1980년 사망)의 글은 저작권 보호 중이므로 짧은 인용권 범위로만 쓰거나 창작 대사로 대체한다. 가짜로 떠도는 명언(예: 볼테르가 실제로 쓰지 않은 «Je ne suis pas d'accord avec ce que vous dites, mais je me battrai…» — 실제로는 1906년 전기 작가의 요약문)은 쓰지 않는다.
A28: 1 | B28: (Silencio.) 폭발 직후 정적 | C28: «Oh là.» — 정적 대신 짧은 감탄으로 멈춤을 표현 | D28: Monique
A29: 인물 | B29: 출처 | C29: 쓰는 방식 | D29: 실제 인용 예시 (FR) | E29: 등장 부
A30: Monique | B30: 프랑스 속담(proverbes) | C30: 인용이 아니라 그냥 말버릇처럼 자연스럽게 섞인다. 따뜻하고 실용적. | D30: Petit à petit, l'oiseau fait son nid. / Qui se ressemble s'assemble. | E30: 거의 전 화
A31: Napoléon | B31: 코르네유·자기 편지(부활자 특권) | C31: 정중하게 비꼬는 코미디로(평소), 죽음 앞에서는 무겁게(11부). | D31: À vaincre sans péril, on triomphe sans gloire. (Corneille, Le Cid) / « Impossible n'est pas français » — 1813년 편지 문구가 변형된 말이라 원문 확인 후 사용 | E31: 1부, 11부
A32: Curie | B32: 파스칼·라퐁텐 등 | C32: 감정으로 낭송하지 않고 서지 정보처럼 인용한다 — 「몇 번째 선반」식 습관과 같은 화법. | D32: L'homme n'est qu'un roseau, le plus faible de la nature ; mais c'est un roseau pensant. Pascal, Pensées. | E32: 1·2·6·11·12부
A33: Hugo | B33: 자기 작품(위고) | C33: 자기 문장을 인용하다 들키면 모른 척한다 — 부활자의 겸손 개그. 시적이고 장엄한 톤. | D33: Ceux qui vivent, ce sont ceux qui luttent. (Hugo, Les Châtiments) / Demain, dès l'aube… (Hugo, Les Contemplations) | E33: 6부 이후
A34: Nicolas | B34: 1789년 인권선언·위고의 정치 연설 | C34: 대통령이 되어 가며 연설에 섞어 쓴다. | D34: Les hommes naissent et demeurent libres et égaux en droits. (인권선언 제1조) | E34: 8~13부
A35: 8 | B35: 시간 경과 | C35: «Ça fait trois mois depuis l'expulsion.» | D35: Voltaire (질문 형태)
A36: 9 | B36: 신문 기사 삽입 | C36: Voltaire가 기사 첫 문단을 소리 내어 읽는다 | D36: Voltaire
A37: 10 | B37: 연설문 초고 삽입 | C37: Hugo가 초고를 읽고 Nicolas가 고친다 | D37: Hugo, Nicolas
A38: 11 | B38: 투표 결과 전광판·자막 | C38: 하원의장이 표결 결과를 낭독한다: «Majorité requise pour l'adoption de la motion de censure : deux cent quatre-vingt-neuf. Pour l'adoption : deux cent quatre-vingt-huit.» | D38: PRÉSIDENTE DE L'ASSEMBLÉE NATIONALE
A39: 12 | B39: 대선 결과 선포·취임식 | C39: 헌법재판소장이 결과를 선포하고, 취임식에서 Nicolas가 첫 연설을 한다 (프랑스 대통령은 선서하지 않는다). | D39: PRÉSIDENT DU CONSEIL CONSTITUTIONNEL, Nicolas

Sheet 1부_시범대사
A1: 1부 시범 장면 — Manon 1차 폭발 (지문 없이 대사만, B1, 일반화된 예시)
A2: 장소·시간·행동을 모두 대사로 처리한 샘플로, 한 화(120턴) 중 폭발 장면 22턴을 발췌했다. 단어 수는 수식으로 자동 계산되며 상한을 넘으면 '초과'로 표시됩니다. (문장부호 앞 공백은 좁은 공백이라 단어로 세지 않음)
C4: 1부 대사 상한 (단어) | D4: 15 | E4: ← 노란 셀은 가정값 (교재 규칙 초안: 15단어 이내)
C5: 총 대사 수 | D5: =COUNTA(B8:B29) -> 22
C6: 상한 초과 대사 수 | D6: =COUNTIF(G8:G29,"초과") -> 0
A7: No | B7: 화자 | C7: 대사 (FR) | D7: 한국어 (낭독 제외) | E7: 기능·학습 포인트 | F7: 단어 수 | G7: 판정
A8: 1 | B8: MONIQUE | C8: Il est cinq heures. La réunion du cabinet commence, ici en bas, à ma table. | D8: 다섯 시예요. 사무소 회의 시작이야, 여기 아래 내 테이블에서. | E8: 지문 대체: 시간·장소를 Monique가 알림 | F8: =LEN(TRIM(C8))-LEN(SUBSTITUTE(TRIM(C8)," ",""))+1 -> 15 | G8: =IF(F8<=$D$4,"OK","초과") -> OK
A9: 2 | B9: LÉA | C9: C'est simple. On aligne les parties prenantes et on scale l'impact. | D9: 간단해요. 이해관계자를 정렬하고 임팩트를 스케일업하죠. | E9: 경영 용어 제시 (aligner, scaler, impact) | F9: =LEN(TRIM(C9))-LEN(SUBSTITUTE(TRIM(C9)," ",""))+1 -> 11 | G9: =IF(F9<=$D$4,"OK","초과") -> OK
A10: 3 | B10: MANON | C10: Pardon, ça veut dire quoi ? | D10: 실례지만, 그게 무슨 뜻이에요? | E10: 1단계: 정중한 질문 | F10: =LEN(TRIM(C10))-LEN(SUBSTITUTE(TRIM(C10)," ",""))+1 -> 5 | G10: =IF(F10<=$D$4,"OK","초과") -> OK
A11: 4 | B11: LÉA | C11: On optimise le flux de valeur pour maximiser les synergies. | D11: 가치 흐름을 최적화해 시너지를 극대화합니다. | E11: 알맹이 없는 용어의 반복 | F11: =LEN(TRIM(C11))-LEN(SUBSTITUTE(TRIM(C11)," ",""))+1 -> 10 | G11: =IF(F11<=$D$4,"OK","초과") -> OK
A12: 5 | B12: MANON | C12: Vous pouvez m'expliquer comme si j'avais cinq ans ? | D12: 다섯 살한테 설명하듯 해 주실래요? | E12: 2단계: 슬슬 짜증 | F12: =LEN(TRIM(C12))-LEN(SUBSTITUTE(TRIM(C12)," ",""))+1 -> 8 | G12: =IF(F12<=$D$4,"OK","초과") -> OK
A13: 6 | B13: LÉA | C13: Bien sûr. On crée de la valeur avec un modèle scalable et aligné. | D13: 물론이죠. 확장 가능하고 정렬된 모델로 가치를 만듭니다. | E13: 동어반복 — 여전히 설명이 안 됨 | F13: =LEN(TRIM(C13))-LEN(SUBSTITUTE(TRIM(C13)," ",""))+1 -> 13 | G13: =IF(F13<=$D$4,"OK","초과") -> OK
A14: 7 | B14: MANON | C14: ÇA SUFFIT ! Je comprends rien ! Une heure que je hoche la tête. | D14: 그만! 하나도 모르겠어요! 한 시간째 고개만 끄덕이고 있다고요. | E14: 3단계: 폭발 (톤 급상승) | F14: =LEN(TRIM(C14))-LEN(SUBSTITUTE(TRIM(C14)," ",""))+1 -> 12 | G14: =IF(F14<=$D$4,"OK","초과") -> OK
A15: 8 | B15: MONIQUE | C15: Oh là. Je pose cette assiette avant qu'elle s'envole. | D15: 어이쿠. 접시 날아가기 전에 내려놔야겠네. | E15: 지문 대체: 접시 내려놓는 행동을 대사로 | F15: =LEN(TRIM(C15))-LEN(SUBSTITUTE(TRIM(C15)," ",""))+1 -> 9 | G15: =IF(F15<=$D$4,"OK","초과") -> OK
A16: 9 | B16: CAMILLE | C16: D'abord, respire. | D16: 우선, 숨 쉬어. | E16: Camille의 고정 반응 | F16: =LEN(TRIM(C16))-LEN(SUBSTITUTE(TRIM(C16)," ",""))+1 -> 2 | G16: =IF(F16<=$D$4,"OK","초과") -> OK
A17: 10 | B17: MANON | C17: Ne me dites pas « respire » ! | D17: «숨 쉬어»라고 하지 마세요! | E17: Camille에게 vous 유지 | F17: =LEN(TRIM(C17))-LEN(SUBSTITUTE(TRIM(C17)," ",""))+1 -> 5 | G17: =IF(F17<=$D$4,"OK","초과") -> OK
A18: 11 | B18: JEANNE | C18: Rien à sig… Non. Je ferais mieux de me taire. | D18: 이상 없… 아니. 입 다무는 게 낫겠어. | E18: Jeanne의 고정 반응 (카메오) | F18: =LEN(TRIM(C18))-LEN(SUBSTITUTE(TRIM(C18)," ",""))+1 -> 10 | G18: =IF(F18<=$D$4,"OK","초과") -> OK
A19: 12 | B19: CURIE | C19: Je n'ai rien dit. | D19: 나는 아무 말도 안 했어. | E19: Curie의 고정 반응 (카메오) — 침묵 대신 시그니처 | F19: =LEN(TRIM(C19))-LEN(SUBSTITUTE(TRIM(C19)," ",""))+1 -> 4 | G19: =IF(F19<=$D$4,"OK","초과") -> OK
... A23: 16 | B23: JULIEN | C23: Je traduis. Ça veut dire : licencier des gens pour économiser. | D23: 내가 번역하지. 사람을 해고해서 돈을 아끼자는 뜻이야. | E23: 쉬운 말로 재설명 (어휘 교습 장면) | F23: =LEN(TRIM(C23))-LEN(SUBSTITUTE(TRIM(C23)," ",""))+1 -> 10 | G23: =IF(F23<=$D$4,"OK","초과") -> OK
A24: 17 | B24: LÉA | C24: Ce n'est pas exactement ce que j'ai dit. | D24: 제가 말한 건 정확히 그게 아닌데요. | F24: =LEN(TRIM(C24))-LEN(SUBSTITUTE(TRIM(C24)," ",""))+1 -> 8 | G24: =IF(F24<=$D$4,"OK","초과") -> OK
A25: 18 | B25: JULIEN | C25: C'est exactement ce que tu as dit. | D25: 정확히 네가 한 말이야. | E25: 짧은 반박 — 티키타카 | F25: =LEN(TRIM(C25))-LEN(SUBSTITUTE(TRIM(C25)," ",""))+1 -> 7 | G25: =IF(F25<=$D$4,"OK","초과") -> OK
A26: 19 | B26: MANON | C26: Sérieux ? Tous ces mots pour dire ça ? | D26: 정말요? 겨우 그 말 하려고 그렇게 많은 단어를요? | E26: Manon이 옳았음이 드러남 | F26: =LEN(TRIM(C26))-LEN(SUBSTITUTE(TRIM(C26)," ",""))+1 -> 7 | G26: =IF(F26<=$D$4,"OK","초과") -> OK
A27: 20 | B27: LÉA | C27: Bon. Parfois, oui. | D27: 음. 가끔은, 그렇죠. | E27: Léa의 성장 씨앗 | F27: =LEN(TRIM(C27))-LEN(SUBSTITUTE(TRIM(C27)," ",""))+1 -> 3 | G27: =IF(F27<=$D$4,"OK","초과") -> OK
A28: 21 | B28: MONIQUE | C28: Asseyez-vous, je vous apporte quelque chose. Le ventre vide, on ne réfléchit pas bien. | D28: 다들 앉아, 뭐 좀 내올게. 배가 비면 생각이 안 돼. | E28: vous(복수) 명령형, Monique의 시그니처 2개 | F28: =LEN(TRIM(C28))-LEN(SUBSTITUTE(TRIM(C28)," ",""))+1 -> 14 | G28: =IF(F28<=$D$4,"OK","초과") -> OK
A29: 22 | B29: MANON | C29: D'accord. Mais demain, sans mots bizarres, s'il vous plaît. | D29: 알았어요. 그래도 내일은 이상한 말 없이 부탁해요. | F29: =LEN(TRIM(C29))-LEN(SUBSTITUTE(TRIM(C29)," ",""))+1 -> 9 | G29: =IF(F29<=$D$4,"OK","초과") -> OK

Sheet 변경이력_미결
A1: 변경 이력과 미결 사항
A3: 1. 변경 이력 (1~47: 마드리드판 기획 이력 — 인물명은 파리판 대응 인물로 바꿔 표기 / 48~: 파리판 현지화)
A4: No | B4: 항목 | C4: 이전 | D4: 이후 | E4: 반영 시트
A5: 1 | B5: 인원 | C5: 13인 (내각) | D5: 14인 — 출처 담당(현 Curie), 은행원(현 Philippe) 추가. 14인 모두가 장관은 아니므로 '내각'보다 핵심 그룹 개념 사용 (파리판에서 Olympe 추가로 15인) | E5: 개요, 캐릭터
A6: 2 | B6: 출처 담당 인물의 성 | C6: (마드리드판 스페인식 성 교체) | D6: 파리판에서는 역사 인물 Marie Curie로 대체되어 해당 없음 | E6: 캐릭터
A7: 3 | B7: 가상 상호명 | C7: 독일식 가상 상호 | D7: Bertin & Roux Audit / Zénith Consulting (파리판) | E7: 캐릭터
A8: 4 | B8: 기관 실명 | C8: 실존 은행·병원명 | D8: Banque Atlantique, Hôpital Saint-Bernard 등 가상명 (이야기 속에서 부패와 얽히기 때문) | E8: 캐릭터
A9: 5 | B9: Napoléon | C9: 우아한 은퇴 인물 | D9: 가장 까칠한 심술 영감 + 시한부 (파리판: 부활한 Napoléon, 11부 12화 사망). 가짜 병은 엄살, 진짜 병은 숨김 | E9: Napoléon_죽음
A10: 6 | B10: Manon 폭발 | C10: 자주 폭발하는 인물 (안) | D10: 폭발은 1부·9부 딱 2회. 욕은 폭발 장면 한정 | E10: Manon_폭발과욕
A11: 7 | B11: Curie | C11: 침묵으로 대답 | D11: 결론 대신 출처(서가 위치·법령·검색어)를 가리킴 | E11: Curie_출처
A12: 8 | B12: Curie 대사 | C12: «돈을 따라가라. 그리고 그 돈을 감시하는 법도.» | D12: «Tout argent a une loi qui le surveille. Cherche-la.» — Philippe의 시그니처 «Suivez l'argent.»와 중복 방지 | E12: Curie_출처
A13: 9 | B13: 출처표 정정 | C13: 주거·퇴거: 형사·민사소송법 | D13: 민사집행법전의 퇴거(expulsion) 절차 (파리판) | E13: Curie_출처
A14: 10 | B14: 형식 | C14: 상황 설명 30% + 대화 70% | D14: 전 화 100% 대화문 (지문 없음) | E14: 대화문규칙
A15: 11 | B15: 1부 시범 장면 | C15: (Silencio.), (Monique deja el plato…) 등 괄호 지문 포함 | D15: 모든 지문을 대사로 대체 | E15: 1부_시범대사
A16: 12 | B16: 부 수 | C16: 11부작 (132화) | D16: 12부작 (144화) — 12부는 1부 장면으로 돌아오는 원형 구조 | E16: 개요, 13부_구성
... A63: 59 | B63: 현실 수치 | C63: 스페인 부채 약 100%, 청년 실업 23.8% | D63: 프랑스 부채 117.5%(2026년 1분기 말), 15~24세 실업률 21.6%·전체 8.3%(2026 2분기) — INSEE, 2026-09-25 검색 확인 | E63: 현안_배치
A65: 2. 미결 사항 (확정 필요)
A66: No | B66: 항목 | C66: 내용 | D66: 제안 | E66: 관련 시트
A67: 1 | B67: 가상 인명 점검 | C67: Delorme·Verdier·Bertin·Garnier·Madeleine·Chloé·Sandrine 등 가상 인물의 이름이 관련 분야의 실존 인물과 겹치지 않는지. | D67: 집필 전 동명 실존 인물 검색 | E67: 아크_구성계획
A68: 2 | B68: Curie 카드의 범위 | C68: 카드를 전 화(156화)에 넣을지, Curie 등장 화에만 넣을지. | D68: 등장 화에만 넣고, 미등장 화는 Manon이 사전(아카데미 사전·CNRTL)을 찾는 짧은 대사로 대체 | E68: Curie_출처
A69: 3 | B69: Manon → 주력 4인 호칭 전환 | C69: Napoléon에게만 12부 1화에서 tu로 전환한다는 것 외에, 다른 인물에게 언제 tu로 넘어가는지 미정. | D69: 6부 만남 이후 자연스럽게 tu (Napoléon·Philippe·Curie는 vous 유지) | E69: 호칭규칙
A70: 4 | B70: 경과 연수·부활자 나이 | C70: 1부→11부 6년 가정(Napoléon 외형 51→57세). 부활자의 나이를 외형 나이로 쓸지 생몰년으로 쓸지. | D70: 확정 시 개요!C11만 수정. 캐릭터 시트는 외형 나이 + 생몰년 병기 유지 | E70: 개요
A71: 5 | B71: 총리 배역 | C71: Olympe를 총리로 설정(신규). 대안: 가상 외부 인사 총리 + Olympe는 여성·인권 장관. | D71: Olympe 총리안 권장 — 15번째 배역에 서사 몫이 생기고, 불신임안 화의 중심 인물이 된다 | E71: 캐릭터, 정치경로_의석
A72: 6 | B72: 법령·조항 확인 | C72: 출처표·제도표의 법령 번호·조항은 기획 시점 지식 기준. | D72: 교재 반영 전 Légifrance 현행본(version en vigueur)으로 확인 | E72: Curie_출처, 정치제도
A73: 7 | B73: 대화량 실측 교정 | C73: 화당 120턴은 확정. 화자 점유율·평균 단어/턴·낭독 속도(130단어/분)는 가정값이다. | D73: 1부 1~3화 대본을 쓴 뒤 실제 턴·단어를 재서 '턴_설계'의 파란 값을 교정 | E73: 턴_설계
A74: 8 | B74: Sartre 비중·저작권 | C74: Sartre가 가장 얇고, 1980년 사망이라 그의 글은 저작권 보호 중이다. | D74: 3·5부 카페 장면 확대, 12부 애도 장면 배정. 인용은 짧은 인용 범위 또는 창작 대사 | E74: 등장비중, 대화문규칙
A75: 9 | B75: 정부 형태 | C75: Maison Commune 단독 상대다수 정부 + PPS·AE 법안별 지지 (현재 설정) | D75: PPS 장관을 포함한 연립으로 갈지 결정 | E75: 정치경로_의석
A76: 10 | B76: 겸직 규정 확인 | C76: Julien·Camille가 장관이 된 뒤 파리 시의원직을 유지할지(법적 겸직 금지 대상은 아니나 관행상 사임하는 경우가 많음). | D76: 헌법 제23조·선거법전 확인 후 확정 | E76: 정치제도
A77: 11 | B77: 가상 수치 | C77: 득표율(22.3%·53%)·의석 수(198·288 등)와 1표 차 설정은 교육용 가상 수치. | D77: 드라마 효과에 맞춰 조정 가능 (정치경로_의석의 파란 셀) | E77: 정치경로_의석
A78: 12 | B78: 공식 낭독자 방침 | C78: 대선 결과는 헌법재판소장, 불신임안 결과는 하원의장이 낭독. 대통령 Nicolas는 직접 대사를 가진다. | D78: 확정 필요 | E78: 대화문규칙
... A90: 24 | B90: 앵발리드 무덤 | C90: Napoléon의 실제 무덤(앵발리드)과 두 번째 장례의 관계. | D90: 12부 1화에서 농담으로만 언급하고 매장지는 열어 둔다 | E90: Napoléon_죽음
