Workbook

Sheet 개요
A1: Madrid 스페인어 낭독 교재 — 캐릭터 바이블 (Biblia de Personajes)
A2: v20.0 · 2026-09-22 · 마드리드 배경 13부작 옴니버스(156화) · 1·2부 전체(24화) 대본 완성 · 화당 120턴 | C2: v26.0 · 2026-09-25 · 마드리드 배경 13부작 옴니버스(156화) · 1~8부 전체(96화) + 9부 1화 완성 · 1~6부 화당 120턴 · 7부부터 화당 180턴 · 다음: 9부 2화 · 다른 대화창에서 이어 쓰려면 '이어쓰기_가이드' 시트부터
B4: 기본 설정
B5: 부 수 | C5: 13 | D5: 1 사무소(개소 1개월 후, 6사건×2화) → 2~5 각자의 과거 → 6 만남 → 7 전면전 → 8 창당 → 9 시의회·자치의회 → 10 총선·총리 선출 → 11 국정 I(브뤼셀·Anselmo 사망) → 12 국정 II(장례·메모 승계) → 13 귀환(원형 구조)
B6: 부당 화 수 | C6: 12 | D6: 각 부 12화
B7: 총 화 수 | C7: =C5*C6 | D7: 부 수 × 부당 화 수 (자동 계산)
B8: 등장인물 수 | C8: =COUNTA(캐릭터!$D$5:$D$19) | D8: 캐릭터 시트의 약칭 개수
B9: 남성 인물 수 | C9: =COUNTIF(캐릭터!$G$5:$G$19,"남") | D9: 음색이 다양할수록 화자 구분이 쉬워 남 9 : 여 6으로 배분
B10: 여성 인물 수 | C10: =COUNTIF(캐릭터!$G$5:$G$19,"여")
B11: 1부→11부 경과 연수 (가정) | C11: 6 | D11: 가정값: Anselmo가 1부 74세 → 11부 약 80세가 되도록 잡음. 확정 시 이 셀만 수정하면 캐릭터 시트의 나이가 자동 갱신. (캐릭터 시트 '나이(11부)' 열)
B12: 배경·언어 | C12: 마드리드 | D12: 스페인 본토 스페인어: 친한 사이 vosotros, 공식 석상은 ustedes / señorías.
B13: 형식 | C13: 전 화 100% 대화문, 화당 120턴(7부부터 180턴, 8·9부도 180턴 유지) | D13: ="지문(Narración) 없음. 화당 "&턴_설계!$B$5&"턴 × "&C7&"화 = "&TEXT(C7*턴_설계!$B$5,"#,##0")&"턴. 상세는 '대화문규칙'·'턴_설계' 시트."
B15: 그룹별 인원
B16: 주력 4인 | C16: =COUNTIF(캐릭터!$B$5:$B$19,B16) | D16: Mateo(변호사) · Javier(의사) · Sofía(회계사) · Diego(컨설턴트)
B17: 올드보이 자문단 | C17: =COUNTIF(캐릭터!$B$5:$B$19,B17) | D17: Anselmo(외교관) · Ramón(장군) · Raimundo(전 CNI) · Inés(기자) · Lucía(심리학자) ※ La Vieja Guardia = Anselmo · Ramón · Raimundo
B18: 서민·청년 | C18: =COUNTIF(캐릭터!$B$5:$B$19,B18) | D18: Pepa(바 사장) · Nieves(노조위원장) · Tomás(작가 지망생) · Carmen(인턴)
B19: 금융 | C19: =COUNTIF(캐릭터!$B$5:$B$19,B19) | D19: Gonzalo(전 은행 지점장)
B20: 특별 인물 | C20: =COUNTIF(캐릭터!$B$5:$B$19,B20) | D20: Cervantes(부활한 소설가, 3부부터 사무소 합류)
B22: 시트 안내 (클릭하면 이동)
B23: 캐릭터 | C23: 기준표 | D23: 15인의 이름·나이·결핍·말투·시그니처·낭독 포인트·대화문 장치·직책·현안 담당
B24: 등장비중 | C24: 기준표 | D24: 13부 배분표, 합계·비중·등급(수식), 조연 단독 중심 화 목표
B25: 턴_설계 | C25: 기준표 | D25: 화당 120턴 설계: 부별 화자 점유율(턴 기준), 평균 단어/턴, 화당 단어·낭독 시간(수식), 화 유형별 턴 구성, 집필 규칙
B26: 12부_구성 | C26: 구조 | D26: 12부 한눈에 보기: 배경·핵심 내용·난이도(CEFR)·반영 제도
B27: 아크_구성계획 | C27: 구성 계획 | D27: 1~12부 아크별 구성 계획: 서사 기능·로그라인·비트·인물 아크·복선·현안·언어 설계
B28: 화별목차_전체 | C28: 목차 | D28: 1~12부 144화의 서사 기능·제목·핵심 사건·반영 제도·인물·현안 (필터 가능)
B29: 복선_회수 | C29: 구성 계획 | D29: 복선 설치→회수 50건과 간격(부)을 수식으로 계산 (34~50번: 5·6부 신규, 회수 완료분은 H열에 표시)
B30: 현안_배치 | C30: 현안 | D30: 스페인 현안 15개를 어느 화에 어떻게 녹일지 배치, 균형 유의, 현실 기준값
B31: 현안_분포 | C31: 현안 | D31: 부 × 현안 분포표: 전용 화(●)와 곁가지(○)를 수식으로 집계
B32: 정치제도 | C32: 현실 제도 | D32: 정당·선거·의회·정부·자치주·사법·EU 제도 기준표 (확인 상태 표시)
B33: 정치경로_의석 | C33: 현실 제도 | D33: 창당→총리 경로와 가상 의석·표결 시뮬레이션(수식): investidura 1·2차, 불신임안
B34: 호칭규칙 | C34: 규칙 | D34: tú / usted / vosotros / ustedes, 의회·국왕·시의회 공식 호칭
... B41: 이어쓰기_가이드 | C41: 관리 | D41: 새 대화창 인수인계: 진행 상황, docx 형식, 화자 색, 5·6부 확정 설정·수치, 호칭 현황, 7부 집필 메모(Picasso 합류), 5·6부 가상 인물 부록
B42: 범례
B43: 파란 글씨 | C43: 직접 입력한 값 (수정 가능)
B44: 노란 배경 | C44: 가정 · 확정이 필요한 값
B45: 검정 글씨 | C45: 수식으로 계산되는 값 (직접 수정하지 말 것)
B47: 주의: 성별·나이·기관명은 기획용 가상 설정입니다. 법령 번호·조항은 교재에 넣기 전에 BOE(boe.es)의 현행 텍스트(texto consolidado)로 확인하세요.

Sheet 이어쓰기_가이드
A1: 이어쓰기 가이드 — 새 대화창에서 이어 쓰기
A2: v26.0 · 2026-09-25 기준. 새 대화창에서는 이 시트를 먼저 읽고, '시작 방법'대로 파일을 올린다.
A5: 1. 진행 상황
A6: 항목 | B6: 내용 | C6: 비고
A7: 완성 | B7: 1~8부 전체 96화 + 9부 1화 (총 97화) | C7: 7부 대본: 7부N화_*.docx (N=1~12, 8~12화는 v26 작업분) · 8부: 8부N화_*.docx (N=1~12) · 9부: 9부1화_La_constitucion_de_la_Corporacion.docx
A8: 다음 작업 | B8: 9부 2화 「El primer Pleno」 — 화별목차_전체 9부 2행 + 아래 11번 9부 집필 메모 | C8: 9부 2화 도입(22턴) 초안만 작성된 상태에서 중단 — 새로 쓰거나 이어 쓰기
A9: 시간 구조 | B9: 6부(약 1년 전) → 6부 12화 «Mañana, a las cinco» → 1부 1화(개소 1개월 후) → 2~5부 프레임(1부 직후 금요일들) → 7부 | C9: 6부 11화 제비뽑기 순서 Mateo→Javier→Sofía→Diego가 2~5부 프레임 순서
A10: 워크북 갱신 방침 | B10: 부가 끝날 때 또는 요청 시 갱신 | C10: v25 = 7부 1~5화 반영 + 턴 120→180 · v26 = 7부 8~12화·8부 전체·9부 1화 반영, 색·가상 인물·복선·의석 보강
A12: 2. 새 대화창 시작 방법
A13: 순서 | B13: 내용 | C13: 비고
A14: ① 올릴 파일 | B14: 이 워크북(v26) + 형식 틀 docx 1편(예: 9부1화_La_constitucion_de_la_Corporacion.docx 또는 7부7화_Represalias.docx) | C14: 7부부터는 프레임 없는 본편 → 직전 화 docx를 틀로. 연속성이 중요하면 직전 2~3화도 함께
A15: ② 요청 예시 | B15: "7부 1화 만들어. 형식은 첨부한 6부12화 docx와 똑같이. 설정은 워크북 이어쓰기_가이드 참고."
A16: ③ 작업 방식 | B16: 틀 docx 패키지(스타일·머리글·바닥글)를 복사해 document.xml 본문만 새로 생성. 머리글 «Madrid — N부 · N화 · 제목»과 core.xml 제목만 교체 | C16: 5·6부 24편 모두 이 방식
A17: ④ 점검 | B17: 1~6부: 120턴(15·30·30·30·15) · 7~9부: 180턴(표준 22·45·45·45·23, 8부는 사용자 확정, 9부 1화도 180) · 같은 화자 연속 없음(섹션 경계 포함) · 대사 약 22단어 이하(낭독 턴 예외: 기사·조문·선서문·연설) · 한국어 대역 누락 없음 · docx 유효성 검사 | C17: 화자명에 악센트가 있으면(RAMÓN 등) 턴 수 셀 때 정규식에 포함 · 7부 표지 «대사 180턴»으로 표기
A19: 3. 대본 docx 형식 사양
A20: 요소 | B20: 사양 | C20: 비고
A21: 파일명 | B21: N부M화_Titulo_con_guiones.docx (악센트 제거) | C21: 예: 6부12화_El_rotulo.docx
A22: 표지 | B22: MADRID / 스페인어 낭독 교재 / N부 · M화 / 제목(굵은 이탤릭 20pt, 1F3864) / 부제 / «대사 N턴 · 난이도 … · 배경: …»(N=120, 7부부터 180) / «지문 없이 대사만으로 구성 · 스페인어 본문 + 한국어 대역» / 등장인물(이름 굵게 + 설명) / ※ 도입 설명(표현 초점 포함 가능) | C22: 부제 — 본편: «한국어 제목 · 시점, 장소» / 프레임: «한국어 제목 · 프레임 — N부의 N번째 금요일»
A23: 섹션 | B23: «도입 — …», «장면 1 — …», «장면 2 — …», «장면 3 — …», «마무리 — …» (스페인어 대문자). 남색 굵게 12pt + 밑줄 | C23: 턴 수로 경계를 잡되, 경계 앞뒤 같은 화자 금지
A24: 대사 1턴 | B24: ① 화자명(대문자, 굵게, 화자 색, 10pt) + 공백 3칸 + 스페인어(11pt, 1A1A1A) ② 한국어 대역(9pt, 808080 이탤릭), 들여쓰기 200 | C24: 지문 없음 — 시간·장소는 대사로 (Pepa·Ramón의 «Informo»가 주로 담당)
A25: 마지막 쪽 | B25: 쪽 나눔 → «다음 화 예고» + 한 줄 | C25: 부의 마지막 화는 다음 부 1화를 예고
A26: 난이도 | B26: 1부 B1 · 2~5부 B2~C1 · 6부 B2 · 7부 이후 아크_구성계획 기준 | C26: 6부 화별 표현 초점을 ※ 줄에 적음
A28: 4. 화자 색 (7부부터 고정 팔레트)
A29: 화자 | B29: 색 (hex) | C29: 비고
A30: DIEGO | B30: 2E75B6
A31: MATEO | B31: C55A11
A32: JAVIER | B32: 525252
A33: SOFÍA | B33: 38761D
A34: CARMEN | B34: 0B5394
A35: PEPA | B35: AA3939
A36: ANSELMO | B36: 6D4C41 | C36: 5부 프레임은 7F6000, 6부 4화는 8E24AA였음
A37: RAMÓN | B37: 7F6000 | C37: Anselmo와 같은 화에 나오면 Anselmo를 6D4C41로
A38: NIEVES | B38: 8E24AA
A39: RAIMUNDO | B39: 7F7F7F
A40: INÉS | B40: C00000
A41: TOMÁS | B41: BF8F00 | C41: 6부 9화만 8E24AA
A42: LUCÍA | B42: B45F06
A43: GONZALO | B43: 0E7C86
A44: CERVANTES | B44: 제안: 1F3864 계열 피하고 4E342E
A45: PICASSO (7부~) | B45: 제안: E69138
A46: KARIM (재등장 가상인물) | B46: 5B9BD5 | C46: 6부 12화부터 고정. Fátima의 남편
A47: BILAL (재등장 가상인물) | B47: A64D79 | C47: 7부 4화부터 고정. Karim의 친구
A48: 가상·단역 | B48: 5B9BD5 · A64D79 · 7030A0 · 7F7F7F 중 화 안 중복 없게 | C48: Quintana 7030A0 고정 권장 · Karim·Bilal은 위 전용 색 사용 · 7F7F7F는 Raimundo와 겹치므로 단역에 쓰지 않기 · 일회성 인물은 5B9BD5·A64D79·7030A0 중 화 안 중복 없게 · 9부 재등장 인물 색은 아래 두 행
A49: MILAGROS (9부 시의원) | B49: A0522D | C49: 9부 1화부터 고정. 명부 3번 시의원
A50: IKER (9부 시의원) | B50: A64D79 | C50: 9부 1화부터 고정 권장. 같은 화에 Bilal이 나오면 Bilal에 다른 색
A52: 5. 5부 확정 설정 · 수치
A53: 항목 | B53: 내용 | C53: 출처
A54: 시간선 | B54: 2화 9년 전(입사 25세) → 3화 8년 전(매니저 28세) → 4~11화 2년 전(프린시펄 약 34세). 사직은 1월(보너스 3월 지급 전). | C54: 5부 2·3·4·11화
A55: Cenit | B55: 카스테야나 대로 32층, Sala Norte, 유리 회의실 «la pecera». 대표 파트너 Enrique Mazón. «Nuestro out casi siempre es el in de otra empresa». | C55: 2·4·11화
A56: Almudena Roig | B56: 2화 매니저 → 4화 파트너. 서른두 살에 바야돌리드 공장 폐쇄(200명)를 거절했고 다른 사람이 3주 만에 해냄 → '거의'가 9년. 냉소 질문 최종 답(11화): 정직한 줄 알았으나 위험한 쪽. | C56: 2·4·6·11화
A57: Meridiano Movilidad | B57: 직원 2,300, 연 비용 2억 1,400만(인건비 61·연료 18·정비 11·기타 10%). 목표 18%=3,850만. 1인 4만 6천 → 전부 인력이면 840명. | C57: 4화
A58: 모델·C47 | B58: 비인력 레버 1,950만(경유 650만·구매 400만·노선·차고지 Alcorcón→Leganés·중정비 외주). A 290(14%) · B 412(18.1%) · C 560(22%). C열=인원, 47행=합계. 기준 «Menor coste de salida». | C58: 6화
A59: ERE | B59: Cristina Llorente(노무) 주관. 노조 4안. 초과근무 310만=67개 자리. 합의 345명, 희망퇴직 35일치, Nieves 노조 미서명. | C59: 7·10화
A60: 유출·상담 | B60: 새벽 1시 52분 자동완성 «N»→Nieves. 35세 미만 22%→56%, 5년 미만 268, 임시직 58/58, 55세 이상 9. Lucía 첫 상담, 숙제 "숫자 아닌 것 하루 하나". | C60: 8화
A61: 파업·해고 | B61: 14일, 필수 유지 40/20%. 영상+비밀유지로 Nieves 징계 해고, 블랙리스트. Diego의 진술을 Almudena가 막음(이카로 1·2 해지 위험). | C61: 10화
A62: Yolanda Prieto | B62: 29세, 딸 둘, 헤타페 노선, 근속 3년, 212행. 345명에 없음(잔류). | C62: 7·8·10·11·12화
A63: 사직 | B63: 보너스 5만 5천(412명당 134유로)을 포기. Quintana의 이카로 2(물류·청소·경비 3사 약 6천 명) 거절. 사직서 «Algunos, demasiado bien aprendidos». C47 한 장 인쇄. | C63: 11화
A64: 프레임 요약 | B64: 5화 엑셀 한 장·Carmen의 이메일 해고 과거, 9화 «Cuatrocientos doce», 12화 Yolanda 결과·Rueda 공방 폐업·초록 포스터. | C64: 5·9·12화
A66: 6. 6부 확정 설정 · 수치
A67: 항목 | B67: 내용 | C67: 출처
A68: 14동 | B68: Vallecas, 엘리베이터 없음, 5층×4 + 1층 2 = 22가구. 1층 왼쪽 진료소(화·금, 약 900명), 오른쪽 옛 잡화점(총회 장소). 철문 빈집 4(6천 유로 cash for keys: 1층 Luisa, 3층 루마니아 가족, 젊은 부부 둘). 2층 A Carmen(곰팡이 "포르투갈"), 3층 B Nieves, 4층 C Marina, 5층 A Ramón, 5층 Pura(88). | C68: 1·3화
A69: Fondo Cardinal | B69: SOCIMI, 마드리드 건물 38채. 14동 310만 유로, "퇴거 진행 중". 메리디아노 살루드→카르디날 홀딩스 4천만 유로 0.5%(시장 약 5%). 카르디날 홀딩스 단독 관리자 = 인베르시오네스 메리디아노(상업등기 공보). | C69: 5·8화
A70: 같은 이름 | B70: Mateo(조항·고객 Grupo Meridiano) / Javier(산 바르톨로메 → 메리디아노 살루드, 병상 인센티브, Nilda) / Sofía(감사 의견 → 병원 계약 확정 + 이카로 착수) / Diego(병원 효율 발표, 이카로, 조항용 시나리오 템플릿). | C70: 6화
A71: Fátima 가족 | B71: 1층 C. Karim(이카로 정비 외주 해고 → 6부 12화 모라탈라스 오토바이 정비소 정규직). Adam 9, Salma, Yusuf 4(천식). 목요일 9시 집행 → 정지 결정. | C71: 7·8·9·12화
A72: 집행 정지 | B72: 취약·대안 없음 → 정지, 12월 31일까지(해마다 연장). 임대인 2채 이하 예외 → 펀드엔 해당 없음. «Es un respiro, no una victoria». | C72: 8·9화
A73: 사무소 | B73: 라바피에스, Eusebio Palacios(소규모 임대인, 홀아비) 건물. 1층 Casa Pepa(1994년 마놀로가 칠한 간판), 2층 약 60㎡. 월세 1,300(가게 700·사무실 600)+매일 8시 커피+일요일 토르티야, 5년. 은행 보증서는 Gonzalo가 옛 인턴 지점장과. 명판 «El Despacho de Lavapiés. Primera planta. Llame fuerte». | C73: 10·12화
A74: 식탁의 규칙 | B74: 1 낼 수 없는 사람은 안 내고 두 번 묻지 않는다 · 2 회의는 다섯 시 정각(Pepa의 쉬는 시간) · 3 금요일 한 명씩 이야기, 오늘은 안 돼 가능 · 4 아무도 숫자가 아니다 · 5 읽지 않은 것에 서명하지 않는다 · 6 진실은 면전에서 · 7 어디서 왔는지 묻지 않고 뭘 먹고 싶은지 묻는다 · 각주: 매트릭스 금지, Anselmo=청하지 않은 고문 · Gonzalo: 1유로마다 영수증 · Inés: 출처 둘+타당한 이유 없이 밖으로 안 나감. | C74: 11화
A75: 합류 순서 | B75: Carmen·Marina(1) → Nieves·Ramón(3) → Pepa·Anselmo(4) → Raimundo·Inés(8) → Tomás·Lucía(9) → Gonzalo(10). Carmen 인턴(11). | C75: 6부
A76: 시그니처 사용 | B76: Diego «Pongámoslo en una ma—» 두 번 자제. «Vale, sin diapositivas»는 13부 6화까지 보존(6부에서 Diego는 쓰지 않음). Anselmo «No está mal» 미사용. Ramón «Sin novedad» 말버릇으로만. Tomás 첫 연설 «Hoy nadie se ha ido. Y nadie se va a ir solo.» | C76: 전체
A78: 7. 7부 집필 메모 (Picasso 합류)
A79: 항목 | B79: 내용 | C79: 주의
A80: Picasso 설정 | B80: Cervantes에 이은 두 번째 "설명되지 않는 부활". 법적으로 죽은 사람이라 서명할 수 없는 "가장 비싼 서명" ↔ Sofía. 마드리드 연결: 산 페르난도 왕립 아카데미(1897), 잡지 «Arte Joven»(1901), 게르니카(레이나 소피아). 7부 1화에서 Casa Pepa에 손님으로 등장, Ramón이 수습 열쇠를 내줌(합류 완료). | C80: 실제 발언 창작 인용 금지. 작품은 말로만 묘사. 여성 관계 비판은 Carmen·Nieves·Lucía가 정면으로
A81: 부별 역할(제안) | B81: 7부 2화에서 접수 매트릭스에 색칠(완료) · 7부 시위 포스터(Nieves와, 예정) · 8부 당 상징 부탁을 망설임 · 11부 국방비 논쟁에서 게르니카 · 13부 귀환 | C81: Franco는 부재로만(Anselmo·Ramón 세대 회상), El Cid는 인용으로만(«¡Dios, qué buen vassallo, si oviesse buen señor!»)
A82: 수용 장치 | B82: 6부 11화 Pepa의 규칙 7 + Raimundo «존재하지 말아야 할 사람까지» | C82: Cervantes와의 첫 대면을 7부 초반에
A83: 이어받을 실 | B83: Sofía의 USB + 상업등기(복선 44, 7부 5화 회수 완료) · Gonzalo의 카르디날 홀딩스(45, 7부 5화 회수 완료) · Nieves 무효 소송 계류 · Karim 분할 상환(6부 12화 계속 진행, 7부 4화 Bilal 소개) · Inés의 두 번째 출처(국립도서관 연차 보고서, 확보 완료·미발표) · 이카로 2 해고(50, 7부 1화 발표 확인) | C83: 7부 6화(El expediente)에서 이 실들을 모아 querella 작성 예정
A84: 호칭 | B84: 네 사람 상호 tú. Carmen→네 사람 usted(인턴), Diego→Carmen usted(→5부 5화에서 tú, 시간순으론 7부 이후) | C84: 5부 5화 프레임 시점이 7부보다 앞인지 뒤인지 확인
A86: 8. 5·6부 가상 인물 부록
A87: 이름 | B87: 소속·역할 / 등장 | C87: 말투·호칭
A88: Almudena Roig | B88: Cenit 매니저→파트너 · 5부 2·4·6·7·8·10·11 | C88: 간결·냉소, Diego와 tú
A89: Marcos | B89: Diego 입사 동기 → Meridiano Movilidad 경영관리 · 5부 2·4·6·7 | C89: 숫자로 말함, Diego와 tú
A90: Julián·Alba·Mariano·Rafa Rueda | B90: Vallecas 가구 공방 · 5부 3 (6부 1: 여름에 폐업) | C90: Julián은 usted+"hijo", Alba «Quítese el reloj»
A91: Ernesto Lastra | B91: GM 재무 담당 이사 · 5부 4·6 | C91: «Seré breve», usted
A92: Fermín Robles | B92: Meridiano Movilidad 운영, 31년 차, 헤타페 노선 기사 출신, 3월 은퇴 · 5부 4·7·10·11 | C92: 속담(«Quien avisa no es traidor», «Mal de muchos…», «Más vale ponerse una vez colorado…»), Diego에게 tú
A93: Irene | B93: Cenit 신입 애널리스트 · 5부 6·8·11 | C93: 용어를 되묻고 받아 적음
A94: Borja | B94: Cenit 시니어 어소시에이트 · 5부 6 | C94: 농담·냉소
A95: Cristina Llorente | B95: Meridiano Movilidad 노무 담당 이사 · 5부 7·8·10 | C95: 절차적, 정중
A96: Yolanda Prieto | B96: 헤타페 노선 기사, 29세, 딸 둘 · 5부 7·8·10·11·12 | C96: 직설적, «No me lo diga»
A97: Enrique Mazón | B97: Cenit 대표 파트너 · 5부 11 | C97: Diego에게 tú
A98: 경비원 | B98: Cenit 건물 · 5부 4·11 | C98: 단역
... A103: Manolo | B103: Pepa의 고인 남편, 1994년 간판 · 6부 12 (언급) | C103: —
A105: 9. 7부 1~5화 신규 가상 인물 부록
A106: 이름 | B106: 소속·역할 / 등장 | C106: 말투·호칭
A107: Bilal | B107: Karim의 친구, 건설 노동자, 3년째 서류 없음 · 7부 4화(도입)·5화(언급) | C107: 정중, usted. 색 A64D79 고정
A108: Karim | B108: Fátima의 남편, 정비공 (6부 12화부터 재등장) · 7부 1·4화 | C108: Pepa·규칙 7을 인용. 색 5B9BD5 고정
A109: Milagros | B109: Grupo Meridiano 청소 협력업체(Limpiezas Tajo Norte, 가상) 노동자 대표 · 7부 2화 | C109: 직설적, Nieves와 tú
A110: Ángeles | B110: 79세 세입자, Ave María 거리 · 7부 2화 | C110: 느리고 예의 바름, usted
A111: Iker | B111: 22세 무급 인턴(가짜 becario) · 7부 2화 | C111: 짧고 급함, 또래에게 tú
A112: Elena | B112: 34세, N4(성폭력 관련 법 소급) 사건 피해자 · 7부 3화 | C112: 절제된 어조, 스스로 거리를 두고 말함. 본인 동의 없이 재등장·인용 금지
A114: 10. 7부 8~12화 확정 설정 · 수치
A115: 항목 | B115: 내용 | C115: 출처
...

Sheet 캐릭터
A1: 캐릭터 바이블 — 15인
A2: La Vieja Guardia = Anselmo · Ramón · Raimundo | '대화문 장치' 열: 지문이 없으므로 이 인물이 말로 상황을 전달한다 | 등장 화 수·등급은 '등장비중' 시트에서 자동 조회 | 직책은 현실 직제 기준 제안 | 현안 담당 ID는 '현안_배치' 시트
A4: No | B4: 그룹 | C4: 이름 | D4: 약칭 | E4: 나이 (1부) | F4: 나이 (11부) | G4: 성별 | H4: 직업·신분 | I4: 전 소속 (가상) | J4: 결핍 (Herida) | K4: 말투 | L4: 시그니처 표현 | M4: 낭독 포인트 | N4: 대화문 장치 (지문 대체) | O4: 정치 직책 (8~12부, 제안) | P4: 1부 등장 방식 | Q4: 등장 화 수 | R4: 등급 | S4: 현안 담당 (ID)
A5: 1 | B5: 주력 4인 | C5: Mateo Ferrer Alcántara | D5: Mateo | E5: 39 | F5: =E5+개요!$C$11 | G5: 남 | H5: 변호사 (M&A·규제 전문) | I5: Aguirre & Salvat Abogados (전 파트너 후보) | J5: 승소율은 높지만, 자신이 이긴 강제 퇴거 사건 하나가 계속 마음에 걸린다. | K5: 문장이 완결되고 접속법이 정확한 격식체. 초반엔 차갑고 조항을 인용, 후반엔 연설가로 성장해 문장이 따뜻해진다. | L5: Vayamos por partes. Con todo respeto, eso no es lo que dice el artículo. (후반) No les pido que crean en mí. Les pido que lean el texto. (8~13부, 정치 연설) Caminante, no hay camino, se hace camino al andar. (Machado) | M5: 또박또박, 중저음. 쉼표마다 정확히 숨을 쉰다. | N5: 조항을 소리 내어 읽어 법적 상황을 설명한다 (예: «Artículo 24: …»). | O5: 당 대표(8부) → 하원의원·총리 후보(10부) → 총리 (Presidente del Gobierno) | P5: 본격 | Q5: =INDEX(등장비중!$O$5:$O$18,MATCH($D5,등장비중!$A$5:$A$18,0)) | R5: =INDEX(등장비중!$Q$5:$Q$18,MATCH($D5,등장비중!$A$5:$A$18,0)) | S5: P2·P3·N4
A6: 2 | B6: 주력 4인 | C6: Javier Molina Ríos | D6: Javier | E6: 41 | F6: =E6+개요!$C$11 | G6: 남 | H6: 응급의학과 전문의 | I6: Hospital Universitario San Bartolomé (가상) | J6: 살리지 못한 환자의 이름을 전부 외우고 있다. | K6: 문장이 짧고 명령형이 많다. 블랙유머. 화가 나면 오히려 조용해진다. | L6: Eso no es una estadística; es una persona. Primero, respira. He visto cosas peores un martes cualquiera. | M6: 빠른 템포, 짧은 호흡. 1부에서 B1 문장 길이를 지켜 주는 핵심 화자. | N6: 명령형으로 행동을 말하며 진행한다 (예: «Tensión, oxígeno, sala dos.»). 행동 묘사 지문을 대신한다. | O6: 자치의회 의원(9부) → 보건부 장관 (Ministro de Sanidad) | P6: 본격 | Q6: =INDEX(등장비중!$O$5:$O$18,MATCH($D6,등장비중!$A$5:$A$18,0)) | R6: =INDEX(등장비중!$Q$5:$Q$18,MATCH($D6,등장비중!$A$5:$A$18,0)) | S6: S3·S4·S2·N1
A7: 3 | B7: 주력 4인 | C7: Sofía Lozano Prieto | D7: Sofía | E7: 37 | F7: =E7+개요!$C$11 | G7: 여 | H7: 회계사 (감사·세무) | I7: Ochoa & Ruiz Auditores (전 시니어 파트너) | J7: 부정을 발견하고도 서명했던 기억. 다시는 서명하지 않겠다고 다짐한 사람. | K7: 건조하고 정확. 숫자를 정확한 단위로 읽는다. 비꼬는 유머. | L7: A ver los papeles. Esto no cuadra. Enséñame los números y te diré quién eres. | M7: 숫자를 읽을 때 속도를 일정하게 유지, 결론 문장에서 톤을 낮춘다. | N7: 숫자를 소리 내어 읽으며 상황을 전달하고, 어려운 말을 '번역'해 준다 (예: «Lo traduzco yo.»). | O7: 시의원(9부) → 부총리 겸 재무부 장관 (Hacienda) | P7: 본격 | Q7: =INDEX(등장비중!$O$5:$O$18,MATCH($D7,등장비중!$A$5:$A$18,0)) | R7: =INDEX(등장비중!$Q$5:$Q$18,MATCH($D7,등장비중!$A$5:$A$18,0)) | S7: E3·N2·E1
A8: 4 | B8: 주력 4인 | C8: Diego Navarro Beltrán | D8: Diego | E8: 36 | F8: =E8+개요!$C$11 | G8: 남 | H8: 전략 컨설턴트 (조직·정책 설계) | I8: Cenit Consultores (전 소속) | J8: 자신이 만든 구조조정 엑셀 한 칸이 수백 명의 실직이었음을 뒤늦게 알게 된다. | K8: 영어식 경영 용어가 섞인 빠른 말투 (alinear, escalable, impacto, stakeholders). 성장하며 쉬운 말로 바뀐다 — 이 변화 자체가 학습 포인트. | L8: Pongámoslo en una matriz. (후반) Vale, sin diapositivas: ¿qué necesitas? | M8: 초반엔 숨 가쁜 프레젠테이션 톤, 후반엔 느리고 솔직한 톤. | N8: 프레젠테이션식 브리핑으로 계획과 상황을 설명한다. | O8: 캠프 참모(8~10부) → 대통령실장 (Director del Gabinete de la Presidencia) | P8: 본격 | Q8: =INDEX(등장비중!$O$5:$O$18,MATCH($D8,등장비중!$A$5:$A$18,0)) | R8: =INDEX(등장비중!$Q$5:$Q$18,MATCH($D8,등장비중!$A$5:$A$18,0)) | S8: P1·E2·S1·N2
A9: 5 | B9: 올드보이 자문단 | C9: Anselmo Vidal de Arteaga | D9: Anselmo | E9: 74 | F9: =E9+개요!$C$11 | G9: 남 | H9: 은퇴 외교관 (전 주EU 대사) | I9: 외교부 (전 주EU 대사) — 파벌 싸움에 밀려 은퇴 | J9: 초대장이 오지 않는 전화기를 본다. 엄살 뒤에 진짜 병(만성 심부전)을 숨기고 있다. | K9: 우아하고 완곡. 조건법·접속법 과거를 자주 쓴다. 정중하게 독을 뿌리는 '가장 까칠하고 심술 맞은' 인물. 여럿에게는 ustedes. | L9: Permítame una precisión. Cuando yo era embajador… Discrepo, con todo el cariño. Qué manera de estropear un buen café. En mis tiempos, esto se arreglaba con una llamada. No está mal. (최고의 칭찬 — 복선) Este será mi último invierno. / Anótenlo en mi testamento. (고전 인용) Toda la vida es sueño, y los sueños, sueños son. (Calderón) — 11부: Nuestras vidas son los ríos que van a dar en la mar, que es el morir. (Manrique) | M9: 느리고 품위 있는 리듬. 문장 끝을 살짝 올리며 비꼰다. | N9: «Cuando yo era embajador…» 회상과 논평으로 분위기를 전달한다. 커피 불평으로 장소(Casa Pepa)를 알린다. | O9: 외교 자문 (11부 6화 사망) | P9: 준본격 (겨울 복선) | Q9: =INDEX(등장비중!$O$5:$O$18,MATCH($D9,등장비중!$A$5:$A$18,0)) | R9: =INDEX(등장비중!$Q$5:$Q$18,MATCH($D9,등장비중!$A$5:$A$18,0)) | S9: P2·E3
A10: 6 | B10: 올드보이 자문단 | C10: Ramón Iturbe Calleja | D10: Ramón | E10: 68 | F10: =E10+개요!$C$11 | G10: 남 | H10: 예편한 소장 (별 2개) | I10: 육군 (소장으로 예편) | J10: 방산 비리를 덮지 않아 별 하나를 더 달지 못했다. | K10: 단문과 명령형 중심. 군대식 보고 형식. | L10: Sin novedad. Esto se resuelve con logística, no con discursos. ¡Orden! | M10: 짧고 단단하게 끊는다. 볼륨보다 명료함. | N10: 보고 형식으로 현장 상황을 전달한다 (예: «Informo: …»). | O10: 캠프 총괄(8~10부) → 국가안보실장 (Departamento de Seguridad Nacional) | P10: 카메오 | Q10: =INDEX(등장비중!$O$5:$O$18,MATCH($D10,등장비중!$A$5:$A$18,0)) | R10: =INDEX(등장비중!$Q$5:$Q$18,MATCH($D10,등장비중!$A$5:$A$18,0)) | S10: N1·N3·S3·N5
A11: 7 | B11: 올드보이 자문단 | C11: Raimundo Salcedo Vera | D11: Raimundo | E11: 66 | F11: =E11+개요!$C$11 | G11: 남 | H11: 전 CNI 요원, 현 고서점 주인 | I11: CNI(국립정보센터) → 고서점 운영 | J11: 너무 많이 알아서 쫓겨났다. 지금은 고서점 안쪽 방에서 산다. | K11: 낮고 느리며, 결론을 직접 말하지 않고 '출처만 가리킨다'. 모두에게 tú — 그래서 더 위협적. 욕은 하지 않는다. | L11: Yo no he dicho nada. Pero mira en… No te lo digo. Te digo dónde está. Casi todo está en fuentes abiertas. Solo hay que saber leer. Búscalo tú. Eso no lo sabes por mí. Todo el mundo tiene un cajón que no abre. (고전 인용, 서지 톤) Polvo serán, mas polvo enamorado. Quevedo, soneto «Amor constante más allá de la muerte». | M11: 속삭이듯 낮은 음역. 문장 사이 호흡을 길게 둔다 (침묵 대신 출처 안내). | N11: 카드(ficha)를 구술한다 («Anota. Busca: … Dónde: …»). 손짓 대신 «Tercera balda, a tu izquierda.»처럼 서가 위치를 말한다. | O11: 정보기관 감독 개혁 자문 (CNI는 국방부 소속) | P11: 카메오 (고서점 주인·바 단골) | Q11: =INDEX(등장비중!$O$5:$O$18,MATCH($D11,등장비중!$A$5:$A$18,0)) | R11: =INDEX(등장비중!$Q$5:$Q$18,MATCH($D11,등장비중!$A$5:$A$18,0)) | S11: P3
A12: 8 | B12: 올드보이 자문단 | C12: Inés Carvajal | D12: Inés | E12: 52 | F12: =E12+개요!$C$11 | G12: 여 | H12: 탐사보도 기자 | I12: El Diario de la Capital (전 데스크) → 독립매체 La Hoja Abierta | J12: 진실을 쓰다 쫓겨났고, 독립매체는 늘 적자다. | K12: 질문형 문장이 많고 빠르고 정확. 취재할 때는 usted, 친해지면 tú. | L12: Necesito dos fuentes. Eso, ¿lo puedes probar? Esto no sale de aquí. | M12: 뉴스 앵커 톤과 취재 현장의 거친 톤을 오간다. | N12: 인터뷰 질문으로 사건의 경위와 시간 경과를 끌어낸다. | O12: 커뮤니케이션 국무차관 (Secretaría de Estado de Comunicación) | P12: 카메오 | Q12: =INDEX(등장비중!$O$5:$O$18,MATCH($D12,등장비중!$A$5:$A$18,0)) | R12: =INDEX(등장비중!$Q$5:$Q$18,MATCH($D12,등장비중!$A$5:$A$18,0)) | S12: P3·N1
A13: 9 | B13: 올드보이 자문단 | C13: Dra. Lucía Bermejo | D13: Lucía | E13: 49 | F13: =E13+개요!$C$11 | G13: 여 | H13: 임상심리학자 (시간강사) | I13: 대학 시간강사 (교수 임용 3회 낙방) | J13: 논문은 많은데 세상이 알아주지 않아 자기 확신이 흔들린다. | K13: 차분하고 천천히 말하며, 상대의 말을 되받아 정리한다. | L13: ¿Y cómo te hace sentir eso? (다들 질색하는 반복 개그) Fíjate en lo que no dice. | M13: 부드럽고 낮은 톤, 일정한 속도. | N13: 상대의 말을 되받아 요약해 준다 → 대화의 정리·복습 역할. | O13: 메시지·정신건강 정책 자문 | P13: 카메오 | Q13: =INDEX(등장비중!$O$5:$O$18,MATCH($D13,등장비중!$A$5:$A$18,0)) | R13: =INDEX(등장비중!$Q$5:$Q$18,MATCH($D13,등장비중!$A$5:$A$18,0)) | S13: N4·N5·S2
A14: 10 | B14: 서민·청년 | C14: Josefa «Pepa» Ortega | D14: Pepa | E14: 63 | F14: =E14+개요!$C$11 | G14: 여 | H14: 바 사장 (Casa Pepa, 30년 운영) | I14: Casa Pepa, Lavapiés → 사무소 1층으로 이전 | J14: 임대료 폭등으로 가게를 잃었다. 사무소 1층이 새 아지트가 된다. | K14: 마드리드 토박이 구어체. 누구에게나 tú, 'hijo/hija'라고 부른다. | L14: Sentaos, que os pongo algo. Con el estómago vacío no se piensa. ¡Anda ya! Invita la casa. (refranes) No hay mal que por bien no venga. / Dime con quién andas y te diré quién eres. | M14: 따뜻하고 넉넉한 톤. 1부 B1 대화의 기준점. | N14: 장면을 여는 사람: 시간·장소·식사를 말로 알린다 (예: «Son las cinco. Reunión en mi mesa.»). | O14: 소상공인 정책 자문 (비공식) | P14: 본격 | Q14: =INDEX(등장비중!$O$5:$O$18,MATCH($D14,등장비중!$A$5:$A$18,0)) | R14: =INDEX(등장비중!$Q$5:$Q$18,MATCH($D14,등장비중!$A$5:$A$18,0)) | S14: E1·S2·E2
A15: 11 | B15: 서민·청년 | C15: Nieves Barroso | D15: Nieves | E15: 55 | F15: =E15+개요!$C$11 | G15: 여 | H15: 전 대중교통 노조위원장 | I15: 마드리드 대중교통 노조 (파업 책임으로 해고·블랙리스트) | J15: 파업 책임으로 해고되어 블랙리스트에 올랐지만 후회하지 않는다. | K15: 거칠고 직설적. 구호형 문장. 청중에겐 «compañeros y compañeras». | L15: ¡Aquí no se rinde nadie! Esto se arregla en la calle. No me toques las narices. | M15: 큰 볼륨, 강한 억양. 문장 끝을 내리꽂는다. | N15: 구호와 함성으로 군중·현장의 분위기를 전달한다. | O15: 사회적 대화(Diálogo Social) 자문 | P15: 카메오 | Q15: =INDEX(등장비중!$O$5:$O$18,MATCH($D15,등장비중!$A$5:$A$18,0)) | R15: =INDEX(등장비중!$Q$5:$Q$18,MATCH($D15,등장비중!$A$5:$A$18,0)) | S15: S1·S2·E2
A16: 12 | B16: 서민·청년 | C16: Tomás Iglesias | D16: Tomás | E16: 44 | F16: =E16+개요!$C$11 | G16: 남 | H16: 20년째 작가 지망생 (연설문 작가) | I16: 편의점 야간 알바·대필 (원고를 다섯 번 갈아엎음) | J16: 자신의 첫 문장이 늘 불안하다. | K16: 은유를 남발하다가 핀잔을 듣는다. 결정적 순간에는 가장 단순한 문장이 나온다. | L16: Es que la primera frase lo es todo. Dejadme buscar una metáfora. (고전 인용, 도피처) Verde que te quiero verde. (Lorca) / ¿Qué es poesía?… Poesía… eres tú. (Bécquer) | M16: 시적일 때는 느리고 감정적, 평소엔 머뭇거리는 톤. | N16: 초고를 소리 내어 읽으며 연설·글의 내용을 보여 준다. | O16: 연설 담당관 (Gabinete) | P16: 카메오 (고서점 손님 — Raimundo와 연결) | Q16: =INDEX(등장비중!$O$5:$O$18,MATCH($D16,등장비중!$A$5:$A$18,0)) | R16: =INDEX(등장비중!$Q$5:$Q$18,MATCH($D16,등장비중!$A$5:$A$18,0)) | S16: N1·N5
... A18: 14 | B18: 금융 | C18: Gonzalo Arévalo Sanz | D18: Gonzalo | E18: 58 | F18: =E18+개요!$C$11 | G18: 남 | H18: 전 은행 지점장 | I18: Banco Ibérico (25년 근속) | J18: 불법 대출 공모를 내부 고발하다 해고되었고, 가족에게도 이유를 다 말하지 못했다. | K18: 정중하고 조심스러운 은행원식 완곡어법. 비유가 실무적 («돈은 물처럼 낮은 곳으로 흐릅니다»). | L18: Sigue el dinero. El dinero siempre deja huella. Cuando yo dirigía la sucursal… | M18: 차분하고 신중하게. 숫자와 계좌 경로를 설명할 때는 또렷하게. | N18: 돈의 경로를 «De A pasa a B…»식으로 말로 그려 준다. | O18: 금융 개혁 자문 | P18: 카메오 (의뢰인) | Q18: =INDEX(등장비중!$O$5:$O$18,MATCH($D18,등장비중!$A$5:$A$18,0)) | R18: =INDEX(등장비중!$Q$5:$Q$18,MATCH($D18,등장비중!$A$5:$A$18,0)) | S18: E3·N2
A19: 15 | B19: 특별 인물 | C19: Miguel de Cervantes Saavedra | D19: Cervantes | E19: 68 | F19: =E19+개요!$C$11 | G19: 남 | H19: 소설가·극작가 (부활 후 무직 → 사무소 자료실 담당) | I19: 무적함대 식량·세금 징수관 (역사적 배경, 가상 반영) → 1616년 사망 → 3부에서 부활 | J19: 살아서는 가난·투옥·인정받지 못함. 이제 모두가 이름은 아는데 아무도 그가 '그 사람'이라 믿지 않고, 왜 돌아왔는지 본인도 모른다. | K19: 어른에게는 vuestra merced(3인칭 동사), 젊은이에게는 vos(-áis/-éis). venta·brebaje·ingenio·mas·había de 등 옛 어휘. 철자는 현대식. | L19: Para servir a vuestras mercedes. Jamás escribí tal cosa. (고전 인용, 본인 작품만 정확히) «Cada uno es hijo de sus obras.» (Quijote 1부 4장) | M19: 정중한 고어체 리듬, 현대 철자로 알아듣기 쉽게. vuestra merced/vos 사용을 낭독 포인트로 삼는다. | N19: 현대 사물을 옛말로 묘사하면 주변 인물이 현대어로 정정해 준다 (양방향 어휘 학습 장치). 가짜 명언은 본인이 직접 교정한다. | O19: (7부) 민사등록·신원 회복 의뢰인 → (8부) 창당 발기인 → (10부) 하원의원(Madrid 명부) → (11~12부) 문화부 장관 (Ministro de Cultura), 12부 Anselmo 사후 외교 비공식 자문 겸임 | P19: 미등장 (3부 1화부터 등장) | Q19: =INDEX(등장비중!$O$5:$O$19,MATCH($D19,등장비중!$A$5:$A$19,0)) | R19: =INDEX(등장비중!$Q$5:$Q$19,MATCH($D19,등장비중!$A$5:$A$19,0)) | S19: —

Sheet 등장비중
A1: 인물별 등장 비중 (부별 등장 화 수)
A2: 등장 화 = 대사가 있는 화 수 (기획용 초안). 파란 숫자는 직접 입력값이며 수정하면 합계·비중·등급이 자동 갱신됩니다.
A4: 인물 (약칭) | B4: 1부 사무소 | C4: 2부 Mateo | D4: 3부 Javier | E4: 4부 Sofía | F4: 5부 Diego | G4: 6부 만남 | H4: 7부 전면전 | I4: 8부 창당 | J4: 9부 지방 의회 | K4: 10부 총선·총리 | L4: 11부 국정 I | M4: 12부 국정 II | N4: 13부 귀환 | O4: 합계 | P4: 비중 | Q4: 등급 | R4: 검증 (≤부당 화 수) | S4: 단독 중심 화 목표 (조연)
A5: Mateo | B5: 7 | C5: 12 | D5: 3 | E5: 3 | F5: 3 | G5: 12 | H5: 11 | I5: 12 | J5: 11 | K5: 11 | L5: 10 | M5: 3 | N5: 10 | O5: =SUM(B5:N5) | P5: =O5/개요!$C$7 | Q5: =IF(P5>=$B$23,"주연",IF(P5>=$B$24,"준주연",IF(P5>=$B$25,"핵심 조연","조연"))) | R5: =IF(MAX(B5:N5)<=개요!$C$6,"OK","확인") | S5: —
A6: Javier | B6: 6 | C6: 3 | D6: 12 | E6: 3 | F6: 3 | G6: 12 | H6: 10 | I6: 10 | J6: 8 | K6: 10 | L6: 10 | M6: 2 | N6: 9 | O6: =SUM(B6:N6) | P6: =O6/개요!$C$7 | Q6: =IF(P6>=$B$23,"주연",IF(P6>=$B$24,"준주연",IF(P6>=$B$25,"핵심 조연","조연"))) | R6: =IF(MAX(B6:N6)<=개요!$C$6,"OK","확인") | S6: —
A7: Sofía | B7: 7 | C7: 3 | D7: 3 | E7: 12 | F7: 3 | G7: 12 | H7: 11 | I7: 10 | J7: 10 | K7: 11 | L7: 10 | M7: 8 | N7: 9 | O7: =SUM(B7:N7) | P7: =O7/개요!$C$7 | Q7: =IF(P7>=$B$23,"주연",IF(P7>=$B$24,"준주연",IF(P7>=$B$25,"핵심 조연","조연"))) | R7: =IF(MAX(B7:N7)<=개요!$C$6,"OK","확인") | S7: —
A8: Diego | B8: 6 | C8: 3 | D8: 3 | E8: 3 | F8: 12 | G8: 12 | H8: 10 | I8: 11 | J8: 10 | K8: 10 | L8: 9 | M8: 3 | N8: 9 | O8: =SUM(B8:N8) | P8: =O8/개요!$C$7 | Q8: =IF(P8>=$B$23,"주연",IF(P8>=$B$24,"준주연",IF(P8>=$B$25,"핵심 조연","조연"))) | R8: =IF(MAX(B8:N8)<=개요!$C$6,"OK","확인") | S8: —
A9: Anselmo | B9: 4 | C9: 2 | D9: 2 | E9: 2 | F9: 2 | G9: 7 | H9: 9 | I9: 7 | J9: 9 | K9: 9 | L9: 9 | M9: 0 | N9: 3 | O9: =SUM(B9:N9) | P9: =O9/개요!$C$7 | Q9: =IF(P9>=$B$23,"주연",IF(P9>=$B$24,"준주연",IF(P9>=$B$25,"핵심 조연","조연"))) | R9: =IF(MAX(B9:N9)<=개요!$C$6,"OK","확인") | S9: 2
A10: Ramón | B10: 3 | C10: 1 | D10: 1 | E10: 1 | F10: 1 | G10: 6 | H10: 8 | I10: 9 | J10: 8 | K10: 8 | L10: 7 | M10: 4 | N10: 7 | O10: =SUM(B10:N10) | P10: =O10/개요!$C$7 | Q10: =IF(P10>=$B$23,"주연",IF(P10>=$B$24,"준주연",IF(P10>=$B$25,"핵심 조연","조연"))) | R10: =IF(MAX(B10:N10)<=개요!$C$6,"OK","확인") | S10: 2
A11: Raimundo | B11: 3 | C11: 1 | D11: 1 | E11: 2 | F11: 1 | G11: 5 | H11: 8 | I11: 6 | J11: 8 | K11: 8 | L11: 7 | M11: 3 | N11: 7 | O11: =SUM(B11:N11) | P11: =O11/개요!$C$7 | Q11: =IF(P11>=$B$23,"주연",IF(P11>=$B$24,"준주연",IF(P11>=$B$25,"핵심 조연","조연"))) | R11: =IF(MAX(B11:N11)<=개요!$C$6,"OK","확인") | S11: 2
A12: Inés | B12: 2 | C12: 1 | D12: 1 | E12: 3 | F12: 1 | G12: 5 | H12: 10 | I12: 7 | J12: 8 | K12: 8 | L12: 7 | M12: 3 | N12: 7 | O12: =SUM(B12:N12) | P12: =O12/개요!$C$7 | Q12: =IF(P12>=$B$23,"주연",IF(P12>=$B$24,"준주연",IF(P12>=$B$25,"핵심 조연","조연"))) | R12: =IF(MAX(B12:N12)<=개요!$C$6,"OK","확인") | S12: 2
A13: Lucía | B13: 1 | C13: 1 | D13: 2 | E13: 1 | F13: 2 | G13: 4 | H13: 7 | I13: 8 | J13: 6 | K13: 7 | L13: 6 | M13: 2 | N13: 7 | O13: =SUM(B13:N13) | P13: =O13/개요!$C$7 | Q13: =IF(P13>=$B$23,"주연",IF(P13>=$B$24,"준주연",IF(P13>=$B$25,"핵심 조연","조연"))) | R13: =IF(MAX(B13:N13)<=개요!$C$6,"OK","확인") | S13: 2
A14: Pepa | B14: 12 | C14: 2 | D14: 2 | E14: 2 | F14: 2 | G14: 5 | H14: 8 | I14: 6 | J14: 4 | K14: 5 | L14: 8 | M14: 3 | N14: 10 | O14: =SUM(B14:N14) | P14: =O14/개요!$C$7 | Q14: =IF(P14>=$B$23,"주연",IF(P14>=$B$24,"준주연",IF(P14>=$B$25,"핵심 조연","조연"))) | R14: =IF(MAX(B14:N14)<=개요!$C$6,"OK","확인") | S14: 2
A15: Nieves | B15: 2 | C15: 1 | D15: 2 | E15: 1 | F15: 3 | G15: 5 | H15: 9 | I15: 8 | J15: 6 | K15: 6 | L15: 7 | M15: 2 | N15: 6 | O15: =SUM(B15:N15) | P15: =O15/개요!$C$7 | Q15: =IF(P15>=$B$23,"주연",IF(P15>=$B$24,"준주연",IF(P15>=$B$25,"핵심 조연","조연"))) | R15: =IF(MAX(B15:N15)<=개요!$C$6,"OK","확인") | S15: 2
A16: Tomás | B16: 1 | C16: 1 | D16: 1 | E16: 1 | F16: 1 | G16: 4 | H16: 6 | I16: 9 | J16: 7 | K16: 9 | L16: 7 | M16: 4 | N16: 7 | O16: =SUM(B16:N16) | P16: =O16/개요!$C$7 | Q16: =IF(P16>=$B$23,"주연",IF(P16>=$B$24,"준주연",IF(P16>=$B$25,"핵심 조연","조연"))) | R16: =IF(MAX(B16:N16)<=개요!$C$6,"OK","확인") | S16: 2
A17: Carmen | B17: 12 | C17: 4 | D17: 4 | E17: 4 | F17: 4 | G17: 8 | H17: 10 | I17: 10 | J17: 9 | K17: 9 | L17: 10 | M17: 3 | N17: 12 | O17: =SUM(B17:N17) | P17: =O17/개요!$C$7 | Q17: =IF(P17>=$B$23,"주연",IF(P17>=$B$24,"준주연",IF(P17>=$B$25,"핵심 조연","조연"))) | R17: =IF(MAX(B17:N17)<=개요!$C$6,"OK","확인") | S17: —
A18: Gonzalo | B18: 2 | C18: 1 | D18: 1 | E18: 3 | F18: 1 | G18: 5 | H18: 8 | I18: 5 | J18: 7 | K18: 7 | L18: 9 | M18: 1 | N18: 6 | O18: =SUM(B18:N18) | P18: =O18/개요!$C$7 | Q18: =IF(P18>=$B$23,"주연",IF(P18>=$B$24,"준주연",IF(P18>=$B$25,"핵심 조연","조연"))) | R18: =IF(MAX(B18:N18)<=개요!$C$6,"OK","확인") | S18: 2
A19: Cervantes | B19: 0 | C19: 0 | D19: 4 | E19: 2 | F19: 2 | G19: 6 | H19: 6 | I19: 8 | J19: 5 | K19: 8 | L19: 6 | M19: 9 | N19: 8 | O19: =SUM(B19:N19) | P19: =O19/개요!$C$7 | Q19: =IF(P19>=$B$23,"주연",IF(P19>=$B$24,"준주연",IF(P19>=$B$25,"핵심 조연","조연"))) | R19: =IF(MAX(B19:N19)<=개요!$C$6,"OK","확인") | S19: 2
A20: 부별 연인원 (합계) | B20: =SUM(B5:B19) | C20: =SUM(C5:C19) | D20: =SUM(D5:D19) | E20: =SUM(E5:E19) | F20: =SUM(F5:F19) | G20: =SUM(G5:G19) | H20: =SUM(H5:H19) | I20: =SUM(I5:I19) | ... O20: =SUM(O5:O19) | S20: =SUM(S5:S19)
A22: 등급 기준 (비중 ≥)
A23: 주연 | B23: 0.69 | C23: ← 기준값은 등급 구분(주연 4 / 준주연 1 / 핵심 조연 4 / 조연 5)을 재현하도록 정한 제안값입니다.
A24: 준주연 | B24: 0.6
A25: 핵심 조연 | B25: 0.4
A26: 조연 | B26: 그 미만
A28: 배분 원칙
A29: 1. 1부는 개소 1개월 후 시점: Carmen·Pepa가 전 화에, 주력 4인은 사건별로 2~3인씩 교대 등장(전원 겹치지 않음). Anselmo 4화, Raimundo 3화(1·2·6화)로 자주 얼굴을 비추고 '이번 겨울이 마지막' 복선을 1화부터 깐다. 나머지는 사건마다 다른 조합으로 카메오.
A30: 2. 2~5부: 각 주인공이 자기 부 12화 전부에 나오고, 다른 주력 3인은 3화씩 스쳐 지나가며 6부 만남을 예고. Carmen은 4화씩 '사무소에서 이야기를 듣는 프레임'으로 등장해 회상을 잇는다.
A31: 3. 자문단은 과거와 겹치는 곳에만 배치: Nieves-5부(Diego의 구조조정 현장), Gonzalo·Inés-4부(Sofía의 감사 사건), Lucía-3부·5부(트라우마·번아웃 상담).
A32: 4. 자문단 본격 비중은 7~10부에서 최고치: 7부 Inés·Nieves(공론화·현장 조직), 8부 Tomás·Lucía·Ramón(선언문·메시지·캠프), 10부 Tomás·Inés·Raimundo(취임 연설·대변인·정보 감독).
A33: 5. 11부(국정 I)는 Anselmo가 9~12화에서 브뤼셀 직접 협상을 이끌며 최고치(9화)를 찍고 12화에서 사망한다. Gonzalo는 앞선 주거·금융 국내 현안 화에서 정점.
A34: 6. 12부(국정 II)는 Anselmo 사후: 1화 장례식에서 Ramón·Raimundo·Javier가 몰리고, Sofía·Tomás가 유작 메모를 이어받는 3화에서 비중이 오른다.
A35: 7. 13부(귀환, 구 12부)는 원형 구조: Carmen 12화 전부, Pepa 10화. Anselmo는 유언장·회상으로 3화, Mateo·Javier·Sofía·Diego는 사무소의 손님으로 9~10화 등장.
A36: 8. Anselmo는 11부 12화(브뤼셀 승리 직후)에서 사망한다. 12부 1화 장례식, 2·3화 유작 메모 승계, 13부 2화 유언장까지 이어진다.
A37: 9. 등장 화 수와 대사량은 다르다: Carmen은 약 67%지만 문장이 짧아 대사량은 Mateo의 절반 이하가 되게 하고, Anselmo·Tomás는 화당 대사가 길어도 된다.
A38: 10. 조연 9인은 화 전체의 중심이 되는 에피소드를 각자 2개 이상 배정(R열 목표). 자기 이야기가 한 번도 없으면 얇은 인물이 된다.
A39: 11. Lucía가 가장 얇다(약 36%): 3·5부 상담 장면을 늘리거나, 11부 Anselmo 애도 상담을 맡겨 서사를 넓히는 안을 검토.

Sheet 턴_설계
A1: 대화량 설계: 화당 120턴
A2: 한 화 = 대화 120턴, 전체 144화 = 17,280턴(기준값). 7부부터는 화당 180턴으로 상향(아래 39행 C39 참고). 점유율·평균 단어/턴·배율·낭독 속도는 가정값(파란 숫자)이며 수정하면 아래 표가 자동 갱신됩니다.
A4: 1. 기본 설정
A5: 화당 대화 턴 | B5: 120
A6: 낭독 속도 (단어/분, 가정) | B6: 130
A7: 총 화 수 | B7: =개요!$C$7
A8: 총 대화 턴 | B8: =B5*B7
A9: 턴 정의 | B9: 화자 표기 한 줄 = 1턴 (화자가 바뀌면 새 턴). 연설·조항·기사 낭독처럼 긴 발화도 1턴으로 센다.
A11: 2. 부별 화자 점유율 (턴 기준, 각 부의 합 = 100%)
A12: 인물 | B12: 평균 단어/턴 | C12: 1부 | D12: 2부 | E12: 3부 | F12: 4부 | G12: 5부 | H12: 6부 | I12: 7부 | J12: 8부 | K12: 9부 | L12: 10부 | M12: 11부 | N12: 12부
A13: Mateo | B13: 13 | C13: 0.13 | D13: 0.48 | E13: 0.03 | F13: 0.02 | G13: 0.02 | H13: 0.13 | I13: 0.14 | J13: 0.15 | K13: 0.08 | L13: 0.18 | M13: 0.15 | N13: 0.07
A14: Javier | B14: 8 | C14: 0.12 | D14: 0.03 | E14: 0.46 | F14: 0.04 | G14: 0.03 | H14: 0.12 | I14: 0.07 | J14: 0.08 | K14: 0.11 | L14: 0.06 | M14: 0.09 | N14: 0.06
A15: Sofía | B15: 11 | C15: 0.12 | D15: 0.04 | E15: 0.04 | F15: 0.46 | G15: 0.04 | H15: 0.12 | I15: 0.1 | J15: 0.09 | K15: 0.15 | L15: 0.08 | M15: 0.11 | N15: 0.07
A16: Diego | B16: 12 | C16: 0.12 | D16: 0.05 | E16: 0.03 | F16: 0.03 | G16: 0.46 | H16: 0.12 | I16: 0.06 | J16: 0.09 | K16: 0.08 | L16: 0.11 | M16: 0.08 | N16: 0.07
A17: Anselmo | B17: 14 | C17: 0.08 | D17: 0.04 | E17: 0.04 | F17: 0.04 | G17: 0.04 | H17: 0.04 | I17: 0.06 | J17: 0.05 | K17: 0.04 | L17: 0.06 | M17: 0.04 | N17: 0.02
A18: Ramón | B18: 7 | C18: 0.02 | D18: 0.01 | E18: 0.01 | F18: 0.01 | G18: 0.01 | H18: 0.05 | I18: 0.06 | J18: 0.06 | K18: 0.04 | L18: 0.08 | M18: 0.07 | N18: 0.06
A19: Raimundo | B19: 9 | C19: 0.02 | D19: 0.01 | E19: 0.01 | F19: 0.01 | G19: 0.01 | H19: 0.03 | I19: 0.06 | J19: 0.03 | K19: 0.04 | L19: 0.03 | M19: 0.05 | N19: 0.08
A20: Inés | B20: 10 | C20: 0.02 | D20: 0.01 | E20: 0.03 | F20: 0.04 | G20: 0.01 | H20: 0.03 | I20: 0.08 | J20: 0.06 | K20: 0.07 | L20: 0.05 | M20: 0.06 | N20: 0.05
A21: Lucía | B21: 9 | C21: 0.01 | D21: 0.01 | E21: 0.04 | F21: 0.01 | G21: 0.04 | H21: 0.03 | I21: 0.05 | J21: 0.06 | K21: 0.04 | L21: 0.05 | M21: 0.04 | N21: 0.05
A22: Pepa | B22: 9 | C22: 0.12 | D22: 0.04 | E22: 0.03 | F22: 0.03 | G22: 0.03 | H22: 0.05 | I22: 0.04 | J22: 0.05 | K22: 0.03 | L22: 0.04 | M22: 0.04 | N22: 0.13
A23: Nieves | B23: 10 | C23: 0.01 | D23: 0.02 | E23: 0.01 | F23: 0.01 | G23: 0.09 | H23: 0.05 | I23: 0.06 | J23: 0.08 | K23: 0.08 | L23: 0.06 | M23: 0.05 | N23: 0.05
A24: Tomás | B24: 12 | C24: 0.02 | D24: 0.01 | E24: 0.01 | F24: 0.01 | G24: 0.01 | H24: 0.03 | I24: 0.03 | J24: 0.08 | K24: 0.05 | L24: 0.07 | M24: 0.05 | N24: 0.05
... A27: 엑스트라(가상) | B27: 10 | C27: 0.03 | D27: 0.15 | E27: 0.17 | F27: 0.13 | G27: 0.12 | H27: 0.07 | I27: 0.07 | J27: 0.03 | K27: 0.05 | L27: 0.05 | M27: 0.04 | N27: 0.04
A28: 합계 | C28: =SUM(C13:C27) | D28: =SUM(D13:D27) | E28: =SUM(E13:E27) | F28: =SUM(F13:F27) | G28: =SUM(G13:G27) | H28: =SUM(H13:H27) | I28: =SUM(I13:I27) | J28: =SUM(J13:J27) | ... N28: =SUM(N13:N27)
A29: 검증 | C29: =IF(ROUND(C28,4)=1,"OK","확인") | D29: =IF(ROUND(D28,4)=1,"OK","확인") | E29: =IF(ROUND(E28,4)=1,"OK","확인") | F29: =IF(ROUND(F28,4)=1,"OK","확인") | G29: =IF(ROUND(G28,4)=1,"OK","확인") | H29: =IF(ROUND(H28,4)=1,"OK","확인") | I29: =IF(ROUND(I28,4)=1,"OK","확인") | J29: =IF(ROUND(J28,4)=1,"OK","확인") | ... N29: =IF(ROUND(N28,4)=1,"OK","확인")
A31: 3. 부별 턴·단어·낭독 시간 (수식)
A32: 부 | B32: 난이도 배율 | C32: 화당 턴 | D32: 부 총 턴 | E32: 평균 단어/턴 | F32: 화당 단어 | G32: 부 총 단어 | H32: 화당 낭독 (분) | I32: 부 총 낭독 (시간)
A33: 1부 | B33: 0.8 | C33: =$B$5 | D33: =C33*개요!$C$6 | E33: =SUMPRODUCT(C$13:C$27,$B$13:$B$27)*B33 | F33: =C33*E33 | G33: =F33*개요!$C$6 | H33: =F33/$B$6 | I33: =H33*개요!$C$6/60
A34: 2부 | B34: 1 | C34: =$B$5 | D34: =C34*개요!$C$6 | E34: =SUMPRODUCT(D$13:D$27,$B$13:$B$27)*B34 | F34: =C34*E34 | G34: =F34*개요!$C$6 | H34: =F34/$B$6 | I34: =H34*개요!$C$6/60
A35: 3부 | B35: 1 | C35: =$B$5 | D35: =C35*개요!$C$6 | E35: =SUMPRODUCT(E$13:E$27,$B$13:$B$27)*B35 | F35: =C35*E35 | G35: =F35*개요!$C$6 | H35: =F35/$B$6 | I35: =H35*개요!$C$6/60
A36: 4부 | B36: 1 | C36: =$B$5 | D36: =C36*개요!$C$6 | E36: =SUMPRODUCT(F$13:F$27,$B$13:$B$27)*B36 | F36: =C36*E36 | G36: =F36*개요!$C$6 | H36: =F36/$B$6 | I36: =H36*개요!$C$6/60
A37: 5부 | B37: 1 | C37: =$B$5 | D37: =C37*개요!$C$6 | E37: =SUMPRODUCT(G$13:G$27,$B$13:$B$27)*B37 | F37: =C37*E37 | G37: =F37*개요!$C$6 | H37: =F37/$B$6 | I37: =H37*개요!$C$6/60
A38: 6부 | B38: 1 | C38: =$B$5 | D38: =C38*개요!$C$6 | E38: =SUMPRODUCT(H$13:H$27,$B$13:$B$27)*B38 | F38: =C38*E38 | G38: =F38*개요!$C$6 | H38: =F38/$B$6 | I38: =H38*개요!$C$6/60
A39: 7부 | B39: 1 | C39: 180 | D39: =C39*개요!$C$6 | E39: =SUMPRODUCT(I$13:I$27,$B$13:$B$27)*B39 | F39: =C39*E39 | G39: =F39*개요!$C$6 | H39: =F39/$B$6 | I39: =H39*개요!$C$6/60
A40: 8부 | B40: 1.1 | C40: =$B$5 | D40: =C40*개요!$C$6 | E40: =SUMPRODUCT(J$13:J$27,$B$13:$B$27)*B40 | F40: =C40*E40 | G40: =F40*개요!$C$6 | H40: =F40/$B$6 | I40: =H40*개요!$C$6/60
A41: 9부 | B41: 1.1 | C41: =$B$5 | D41: =C41*개요!$C$6 | E41: =SUMPRODUCT(K$13:K$27,$B$13:$B$27)*B41 | F41: =C41*E41 | G41: =F41*개요!$C$6 | H41: =F41/$B$6 | I41: =H41*개요!$C$6/60
A42: 10부 | B42: 1.2 | C42: =$B$5 | D42: =C42*개요!$C$6 | E42: =SUMPRODUCT(L$13:L$27,$B$13:$B$27)*B42 | F42: =C42*E42 | G42: =F42*개요!$C$6 | H42: =F42/$B$6 | I42: =H42*개요!$C$6/60
A43: 11부 | B43: 1.2 | C43: =$B$5 | D43: =C43*개요!$C$6 | E43: =SUMPRODUCT(M$13:M$27,$B$13:$B$27)*B43 | F43: =C43*E43 | G43: =F43*개요!$C$6 | H43: =F43/$B$6 | I43: =H43*개요!$C$6/60
A44: 12부 | B44: 0.8 | C44: =$B$5 | D44: =C44*개요!$C$6 | E44: =SUMPRODUCT(N$13:N$27,$B$13:$B$27)*B44 | F44: =C44*E44 | G44: =F44*개요!$C$6 | H44: =F44/$B$6 | I44: =H44*개요!$C$6/60
A45: 전체 | D45: =SUM(D33:D44) | E45: =G45/D45 | F45: =AVERAGE(F33:F44) | G45: =SUM(G33:G44) | H45: =AVERAGE(H33:H44) | I45: =SUM(I33:I44)
A46: ※ 난이도 배율: 1·12부(B1~B2)는 짧게 0.8, 10~11부(C1~C2)는 길게 1.2. 화당 단어는 '평균 단어/턴 × 120턴', 낭독 시간은 낭독 속도로 환산한 추정치.
A47: ※ 7부(39행)의 화당 턴은 2026-09-25 사용자 요청으로 120 → 180으로 수동 상향 조정(C39 = 180, 수식 대신 값 직접 입력). 8부 이후에도 180을 유지할지는 변경이력_미결 미결 31번 참고. B8(총 대화 턴)은 전 부 120 가정의 구 추정치이며, 실제 총합은 D45(부별 실제 합)를 참고할 것.
A49: 4. 화 유형별 턴 구성 (합계 = 화당 120턴)
A50: 화 유형 | B50: 도입 | C50: 장면 1 | D50: 장면 2 | E50: 절정·전환 | F50: 마무리 | G50: 합계 | H50: 검증 | I50: 적용
A51: 일반 화 | B51: 15 | C51: 35 | D51: 30 | E51: 25 | F51: 15 | G51: =SUM(B50:F50) | H51: =IF(G50=$B$5,"OK","확인") | I51: 발단·전개·위기 화 대부분
A52: 프레임 화 | B52: 15 | C52: 30 | D52: 30 | E52: 25 | F52: 20 | G52: =SUM(B51:F51) | H52: =IF(G51=$B$5,"OK","확인") | I52: 2~5부 1·5·9·12화: 금요일 프레임(도입·마무리)과 과거 장면
A53: 폭발·감정 정점 화 | B53: 15 | C53: 30 | D53: 25 | E53: 35 | F53: 15 | G53: =SUM(B52:F52) | H53: =IF(G52=$B$5,"OK","확인") | I53: 1부 6화, 9부 6화 등 인물의 감정이 터지는 화
A54: 표결·절차 화 | B54: 15 | C54: 30 | D54: 25 | E54: 35 | F54: 15 | G54: =SUM(B53:F53) | H54: =IF(G53=$B$5,"OK","확인") | I54: 10부 7·12화 investidura, 11부 10화 불신임안 (의장의 결과 낭독 포함)
A55: 재난·추도 화 | B55: 10 | C55: 30 | D55: 30 | E55: 40 | F55: 10 | G55: =SUM(B54:F54) | H55: =IF(G54=$B$5,"OK","확인") | I55: 11부 6화(Anselmo 죽음), 11화(DANA)
A56: 원형·회고 화 | B56: 20 | C56: 25 | D56: 25 | E56: 25 | F56: 25 | G56: =SUM(B55:F55) | H56: =IF(G55=$B$5,"OK","확인") | I56: 12부 1·11·12화: 1부 대사를 되풀이하고 마무리를 길게
A57: 일반 화 (7부부터, 180턴) | B57: 22 | C57: 45 | D57: 45 | E57: 45 | F57: 23 | G57: =SUM(B57:F57) | H57: =IF(G57=180,"OK","확인") | I57: 7부 이후 일반 화 표준(180턴 기준, $B$5=120 기준 검증식과 별개로 180 고정 비교)
A59: 5. 집필 규칙
A60: 1. 1부는 한 턴 15단어 이내를 지킨다. 연설·조항·기사·카드처럼 긴 낭독은 예외로 두되 1턴으로 세고, 화당 최대 3개까지만 쓴다.
A61: 2. 지문이 없으므로 장소·시간·행동을 알리는 턴이 화당 5~10턴 필요하다 (Pepa의 시간 안내, Ramón의 보고, 의장의 결과 낭독 등).
A62: 3. Carmen의 질문 → 쉬운 재설명 짝은 화당 3~6쌍(6~12턴)을 기본으로 한다. 어려운 용어를 도입할 때 반드시 사용한다.
A63: 4. 시그니처 표현은 화자당 1~2회. 120턴 안에서 같은 시그니처가 반복되지 않게 배분한다.
A64: 5. 화자 점유율은 턴 수 기준이다. Carmen처럼 턴은 많지만 짧게 말하는 인물은 평균 단어/턴을 낮게 잡았다.
A65: 6. 표의 파란 숫자는 가정값이다. 1부 1~3화 대본을 쓴 뒤 실제 턴·단어 수를 재서 점유율과 평균 단어/턴을 교정한다.
A66: 7. 7부부터 화당 180턴(기존 15·30·30·30·15의 1.5배 근사: 22·45·45·45·23 표준). 1~6부는 120턴을 그대로 유지한다. 실제 집필 결과는 7부1화 15·30·30·30·15(180턴 적용 전 마지막), 7부2화 15·30·30·30·15, 7부3화 22·45·45·45·23, 7부4화 27·48·38·39·28, 7부5화 26·46·52·31·25.

Sheet 12부_구성
A1: 13부 구성 (13부 × 12화 = 156화)
A2: 정치 파트(8~11부)는 현실 정치 제도에 맞춰 재설계했습니다. 화별 목차는 '화별목차_전체', 제도 근거는 '정치제도' 시트.
A4: 부 | B4: 제목 (ES) | C4: 한국어 | D4: 배경 | E4: 핵심 내용 | F4: 난이도 (CEFR) | G4: 반영 제도·전문 영역 | H4: 시점
A5: 1 | B5: El Despacho de Lavapiés | C5: 라바피에스 사무소 | D5: Lavapiés의 작은 사무실 (1층은 Pepa의 바), 개소 1개월 후 | E5: 이미 한 달째 좌충우돌 중인 팀이 이웃들의 사건 6개를 2화씩(도입→해결) 풀어 간다. 자기소개 대신 '이 사람들이 어쩌다 이렇게 됐지?' 하는 궁금증(In medias res)으로 시작. | F5: B1 | G5: 생활 법률·노동·의료·금융 기초 어휘, 반복되는 말다툼, Carmen 1차 폭발(6화) | H5: 현재(개소 후 1개월)
A6: 2 | B6: El Abogado | C6: 변호사 | D6: Paseo de la Castellana의 대형 로펌 | E6: 승소율 100%의 이면: 강제 퇴거 사건이 Mateo의 결핍이 된다. | F6: B2~C1 | G6: 상법, 소송, 퇴거 절차(LEC) | H6: 과거
A7: 3 | B7: El Médico | C7: 의사 | D7: Hospital San Bartolomé 응급실 (가상) | E7: 예산 삭감과 외주 압박 속에서 치료받지 못하는 환자들. Javier의 이름 목록. | F7: B2~C1 | G7: 의학·보건행정, 자치주 보건 체계(SERMAS), 병원 외주(gestión indirecta) | H7: 과거
A8: 4 | B8: La Auditora | C8: 회계사 | D8: Ochoa & Ruiz Auditores (가상) | E8: 역외 탈세·자금세탁 정황을 발견하지만 조직의 묵인 압박. 서명하지 않겠다는 다짐의 기원. | F8: B2~C1 | G8: 감사·세무, 자금세탁방지법(Ley 10/2010), 감사법(ICAC) | H8: 과거
A9: 5 | B9: El Consultor | C9: 컨설턴트 | D9: Cenit Consultores (가상) | E9: 구조조정 엑셀 한 칸이 수백 명의 실직이었음을 깨닫는다. Nieves와의 첫 접점. | F9: B2~C1 | G9: 경영 전략, 집단해고(ERE), 노동법 | H9: 과거
A10: 6 | B10: El Encuentro | C10: 운명적 만남 | D10: Vallecas의 서민 주거 지역, 작은 카페 | E10: 강제 퇴거와 의료 방치가 한 건으로 얽힌 사건에서 네 사람이 만나 사무소를 차리기로 한다. | F10: B2 | G10: 협상·설득 구어체 | H10: 현재로 수렴
A11: 7 | B11: La Red de Resistencia | C11: 사무소 2탄: 전면전 | D11: 법원, 시청 앞, 마드리드 전역 | E11: 부당 해고·의료 사고·탈세 대기업 상대 집단 대응. 내부 제보자를 보호하고 acusación popular로 고소한다. | F11: B2~C1 | G11: querella, acusación popular, Fiscalía Anticorrupción, 내부고발자 보호법(Ley 2/2023) | H11: 과거→현재
A12: 8 | B12: El Despertar Cívico | C12: 정치적 각성과 창당 | D12: Puerta del Sol, 시민 집회 | E12: 시민 입법발의가 좌초하자 스스로 정당 «Casa Común»을 창당해 첫 지방·자치 선거에 나선다. | F12: B2~C1 | G12: 집회 신고, 정당 등록(Registro de Partidos Políticos), 정관, 정당 재정, 선거운동 규칙 | H12: 정치
A13: 9 | B13: En Cibeles y en la Asamblea | C13: 시의회와 자치의회 | D13: Palacio de Cibeles, Asamblea de Madrid(Vallecas 소재) | E13: Sofía는 시의회에서 예산을, Javier는 자치의회에서 보건을 파고든다. 스캔들 폭로와 Carmen의 2차 폭발. | F13: C1 | G13: Pleno, 예산 집행 규정, 공공계약, 자치주 권한(보건·주거), 조사·고소 | H13: 정치
A14: 10 | B14: Hacia La Moncloa | C14: 총선에서 총리 선출까지 | D14: Congreso de los Diputados, Zarzuela, La Moncloa | E14: 해산·총선·개원·국왕 협의·첫 후보 실패·2개월 시계·재선거·1표 차 총리 선출. | F14: C1~C2 | G14: 선거 절차, 개원, investidura(art. 99), 해산(art. 115), 국왕 앞 선서 | H14: 정치
A15: 11 | B15: La Gran Batalla Social I | C15: 사회 현안 전투 I | D15: La Moncloa, Consejo de Ministros, 브뤼셀 | E15: 소수 정부로 주거·보건·이민·청년·물가 국내 현안을 돌파한 뒤, Anselmo가 직접 브뤼셀 협상(NATO 방위비·EU 재정규칙)에 나서 승리하고 귀국 직후 사망한다. | F15: C1~C2 | G15: Consejo de Ministros, 자치주 협의체, NATO 방위비 목표(2025 헤이그 합의), EU 재정규칙 | H15: 정치
A16: 12 | B16: La Gran Batalla Social II | C16: 사회 현안 전투 II | D16: La Moncloa, 브뤼셀, 재난 현장 | E16: 장례식으로 열고 Anselmo의 유작 메모로 브뤼셀 후속 협상을 마무리한다. 플랫폼 노동·정보기관 사찰·청년 정신건강 등 새 현안과 건설적 불신임안 방어, DANA 재난, 예산안까지. | F16: C1~C2 | G16: 메모 승계, 법률 vs 긴급 칙령, 헌법재판소, 불신임안, DANA 민방위, 예산 | H16: 정치
A17: 13 | B17: De vuelta a Lavapiés | C17: 귀환 | D17: Lavapiés, Casa Pepa | E17: 1부 1화와 같은 대사로 시작해 원을 닫는다. Anselmo의 유언장, 새 인턴, 이제 설명하는 쪽이 된 Carmen. | F17: B1~B2 | G17: 유언(notaría, albacea), 고위직 겸직 제한, 재단 전환, 원형 구조 | H17: 귀환
A19: 흐름: 현재(1) → 과거(2~5) → 교차(6) → 전면전(7) → 정치(8 창당 → 9 지방 → 10 총선·총리) → 정부(11) → 귀환(12, 원형 구조). 난이도는 B1 → C1/C2 → B1~B2로 올라갔다 내려와 마무리가 부드럽고, 12부에서 1부 장면을 다시 읽으면 낭독 실력의 성장을 스스로 확인할 수 있다.

Sheet 아크_구성계획
A1: 아크별 구성 계획 (1~12부)
A2: 각 부(아크)의 서사 기능, 변화, 비트(발단→결말), 인물 아크, 복선, 현안·제도, 언어 설계를 한 블록으로 정리. 화별 세부는 '화별목차_전체', 복선 추적은 '복선_회수'.
A4: 1부 | B4: El Despacho de Lavapiés — 라바피에스 사무소 | 난이도 B1 | 사무소 개소 1개월 후(6부 12화로부터 약 4주). Lavapiés 사무소와 1층 Pepa의 바.
A5: 서사 기능 | B5: 독자 진입 장치. 이미 굴러가는(그러나 여전히 좌충우돌하는) 사무소를 보여 주어 '이 사람들이 어쩌다 이렇게 됐지?' 하는 궁금증을 만든다. 자기소개 대신 여섯 사건을 통해 인물의 습관과 리듬을 익히게 한다.
A6: 로그라인 | B6: 개소 한 달째, 여전히 순서 하나 못 정하고 매번 다투는 네 전문가와 팀이 그래도 이웃들의 사건 여섯 개를 하나씩 해결해 나가지만, 마지막 사건의 서류에서 Mateo의 옛 로펌 이름이 튀어나온다.
A7: 변화 (시작 → 끝) | B7: '한 달이나 됐는데 아직도 이 모양' → 그래도 매번 어떻게든 해결하는 팀이라는 신뢰. 그러나 각자의 과거는 여전히 미해결이고, 옛 로펌 이름이 도착한다.
A8: 핵심 갈등 | B8: 전문가의 말투 vs 이웃의 삶 / 여전히 못 정한 방법 / 각자 숨기는 과거
A9: 비트 1 | B9: 사건1 임대료 조작, 1~2화(Fátima): 도입에서 여전히 자리 못 잡은 한 달 차 팀의 말다툼을 보여 주고, 해결에서 Raimundo의 책·카드 #1(LAU)로 부당 인상을 막는다.
A10: 비트 2 | B10: 사건2 퇴거 집행, 3~4화: 밤 여덟 시 급보 → 아침 집행 저지. Ramón·Nieves 첫 카메오, 넷의 역할 분담(서류·건강·숫자·동선)이 처음으로 손발이 맞는다.
A11: 비트 3 | B11: 사건3 임금 체불, 5~6화: Diego의 컨설팅 용어가 청년 노동자를 지치게 하고, 협상 중 Carmen이 1차 폭발한다. 폭발 후 쉬운 말로 다시 협상해 해결.
A12: 비트 4 | B12: 사건4 의료 접근, 7~8화: 서류 없는 가족의 아이가 진료를 못 받는다. Lucía·Tomás 카메오, Anselmo의 가짜 무릎이 진짜 아픈 아이 앞에서 조용해지는 대비.
A13: 비트 5 | B13: 사건5 금융 사기, 9~10화: 저축을 잃은 이웃을 두고 Sofía가 장부를, 낯선 Gonzalo가 계좌 흐름을 추적한다. Inés 카메오. Gonzalo는 설명 없이 사라지고 Sofía는 은행 이름에 말없이 굳는다.
A14: 비트 6 | B14: 사건6 오래된 서류·훅, 11~12화: 수십 년 전 퇴거 서류의 절차 오류를 바로잡다가 서명란에서 Mateo의 옛 로펌 이름을 발견한다. Mateo가 얼어붙고 금요일 이야기(2부)가 예고된다.
A15: 인물 아크 | B15: Carmen=독자의 대리인(질문), 한 달이 지나도 Mateo에게 usted 유지. Anselmo=심술과 복선(매년 하는 소리라는 게 드러남). Pepa=정서적 중심. 카메오는 사건별로 분산: Raimundo(1·2·11화), Ramón·Nieves(3·4화), Lucía·Tomás(7화), Gonzalo·Inés(9·10·11화). 폭발 화(6화)에는 Ramón·Pepa·Raimundo의 고정 반응만 남기고 Nieves의 욕은 9부 2차 폭발로 이관해 과밀을 해소.
... A19: 언어 설계 | B19: B1. 한 줄 15단어 이내, 현재·명령형·간단한 과거. tú·vosotros 중심. 낭독: 빠른 티키타카로 입 풀기. Mateo·Anselmo의 격식체는 한두 줄 맛보기. 매 사건 2화(도입→해결) 리듬을 반복해 구조를 익히게 한다.
A20: 대화량 (화당 120턴) | B20: ="화당 "&턴_설계!$B$5&"턴 · 부 총 "&TEXT(턴_설계!D33,"#,##0")&"턴 · 화당 약 "&TEXT(턴_설계!F33,"#,##0")&"단어 · 낭독 약 "&TEXT(턴_설계!H33,"0.0")&"분 (평균 "&TEXT(턴_설계!E33,"0.0")&"단어/턴)"
A21: Carmen 질문·Raimundo 카드 | B21: Carmen: 임대·노동·의료·금융 기초 용어(fianza, contrato temporal, padrón, cuenta bancaria). 카드: LAU(Ley 29/1994), 사전(DLE·DPEJ).
A22: 다음 부 연결 | B22: 2부: 금요일마다 한 명씩 과거를 이야기하는 규칙 — 첫 번째는 Mateo.
A24: 2부 | B24: El Abogado — 변호사 | 난이도 B2~C1 | 프레임: 1부와 같은 첫 겨울의 금요일 밤. 과거: 약 5년 전, Paseo de la Castellana의 대형 로펌.
A25: 서사 기능 | B25: 첫 과거 회상. 공동 악역 Grupo Meridiano를 도입하고 '법을 잘 쓰는 것과 옳은 것은 다르다'는 이 이야기의 첫 질문을 던진다. 프레임(Pepa의 식탁)과 과거를 오가는 구조 실험.
A26: 로그라인 | B26: 승소율 100%의 파트너 후보가 대형 고객의 주택 포트폴리오를 비우는 조항을 설계해 재판에서 이기고, 그 승리가 한 노인의 죽음이 되었음을 알게 된다.
A27: 변화 (시작 → 끝) | B27: 자랑스러운 승자 → 자기 승리에 사직서를 낸 사람.
A28: 핵심 갈등 | B28: 잘 쓰는 법 vs 옳은 것 / 파트너 승진 vs 양심
A29: 비트 1 | B29: 발단(1~3화): 금요일 프레임, 카스티야나의 월요일, VIP 고객 Quintana.
A30: 비트 2 | B30: 전개(4~5화): 실사에서 Lavapiés 건물 발견 / 프레임에서 그곳이 Pepa의 거리였음이 드러남.
A31: 비트 3 | B31: 미드포인트(6화): 조항 설계 — Mateo가 스스로 함정을 만든다.
A32: 비트 4 | B32: 위기(7~9화): 주민 총회(Remedios), 재판 승소, 프레임에서 Mateo의 말이 막힘.
A33: 비트 5 | B33: 절정(10~11화): 살라망카 축하 만찬 중 부고, 손녀 Marina의 방문.
... A39: 언어 설계 | B39: B2~C1. 접속법 현재·과거, 수동태, 법률 문어체. 과거 장면은 격식 문어, 프레임 장면은 B1로 두어 톤을 대비. 발성: 또박또박, 중저음.
A40: 대화량 (화당 120턴) | B40: ="화당 "&턴_설계!$B$5&"턴 · 부 총 "&TEXT(턴_설계!D34,"#,##0")&"턴 · 화당 약 "&TEXT(턴_설계!F34,"#,##0")&"단어 · 낭독 약 "&TEXT(턴_설계!H34,"0.0")&"분 (평균 "&TEXT(턴_설계!E34,"0.0")&"단어/턴)"
A41: Carmen 질문·Raimundo 카드 | B41: Carmen: demanda·sentencia·cláusula 등 법률 용어. 카드: Registro de la Propiedad, LAU, LEC 퇴거 절차.
A42: 다음 부 연결 | B42: 3부: 응급실에서 쓰러진 Mateo — 다음 금요일은 Javier의 이야기.
A44: 3부 | B44: El Médico — 의사 | 난이도 B2~C1 | 프레임: 금요일 밤. 과거: 약 4년 전, Hospital San Bartolomé(가상) 응급실.
A45: 서사 기능 | B45: 인간의 생명과 공공 보건이라는 정서적 무게. Grupo Meridiano의 두 번째 얼굴(병원 외주)을 보여 주고, 폭염·고령 환자·서류 없는 환자 등 현안을 응급실에서 체감하게 한다.
A46: 로그라인 | B46: 응급의가 예산 삭감과 병원 외주 속에서 환자를 잃기 시작하고, 이름을 적어 두다가 내부 보고를 올리지만 징계로 돌아온다.
A47: 변화 (시작 → 끝) | B47: 시스템을 믿는 의사 → 이름 명단만 든 사직자.
A48: 핵심 갈등 | B48: 의료 윤리 vs 관리 효율 / 침묵하는 동료들
A49: 비트 1 | B49: 발단(1~3화): 금요일 프레임, 야간 근무(Mateo 진료), 폭염 환자 폭증.
A50: 비트 2 | B50: 전개(4~5화): 병원 외주 발표(컨설턴트 Diego 등장), 프레임에서 수첩 명단과 Anselmo의 부은 발목.
A51: 비트 3 | B51: 미드포인트(6화): '명단의 첫 번째' — 서류 없는 환자가 병상 지연으로 숨진다.
A52: 비트 4 | B52: 위기(7~9화): 원장의 통계, 징계 절차, 프레임에서 Lucía의 되받기.
A53: 비트 5 | B53: 절정(10~11화): 병상 없는 밤, 사직.
... A59: 언어 설계 | B59: B2~C1. 의학 어휘, 짧은 명령형, 긴박한 호흡. 발성: 빠른 템포와 짧은 호흡.
A60: 대화량 (화당 120턴) | B60: ="화당 "&턴_설계!$B$5&"턴 · 부 총 "&TEXT(턴_설계!D35,"#,##0")&"턴 · 화당 약 "&TEXT(턴_설계!F35,"#,##0")&"단어 · 낭독 약 "&TEXT(턴_설계!H35,"0.0")&"분 (평균 "&TEXT(턴_설계!E35,"0.0")&"단어/턴)"
A61: Carmen 질문·Raimundo 카드 | B61: Carmen: triaje·constantes·sepsis 등 의학 용어. 카드: Ley 41/2002, Ley 14/1986, SERMAS.
A62: 다음 부 연결 | B62: 4부: Sofía — «Mi turno.» 그 서명의 주인.
A64: 4부 | B64: La Auditora — 회계사 | 난이도 B2~C1 | 프레임: 금요일 밤. 과거: 약 3년 전, Ochoa & Ruiz Auditores(가상).
A65: 서사 기능 | B65: 돈의 흐름과 '서명의 책임'. 부패의 공모가 일상 업무의 얼굴로 온다는 것을 보여 주고, 이후 아크의 결정적 증거(USB)를 만든다.
A66: 로그라인 | B66: 시니어 파트너가 최대 고객의 이상 거래를 발견하지만, 압박과 승진 앞에서 결국 '깨끗한' 의견서에 서명하고 그 서명이 다른 사람의 죽음과 해고에 쓰인다.
A67: 변화 (시작 → 끝) | B67: 정확함을 자랑하던 감사인 → '서명한 사람'. 다시는 서명하지 않겠다는 다짐.
A68: 핵심 갈등 | B68: 감사인의 독립성 vs 수임료 / 정확함 vs 생존
A69: 비트 1 | B69: 발단(1~3화): '내가 서명했다' 프레임, 결산 마감, 돈 잘 주는 고객.
A70: 비트 2 | B70: 전개(4~5화): '이건 안 맞아' — 특수관계자 대출 발견 / 프레임에서 아버지 이야기.
A71: 비트 3 | B71: 미드포인트(6화): 파트너 회의 — 한정 의견 주장, 리스크 위원회로 에스컬레이션.
A72: 비트 4 | B72: 위기(7~9화): 위원회의 '증거 불충분', 살라망카의 점심(위협), 프레임 '서명했나요?'.
A73: 비트 5 | B73: 절정(10~11화): 서명, 그리고 서명 이후 — 계약 확정과 구조조정 통보, 사직.
... A79: 언어 설계 | B79: B2~C1. 숫자 낭독, 수동태·조건문, 감사 보고서체. 발성: 일정한 속도, 결론 문장에서 톤 낮춤.
A80: 대화량 (화당 120턴) | B80: ="화당 "&턴_설계!$B$5&"턴 · 부 총 "&TEXT(턴_설계!D36,"#,##0")&"턴 · 화당 약 "&TEXT(턴_설계!F36,"#,##0")&"단어 · 낭독 약 "&TEXT(턴_설계!H36,"0.0")&"분 (평균 "&TEXT(턴_설계!E36,"0.0")&"단어/턴)"
A81: Carmen 질문·Raimundo 카드 | B81: Carmen: balance·cuenta de resultados·materialidad 등 회계 용어. 카드: Ley 22/2015, ICAC, Registro Mercantil.
A82: 다음 부 연결 | B82: 5부: Diego — 그 의견서 이후 시작된 구조조정 명단의 주인.
A84: 5부 | B84: El Consultor — 컨설턴트 | 난이도 B2~C1 | 프레임: 금요일 밤. 과거: 약 2년 전, Cenit Consultores(가상) 32층.
A85: 서사 기능 | B85: 효율의 이름으로 사람이 숫자가 되는 순간. 노동(Nieves), 청년 고용(S1), 영세 기업 구조(E2)를 도입하고 Diego의 말투 변화를 예고한다.
A86: 로그라인 | B86: 전략 컨설턴트가 영세 기업을 살리려던 낙관에서 출발해, 대형 고객 구조조정 모델의 셀 하나가 412명의 해고임을 알게 된다.
A87: 변화 (시작 → 끝) | B87: '스케일'을 믿던 사람 → 사람을 숫자로 본 죄책감을 인정하는 사람(프레젠테이션 톤에서 솔직한 톤으로 가는 시작).
A88: 핵심 갈등 | B88: 효율 vs 사람 / 조직 충성 vs 양심
A89: 비트 1 | B89: 발단(1~3화): 매트릭스 프레임, Cenit 32층, Rueda 공방(영세 기업의 실패).
A90: 비트 2 | B90: 전개(4~5화): 이카로 프로젝트 킥오프 / 프레임 '엑셀 한 장'.
A91: 비트 3 | B91: 미드포인트(6화): C47 셀 — 412개 일자리, 샴페인.
A92: 비트 4 | B92: 위기(7~9화): 협상 테이블에서 Nieves와 대면, 잘못 보낸 이메일과 Lucía 상담, 프레임 '412'.
A93: 비트 5 | B93: 절정(10~11화): 파업과 Nieves의 해고, 마지막 회의에서 사직.
... A99: 언어 설계 | B99: B2~C1. 경영 외래어(alinear, escalable), 프레젠테이션 톤. 발성: 숨 가쁜 톤에서 느린 솔직한 톤으로.
A100: 대화량 (화당 120턴) | B100: ="화당 "&턴_설계!$B$5&"턴 · 부 총 "&TEXT(턴_설계!D37,"#,##0")&"턴 · 화당 약 "&TEXT(턴_설계!F37,"#,##0")&"단어 · 낭독 약 "&TEXT(턴_설계!H37,"0.0")&"분 (평균 "&TEXT(턴_설계!E37,"0.0")&"단어/턴)"
A101: Carmen 질문·Raimundo 카드 | B101: Carmen: stakeholder·escalar·sinergia·KPI 등 경영 용어. 카드: Estatuto de los Trabajadores 제51조.
A102: 다음 부 연결 | B102: 6부: 바예카스 — 네 사람이 같은 총회에.
A104: 6부 | B104: El Encuentro — 운명적 만남 | 난이도 B2 | 약 1년 전(1부보다 앞). Vallecas '14번 블록' → Lavapiés 사무소 개소.
A105: 서사 기능 | B105: 퍼즐 완성. 네 개의 과거가 하나의 이름(Grupo Meridiano)으로 수렴하고 팀이 결성된다. 1부의 '왜?'에 대한 대답이자 시간의 고리를 닫는 아크.
A106: 로그라인 | B106: 각자 무너진 네 사람이 같은 건물을 지키려고 모였다가 자기들이 서로 다른 얼굴의 같은 회사를 도왔음을 알게 되고, 서로를 비난한 끝에 처음으로 함께 이긴다.
A107: 변화 (시작 → 끝) | B107: 혼자 무너진 네 사람 → 서로의 죄를 아는 팀.
A108: 핵심 갈등 | B108: 서로에 대한 책임(공모) vs 함께 속죄
A109: 비트 1 | B109: 발단(1~3화): 바예카스의 화요일, 낯선 넷, 14번 블록.
A110: 비트 2 | B110: 전개(4~5화): 계단의 밤(첫 속내), Sofía의 서류.
A111: 비트 3 | B111: 미드포인트(6화): '같은 이름' — 네 개의 과거가 Meridiano 하나로 이어진다.
A112: 비트 4 | B112: 위기(7~9화): 서로에 대한 비난, 퇴거 아침 영시의 협업, 첫 정지 승리.
A113: 비트 5 | B113: 절정(10~11화): 라바피에스의 가게, 식탁의 규칙(금요일 이야기 전통).
... A119: 언어 설계 | B119: B2. 감정 폭발·설득 구어체, 다툼과 화해. 발성: 소리 높임과 회복의 대비. usted → tú 전환의 시작.
A120: 대화량 (화당 120턴) | B120: ="화당 "&턴_설계!$B$5&"턴 · 부 총 "&TEXT(턴_설계!D38,"#,##0")&"턴 · 화당 약 "&TEXT(턴_설계!F38,"#,##0")&"단어 · 낭독 약 "&TEXT(턴_설계!H38,"0.0")&"분 (평균 "&TEXT(턴_설계!E38,"0.0")&"단어/턴)"
A121: Carmen 질문·Raimundo 카드 | B121: Carmen: '¿Qué es un fondo buitre?' 등 소유 구조 용어. 카드: Registro Mercantil, 퇴거 유예 규정.
A122: 다음 부 연결 | B122: 1부 1화 — 원이 닫힌다. 그리고 7부로.
A124: 7부 | B124: La Red de Resistencia — 전면전 | 난이도 B2~C1 | 사무소 개소 1년 후. 법원, 시청 앞, 마드리드 전역.
A125: 서사 기능 | B125: 전문 능력이 결합되어 첫 결정적 승리를 얻지만, 판결이 법 앞에서 무력할 수 있음을 배운다. 정치의 필요성을 낳는 아크.
A126: 로그라인 | B126: 사무소가 고소·내부고발·보도를 결합해 Grupo Meridiano를 상대로 전면전을 벌이고 법원 결정을 얻지만, 그 승리를 뒤집을 법이 준비되고 있음을 알게 된다.
A127: 변화 (시작 → 끝) | B127: 사건을 푸는 사무소 → 법을 바꿔야 한다는 결론.
A128: 핵심 갈등 | B128: 합법 vs 효율(도청기) / 승리의 지속 가능성
A129: 비트 1 | B129: 발단(1~3화): 1년 후, 계단 위의 줄, 피해자를 벌한 법(N4).
A130: 비트 2 | B130: 전개(4~5화): 서류 없는 사람들(S2), Gonzalo의 제보.
A131: 비트 3 | B131: 미드포인트(6화): 사건 파일 — 고소장(acusación popular) 제출.
A132: 비트 4 | B132: 위기(7~9화): 보복, 전등 속 마이크(위법 수집 증거 논쟁), 동네의 보초.
A133: 비트 5 | B133: 절정(10~11화): 법원 결정과 피의자 소환 / 다가오는 법(acusación popular 제한 법안).
... A139: 언어 설계 | B139: B2~C1. 집단 소송·성명서·인터뷰 어휘. 발성: 긴박한 대화와 기자회견 톤.
A140: 대화량 (화당 120턴) | B140: ="화당 "&턴_설계!$B$5&"턴 · 부 총 "&TEXT(턴_설계!D39,"#,##0")&"턴 · 화당 약 "&TEXT(턴_설계!F39,"#,##0")&"단어 · 낭독 약 "&TEXT(턴_설계!H39,"0.0")&"분 (평균 "&TEXT(턴_설계!E39,"0.0")&"단어/턴)"
...

Sheet 화별목차_전체
A1: 전체 화별 목차 (1~12부, 144화)
A2: 현실 제도와 현안(ID는 '현안_배치' 시트)을 반영한 초안. 의석 수·결과는 가상 수치. 모든 화는 지문 없이 대화문으로만 진행한다.
A4: 부 | B4: 화 | C4: 서사 기능 | D4: 제목 (ES) | E4: 한국어 | F4: 핵심 사건 | G4: 반영 제도·전문 영역 | H4: 주요 인물 | I4: 반영 현안 (ID) | J4: 턴 수
A5: 1 | B5: 1 | C5: 사건1 도입 | D5: Otra carta más | E5: 또 다른 편지 | F5: 사무소 개소 1개월 후. 다섯 시, 여전히 방법을 못 정한 채 매일 다투는 팀. Fátima가 두 번째로 찾아와 새 퇴거 예고장을 보인다. Carmen은 여전히 Mateo에게 usted를 쓴다. Raimundo가 지나가며 «날짜를 세어 보라»는 힌트만 던지고, 계약서가 없어 다음 날로 미뤄진다. | G5: 생활 법률 구어체, 반복되는 말다툼 (B1) | H5: Pepa, Mateo, Javier, Sofía, Diego, Carmen, Anselmo, Fátima, Raimundo | I5: E1 | J5: =턴_설계!$B$5
A6: 1 | B6: 2 | C6: 사건1 해결 | D6: La cláusula que no sube | E6: 오르지 않는 조항 | F6: [사건1 해결] Fátima와 Carmen이 계약서를 가져온다. Raimundo의 카드 #1(LAU 조항)로 인상률이 부당함을 확인하고, 열흘의 기한 안에 답장을 쓴다. 사무소의 첫 번째 규칙(가난한 이웃에겐 돈을 받지 않는다)이 확인된다. | G6: 임대차(LAU), 소비자물가지수 조정, 기한·답변 | H6: Mateo, Sofía, Diego, Fátima, Raimundo, Carmen, Pepa | I6: E1 | J6: =턴_설계!$B$5
A7: 1 | B7: 3 | C7: 사건2 도입 | D7: Aviso de las ocho | E7: 여덟 시의 통지 | F7: [사건2 도입] 밤 여덟 시, 퇴거 집행이 다음 날 아침으로 잡혔다는 급보가 온다. Ramón이 주민을 조직하고 Nieves가 이웃들을 모은다. 네 사람이 각자 서류·건강·숫자·동선을 맡아 밤새 준비하지만 승산은 불투명하다. | G7: 퇴거 집행 예고, 긴급 동원, 이웃 조직 | H7: Mateo, Javier, Sofía, Diego, Ramón, Nieves, Carmen, Pepa | I7: S1 | J7: =턴_설계!$B$5
A8: 1 | B8: 4 | C8: 사건2 해결 | D8: El furgón que no llegó | E8: 오지 않은 트럭 | F8: [사건2 해결] 집행 당일 아침. Mateo의 긴급 신청, Javier의 취약계층 진단서, Sofía의 금액 계산, Diego의 동선 배치가 맞물려 집행이 연기된다. Ramón의 «Sin novedad» 보고로 마무리된다. | G8: 가처분 신청, 취약계층 유예, 집행관 대응 | H8: Mateo, Javier, Sofía, Diego, Ramón, Nieves, Carmen, Pepa | I8: S1 | J8: =턴_설계!$B$5
A9: 1 | B9: 5 | C9: 사건3 도입 | D9: El becario de la fábrica | E9: 공장의 인턴 | F9: [사건3 도입] 임금 체불과 부당한 초과근무에 지친 청년 노동자 Álvaro(가상)가 찾아온다. Diego가 컨설팅 용어로 상황을 분석하려 하고 Carmen이 통역하듯 애쓰지만 Álvaro는 점점 지쳐 간다. | G9: 임시 계약, 초과근무, 경영 용어의 벽 | H9: Diego, Carmen, Sofía, Pepa, Álvaro(가상) | I9: S1 | J9: =턴_설계!$B$5
A10: 1 | B10: 6 | C10: 사건3 해결(폭발) | D10: ¡Basta! | E10: 그만! | F10: [사건3 해결] 협상 자리에서 Diego의 용어가 한 시간째 이어지자 Carmen이 폭발한다(1차 폭발). Javier·Ramón·Pepa·Raimundo의 고정 반응, Anselmo의 «Mentecata… Pregunta.», Sofía의 «Lo traduzco yo.» 이후 쉬운 말로 다시 협상해 밀린 임금 지급에 합의한다. | G10: 감정 표현, 전문 용어 → 쉬운 말, 임금 체불 합의 | H10: Carmen, Diego, Sofía, Javier, Anselmo, Ramón, Pepa, Raimundo, Álvaro(가상) | I10: S1 | J10: =턴_설계!$B$5
A11: 1 | B11: 7 | C11: 사건4 도입 | D11: La niña con fiebre | E11: 열이 나는 아이 | F11: [사건4 도입] 서류가 없어 소아과 예약을 못 잡는 가족이 찾아온다. Javier가 나서고 Lucía가 친구로 들러 «¿Y cómo te hace sentir eso?»를 처음 선보인다. 마침 들른 Tomás는 Anselmo에게 원고를 놀림받다 «No está mal.»라는 최고의 칭찬을 듣는다. 정작 진짜 아픈 아이 앞에서 Anselmo는 자기 무릎 타령을 멈춘다. | G11: 서류 없는 가족의 의료 접근, 증상 표현 | H11: Javier, Lucía, Anselmo, Tomás, Carmen, Pepa, 가족(가상) | I11: S2 | J11: =턴_설계!$B$5
A12: 1 | B12: 8 | C12: 사건4 해결 | D12: Un volante para todos | E12: 모두를 위한 진료 의뢰서 | F12: [사건4 해결] Mateo와 Javier가 주민등록(padrón) 경로를 찾아내 아이가 진료를 받는다. Anselmo가 평소와 달리 조용히 커피를 마신다. | G12: 주민등록·거주 등록 경로, 진료 의뢰서 | H12: Javier, Mateo, Carmen, Pepa, 가족(가상) | I12: S2 | J12: =턴_설계!$B$5
A13: 1 | B13: 9 | C13: 사건5 도입 | D13: La viuda del quinto | E13: 5층의 미망인 | F13: [사건5 도입] 가짜 투자에 저축을 잃은 노년의 이웃 Encarna(가상)가 찾아온다. Sofía가 장부를 살피는 동안, 양복 입은 낯선 남자 Gonzalo가 나타나 은행 쪽 흐름을 봐 주겠다고 하면서도 자기 이야기는 하지 않는다. Inés가 냄새를 맡고 기웃거린다. | G13: 저축·투자 사기, 은행 계좌 기초 어휘 | H13: Sofía, Gonzalo, Inés, Carmen, Pepa, Encarna(가상) | I13: E3 | J13: =턴_설계!$B$5
A14: 1 | B14: 10 | C14: 사건5 해결 | D14: Sigue el dinero | E14: 돈을 따라가라 | F14: [사건5 해결] Gonzalo의 계좌 흐름 추적과 Sofía의 장부 대조로 사기 계좌를 찾아 돈 일부를 되찾는다. Gonzalo는 설명 없이 떠나고, Sofía는 «Banco Ibérico»라는 이름에 말없이 굳는다. | G14: 자금 흐름 추적, 계좌·송금 어휘 | H14: Sofía, Gonzalo, Carmen, Pepa, Encarna(가상) | I14: E3 | J14: =턴_설계!$B$5
A15: 1 | B15: 11 | C15: 사건6 도입 | D15: Un papel de hace años | E15: 수년 전 서류 | F15: [사건6 도입] Fátima의 남편이 수십 년 전 다른 건물에서 받은 낡은 퇴거 서류를 들고 온다. 당장 급한 사안은 아니지만 오래된 절차 오류가 보인다. Inés가 취재 각도로 흥미를 보인다. | G15: 오래된 서류 판독, 절차 하자 | H15: Mateo, Inés, Carmen, Pepa, Fátima의 남편(가상) | I15: E1 | J15: =턴_설계!$B$5
A16: 1 | B16: 12 | C16: 사건6 해결(훅) | D16: La firma | E16: 서명 | F16: [사건6 해결·훅] 절차 오류를 바로잡아 오래된 기록을 정정하지만, 진짜 충격은 서류 맨 아래: Mateo의 옛 로펌 «Aguirre & Salvat»의 서명이다. Mateo가 얼어붙고 Pepa가 «Sentaos, que os pongo algo.»로 분위기를 잇는다. 금요일에는 Mateo의 이야기가 시작된다. | G16: 서명·기록 정정, 이름 확인 | H16: Mateo, Pepa, Carmen, Anselmo, Fátima의 남편(가상) | I16: E1 | J16: =턴_설계!$B$5
A17: 2 | B17: 1 | C17: 발단 | D17: Viernes de historias | E17: 금요일의 이야기 | F17: (프레임) Pepa의 식탁에서 금요일마다 한 사람이 과거를 이야기하는 규칙이 시작된다. Carmen이 Mateo에게 왜 로펌을 그만뒀느냐고 묻고 Mateo는 «Vayamos por partes.»로 시작한다. | G17: 격식체(usted)와 tú의 대비, 과거 이야기 도입 | H17: Carmen, Mateo, Pepa, Anselmo | I17: E1 | J17: =턴_설계!$B$5
A18: 2 | B18: 2 | C18: 발단 | D18: Un lunes en la Castellana | E18: 카스티야나의 월요일 | F18: (과거) 승소율 100%의 파트너 후보 Mateo의 하루. 새벽 편의점에서 야간 점원 Tomás와 마주친다. 상사 Salvat(가상)이 파트너 승진을 암시한다. | G18: 로펌 어휘: socio, honorarios, cartera de clientes | H18: Mateo, Tomás, Salvat(가상) | J18: =턴_설계!$B$5
A19: 2 | B19: 3 | C19: 발단 | D19: El cliente estrella | E19: VIP 고객 | F19: 대형 고객 Grupo Meridiano의 회장 Quintana(가상)를 소개받는다. 회의석에는 고객 측 컨설턴트 Diego와 매각 은행 지점장 Gonzalo가 있다. | G19: 인수합병 어휘: adquisición, cartera, cláusula | H19: Mateo, Diego, Gonzalo, Quintana(가상) | I19: E1 | J19: =턴_설계!$B$5
A20: 2 | B20: 4 | C20: 전개 | D20: La cartera de Lavapiés | E20: 라바피에스 자산 포트폴리오 | F20: 실사(due diligence). 포트폴리오에 Lavapiés 건물 12채가 들어 있다. 감사인 Sofía가 «Esto no cuadra»를 흘리고, 고서점에서 등기 자료를 찾던 Mateo에게 Raimundo가 «Búscalo tú.» | G20: 실사, 등기(Registro de la Propiedad), 임차인 명부 | H20: Mateo, Sofía, Raimundo | I20: E1 | J20: =턴_설계!$B$5
A21: 2 | B21: 5 | C21: 전개 | D21: Viernes: la calle de Pepa | E21: 금요일: Pepa의 거리 | F21: (프레임) 그 포트폴리오에 Pepa의 가게가 있던 건물이 들어 있었음이 밝혀진다. Carmen은 놀라 usted를 놓치고 Mateo는 잠시 침묵한다. | G21: 감정 표현, 놀람 | H21: Pepa, Mateo, Carmen | I21: E1 | J21: =턴_설계!$B$5
A22: 2 | B22: 6 | C22: 미드포인트 | D22: La cláusula | E22: 조항 | F22: 임차인을 비우는 가장 '깨끗한' 방법으로 Mateo가 «resolución por obras de rehabilitación» 조항을 설계한다. Diego의 재무 모델이 이를 뒷받침한다. | G22: 임대 해지, 리모델링 사유, 통지 요건 | H22: Mateo, Diego, Salvat(가상) | I22: E1 | J22: =턴_설계!$B$5
A23: 2 | B23: 7 | C23: 위기 | D23: La asamblea de vecinos | E23: 주민 총회 | F23: 세입자들이 총회를 연다. 노조 출신 Nieves가 이끌고, 응급실 의사 Javier가 공황을 일으킨 노인을 돌본다. Mateo는 78세 Remedios(가상)를 만난다. | G23: 총회·발언·동의, 항의 표현 | H23: Mateo, Nieves, Javier, Remedios(가상) | I23: E1 | J23: =턴_설계!$B$5
A24: 2 | B24: 8 | C24: 위기 | D24: El juicio | E24: 재판 | F24: 심리(vista)와 판결. Mateo가 승소한다. 취재하던 Inés가 «¿Está orgulloso?»라고 묻는다. 감사인 Sofía는 고객의 장부를 보고 고개를 젓는다. | G24: 소송: demanda, vista, sentencia, costas | H24: Mateo, Inés, Sofía, 판사(가상) | I24: E1·P3 | J24: =턴_설계!$B$5
A25: 2 | B25: 9 | C25: 위기 | D25: Viernes: sigue | E25: 금요일: 계속해 | F25: (프레임) Mateo가 말을 잇지 못하자 Anselmo가 «Cuando yo era embajador…»로 시간을 벌어 주고 Pepa가 «Sigue.»라고 한다. Carmen은 «¿Y ella?»라고 묻는다. | G25: 위로·재촉 표현 | H25: Mateo, Anselmo, Pepa, Carmen | J25: =턴_설계!$B$5
A26: 2 | B26: 10 | C26: 절정 | D26: Una cena en Salamanca | E26: 살라망카의 저녁 | F26: 승소 축하 만찬. 파트너들이 건배하는 동안 Quintana가 다음 포트폴리오를 건넨다. Mateo의 휴대전화가 울린다. | G26: 고급 식당 표현, 건배·축하 | H26: Mateo, Salvat(가상), Quintana(가상), Sofía | J26: =턴_설계!$B$5
A27: 2 | B27: 11 | C27: 절정 | D27: La nieta de Remedios | E27: Remedios의 손녀 | F27: Remedios가 퇴거 석 달 뒤 세상을 떠났다는 소식. 손녀 Marina(가상)가 사무실로 찾아와 조용히 묻는다: «¿Usted ganó?» | G27: 조의·항의, 문서 vs 사람 | H27: Mateo, Marina(가상) | I27: E1 | J27: =턴_설계!$B$5
A28: 2 | B28: 12 | C28: 결말·훅 | D28: Viernes: la renuncia | E28: 금요일: 사직 | F28: (프레임+과거) Mateo가 다음 포트폴리오 서명을 거부하고 사직서를 낸다. 짐 상자를 든 채 응급실 대기실에서 쓰러지고 Javier가 그를 진료한다. Carmen은 여전히 usted를 쓴다. | G28: 사직·거절 표현, 접속법 | H28: Mateo, Javier, Carmen, Pepa | J28: =턴_설계!$B$5
A29: 3 | B29: 1 | C29: 발단 | D29: Viernes: los nombres | E29: 금요일: 이름들 | F29: (프레임) Javier가 «Eso no es una estadística; es una persona.»라며 이야기를 시작한다. Anselmo가 계단을 오르내리다 숨을 고르는 것을 Javier가 흘끗 본다. | G29: 의학 어휘 도입 | H29: Javier, Carmen, Anselmo, Pepa, Cervantes(신규) | J29: =턴_설계!$B$5
A30: 3 | B30: 2 | C30: 발단 | D30: Turno de noche | E30: 야간 근무 | F30: (과거) San Bartolomé 응급실의 야간 근무. 분류(triaje), 병상, 간호사 Marisol(가상)과의 호흡. 가슴 통증으로 실려 온 Mateo를 진료한다. | G30: triaje, constantes, camilla, box | H30: Javier, Marisol(가상), Mateo, Lucas(가상), Nacho(가상) | J30: =턴_설계!$B$5
A31: 3 | B31: 3 | C31: 발단 | D31: La ola de calor | E31: 폭염 | F31: 폭염에 고령 환자가 몰려 응급실이 넘친다. 산소·수액·얼음. Javier는 밤새 환자 이름을 외운다. | G31: 열사병(golpe de calor), 탈수, 고령 환자 | H31: Javier, Marisol(가상), Lucas(가상), Nacho(가상), Rosa·Julián·Carmela·Pilar(가상) | I31: S4·S3 | J31: =턴_설계!$B$5
A32: 3 | B32: 4 | C32: 전개 | D32: Un contrato que no se lee | E32: 읽히지 않는 계약 | F32: 병원이 검사·병상 관리를 Meridiano Salud에 외주한다고 발표한다. 원장 회의에서 컨설턴트 Diego가 '효율' 발표를 한다. | G32: 외주(gestión indirecta), 예산, 입찰 | H32: Javier, Diego, 원장(가상), Marisol(가상), Lucas(가상), Nacho(가상), Amparo(가상) | I32: S3 | J32: =턴_설계!$B$5
A33: 3 | B33: 5 | C33: 전개 | D33: Viernes: la lista | E33: 금요일: 명단 | F33: (프레임) Carmen이 Javier의 수첩 명단을 본다. Javier는 «He visto cosas peores un martes cualquiera.»로 넘긴다. Anselmo는 발목이 부었냐는 물음에 «Es el calzado.» | G33: 명단·숫자 읽기 | H33: Javier, Carmen, Anselmo, Pepa, Cervantes | J33: =턴_설계!$B$5
A34: 3 | B34: 6 | C34: 미드포인트 | D34: La primera de la lista | E34: 명단의 첫 번째 | F34: 서류 없는 20대 여성이 패혈증으로 실려 오지만 병상 배정이 아홉 시간 지연되어 숨진다. 외주 병상관리가 '비용 검토' 중이었다. Javier가 수첩에 첫 이름을 쓴다. | G34: 패혈증(sepsis), 병상 관리, 서류 없는 환자의 접근권(확인) | H34: Javier, Marisol(가상), Nilda·Teresa(가상), Lucas(가상), 원장(가상) | I34: S2·S3 | J34: =턴_설계!$B$5
A35: 3 | B35: 7 | C35: 위기 | D35: Las cifras del director | E35: 원장의 숫자 | F35: 원장이 '대기 시간 개선' 통계를 발표한다. 외주 업체의 재무를 자문하는 Sofía가 배석한다. Javier가 내부 사망 사례 보고서를 제출한다. | G35: 통계 읽기, 보고서 어휘 | H35: Javier, 원장(가상), Sofía, Lucas·Marisol(가상) | I35: P3 | J35: =턴_설계!$B$5
A36: 3 | B36: 8 | C36: 위기 | D36: El expediente | E36: 징계 절차 | F36: 보고서 유출 의혹으로 징계 절차가 시작된다. 취재하는 Inés에게 Javier가 «Esto no sale de aquí.»를 듣는다. | G36: 징계(expediente disciplinario), 비밀유지 | H36: Javier, Inés, 원장(가상), Clara(가상), Lucas·Marisol(가상) | I36: P3 | J36: =턴_설계!$B$5
A37: 3 | B37: 9 | C37: 위기 | D37: Viernes: ¿y cómo te hace sentir? | E37: 금요일: 기분이 어때요? | F37: (프레임) Lucía가 Javier에게 감정을 되묻는다. Javier는 «Primero, respira.»로 받아친다. Carmen이 Lucía의 화법을 흉내 낸다. | G37: 감정 표현, 되받기 화법 | H37: Javier, Lucía, Carmen, Anselmo, Pepa, Cervantes | J37: =턴_설계!$B$5
A38: 3 | B38: 10 | C38: 절정 | D38: Una noche sin camas | E38: 병상 없는 밤 | F38: 버스 사고와 폭염이 겹친 밤. 병상이 없어 복도까지 환자가 찬다. Javier가 즉흥으로 일곱 명을 살리고 한 명을 잃는다. | G38: 대량 환자(catástrofe), 우선순위, 명령형 | H38: Javier, Marisol(가상), Nacho(가상), Aurora·Rubén·Sara(가상) | I38: S4 | J38: =턴_설계!$B$5
A39: 3 | B39: 11 | C39: 절정 | D39: La renuncia del doctor | E39: 의사의 사직 | F39: 징계 통보와 마지막 근무. 수첩을 덮고 사직서를 낸다. Marisol이 «Doctor, no se vaya.» | G39: 사직서, 작별 | H39: Javier, Marisol(가상), 원장(가상), Lucas·Nacho(가상) | J39: =턴_설계!$B$5
A40: 3 | B40: 12 | C40: 결말·훅 | D40: Viernes: una firma | E40: 금요일: 한 사람의 서명 | F40: (프레임) Javier가 «El informe de auditoría del contrato llevaba una firma.»라고 말한다. Sofía가 조용히 «Mi turno.» | G40: 서명·책임 표현 | H40: Javier, Sofía, Carmen, Anselmo, Pepa, Cervantes | J40: =턴_설계!$B$5
A41: 4 | B41: 1 | C41: 발단 | D41: Viernes: yo firmé | E41: 금요일: 내가 서명했다 | F41: (프레임) Sofía가 «A ver los papeles.»를 습관처럼 하다가 «Yo firmé.»라고 시작한다. Carmen이 숫자를 못 읽어 질문한다. | G41: 회계 어휘 도입 | H41: Sofía, Carmen, Javier, Anselmo | J41: =턴_설계!$B$5
A42: 4 | B42: 2 | C42: 발단 | D42: Cierre de ejercicio | E42: 결산 마감 | F42: (과거) Ochoa & Ruiz의 결산 감사 마감 주간. 표본추출(muestreo)과 중요성(materialidad). Sofía의 정확성과 냉소. | G42: 감사 절차 어휘 | H42: Sofía, Ochoa(가상), 후배 감사인(가상) | J42: =턴_설계!$B$5
A43: 4 | B43: 3 | C43: 발단 | D43: El cliente que paga bien | E43: 돈 잘 주는 고객 | F43: Grupo Meridiano가 회사 수임료의 15%를 차지한다. 독립성과 감사인 순환 규정이 문제가 된다. Ochoa는 '관계'를 강조한다. | G43: 독립성, 수임료 집중, 감사인 순환 | H43: Sofía, Ochoa(가상) | J43: =턴_설계!$B$5
A44: 4 | B44: 4 | C44: 전개 | D44: Esto no cuadra | E44: 이건 안 맞아 | F44: 특수관계자 대출이 네덜란드 지주회사로 흘러간 흔적. 은행 자료를 보내 준 Gonzalo가 «Sigue el dinero.» | G44: 특수관계자 거래, 조세 회피처 | H44: Sofía, Gonzalo | J44: =턴_설계!$B$5
A45: 4 | B45: 5 | C45: 전개 | D45: Viernes: el padre de Sofía | E45: 금요일: Sofía의 아버지 | F45: (프레임) 정직한 장부를 지키다 해고된 아버지 이야기. «Enséñame los números y te diré quién eres.»의 기원. | G45: 가족 이야기, 과거 | H45: Sofía, Carmen, Pepa | J45: =턴_설계!$B$5
A46: 4 | B46: 6 | C46: 미드포인트 | D46: La reunión de socios | E46: 파트너 회의 | F46: Sofía가 '한정 의견(con salvedades)'을 주장하자 파트너들이 승진과 고객 유지를 들어 설득한다. Sofía는 리스크 위원회로 사안을 올린다. | G46: 의견 종류: favorable, con salvedades, desfavorable, denegada | H46: Sofía, Ochoa(가상), 파트너들 | J46: =턴_설계!$B$5
A47: 4 | B47: 7 | C47: 위기 | D47: El comité de riesgos | E47: 리스크 위원회 | F47: GM의 변호사 서한이 도착한다(고객 측 변호사는 Mateo의 옛 동료). 위원회는 '증거 불충분'으로 결정한다. | G47: 변호사 서한(carta de abogados), 충분한 증거 | H47: Sofía, 위원회(가상) | I47: P3 | J47: =턴_설계!$B$5
A48: 4 | B48: 8 | C48: 위기 | D48: Una comida en Salamanca | E48: 살라망카의 점심 | F48: Quintana가 Sofía에게 점심을 산다. 정중한 위협과 제안: 파트너 승진과 개인 컨설팅. 기자 Inés의 전화가 온다. | G48: 완곡한 압박, 접속법 조건 | H48: Sofía, Quintana(가상), Inés | J48: =턴_설계!$B$5
A49: 4 | B49: 9 | C49: 위기 | D49: Viernes: ¿y firmó? | E49: 금요일: 서명했나요? | F49: (프레임) Carmen이 묻고 Sofía는 «Espera.»라고 한다. Anselmo가 «Todos firmamos algo alguna vez.»라고 말하고 Javier가 눈을 감는다. | G49: 재촉·회피 | H49: Sofía, Carmen, Anselmo, Javier | J49: =턴_설계!$B$5
A50: 4 | B50: 10 | C50: 절정 | D50: La firma | E50: 서명 | F50: Sofía가 '적정' 의견서에 서명한다. 서명 후 그녀는 복사본 USB를 챙긴다. | G50: 서명, 의견서, 책임 | H50: Sofía, Ochoa(가상) | J50: =턴_설계!$B$5
A51: 4 | B51: 11 | C51: 절정 | D51: Después de la firma | E51: 서명 이후 | F51: 그 의견서로 병원 외주 계약이 확정되고(3부의 계약) 구조조정 컨설팅이 시작된다는 통보를 받는다. Sofía는 사직하고 다시는 서명하지 않겠다고 다짐한다. | G51: 결과·책임, 사직 | H51: Sofía, Ochoa(가상), Diego | J51: =턴_설계!$B$5
A52: 4 | B52: 12 | C52: 결말·훅 | D52: Viernes: la lista de Diego | E52: 금요일: Diego의 명단 | F52: (프레임) Sofía가 USB를 꺼내지 않은 채 식탁에 놓고, Diego가 «Yo hacía la lista.»라고 말한다. | G52: 고백 | H52: Sofía, Diego, Carmen, Pepa | J52: =턴_설계!$B$5
A53: 5 | B53: 1 | C53: 발단 | D53: Viernes: en una matriz | E53: 금요일: 매트릭스로 | F53: (프레임) Diego가 «Pongámoslo en una matriz.»로 시작하다 Carmen에게 제지당한다. | G53: 경영 어휘 도입, 쉬운 말로 바꾸기 | H53: Diego, Carmen, Anselmo, Pepa | J53: =턴_설계!$B$5
A54: 5 | B54: 2 | C54: 발단 | D54: Cenit, planta 32 | E54: Cenit, 32층 | F54: (과거) 컨설팅 회사의 문화: up-or-out, 야근, 영어식 스페인어. Diego의 초고속 승진. | G54: alinear, escalable, impacto, stakeholders | H54: Diego, Almudena(가상), Marcos(가상) | J54: =턴_설계!$B$5
A55: 5 | B55: 3 | C55: 발단 | D55: El taller de los Rueda | E55: Rueda 가족의 공방 | F55: 영세 제조업체 컨설팅. Diego의 '규모 키우기' 권고가 현실과 맞지 않아 실패한다. 생산성은 조언이 아니라 구조의 문제임을 처음 본다. | G55: 영세 기업, 생산성, 규모의 경제 | H55: Diego, Julián Rueda(가상), Alba(가상), Mariano(가상) | I55: E2 | J55: =턴_설계!$B$5
A56: 5 | B56: 4 | C56: 전개 | D56: Proyecto Ícaro | E56: 이카로 프로젝트 | F56: GM(Grupo Meridiano)의 자회사 Meridiano Movilidad(시외버스)가 '12개월 내 비용 18% 절감'을 의뢰한다. 킥오프 회의에서 옛 동기 Marcos가 고객 측으로 재등장하고, 운영 담당 Fermín이 밤에 찾아와 «¿Cuánta gente es un dieciocho por ciento?»라고 묻는다. | G56: 프로젝트 관리, 목표, 절감 | H56: Diego, Almudena Roig(파트너, 가상), Marcos(고객 측, 가상), Ernesto Lastra(GM 재무, 가상), Fermín Robles(운영, 가상), 경비원(단역) | J56: =턴_설계!$B$5
A57: 5 | B57: 5 | C57: 전개 | D57: Viernes: un Excel | E57: 금요일: 엑셀 한 장 | F57: (프레임) Diego가 인쇄한 엑셀 한 장을 들고 온다. Sofía는 킥오프에서 인용된 '한정 없는 감사 의견'이 자기 서명이었음을 확인한다. «Yo no despedía gente; movía celdas.» — «¿Y cuántas celdas?» 숫자는 말하지 않고 힌트 'C47'만 남긴다. | G57: 질문·죄책 표현 | H57: Diego, Carmen, Sofía, Pepa | J57: =턴_설계!$B$5
A58: 5 | B58: 6 | C58: 미드포인트 | D58: La celda C47 | E58: C47 셀 | F58: 모델 v14 완성. 시나리오 A 290명(14%)·B 412명(18.1%)·C 560명(22%). B가 C47에 뜨고 승인된다. 선정 기준 "퇴직 비용 최소"가 사실상 젊은 사람부터 자른다. 어항에서 샴페인. Diego는 Fermín에게 "412"를 썼다 지운다. | G58: 모델, 시나리오, 인원 감축 | H58: Diego, Irene(신입 애널리스트, 가상), Borja(시니어 어소시에이트, 가상), Almudena, Lastra, Marcos | I58: S1 | J58: =턴_설계!$B$5
A59: 5 | B59: 7 | C59: 위기 | D59: La mesa de negociación | E59: 협상 테이블 | F59: ERE 협의 기간 첫 회의(레가네스 본사). Nieves 첫 등장: «¿Tú eres el del Excel?», «Detrás de cada celda hay una persona.» 노조 4안(희망퇴직 45일치·58세 이상 조기퇴직·재배치·초과근무 분배). Diego가 초과근무 310만 유로=약 67개 자리라고 말해 버린다. 마무리에 Marcos에게 이름 붙은 명단을 부탁. | G59: ERE, 협의 기간(30일), 노조 대표 | H59: Diego, Nieves, Cristina Llorente(노무, 가상), Fermín, Marcos, Almudena(전화) | I59: S1 | J59: =턴_설계!$B$5
A60: 5 | B60: 8 | C60: 위기 | D60: El correo equivocado | E60: 잘못 보낸 이메일 | F60: 새벽 1시 52분, 이름 붙은 명단+연령 분석(35세 미만 22%→명단 56%, 임시직 100%)이 자동완성으로 Nieves에게 간다. 개인정보 유출(72시간 신고). Diego는 이카로에서 1주 제외, 직원지원프로그램 상담 → Lucía 첫 등장, 번아웃. 첫 이름 «Yolanda». 14일 파업 표결. | G60: 임시 계약, 청년 우선 해고, 죄책감 | H60: Diego, Irene, Almudena, Cristina(전화), Nieves(전화), Lucía | I60: S1 | J60: =턴_설계!$B$5
A61: 5 | B61: 9 | C61: 위기 | D61: Viernes: cuatrocientos doce | E61: 금요일: 412 | F61: (프레임) 종이를 Carmen에게 맡기고 안 보고 «Cuatrocientos doce.» Carmen이 말을 잃는다. Anselmo «Al menos lo dice sin diapositivas», 세르반테스 «Cada uno es hijo de sus obras». Pepa가 '우리 Nieves', '우리 Lucía'를 알아본다. Carmen: «Seis más que yo.» | G61: 숫자 낭독 | H61: Diego, Carmen, Anselmo, Pepa | J61: =턴_설계!$B$5
A62: 5 | B62: 10 | C62: 절정 | D62: La huelga | E62: 파업 | F62: 14일 파업. Diego는 관제실 유리창 뒤. Yolanda는 필수 유지 근무. 회사는 영상과 '비밀 유지 위반'으로 Nieves 징계 → 2주 뒤 해고, 업계 블랙리스트(«Mejor que no»). Almudena가 Diego의 진술을 막는다. ERE 합의 345명(다른 두 노조 서명). | G62: 파업권, 해고, 블랙리스트 | H62: Diego, Fermín, Nieves, Yolanda Prieto(가상), Cristina, Almudena(전화) | I62: S1 | J62: =턴_설계!$B$5
A63: 5 | B63: 11 | C63: 절정 | D63: La última reunión | E63: 마지막 회의 | F63: 밤 11시 15분 Yolanda와의 대화(«No me lo diga»). 보너스 회의: 5만 5천 유로, 파트너 추천 조건=이카로 2. Quintana가 직접 와서 제안, Diego는 Fermín의 질문을 되돌리고 거절·사직. Almudena의 냉소 최종 답(바야돌리드 공장 거절 과거). C47 한 장 인쇄, 경비원 «해 있을 때 나가는 걸 처음 봤다». | G63: 보너스, 거절, 사직 | H63: Diego, Yolanda, Fermín, Enrique Mazón(대표 파트너, 가상), Almudena, Quintana, Irene, 경비원 | J63: =턴_설계!$B$5
A64: 5 | B64: 12 | C64: 결말·훅 | D64: Viernes: un martes en Vallecas | E64: 금요일: 바예카스의 화요일 | F64: (프레임) Yolanda는 345명에 없었다(초과근무 분배 덕분). Carmen이 종이를 돌려준다. 사직 후 1년, Lucía 숙제 수첩, Rueda 공방이 폐업한 걸 보고 옆 문의 초록 포스터(Carmen이 붙인 것)를 발견. Pepa가 네 사람의 도착 이유를 들려주고, 사흘 뒤 계단에서 Nieves와 재회로 6부 예고. | G64: 다음 이야기 예고 | H64: Diego, Carmen, Mateo, Javier, Sofía, Pepa | J64: =턴_설계!$B$5
A65: 6 | B65: 1 | C65: 발단 | D65: Un martes en Vallecas | E65: 바예카스의 화요일 | F65: 14동 세입자 총회. Carmen·Marina가 문을 연다. Mateo(Marina의 편지), Javier(진료소), Sofía(Fondo Cardinal 이름), Diego(포스터) 순으로 도착. 내용증명의 '전면 리모델링 해지' 조항이 Mateo의 것, 첨부 타당성 검토의 시나리오 셋이 Diego의 템플릿. «Cuatro desconocidos». | G65: 총회 공고, 자기소개 | H65: Mateo, Javier, Sofía, Diego, Marina, Carmen | I65: E1 | J65: =턴_설계!$B$5
A66: 6 | B66: 2 | C66: 발단 | D66: Cuatro desconocidos | E66: 네 명의 낯선 사람 | F66: 계약서 15부를 나눠 읽는다(승계, 최소 5/7년). 회의록에 소속을 적자 Aguirre & Salvat / Ochoa & Ruiz에서 흠칫. Javier가 병원 파란 슬라이드, Sofía가 구조조정 설명을 기억. 건너편 바. 마무리에 Mateo–Sofía가 둘만 있을 때 tú, Carmen이 엿듣는다. | G66: 긴장 대화, usted | H66: Mateo, Javier, Sofía, Diego, Carmen, Marina | J66: =턴_설계!$B$5
A67: 6 | B67: 3 | C67: 발단 | D67: El bloque catorce | E67: 14번 블록 | F67: 금요일 건물 순회. Ramón 첫 등장(«Informo»). 진료소 900장, 철문 빈집 넷(6천 유로씩 cash for keys), Carmen 방의 '포르투갈' 곰팡이. 3층 계단에서 Nieves와 재회(5부 12화 대사 그대로), Diego가 모두 앞에서 메일을 고백. 빈집 순서 = '퇴직 비용 최소'. 옥상에서 법원 통지 소문. | G67: 건물·거주 표현 | H67: Mateo, Javier, Sofía, Diego, Ramón, Nieves, Carmen | I67: E1 | J67: =턴_설계!$B$5
A68: 6 | B68: 4 | C68: 전개 | D68: La noche de la escalera | E68: 계단의 밤 | F68: 5층 계단 보초(두 시간씩 세 조). Pepa·Anselmo 첫 등장(Pepa는 월세 두 배로 가게를 잃음). Mateo–Javier 첫 tú(새벽 1시 45분), Javier의 이름 수첩. Sofía 아버지의 해고와 Diego의 412. Anselmo 만리케 인용. 승합차는 오지 않음. | G68: 밤샘 대화, 위로 | H68: Mateo, Javier, Sofía, Diego, Ramón, Pepa, Anselmo | J68: =턴_설계!$B$5
A69: 6 | B69: 5 | C69: 전개 | D69: Los papeles de Sofía | E69: Sofía의 서류 | F69: Sofía가 USB를 연다(Sofía·Mateo·Carmen). 조직도, 메리디아노 살루드→카르디날 홀딩스 4천만 유로 0.5% 대출, 건물 38채, 14동 '퇴거 진행 중'. Sofía의 서명 경위, Mateo 조항의 출처. 내부신고자 보호법. Carmen이 산 바르톨로메·메리디아노 모빌리다드를 잇는다. | G69: 서류 브리핑, 지분 구조 | H69: Sofía, Mateo, Carmen | J69: =턴_설계!$B$5
A70: 6 | B70: 6 | C70: 미드포인트 | D70: Un mismo nombre | E70: 같은 이름 | F70: (미드포인트) 각자 가져온 것: Javier의 편지, Sofía의 USB, Diego의 C47 종이, Mateo의 내용증명. 병상 인센티브·Nilda, Ochoa & Ruiz 인용, 시나리오 템플릿. Carmen이 식탁보에 조직도. «Mi cliente / Mi contrato / Mi informe / Mi plan.» «Lo sabíamos. No queríamos saberlo.» | G70: 책임 표현, 접속법 | H70: Mateo, Javier, Sofía, Diego, Carmen | I70: E1 | J70: =턴_설계!$B$5
A71: 6 | B71: 7 | C71: 위기 | D71: Reproches | E71: 서로에 대한 비난 | F71: 일요일 비난. Javier↔Sofía(«No me tutees para gritarme»), Diego↔Javier, Mateo↔Diego·Sofía. Mateo가 나가고 Javier가 문을 막는다(«서명할래?»). 사과의 연쇄. Marina의 문자: 목요일 9시 1층 C호 Fátima 강제 퇴거(월세 체납, 남편 Karim은 이카로 정비 외주 해고자). | G71: 다툼, 비난·사과 | H71: Mateo, Javier, Sofía, Diego, Carmen | J71: =턴_설계!$B$5
A72: 6 | B72: 8 | C72: 위기 | D72: Hora cero | E72: 영시 | F72: 목요일 새벽. Raimundo 첫 등장 → 상업등기 공보에서 카르디날 홀딩스의 단독 관리자가 인베르시오네스 메리디아노임을 확인. Javier–Sofía tú. 소견서 4장(면허번호 누락을 Sofía가 발견). 집행 정지 제도·소규모 임대인 예외. Inés 첫 등장. 9시 «Hora cero». | G72: 가처분(medida cautelar), 진단서 | H72: Mateo, Javier, Sofía, Diego, Ramón, Raimundo, Inés | I72: E1·S2 | J72: =턴_설계!$B$5
A73: 6 | B73: 9 | C73: 위기 | D73: La primera suspensión | E73: 첫 정지 | F73: 법원이 집행 정지. Lucía(목요일 상담이 계단으로)·Tomás(Raimundo가 보냄) 첫 등장. Fátima 가족(Adam 9·Salma·Yusuf 4). Diego의 고백과 Fátima «오늘 명단을 택할게요». Tomás의 첫 연설 «Hoy nadie se ha ido. Y nadie se va a ir solo.» Javier–Diego tú. | G73: 안도·감사 표현 | H73: Mateo, Javier, Sofía, Diego, Lucía, Tomás, Fátima(가상), Raimundo, Carmen | I73: S2·E1 | J73: =턴_설계!$B$5
A74: 6 | B74: 10 | C74: 절정 | D74: Un local en Lavapiés | E74: 라바피에스의 가게 | F74: 라바피에스 가게+2층 사무실. 소규모 임대인 Eusebio(Pepa 옛 가게 30년 단골)와 협상 1,900→1,300유로+매일 커피+일요일 토르티야, 5년. Gonzalo 첫 등장(보증서·계좌), «Cardinal Holdings가 우리 지점을 거쳐 갔다». Mateo–Diego tú. Sofía의 첫 서명. | G74: 임대 협상, 소규모 임대인 | H74: Mateo, Javier, Sofía, Diego, Pepa, Eusebio Palacios(가상), Gonzalo | I74: E1 | J74: =턴_설계!$B$5
A75: 6 | B75: 11 | C75: 절정 | D75: Las reglas de la mesa | E75: 식탁의 규칙 | F75: 문짝 테이블 첫 금요일, 14명. 규칙 7개(수임료·다섯 시·금요일 이야기·'오늘은 안 돼'·숫자 아님·서명·면전의 진실·어디서 왔는지 묻지 않음)+각주(매트릭스 금지·청하지 않은 고문). 제비뽑기 순서 Mateo→Javier→Sofía→Diego. Carmen «¿Puedo quedarme?» → 인턴, 월요일부터 usted. | G75: 규칙, 약속 표현 | H75: 전원 14명 (Mateo, Javier, Sofía, Diego, Carmen, Pepa, Anselmo, Ramón, Nieves, Raimundo, Inés, Tomás, Lucía, Gonzalo) | I75: S1 | J75: =턴_설계!$B$5
A76: 6 | B76: 12 | C76: 결말·훅 | D76: El rótulo | E76: 간판 | F76: 월요일. Eusebio의 첫 커피, 1994년 마놀로가 칠한 'Casa Pepa' 간판을 다시 건다. 사무소 이름 «El Despacho de Lavapiés», Pepa의 «casa común»(8부 씨앗). 첫 방문객 Karim(정규직), «첫 번째 명단은 용서 못 해요, 두 번째는 고마워요». Sofía–Diego tú. «Mañana, a las cinco.» | G76: 시간 표현, 마무리 | H76: 전원 + Eusebio, Karim(가상) | J76: =턴_설계!$B$5
A77: 7 | B77: 1 | C77: 발단 | D77: Un año después | E77: 1년 후 | F77: 사무소가 커졌다. Pepa가 팀 이름을 호명하며 역할을 소개한다: Ramón 로지스틱스, Raimundo 출처, Inés 공론화, Lucía 상담, Nieves 현장, Tomás 글, Gonzalo 자금. | G77: 역할·업무 분담 | H77: 전원 | J77: 180
A78: 7 | B78: 2 | C78: 발단 | D78: La cola en la escalera | E78: 계단 위의 줄 | F78: 의뢰인 줄이 계단까지 이어진다. 분류 체계(mesa de entrada)를 세우고 Diego의 매트릭스가 처음으로 쓸모 있어진다. | G78: 접수·분류, 순서 | H78: Diego, Carmen, Ramón, Pepa | I78: S1·E1 | J78: 180
A79: 7 | B79: 3 | C79: 발단 | D79: La ley que castigó a la víctima | E79: 피해자를 벌한 법 | F79: 성폭력 피해자 사건. 유리한 신법 소급으로 가해자의 형량이 줄어든 현실에서 Mateo와 Lucía가 피해자를 돕는다. 법을 폐지하자는 쪽과 고치자는 쪽이 사무실 안에서도 갈린다. | G79: 유리한 신법 소급(형법 제2조 2항), consentimiento | H79: Mateo, Lucía, Sofía, Inés | I79: N4 | J79: 180
A80: 7 | B80: 4 | C80: 전개 | D80: Sin papeles | E80: 서류 없는 사람들 | F80: Fátima의 남편이 체류 자격(arraigo)과 노동 서류 문제를 들고 온다. Nieves는 노동, Javier는 의료 접근을 이야기하고 수용의 한계를 두고 의견이 갈린다. | G80: arraigo, permiso de residencia | H80: Mateo, Nieves, Javier, Fátima(가상) | I80: S2 | J80: 180
A81: 7 | B81: 5 | C81: 전개 | D81: La denuncia de Gonzalo | E81: Gonzalo의 제보 | F81: 전 은행 지점장이 내부 자료를 들고 나온다. 내부고발자 보호법과 보호 채널을 검토한다. | G81: 내부고발자 보호(Ley 2/2023), canal de denuncias | H81: Gonzalo, Mateo, Sofía, Inés | I81: P3 | J81: 180
A82: 7 | B82: 6 | C82: 미드포인트 | D82: El expediente | E82: 사건 파일 | F82: Sofía·Gonzalo의 자금 경로 + Raimundo의 공개 출처 + Javier의 사망 사례. Mateo가 acusación popular로 querella를 쓴다. | G82: querella, acusación popular, Fiscalía Anticorrupción | H82: Mateo, Sofía, Gonzalo, Raimundo, Javier | I82: P3 | J82: 180
A83: 7 | B83: 7 | C83: 위기 | D83: Represalias | E83: 보복 | F83: 명예훼손 소송이 Inés에게, 위생 점검이 Pepa의 바에 날아온다. 익명의 협박이 이어진다. | G83: 명예훼손, 협박, 보복 | H83: Inés, Pepa, Mateo, Ramón | I83: P3 | J83: 180
A84: 7 | B84: 8 | C84: 위기 | D84: El micrófono en la lámpara | E84: 전등 속 마이크 | F84: Raimundo가 Casa Pepa 2층 전등에서 GSM 도청기를 찾아낸다. 되쏘자는 Raimundo와 합법 경로만 쓰자는 Mateo가 충돌하고, 현장을 봉인한 뒤 증거 보존 절차(cadena de custodia)를 밟아 경찰에 신고한다. | G84: 위법 수집 증거, 통신 비밀 | H84: Raimundo, Mateo, Ramón, Pepa, Carmen, Lucía | I84: P3 | J84: 180
A85: 7 | B85: 9 | C85: 위기 | D85: La guardia del barrio | E85: 동네의 보초 | F85: 도청기 발견 이튿날, Nieves가 이웃 43명의 교대 근무표를 들고 온다. 보초의 법적 한계(신원 확인은 경찰만, 현행범 체포 LECrim 490조)를 정하고, 서류 없는 Bilal의 자리를 찾는다. Tomás는 건물주 Eusebio의 서면 허가로 벽에 첫 문장을 쓴다. 새벽, 후드 쓴 사람이 다시 나타난다. | G85: 연대·조직 표현 | H85: Nieves, Tomás, Pepa, Ramón, Karim, Bilal, Eusebio | J85: 180
A86: 7 | B86: 10 | C86: 절정 | D86: El auto | E86: 법원 결정 | F86: LexNET으로 결정문 도착. Audiencia Nacional 중앙예심법원이 고소를 수리하고 GM 임원 3명(Lastra·Olmedo·Ferrández, 가상)을 피의자로 소환. 시민 소추인에게 10일 안에 보증금 6천 유로 → 동네가 하루 만에 모은다. Inés는 '무죄 추정'을 지켜 기사를 쓴다. 저녁, 국회 공보에 법안 하나. | G86: 결정문(auto), imputación, comparecencia | H86: Mateo, Sofía, Inés, Gonzalo, Karim | I86: P3 | J86: 180
A87: 7 | B87: 11 | C87: 절정 | D87: La ley que viene | E87: 다가오는 법 | F87: 시민 소추 제한 조직법안(가상)에 '진행 중인 절차에도 적용' 경과 규정. Anselmo는 반대편의 가장 강한 논거(정치적 괴롭힘)를 내놓고, 사무소는 헌법 124·125조로 맞선다. Diego(숫자)와 Nieves(거리)가 부딪치다 손을 잡는다. Anselmo의 '마지막 겨울'. | G87: 입법 발의, 제한 | H87: Anselmo, Mateo, Diego, Nieves | I87: P1·P3 | J87: 180
A88: 7 | B88: 12 | C88: 결말·훅 | D88: Una silla en Sol | E88: 솔의 의자 | F88: 하원이 법안 심의 개시를 170:165로 의결(조직법 통과 176표까지 6표 부족). Nieves가 Sol 집회를 제안, Ramón은 '20명 초과' 기준으로 인원을 센다. Picasso의 서명 없는 포스터, Pepa가 식탁 의자를 0km 지점에 놓는다. Mateo: «Tenemos que cambiar la ley.» | G88: 결단, 제안 | H88: 전원 | I88: P1 | J88: 180
A89: 8 | B89: 1 | C89: 발단 | D89: La asamblea en Sol | E89: 솔 광장의 집회 | F89: 의뢰인들이 Sol에 모인다. 20명 초과라 정부 대표부에 열흘 전 신고, '목적'란과 주최자 서명을 두고 Mateo·Ramón 실랑이. 의뢰인들이 직접 마이크를 잡고 Mateo가 처음 연설한다. | G89: 집회는 사전 통지(LO 9/1983). Sol은 Comunidad de Madrid 청사(Real Casa de Correos) 앞 | H89: Nieves, Ramón, Mateo, Karim, Ángeles, Yolanda | I89: E1·S2 | J89: 180
A90: 8 | B90: 2 | C90: 발단 | D90: Del caso a la ley | E90: 사건에서 법으로 | F90: 사건 파일 47권 중 19건에 같은 조항 — 11년 전 Mateo가 Aguirre y Salvat에서 쓴 '공사를 이유로 한 계약 해지'. LAU상 무효인데 왜 통하는가. 세 가지 길 중 ILP 선택, 발의 위원회 구성. | G90: 법을 바꾸는 세 길: 정부 proyecto, 의원 proposición, 시민 입법발의(ILP) | H90: Mateo, Carmen | J90: 180
A91: 8 | B91: 3 | C91: 발단 | D91: Quinientas mil firmas | E91: 50만 서명 | F91: 하원 의장단이 ILP «Ley de volver a casa» 수리 → 9개월 안에 50만 서명. Pepa·Carmen이 fedatarias especiales로 선서. 서명할 수 없는 사람들(Bilal, 17세 Noa, 법적으로 죽은 Picasso). 여름. | G91: ILP는 서명 50만 (LO 3/1984) | H91: Pepa, Nieves, Carmen, Karim, Bilal, Noa | I91: S1·S2 | J91: 180
A92: 8 | B92: 4 | C92: 전환점 | D92: La toma en consideración | E92: 심의 개시 표결 | F92: 54만 서명. 심의 개시 표결 찬성 78, 반대 168, 기권 104로 기각. 방청석에선 박수·야유 금지. 반대 측의 가장 강한 논거('이미 무효인 조항'). | G92: 큰 정당들이 반대하면 좌초 가능 (헌법 제87조 3항) | H92: Mateo, Inés, Ángeles, Diego, Carmen | J92: 180
A93: 8 | B93: 5 | C93: 미드포인트 | D93: Nace un partido | E93: 정당의 탄생 | F93: 부결 다음 날 다섯 시, Pepa의 «casa común»이 당명이 된다. 공증인 앞 창립 문서 → 내무부 정당 등록부. Picasso는 서명할 수 없고, 기자 Inés는 스스로 서명하지 않는다. Mateo 당 대표. | G93: acta fundacional + Registro de Partidos Políticos 등록 → 법인격 (LO 6/2002) | H93: Pepa, Tomás, Mateo, Picasso, Inés | J93: 180
A94: 8 | B94: 6 | C94: 위기 | D94: Los estatutos | E94: 정관 | F94: Diego의 조직도 vs Nieves의 한 장짜리 원칙. 확정: 총회 주권, 집행위 7인(총회 위임), 3/5 소환, 돈은 두 사람 서명, 피의자 처리 규정, 급여 상한(20년 차 버스 기사 수준, 초과분은 당·파업 기금), 임기 2회 제한, 1인 1표 경선. 첫 총회 표결. | G94: 정당 내부 운영은 민주적이어야 함 (헌법 제6조) | H94: Diego, Nieves, Mateo, Sofía, Karim | I94: P1 | J94: 180
A95: 8 | B95: 7 | C95: 위기 | D95: El dinero limpio | E95: 깨끗한 돈 | F95: 은행이 KYC를 이유로 계좌를 미룬다 → Gonzalo의 옛 인턴 Lorena(지점장). 정당재정법 규칙(법인·익명 기부 금지, 1인 연 5만 상한) + 자체 상한 3천. Fundación Hogar y Futuro(이사장 Beatriz Olmedo)의 '합법' 거액 제안 거절. | G95: 정당 재정 LO 8/2007, LO 3/2015, Tribunal de Cuentas | H95: Sofía, Gonzalo, Lorena, Emisario | J95: 180
A96: 8 | B96: 8 | C96: 위기 | D96: Las candidaturas | E96: 후보 명부 | F96: 5월 지방·자치 선거 소집. 시의회 1번 Sofía, 2번은 cremallera로 Gonzalo(남), 3번 Milagros. 자치의회 1번 Javier, 2번 Yolanda. Pepa는 57번, Rafa Rueda 41번. Carmen이 후보 67명 수락서를 마감 전 제출. | G96: 폐쇄·봉쇄 명부, 성별 균형(LO 3/2007) | H96: Sofía, Javier, Carmen, Diego, Nieves, Milagros, Yolanda | I96: N4·S1 | J96: 180
A97: 8 | B97: 9 | C97: 위기 | D97: La campaña en los barrios | E97: 골목길 캠페인 | F97: 자정의 포스터 붙이기. 무료 게시 공간은 직전 득표 비례라 CC 몫은 최소. 바예카스 14동 가가호호, 날카로운 반론. 선거권 없는 Bilal은 손을 보탠다. Tomás의 첫 자기 이름 연설. | G97: 공식 캠페인 기간, Junta Electoral 감독 | H97: Tomás, Pepa, Ramón, Marina, Bilal | I97: E1·E2·S2 | J97: 180
A98: 8 | B98: 10 | C98: 절정 | D98: El ataque de la prensa | E98: 언론의 공격 | F98: 선거 엿새 전 1면 «2번 후보, 은행에서 비리로 해고». 반박 성명 대신 정정보도 청구(LO 2/1984: 사실만, 7일 안, 3일 안 게재). Gonzalo가 딸 Laura(간호사)에게 내부 고발 이야기를 한다. | G98: 정정권(LO 2/1984), Junta Electoral 제소 | H98: Inés, Mateo, Gonzalo, Laura | J98: 180
A99: 8 | B99: 11 | C99: 절정 | D99: La jornada de reflexión | E99: 숙고의 날 | F99: 숙고의 날. Diego의 마지막 영상 유혹, 공표 못 하는 내부 조사(9% — 5% 문턱까지 떨어질 수도). 추첨으로 투표소 사무원이 된 Carmen의 '중립'. Lucía의 질문이 처음으로 위로가 된다. | G99: 선거 전날 선거운동 금지, 마지막 5일 여론조사 공표 금지 (LOREG) | H99: Lucía, Diego, Carmen | J99: 180
A100: 8 | B100: 12 | C100: 결말·훅 | D100: La noche de las urnas | E100: 개표의 밤 | F100: Carmen은 투표소 사무원(전화로만 합류). 시의회 57석: UCN 23·PPS 19·CC 9(14.8%)·HU 5·Plataforma Vecinal 1, 자치의회 CC 11석(가상). 과반 29 없음 → 알칼데는 다른 당 몫. | G100: 문턱 5%, 시의회 과반 29석 | H100: 전원, Bilal, Yolanda | J100: 180
A101: 9 | B101: 1 | C101: 발단 | D101: La constitución de la Corporación | E101: 시의회 개원 | F101: 개원 전날 밤 PPS가 제안: PPS 19+CC 9+PV 1=29로 Marta Iriarte 알칼데, 대가로 Sofía 주거 부시장 + 조례 1년 유예. 당원 긴급 투표 84% 거부. 연령 의장단(73세 UCN 의원 + 최연소 Iker 24세), 선서, 비밀투표 UCN 28·Iriarte 19·Sofía 9·백지 1 → LOREG 196으로 UCN 명부 1번 알칼데. Sofía가 제안을 공개하고 조례 등록. | G101: 알칼데: 과반 29표 또는 최다득표 명부 1번 (LOREG 제196조) | H101: Sofía, Mateo, Carmen, Gonzalo, Milagros, Iker, Diego, Nieves, Negociadora(PPS), Secretario | J101: 180
...

Sheet 복선_회수
A1: 복선 설치와 회수 (Setup → Payoff)
A2: 설치 부와 회수 부의 간격(부 수)은 수식으로 계산됩니다. 간격이 클수록 오래 기다린 복선이라 낭독 시 기억에 남습니다.
A4: No | B4: 복선(설치) | C4: 유형 | D4: 설치 부 | E4: 설치 위치 | F4: 회수 부 | G4: 간격(부) | H4: 회수 위치와 효과 | I4: 관련 인물
A5: 1 | B5: Anselmo의 «Este será mi último invierno» 반복 | C5: 대사 | D5: 1 | E5: 1부 1화 | F5: 11 | G5: =F5-D5 | H5: 11부 12화 — 양치기 소년 개그가 진짜 죽음이 되는 낙차 | I5: Anselmo
A6: 2 | B6: Anselmo가 Carmen에게 우산을 물려준다고 말한다 | C6: 소품 | D6: 1 | E6: 1부 1화 | F6: 13 | G6: =F6-D6 | H6: 13부 2화 — 유언장에서 우산이 진짜 유산으로 돌아옴 | I6: Anselmo, Carmen
A7: 3 | B7: Anselmo의 부은 발목·숨참 | C7: 설정 | D7: 3 | E7: 3부 1·5화 | F7: 11 | G7: =F7-D7 | H7: 11부 4~6화 — Javier가 진단을 알고도 침묵한 이유가 드러남 | I7: Javier, Anselmo
A8: 4 | B8: Anselmo의 최고 칭찬 «No está mal.» | C8: 대사 | D8: 1 | E8: 1부 7화(Tomás에게 1회) | F8: 11 | G8: =F8-D8 | H8: 11부 12화 — Carmen에게 처음이자 마지막 칭찬, 브뤼셀 승리 직후라 더 무겁다 | I8: Anselmo, Carmen
A9: 5 | B9: Carmen의 1차 폭발 | C9: 사건 | D9: 1 | E9: 1부 6화 | F9: 9 | G9: =F9-D9 | H9: 9부 6화 — 몰라서 화내던 Carmen → 알아서 화내는 Carmen | I9: Carmen
A10: 6 | B10: Carmen의 usted (Anselmo에게) | C10: 호칭 | D10: 1 | E10: 1부 1화 | F10: 11 | G10: =F10-D10 | H10: 11부 7화 — 조사에서 처음 tú — 호칭 전환이 곧 애도 | I10: Carmen, Anselmo
A11: 7 | B11: Raimundo의 카드 #1과 «Búscalo tú.» | C11: 대사 | D11: 1 | E11: 1부 2화 | F11: 13 | G11: =F11-D11 | H11: 13부 10화 — 끝까지 결론을 말하지 않던 그가 처음 답을 말함 | I11: Raimundo, Carmen
A12: 8 | B12: Mateo의 조항 «resolución por obras» | C12: 사건 | D12: 2 | E12: 2부 6화 | F12: 11 | G12: =F12-D12 | H12: 11부 3화 — 자기가 만든 조항을 국정에서 폐지 | I12: Mateo
A13: 9 | B13: Sofía의 «Esto no cuadra» | C13: 대사 | D13: 2 | E13: 2부 4화 | F13: 4 | G13: =F13-D13 | H13: 4부 4화 — 감사인의 눈이 처음 이상을 발견한 순간의 원점 | I13: Sofía
A14: 10 | B14: Mateo와 Sofía, tú로 전환 | C14: 관계 | D14: 2 | E14: 2부 10화 | F14: 6 | G14: =F14-D14 | H14: 6부 — 레스토랑 테라스에서 «같은 배를 탄 사람들끼린 말을 놓는다»며 처음 tú 사용 — 6부 재회 시 이미 tú인 이유 | I14: Mateo, Sofía
A15: 11 | B15: Sofía의 복사본 USB | C15: 소품 | D15: 4 | E15: 4부 10화 | F15: 7 | G15: =F15-D15 | H15: 7부 5~6화 — 서명의 죄가 고소의 증거로 바뀜 | I15: Sofía, Mateo
A16: 12 | B16: Sofía의 «다시는 서명하지 않는다» | C16: 인물 | D16: 4 | E16: 4부 11화 | F16: 11 | G16: =F16-D16 | H16: 11부 9화 — «Yo solo firmo lo que he verificado» — 숫자 서명의 회수 | I16: Sofía
... A63: 59 | B63: Iker — 7부 2화 가짜 인턴 의뢰인 | C63: 인물 | D63: 7 | E63: 7부 2화 | F63: 9 | G63: =F63-D63 | H63: [회수 완료 v26] 9부 1화 최연소 시의원·연령 의장단 | I63: Iker, Sofía
B65: 평균 간격(부) | G65: =AVERAGE(G5:G63)
B66: 가장 긴 복선(부) | G66: =MAX(G5:G63)
B67: 복선 개수 | G67: =COUNTA(B5:B63)

Sheet 현안_배치
A1: 스페인 현안 15개 배치표
A2: 현재 스페인의 쟁점을 이야기 곳곳에 녹이는 계획. 현실의 정당·정치인·참사 희생자는 특정하지 않고 가상 설정으로 각색하며, 제도와 통계만 현실 기준으로 쓴다.
A4: ID | B4: 분야 | C4: 현안 | D4: 스페인어 키워드 | E4: 이야기 속 가상 설정 | F4: 주요 배치 (전용 화) | G4: 곁가지 배치 | H4: 주요 인물 | I4: 권한 소재 | J4: 관련 제도·법 | K4: 낭독 어휘 | L4: 균형·민감도 유의 | M4: 현실 기준값·확인
A5: P1 | B5: 정치 | C5: 정치 파편화와 연정 불안정 | D5: fragmentación, pacto, apoyo puntual, geometría variable | E5: 어떤 정당도 과반이 안 되는 의회. 법안마다 협상 비용이 든다. Casa Común도 소수 정부로 표결마다 다른 파트너를 찾아야 한다. | F5: 9부 5화 불편한 동맹, 10부 8화 두 달의 시계, 11부 10화 합쳐지지 않는 불신임안 | G5: 8부 6화(왜 새 정당인가: 양당 피로), 12부 7화 | H5: Diego, Mateo, Nieves | I5: 하원·시의회 | J5: 헌법 제99·113·134조, 정당 간 협약 | K5: fragmentación, pacto de investidura, cesión, mayoría, bloqueo | L5: 특정 실존 정당·인물을 비난하는 대사 금지. 가상 정당(UCN·PPS·HU·TA·TB)으로만. | M5: 현 정부는 소수 연립 + 지역정당 지지 의존(2026-09 확인). 이야기에는 쓰지 않음
A6: P2 | B6: 정치 | C6: 지역 갈등·사면·재정 분권 | D6: amnistía, indulto, financiación autonómica, Tribunal Constitucional | E6: 지역정당 연합 TB가 지지의 대가로 과거 '독립 추진' 사건 관련자의 사면과 재정 분권을 요구한다. 총리 지명이 여기에 걸린다. | F6: 10부 11화 총리 지명 협상 | G6: 10부 3화(TV 토론 공격), 11부 10화(불신임안에서 TB의 기권), 12부 7화 | H6: Mateo, Anselmo, Nieves, Diego | I6: 하원, 헌법재판소, 자치주 | J6: 헌법 제62조 i, 사면법(LO 1/2024), LOFCA·CPFF | K6: amnistía vs indulto, soberanía, cupo, compensación | L6: 가장 민감. 찬성·반대 논거를 각 인물이 나눠 말하게 하고 결론은 열어 둔다(Mateo는 헌법 우려, Nieves는 지역 간 형평, Diego는 현실 협상). | M6: 사면법 후폭풍과 사법 절차 진행 상황은 반영 전 확인
A7: P3 | B7: 정치 | C7: 사법부 독립과 정치적 대립 | D7: CGPJ, renovación, dilaciones indebidas, instrucción | E7: 사법평의회 갱신이 정당 대립으로 막혀 스캔들 수사가 표류한다. 사무소의 고소가 법원에서 지연된다. | F7: 7부(고소·법원 결정·보복), 9부 9화 고소장 | G7: 2부 8화(재판), 3부(징계·외주), 4부 7화, 10부 11화(협상 조건), 11부 10화(교착) | H7: Mateo, Inés, Raimundo | I7: 하원·상원(위원 선출), 사법부 | J7: 헌법 제122조, LOPJ, 3/5 다수 | K7: renovación, mayoría de tres quintos, dilaciones, instrucción | L7: 여야 모두가 사법부를 압박한다는 비판을 각각 담는다. 실제 재판 결과를 단정하지 않는다. | M7: 최신 갱신 상황 확인
A8: E1 | B8: 경제 | C8: 주거난과 단기 관광 임대 | D8: vivienda, zona tensionada, vivienda turística, gran tenedor, licencia | E8: 월세가 임금보다 빨리 오르고 관광 아파트가 동네를 비운다. 소규모 임대인의 입장(Pepa의 친구)도 대사에 넣는다. | F8: 2부 6화(조항 설계), 6부 1·3·8·10화(Vallecas), 9부 6화(임대 보조 삭감·관광 아파트 조항), 11부 2·3화 | G8: 1부 1·2화(Fátima), 8부 1·9화, 12부 | H8: Pepa, Carmen, Sofía, Mateo | I8: 자치주(주거), 시(도시계획·인허가), 국가(기본 조건·세제) | J8: LAU, Ley 12/2023, 단기임대 등록제(2025, 확인) | K8: vivienda turística, zona tensionada, alquiler de temporada, pequeño propietario | L8: 임차인만 피해자로 그리지 않는다. 소규모 임대인·대형 보유자를 구분해서 말한다. | M8: 단기임대 규제 세부는 확인
A9: E2 | B9: 경제 | C9: 저생산성과 영세 기업 구조 | D9: microempresa, pyme, productividad, I+D, tamaño empresarial | E9: Diego가 컨설팅한 규모의 경제 없는 영세 제조업체들: 해고 없이 살릴 길을 못 찾았던 과거. 11부에서 영세 기업 통합·R&D 전환 사업을 설계한다. | F9: 5부 3화 Rueda 공방 | G9: 8부 9화(골목 상권), 11부 9화, 12부 7화 | H9: Diego, Pepa, Nieves | I9: 국가·자치주 | J9: R&D 세액공제·사회보험(확인), ERE | K9: productividad, escalar, consolidación, I+D+i | L9: '영세 기업이 문제'라는 식의 낙인 대신 구조 문제로 설명한다. | M9: 통계 수치는 반영 전 확인
A10: E3 | B10: 경제 | C10: 국가 부채와 재정 건전성 | D10: deuda pública, regla de gasto, pensiones, revalorización | E10: 부채를 줄이라는 EU 압박과 연금·보건 지출 증가 사이의 줄타기. Sofía가 숫자로 설명하고 Carmen이 되묻는다. | F10: 11부 9화(EU 재정규칙), 11부 12화(예산안) | G10: 12부 7화 | H10: Sofía, Anselmo(메모), Gonzalo | I10: 국가·EU | J10: 중기 재정구조계획, TFUE 126, Pacto de Toledo | K10: deuda, déficit, regla de gasto, sostenibilidad | L10: 긴축 vs 확대 양쪽 논거를 모두 숫자로 제시한다. | M10: 부채는 GDP 대비 약 100% (2026.7 99.9%, 6월 101.5%, 스페인은행)
A11: S1 | B11: 사회 | C11: 청년 고용 불안 | D11: becario, contrato temporal, contrato formativo, SMI | E11: 임시 계약과 저임금으로 청년의 자립이 늦어진다. Carmen이 그 당사자이자 질문자다. | F11: 11부 6화, 12부 5·6화 | G11: 1부(Carmen), 5부(Diego의 인력 감축), 8부, 10부 3화 | H11: Carmen, Nieves, Diego | I11: 국가(노동법)·사회적 대화 | J11: 사회적 대화, 인턴 사회보험(2023 개정, 확인) | K11: becario, contrato, salario mínimo, precariedad | L11: 청년 vs 기성세대 구도로 몰지 않는다(Nieves도 Anselmo도 청년의 편에서 돕는다). | M11: 25세 미만 실업률 23.8%(2026 2분기), 전체 9.9%, 약 2.4배 (INE EPA 2026-09 확인)
A12: S2 | B12: 사회 | C12: 이민·난민과 수용 분담 | D12: arraigo, permiso de residencia, menor no acompañado, acogida, asilo | E12: Lavapiés는 다국적 동네다. 서류 없는 이웃, 체류 자격 사건, 도착 지역의 수용 과부하와 자치주 간 떠넘기기. | F12: 6부 8·9화(퇴거 저지·서류 없는 이웃), 7부 4화(체류 자격), 11부 5화 분담 | G12: 1부 2화, 3부 6화(서류 없는 환자), 8부(투표권 없는 이웃), 10부 3화, 12부 | H12: Pepa, Javier, Mateo, Nieves, Lucía | I12: 국가(외국인법·국경), 자치주(아동 보호·수용) | J12: LO 4/2000, Ley 12/2009, 이주 아동 분산 조치(2025, 확인) | K12: arraigo, acogida, menor no acompañado, solicitud de asilo | L12: 반이민 여론(HU)과 수용 부담 지역의 실제 어려움을 함께 담고, 이주민을 배경이 아닌 화자로 세운다. | M12: 2025년 분산 수용 조치의 현재 상태 확인
A13: S3 | B13: 사회 | C13: 고령화와 텅 빈 스페인(España Vaciada) | D13: despoblación, envejecimiento, natalidad, pensiones | E13: 농촌 진료소가 문을 닫고 자치주는 병원 외주를 늘린다(9부). Ramón의 고향은 학교도 병원도 문을 닫은 내륙 마을이고, 캠페인이 그곳을 지나며 일자리·의료·연금 문제가 되풀이된다(10부). | F13: 9부 7화 자치의회에서의 보건 | G13: 3부(응급실 고령 환자), 10부 2화(Ramón의 고향 마을), 11부 4화, 12부 | H13: Ramón, Javier, Carmen | I13: 자치주·시·국가 | J13: 헌법 제68조 2항(선거구 최소 의석), Pacto de Toledo | K13: despoblación, envejecimiento, natalidad, consultorio rural | L13: '텅 빈 스페인'을 동정하지 않고 마을 사람들이 직접 말하게 한다. | M13: 인구·출생 통계는 반영 전 확인
A14: S4 | B14: 사회 | C14: 가뭄·폭염과 에너지 전환 부담 | D14: sequía, ola de calor, embalse, restricciones de agua | E14: 폭염에 응급실이 넘치고(3부), 저수지가 마른 마을을 지나며(10부), 횡재세 재원을 전환 비용에 쓸지 논쟁한다(11부). | F14: 3부 3·10화(폭염 응급실) | G14: 10부 2화, 11부 4·8·11화, 12부 | H14: Javier, Ramón, Sofía | I14: 국가·자치주·유역기관 | J14: 폭염 경보, 수자원 관리(확인) | K14: sequía, ola de calor, AEMET, embalse, transición energética | L14: 기후를 정치적 구호로 쓰지 않고 현장 사건으로 보여 준다. | M14: 최신 가뭄·폭염 통계 확인
A15: N1 | B15: 재난 | C15: DANA와 방재 체계 | D15: DANA, gota fría, aviso rojo, ES-Alert, UME, damnificados | E15: 지중해 연안에 가상의 DANA 폭우가 덮친다. 경보 지연, 자치주–중앙정부 책임 공방, 긴급사태 선언 여부, 군 투입, 복구와 보험 보상. | F15: 11부 11화 La Gota Fría | G15: 12부(복구 결산) | H15: Ramón, Javier, Mateo, Inés, Tomás | I15: 자치주(1차 대응), 국가(긴급사태·군), EU | J15: Ley 17/2015, 보험보상 기구, EU 연대기금 | K15: protección civil, aviso rojo, emergencia de interés nacional, damnificados | L15: 실제 참사와 희생자를 연상시키므로 추모의 톤을 지키고, 특정 정치인 비난 없이 제도의 공백을 보여 준다. | M15: 실제 사건의 후속 조치·재판은 반영 전 확인
... A22: N8 | B22: 사회 | C22: 청년 정신건강 위기 | D22: salud mental, ansiedad, lista de espera, terapia | E22: 청년 정신건강 상담 대기가 몇 달씩 밀린다. Lucía가 진료 현장에서, Carmen이 자신의 불안을 처음 인정하며 함께 부딪힌다. | F22: 12부 6화 Las Listas de Espera | G22: 1부(Carmen의 폭발과 연결 가능, 곁가지) | H22: Lucía, Carmen, Javier | I22: 자치주(공공 심리 지원) | J22: 정신건강 상담 접근성, 공공 예산 | K22: salud mental, ansiedad, terapia, lista de espera | L22: 청년 정신건강을 극적 소재로만 소비하지 않는다. 낙인 없이, 도움을 구하는 것이 자연스럽다는 톤으로. | M22: 청년 불안장애·상담 대기 증가는 스페인에서 널리 보도된 추세. 최신 통계는 확인 필요
A24: 현실 기준값 (확인일 2026-09-22)
A25: No | B25: 구분 | C25: 항목 | D25: 값 | E25: 출처·비고
A26: 1 | B26: 경제 | C26: 정부 부채 / GDP | D26: 약 100% (2026.7 99.9%, 6월 101.5%) | E26: 스페인은행(Banco de España) 월간 통계. 붙여 주신 자료의 97~99%보다 조금 높다.
A27: 2 | B27: 사회 | C27: 25세 미만 실업률 | D27: 23.8% (2026 2분기), 전체 9.9% | E27: INE 경제활동인구조사(EPA). 청년 실업은 전체의 약 2.4배.
A28: 3 | B28: 정치 | C28: 현 정부 형태 | D28: 소수 연립 + 지역정당 지지 의존 | E28: 이야기에는 실존 정당·인물을 쓰지 않는다. 표현은 '여소야대'가 아니라 '소수 정부'.
A29: 4 | B29: 확인 필요 | C29: 변동이 잦은 항목 | D29: 사면법 절차, DANA 후속, NATO 목표, 이주 아동 분산, 회복기금 시한 | E29: 교재에 넣기 직전 최신 상태를 확인한다.

Sheet 현안_분포
A1: 현안 분포표 (부 × 현안)
A2: ● = 그 화의 주된 사건(전용 화), ○ = 곁가지(대사·서브플롯). 기호를 바꾸면 아래 집계가 자동 갱신됩니다.
A4: ID | B4: 현안 | C4: 1부 | D4: 2부 | E4: 3부 | F4: 4부 | G4: 5부 | H4: 6부 | I4: 7부 | J4: 8부 | K4: 9부 | L4: 10부 | M4: 11부 | N4: 12부 | O4: 13부 | P4: ● 수 | Q4: ○ 수
A5: P1 | B5: 정치 파편화·연정 불안정 | I5: ○ | J5: ○ | N5: ● | O5: ○ | P5: =COUNTIF(C5:O5,"●") | Q5: =COUNTIF(C5:O5,"○")
A6: P2 | B6: 지역 갈등·사면·재정 분권 | N6: ● | O6: ○ | P6: =COUNTIF(C6:O6,"●") | Q6: =COUNTIF(C6:O6,"○")
A7: P3 | B7: 사법부 독립·정치 대립 | D7: ○ | E7: ○ | F7: ○ | I7: ● | K7: ● | N7: ○ | P7: =COUNTIF(C7:O7,"●") | Q7: =COUNTIF(C7:O7,"○")
A8: E1 | B8: 주거난·단기 관광 임대 | C8: ○ | D8: ● | H8: ● | I8: ○ | J8: ○ | M8: ● | O8: ○ | P8: =COUNTIF(C8:O8,"●") | Q8: =COUNTIF(C8:O8,"○")
A9: E2 | B9: 저생산성·영세 기업 | C9: ○ | G9: ● | J9: ○ | N9: ○ | O9: ○ | P9: =COUNTIF(C9:O9,"●") | Q9: =COUNTIF(C9:O9,"○")
A10: E3 | B10: 부채·재정·연금 | M10: ● | N10: ● | O10: ○ | P10: =COUNTIF(C10:O10,"●") | Q10: =COUNTIF(C10:O10,"○")
A11: S1 | B11: 청년 고용 불안 | C11: ○ | G11: ○ | H11: ○ | I11: ○ | J11: ○ | O11: ● | P11: =COUNTIF(C11:O11,"●") | Q11: =COUNTIF(C11:O11,"○")
A12: S2 | B12: 이민·난민·수용 분담 | C12: ○ | E12: ○ | H12: ● | I12: ● | J12: ○ | M12: ● | P12: =COUNTIF(C12:O12,"●") | Q12: =COUNTIF(C12:O12,"○")
A13: S3 | B13: 고령화·텅 빈 스페인 | E13: ○ | K13: ● | O13: ○ | P13: =COUNTIF(C13:O13,"●") | Q13: =COUNTIF(C13:O13,"○")
A14: S4 | B14: 가뭄·폭염·에너지 전환 | E14: ● | N14: ○ | O14: ○ | P14: =COUNTIF(C14:O14,"●") | Q14: =COUNTIF(C14:O14,"○")
A15: N1 | B15: DANA·방재 | N15: ● | O15: ○ | P15: =COUNTIF(C15:O15,"●") | Q15: =COUNTIF(C15:O15,"○")
A16: N2 | B16: 회복기금 집행 | K16: ● | O16: ○ | P16: =COUNTIF(C16:O16,"●") | Q16: =COUNTIF(C16:O16,"○")
A17: N3 | B17: 국방비·NATO | M17: ● | N17: ○ | O17: ○ | P17: =COUNTIF(C17:O17,"●") | Q17: =COUNTIF(C17:O17,"○")
A18: N4 | B18: 성평등·성폭력 법 | I18: ● | J18: ○ | P18: =COUNTIF(C18:O18,"●") | Q18: =COUNTIF(C18:O18,"○")
A19: N5 | B19: 녹색 대 녹색 | L19: ● | M19: ○ | N19: ○ | P19: =COUNTIF(C19:O19,"●") | Q19: =COUNTIF(C19:O19,"○")
A20: N6 | B20: 플랫폼 노동(라이더법) | N20: ● | P20: =COUNTIF(C20:O20,"●") | Q20: =COUNTIF(C20:O20,"○")
A21: N7 | B21: 정보기관 사찰 스캔들 | N21: ● | P21: =COUNTIF(C21:O21,"●") | Q21: =COUNTIF(C21:O21,"○")
A22: N8 | B22: 청년 정신건강 | N22: ● | P22: =COUNTIF(C22:O22,"●") | Q22: =COUNTIF(C22:O22,"○")
B23: 부별 ● 수 | C23: =COUNTIF(C5:C22,"●") | D23: =COUNTIF(D5:D22,"●") | E23: =COUNTIF(E5:E22,"●") | F23: =COUNTIF(F5:F22,"●") | G23: =COUNTIF(G5:G22,"●") | H23: =COUNTIF(H5:H22,"●") | I23: =COUNTIF(I5:I22,"●") | J23: =COUNTIF(J5:J22,"●") | ... O23: =COUNTIF(O5:O22,"●") | P23: =SUM(P5:P22)
B24: 부별 ○ 수 | C24: =COUNTIF(C5:C22,"○") | D24: =COUNTIF(D5:D22,"○") | E24: =COUNTIF(E5:E22,"○") | F24: =COUNTIF(F5:F22,"○") | G24: =COUNTIF(G5:G22,"○") | H24: =COUNTIF(H5:H22,"○") | I24: =COUNTIF(I5:I22,"○") | J24: =COUNTIF(J5:J22,"○") | ... O24: =COUNTIF(O5:O22,"○") | Q24: =SUM(Q5:Q22)
A26: 읽는 법: 1~5부는 곁가지 중심이라 B1~B2 난이도를 지키고, 8·9·11·12부에서 전용 화가 몰린다. 화당 전용 현안은 1개(+곁가지 1~2개)로 제한해 낭독 분량을 지킨다. N6~N8은 12부의 신규 현안으로 각 1개 전용 화를 받는다.
A27: 현안 ID와 설명은 '현안_배치' 시트, 화별 반영은 '화별목차_전체'의 '반영 현안' 열을 참고.

Sheet 정치제도
A1: 현실 정치 제도 기준표 (스페인)
A2: 8~12부에 반영한 실제 제도. 정당·정치인은 전부 가상이며 실존 정치인의 대사는 쓰지 않는다. '검색 확인' 표시는 2026-09-22 기준 자료로 확인한 항목.
A4: 영역 | B4: 제도·규칙 | C4: 핵심 내용 | D4: 근거 | E4: 이야기 반영 | F4: 낭독 어휘 | G4: 확인 상태
A5: 정당·선거 | B5: 정당 창당 | C5: 정당은 창립자들이 서명한 acta fundacional(창립 문서)을 내무부의 Registro de Partidos Políticos에 제출·등록해야 법인격을 얻는다. | D5: LO 6/2002 (정당법) 제3조 | E5: 8부 5화 | F5: acta fundacional, estatutos, inscripción, personalidad jurídica | G5: 검색 확인 (2026-09-22)
A6: 정당·선거 | B6: 정당의 민주적 내부 운영 | C6: 정당의 내부 조직과 운영은 민주적이어야 한다. | D6: 헌법 제6조 | E6: 8부 6화 | F6: estructura interna, democrático, afiliado | G6: 기획 시점 지식 — BOE 확인 필요
A7: 정당·선거 | B7: 정당 재정 | C7: 정당 재정 규율과 Tribunal de Cuentas의 감독. 2015년 개정으로 재정 통제가 강화되었다. | D7: LO 8/2007, LO 3/2015 (LO 6/2002·Tribunal de Cuentas법도 함께 개정) | E7: 8부 7화 | F7: financiación, donación, fiscalización, Tribunal de Cuentas | G7: 검색 확인 (2026-09-22) (개정 사실)
A8: 정당·선거 | B8: 집회 신고 | C8: 집회·시위는 관할 당국에 사전 통지한다 (통상 10일 전, 긴급 시 24시간 전). | D8: LO 9/1983 (집회권) | E8: 8부 1화 | F8: comunicación previa, manifestación, Delegación del Gobierno | G8: 기획 시점 지식 — BOE 확인 필요
A9: 정당·선거 | B9: 시민 입법발의 (ILP) | C9: 서명 50만 명으로 법안을 발의할 수 있으나, 의회가 '심의 개시(toma en consideración)' 표결에서 기각할 수 있다. | D9: LO 3/1984, 헌법 제87조 3항 | E9: 8부 3~4화 | F9: iniciativa legislativa popular, firmas, toma en consideración | G9: 기획 시점 지식 — BOE 확인 필요
A10: 정당·선거 | B10: 총선 제도 | C10: 하원 350석, 52개 선거구, 비례대표(D'Hondt), 선거구별 3% 문턱. 과반은 176석. | D10: LOREG (LO 5/1985) | E10: 10부 | F10: circunscripción, escaño, mayoría absoluta, barrera | G10: 350석·176석은 검색 확인 (2026-09-22), 나머지는 기획 시점 지식 — BOE 확인 필요
A11: 정당·선거 | B11: 후보 등록 서명 요건 | C11: 직전 총선에서 어느 원에서도 의석이 없던 정당은 해당 선거구 유권자의 0.1% 서명을 후보 명부와 함께 내야 한다. 지방선거 의석이 있어도 이 요건은 적용된다. | D11: LOREG 제169조 3항 (LO 2/2011 개정) | E11: 9부 12화, 10부 1화 | F11: avales, firmas, censo electoral, proclamación de candidaturas | G11: 검색 확인 (2026-09-22)
A12: 정당·선거 | B12: 선거 일정 | C12: 해산 칙령 후 54일째 선거, 공식 캠페인 15일, 선거 전날 숙고의 날(선거운동 금지), 마지막 5일 여론조사 공표 금지. | D12: LOREG (제42·51·53·69조 등) | E12: 8부 11화, 10부 | F12: campaña electoral, jornada de reflexión, sondeo | G12: 기획 시점 지식 — BOE 확인 필요
A13: 정당·선거 | B13: 지방·자치 선거 | C13: 4년 주기(5월 넷째 일요일)로 시의회·자치의회가 같은 날 치러진다. 마드리드 시의회는 57석(과반 29), 문턱 5%. 자치의회도 5% 문턱. | D13: LOREG, 마드리드 자치주 선거법 | E13: 8부 12화, 9부 | F13: concejal, pleno, barrera del 5%, corporación | G13: 검색 확인 (2026-09-22) (57석·29석·5%·4년 동시)
A14: 정당·선거 | B14: 알칼데 선출 | C14: concejales 과반(마드리드는 29표)이 지지한 후보가 알칼데. 과반이 없으면 최다득표 명부의 1번 후보가 자동으로 알칼데. | D14: LOREG 제196조 | E14: 9부 1화 | F14: alcalde, investidura municipal, cabeza de lista | G14: 검색 확인 (2026-09-22)
A15: 정당·선거 | B15: 선거 분쟁 | C15: Junta Electoral(중앙·지방)이 선거를 관리하고, 후보 등록 거부(no proclamación) 등은 contencioso-electoral 소송으로 다툰다. | D15: LOREG 제49조 | E15: 8부 10~11화, 10부 | F15: Junta Electoral, recurso contencioso-electoral, amparo | G15: 검색 확인 (2026-09-22) (제49조)
... A52: 정부 | B52: 연금과 Pacto de Toledo | C52: 연금 제도의 지속 가능성은 의회 위원회(Pacto de Toledo)에서 합의 방식으로 논의하는 관행이 있다. | D52: Pacto de Toledo | E52: 11부 12화 | F52: pensiones, revalorización, sostenibilidad | G52: 기획 시점 지식 — BOE 확인 필요
A54: ※ 법령 번호·조항은 교재에 넣기 전에 BOE의 현행 텍스트(texto consolidado)로 반드시 확인하세요. '검색 확인'은 공개 자료에서 교차 확인한 항목이며, 나머지는 기획 시점 지식입니다.

Sheet 정치경로_의석
A1: 정치 경로와 가상 의석 시뮬레이션
A2: 창당에서 총리까지의 경로를 현실 제도에 맞춰 단계화했다. 정당·의석 수는 전부 가상의 교육용 수치이며, 파란 숫자·표결 값은 수정하면 결과가 자동 갱신된다.
A4: 1. 정치 경로 (창당 → 총리)
A5: 단계 | B5: 부·화 | C5: 이야기 사건 | D5: 제도·규칙 | E5: 확인 상태
A6: 1 | B6: 8부 1~4화 | C6: Sol 집회 → 시민 입법발의(ILP)가 심의 개시 표결에서 좌초 | D6: 집회 사전 통지, ILP 서명 50만, toma en consideración | E6: 기획 지식
A7: 2 | B7: 8부 5~7화 | C7: 정당 «Casa Común» 창당 | D7: acta fundacional 제출 → Registro de Partidos Políticos 등록 시 법인격 (LO 6/2002), 재정 LO 8/2007 | E7: 검색 확인
A8: 3 | B8: 8부 8~12화 | C8: 첫 지방·자치 선거 출마, 시의회 57석 중 9석·자치의회 진출 (가상 수치) | D8: 4년 주기, 문턱 5%, 성별 균형 명부, 정정권 | E8: 검색 확인 (57석·5%) · 8부 집필 완료
A9: 4 | B9: 9부 1화 | C9: 시의회 개원, 알칼데 선출은 다른 당의 몫 | D9: 과반 29표 또는 최다득표 명부 1번 자동 취임 (LOREG 196) | E9: 검색 확인 · 9부 1화 집필 완료
A10: 5 | B10: 9부 2~11화 | C10: Sofía는 시의회(예산·계약), Javier는 자치의회(보건)에서 활동. 스캔들 폭로, acusación popular 고소 | D10: 보건·주거는 자치주 권한, Pleno·위원회, Ley 2/2023, LOPJ 11.1 | E10: 기획 지식
A11: 6 | B11: 9부 12화 | C11: 총선 출마 결정. 현직 총리(UCN)가 예산 부결 후 조기 총선을 소집 | D11: 해산: 총리 제안·국왕 칙령(art. 115). 후보 등록에 선거구 유권자 0.1% 서명 필요(LOREG 169.3) | E11: 서명 요건은 검색 확인
A12: 7 | B12: 10부 1~4화 | C12: 총선 1차: 캠페인, TV 토론, 결과 CC 62석 3위 (아래 A블록) | D12: 소집 후 54일째 선거, 캠페인 15일, 350석·D'Hondt·3% 문턱 | E12: 기획 지식
A13: 8 | B13: 10부 5화 | C13: 개원, Mesa·의장 선출, CC 의원단 구성 | D13: 의원단 15석 이상 요건 (CC 62석이라 충족) | E13: 검색 확인
A14: 9 | B14: 10부 6~7화 | C14: 국왕 협의 → UCN 후보 제안 → 1·2차 표결 모두 부결 (A블록) | D14: 헌법 제99조: 1차 절대다수 176, 2차 단순다수(48시간 후) | E14: 검색 확인
A15: 10 | B15: 10부 8화 | C15: 두 달의 시계: 첫 표결 후 2개월 내 아무도 신임받지 못한다 | D15: 제99조 5항: 의회 자동 해산·재선거 (의장 부서) | E15: 검색 확인
A16: 11 | B16: 10부 9~10화 | C16: 재선거 캠페인과 결과: CC 112석 1당이지만 과반 아님 (B블록) | D16: 176석 미달 → 소수 정부·협상 | E16: 가상 수치
... A24: 19 | B24: 12부 | C24: 임기 후반, 사무소를 재단으로 전환 | D24: 고위직 겸직 제한 (Ley 3/2015) | E24: 기획 지식
A26: 2. 가상 정당 (실존 정당·정치인 사용 금지)
A27: 약칭 | B27: 정당명 (가상) | C27: 성격 | D27: 이야기 속 역할
A28: CC | B28: Casa Común | C28: 주인공 정당. Pepa의 식탁에서 나온 이름 | D28: 시민 정당. 창당 → 지방 → 총선 → 총리
A29: UCN | B29: Unión Cívica Nacional | C29: 거대 보수 정당 | D29: 현직 총리 배출, 1차 총선 1당, 첫 investidura 후보 실패
A30: PPS | B30: Partido del Progreso Social | C30: 거대 중도좌파 정당 | D30: 재선거에서 45석으로 추락, Mateo 지지
A31: HU | B31: Hispania Unida | C31: 민족주의 성향 소수당 | D31: UCN과 함께 반대·불신임안 지지
A32: TA | B32: Coalición Territorial A | C32: 지역정당 연합 | D32: 조건부 친여
A33: TB | B33: Coalición Territorial B | C33: 지역정당 연합 | D33: 캐스팅보트: 1차엔 반대, 2차엔 기권 (협상의 열쇠)
A34: PV | B34: Plataforma Vecinal | C34: 지역 주민 후보 플랫폼 | D34: 마드리드 시의회 1석(8부 12화). 9부 1화 알칼데 표결 백지
A35: 3-A. 총선 1차 결과와 UCN 후보 investidura (가상)
A36: 정당 | B36: 의석 | C36: 1차 표결 (절대다수) | D36: 2차 표결 (단순다수, 48시간 후) | E36: 비고
A37: UCN | B37: 118 | C37: Sí | D37: Sí
A38: PPS | B38: 92 | C38: No | D38: No
A39: CC | B39: 62 | C39: No | D39: No
A40: HU | B40: 36 | C40: Sí | D40: Sí
A41: TA | B41: 14 | C41: No | D41: No
A42: TB | B42: 28 | C42: No | D42: Abst
A43: 총 의석 | B43: =SUM(B37:B42) | E43: =IF(B43=350,"350석 OK","350석과 불일치")
A44: 절대다수 (과반) | B44: =INT(B43/2)+1
A45: 찬성 (Sí) | C45: =SUMIF(C37:C42,"Sí",$B$37:$B$42) | D45: =SUMIF(D37:D42,"Sí",$B$37:$B$42)
A46: 반대 (No) | C46: =SUMIF(C37:C42,"No",$B$37:$B$42) | D46: =SUMIF(D37:D42,"No",$B$37:$B$42)
A47: 기권 (Abst) | C47: =SUMIF(C37:C42,"Abst",$B$37:$B$42) | D47: =SUMIF(D37:D42,"Abst",$B$37:$B$42)
A48: 결과 | C48: =IF(C45>=$B$44,"통과","부결") | D48: =IF(D45>D46,"통과","부결") | E48: 1차: 찬성 ≥ 절대다수 / 2차: 찬성 > 반대
A49: 1차 부족 표 | C49: =MAX($B$44-C45,0) | D49: —
A50: 해석: UCN 후보는 154표에 그쳐 1차 부결. 2차도 찬성 154 < 반대 168로 부결. 이후 다른 후보도 성공하지 못하면 첫 표결 후 2개월에 자동 해산(제99조 5항).
A52: 3-B. 재선거 결과와 Mateo investidura (가상, 10부 12화)
A53: 정당 | B53: 의석 | C53: 1차 표결 (절대다수) | D53: 2차 표결 (단순다수, 48시간 후) | E53: 비고
A54: CC | B54: 112 | C54: Sí | D54: Sí
A55: UCN | B55: 108 | C55: No | D55: No
A56: PPS | B56: 45 | C56: Sí | D56: Sí
A57: HU | B57: 34 | C57: No | D57: No
A58: TA | B58: 18 | C58: Sí | D58: Sí
A59: TB | B59: 33 | C59: No | D59: Abst
A60: 총 의석 | B60: =SUM(B54:B59) | E60: =IF(B60=350,"350석 OK","350석과 불일치")
A61: 절대다수 (과반) | B61: =INT(B60/2)+1
A62: 찬성 (Sí) | C62: =SUMIF(C54:C59,"Sí",$B$54:$B$59) | D62: =SUMIF(D54:D59,"Sí",$B$54:$B$59)
A63: 반대 (No) | C63: =SUMIF(C54:C59,"No",$B$54:$B$59) | D63: =SUMIF(D54:D59,"No",$B$54:$B$59)
A64: 기권 (Abst) | C64: =SUMIF(C54:C59,"Abst",$B$54:$B$59) | D64: =SUMIF(D54:D59,"Abst",$B$54:$B$59)
A65: 결과 | C65: =IF(C62>=$B$61,"통과","부결") | D65: =IF(D62>D63,"통과","부결") | E65: 1차: 찬성 ≥ 절대다수 / 2차: 찬성 > 반대
A66: 1차 부족 표 | C66: =MAX($B$61-C62,0) | D66: —
A67: 해석: 1차는 찬성 175표로 절대다수 176에 딱 1표 부족해 부결. TB가 반대에서 기권으로 돌아서는 협상이 끝나면 2차는 찬성 175 > 반대 142로 통과. 실제 사례(2020년 1월): 1차 166:165:18 부결 → 2차 167:165:18 통과 — 같은 구조 (검색 확인).
A69: 3-C. 야당의 건설적 불신임안 (가상, 11부 10화)
A70: 정당 | B70: 의석 | C70: 불신임안 표결 | E70: 비고
A71: UCN | B71: 108 | C71: Sí
A72: HU | B72: 34 | C72: Sí
A73: TB | B73: 33 | C73: Abst
A74: CC | B74: 112 | C74: No
A75: PPS | B75: 45 | C75: No
A76: TA | B76: 18 | C76: No
A77: 총 의석 | B77: =SUM(B71:B76) | E77: =IF(B77=350,"350석 OK","350석과 불일치")
A78: 절대다수 (과반) | B78: =INT(B77/2)+1
A79: 찬성 (Sí) | C79: =SUMIF(C71:C76,"Sí",$B$71:$B$76)
A80: 반대 (No) | C80: =SUMIF(C71:C76,"No",$B$71:$B$76)
A81: 기권 (Abst) | C81: =SUMIF(C71:C76,"Abst",$B$71:$B$76)
A82: 결과 | C82: =IF(C79>=$B$78,"가결","부결")
A83: 부족 표 | C83: =MAX($B$78-C79,0)
A84: 발의 필요 서명 (1/10) | C84: =ROUNDUP(B77/10,0) | E84: =IF(B71>=C84,"제안 정당 의석 충족","미달")
A85: 해석: 발의 요건(35명)은 UCN 단독으로 충족하지만, 대안 후보에 필요한 절대다수 176에 크게 못 미쳐 부결. 불신임안이 부결되면 서명자는 같은 회기에 다시 발의할 수 없다. PPS가 돌아서면 가결도 가능하다는 긴장이 이 화의 서스펜스.
A87: 4. 이야기 속 엑스트라 화자 (전부 가상)
A88: PRESIDENTA DEL CONGRESO(투표 결과를 낭독), ALCALDE / ALCALDESA(UCN, 가상), PRESIDENTE DEL GOBIERNO SALIENTE(UCN, 가상), MODERADORA(TV 토론), NOTARIA(12부 유언장). 국왕은 직접 대사를 주지 않고, 공식 절차 문구는 하원의장 대사로 전달한다. 실존 정치인·정당명은 쓰지 않는다. 9부 추가: NEGOCIADORA(PPS 협상 대표), SECRETARIO(시의회 사무총장), 시의회 ALCALDE(UCN, 무명).
A90: 3-D. 마드리드 시의회 결과와 알칼데 표결 (가상, 8부 12화·9부 1화)
A91: 정당 | B91: 의석 | C91: 알칼데 표결 (9부 1화) | D91: 비고
A92: UCN | B92: 23 | C92: UCN 1번 | D92: HU와 합쳐 28
A93: PPS | B93: 19 | C93: Iriarte
A94: CC | B94: 9 | C94: Sofía | D94: PPS 제안 거절(당원 84%)
A95: HU | B95: 5 | C95: UCN 1번
A96: PV | B96: 1 | C96: Blanco
A97: 총 의석 | B97: =SUM(B92:B96) | C97: =IF(B97=57,"57석 OK","57석과 불일치")
A98: 절대다수 (과반) | B98: =INT(B97/2)+1
A99: UCN 1번 득표 | B99: =SUMIF(C92:C96,"UCN 1번",B92:B96) | C99: =IF(B99>=B98,"과반 당선","과반 미달 → 최다득표 명부 1번 자동 (LOREG 196)")
A100: PPS+CC+PV (제안이 성사됐다면) | B100: =B93+B94+B96 | C100: =IF(B100>=B98,"Iriarte 과반","미달")
A101: 해석: PPS·CC·PV가 합치면 정확히 29표였지만 CC가 대가 있는 제안을 거절했고, 어느 후보도 29표에 못 미쳐 최다득표 명부(UCN) 1번이 자동 취임. 자치의회에서는 CC 11석(다른 당 의석은 미정).

Sheet 호칭규칙
A1: 호칭 규칙 (tú / usted / vosotros / ustedes)
A2: 스페인 본토 스페인어 기준. 라틴아메리카식 ustedes는 공식 석상에서만 사용. 2~5부 '사무소 프레임 장면'은 1부와 같은 규칙을 따른다.
A4: 화자 → 청자 | B4: 1부 (현재) | C4: 2~5부 (각자의 과거) | D4: 6부 이후 | E4: 비고
A5: 주력 4인 상호 | B5: tú | C5: usted (만나기 전이라) | D5: tú | E5: 6부 만남을 기점으로 전환 — 전환 순간을 대사로 드러낼 것
A6: 주력 4인 → Carmen | B6: tú | C6: tú (프레임 장면) | D6: tú | E6: Diego만 예외: 5부 1화~5화 중반까지 Carmen에게 usted를 썼고(1화 대본 기준), 5부 5화에서 말실수로 tú가 나온 뒤 Carmen이 «Tutéeme, si quiere.»라고 허락해 이후 tú. Carmen은 계속 usted.
A7: Carmen → 주력 4인 | B7: usted | C7: usted (프레임 장면) | D7: tú (제안) | E7: 6부에서는 이웃 사이라 tú, 인턴이 되면서(1부) usted로 바뀐다 — 1부 1화 대본에서 «En Vallecas me hablabas de tú.»로 대사 설명. 이후 tú로 돌아갈 시점은 미확정
A8: Carmen → Anselmo | B8: usted | C8: usted | D8: usted 유지 → 11부 7화 조사에서 처음 tú | E8: 7부에서 Anselmo가 «Puede tutearme.»라고 허락해도 Carmen은 습관 때문에 끝내 usted. 폭발 중에도 usted (예: «¡Usted, precisamente usted, no me llame mentecata!»). 폭발 중 tú 실수 금지 — 장례식 전환의 복선.
A9: Carmen → Ramón, Gonzalo | B9: usted | C9: 해당 없음 | D9: usted (전환 시점 미정)
A10: Anselmo → Carmen | B10: tú («muchacha») | C10: 해당 없음 | D10: tú | E10: 처음부터 tú — 욕(mentecata)도 Carmen에게만
A11: Anselmo → 여럿(집단) | B11: ustedes | C11: ustedes | D11: ustedes | E11: 사무소 안에서도 일부러 거리를 두는 심술. 다른 인물의 vosotros와 비교 학습
A12: Anselmo → 개인 (Carmen 외) | B12: usted | C12: usted | D12: 소수에게만 tú
A13: Ramón → 후배들 | B13: tú (명령조) | C13: tú / usted 혼용 | D13: 정치 무대에서는 usted
A14: Raimundo → 전원 | B14: tú | C14: tú | D14: tú | E14: 모두에게 tú — 그래서 더 위협적. «Búscalo tú.»
A15: Pepa, Nieves → 전원 | B15: tú | C15: tú | D15: tú | E15: Pepa는 'hijo/hija'
A16: Inés → 취재 대상 | B16: usted (취재 시) | C16: usted | D16: 친해지면 tú
A17: Cervantes → 연장자 (Anselmo·Pepa) | B17: 해당 없음 (3부부터 등장) | C17: 해당 없음 | D17: vuestra merced (3인칭 동사) 유지 | E17: 3부 1화부터 사용. Pepa에게만 «Tú también, Miguel.»로 먼저 tú를 허락받음(3부 1화) — 본인은 여전히 vuestra merced
A18: Cervantes → 젊은이 (Carmen 등) | B18: 해당 없음 | C18: 해당 없음 | D18: vos (-áis/-éis), «doncella» | E18: 아버지뻘 어른의 옛 화법. 나이 비슷한 인물이 늘어나면(7부 이후) 조정 검토
A19: 전원 → Cervantes | B19: 해당 없음 | C19: 해당 없음 | D19: usted로 시작 (Pepa만 3부 1화부터 tú) | E19: 팀 전체가 tú로 넘어가는 시점 미정 (7부 신원 회복 즈음 제안)
A20: 집단 대화 (사무소 안) | B20: vosotros | C20: vosotros | D20: vosotros | E20: 예: «Sentaos, que os pongo algo.»
A21: 공식 연설·의회 | B21: — | C21: — | D21: ustedes / señorías | E21: 8부 이후 대중 연설, 9부 이후 시의회·자치의회·하원 토론
A22: 하원 (Congreso) | B22: — | C22: — | D22: «Señorías», «señor presidente / señora presidenta» (하원의장), «señora ministra» | E22: 의원들은 서로를 «señoría», 총리는 «señor presidente del Gobierno»로 부른다
A23: 시의회 (Pleno) | B23: — | C23: — | D23: «señor alcalde / señora alcaldesa», «señora concejala» | E23: 발언은 usted, 회의 밖 동료끼리는 tú로 돌아간다
A24: 국왕 | B24: — | C24: — | D24: «Majestad» | E24: 국왕은 직접 대사를 주지 않는다. 의전 절차는 하원의장이 전달
A25: 5부 과거 화 (Cenit) | B25: — | C25: 동료끼리 tú, 고객 임원에게 usted, 고객 측 현장 인물은 usted→tú 전환 | D25: — | E25: Almudena↔Diego tú(한국어 대역은 해요체). Marcos↔Diego tú(반말). Fermín은 5부 4화 로비에서 «¿Te puedo tutear?»로 Diego에게 tú 전환(Diego는 tú로 응답). Lastra↔Diego usted 유지.
A26: Carmen → Diego (프레임) | B26: usted | C26: usted | D26: 미결 (6부 만남 이후 tú 제안) | E26: 5부 5화에서 Diego에게 tú를 허락하면서도 본인은 «Yo sigo con el usted, que me cuesta menos.» — 전환 시점을 6부 이후로 남겨 둠
A27: 6부 주력 4인 상호 (전환 기록) | B27: usted→tú | C27: 화별 전환 | D27: — | E27: Mateo–Sofía: 2부 10화 tú(6부 2화 공개 전엔 숨김) · Mateo–Javier: 6부 4화 새벽 1시 45분 · Javier–Sofía: 6부 8화(«Esto sí es otra cosa») · Javier–Diego: 6부 9화 · Mateo–Diego: 6부 10화 · Sofía–Diego: 6부 12화(마지막). 이후 네 사람은 상호 tú.
A28: Carmen → 주력 4인 | B28: tú (6부) → usted (6부 12화~) | C28: usted | D28: 미결 3번 | E28: 6부에선 이웃이라 전원 tú. 6부 11화 인턴이 되며 '월요일부터 usted' 선언, 6부 12화부터 usted. Tomás 등 비상사에겐 tú 유지.
... A30: 6부 조연 | B30: — | C30: — | D30: — | E30: Lucía: 처음부터 tú 제안(«el miedo no entiende de usted») · Inés: 취재 중 usted → 인터뷰 끝나면 tú · Raimundo·Nieves·Pepa: 전원 tú · Ramón: 후배에게 tú, 네 사람은 Ramón에게 usted · Gonzalo·Eusebio: usted · Fermín(5부): Diego에게 usted→tú(«¿Te puedo tutear?»)

Sheet Carmen_폭발과욕
A1: Carmen의 폭발 (El Estallido) 과 욕 배정
A2: 폭발은 총 2회. 희소성이 가치다. 폭발 뒤에는 반드시 쉬운 말로 다시 설명하는 어휘 교습 장면이 이어진다.
A4: 1. 폭발 배치 (총 2회)
A5: 회차 | B5: 위치 | C5: 성격 | D5: 단계 구성 | E5: 특기 사항
A6: 1차 폭발 | B6: 1부 6화 «¡Basta!» (사건3 «Horas que nadie paga» 해결 화, Diego의 경영 용어가 협상을 막는 장면) | C6: 코미디 — 「몰라서 화내는 Carmen」 | D6: 1단계 → 2단계 → 3단계 전부 노출 | E6: 인물별 고정 반응 패턴을 여기서 한 번에 보여 준다. Ramón·Pepa·Raimundo가 이 화에 함께 등장 — Nieves의 욕은 9부 2차 폭발로 이관해 과밀을 피함.
A7: 2차 폭발 | B7: 9부 (시의회 예산 심의) | C7: 역전 — 「알아서 화내는 Carmen」. 이번엔 Carmen이 옳다. | D7: 1단계에서 곧바로 3단계로 (2단계 생략: '이번엔 참지 않는다') | E7: 관료 전문 용어 속에 서민 예산을 깎는 조항이 숨어 있었고 Carmen이 짚어 낸다. Anselmo가 선을 넘는 말을 하고 Ramón·Pepa이 나무란다.
A8: 사이 구간 | B8: 2~8부 | C8: 폭발 없음 | D8: 1단계 질문만 일상 장치로 반복 | E8: 어휘 학습의 핵심은 1단계 질문. 폭발은 정점 이벤트일 뿐.
A10: 2. 3단계 계단
A11: 단계 | B11: 대사 (ES) | C11: 한국어 | D11: 분위기 | E11: 사용
A12: 1단계 | B12: Perdone, ¿qué significa eso? | C12: 실례지만, 그게 무슨 뜻이에요? | D12: 정중한 질문 | E12: 상시 (매 화 가능)
A13: 2단계 | B13: ¿Me lo explica como si tuviera cinco años? | C13: 다섯 살한테 설명하듯 해 주실래요? | D13: 슬슬 짜증 | E13: 1차 폭발에서만
A14: 3단계 | B14: ¡BASTA! ¡No entiendo nada! | C14: 그만! 하나도 모르겠다고요! | D14: 폭발 | E14: 1차 · 2차(9부)
A16: 3. 폭발 직후 고정 반응 (전부 대사로 처리 — 지문 폐기)
A17: 인물 | B17: 반응 대사 (ES) | C17: 한국어 | D17: 기존 지문 (폐기) | E17: 비고
A18: Javier | B18: Primero, respira. | C18: 우선, 숨 쉬어요. | D18: — | E18: Carmen: «¡No me diga “respira”!»로 받는다
A19: Pepa | B19: Uy. Voy a dejar este plato en la mesa antes de que vuele. | C19: 어이쿠. 접시 날아가기 전에 식탁에 내려놔야겠네. | D19: 말없이 접시를 내려놓음 | E19: 정적의 순간을 웃음으로 대신한다
A20: Ramón | B20: Sin nov… No. Mejor me callo. | C20: 이상 없… 아니. 입 다무는 게 낫겠군. | D20: «Sin novedad»을 하려다 입을 다묾
A21: Raimundo | B21: Yo no he dicho nada. | C21: 나는 아무 말도 안 했어. | D21: 아무 말도 하지 않아 오히려 가장 긴장됨 | E21: 침묵 설정을 폐지하고 시그니처 대사로 대체
A23: 4. 욕 배정 (폭발 장면 한정 — 교재용 순한 표현만)
A24: 인물 | B24: 표현 | C24: 뉘앙스 | D24: 사용 규칙 | E24: 비고
A25: Anselmo | B25: Mentecata / Cabeza de chorlito | C25: 고풍스럽고 격식 있는 욕 — 우아하게 기분 나쁨 | D25: 1차·2차 폭발에서만, Carmen에게만 | E25: 11부 6화 마지막에 «mentecata» 대신 «No está mal.»이 나올 때 낙차가 커진다.
A26: Ramón | B26: ¡Recluta! / Novata | C26: 군대식 신병 취급 | D26: 1차에서 1회 | E26: 1부 6화(폭발 화)에 카메오로 함께 있으므로 여기서 1회 (확정)
A27: Nieves | B27: Melona / Zoquete | C27: 시장통식 직설 | D27: 2차(9부)에서 1회 | E27: 1차 폭발 화의 카메오 과밀을 피해 이관 (확정)
A28: Pepa | B28: Pánfila / Cenutria + «hija» | C28: 애정이 섞여 욕인 줄 모름 | D28: 1차에서 1회
A29: Raimundo | B29: 욕하지 않음 | C29: 대신 출처를 가리킨다 | D29: — | E29: «Búscalo tú.»
A31: 5. 유지 규칙
A32: 1. Carmen이 옳은 경우가 있어야 한다. 2차(9부)에서는 관료 용어에 숨은 삭감 조항을 짚어 낸다. 1차에서도 Diego의 용어(sinergias, escalable)가 알맹이 없었음이 드러난다. Carmen은 '어려운 말로 숨는 어른들'을 드러내는 인물이다.
A33: 2. 폭발 직후에는 누군가 쉬운 말로 다시 설명한다 (전문 표현 → 쉬운 표현 짝 학습). 1차 담당: Sofía — «Lo traduzco yo. Quiere decir: despedir gente para ahorrar.»
A34: 3. 욕과 괴롭힘의 선: 별도 에피소드를 만들지 않고 2차 폭발에 합친다. Anselmo가 정말 아픈 말을 하고 Ramón·Pepa이 나무라며, 사과는 «Retiro lo dicho… en parte.» 정도로 삐딱하게.
A35: 4. 욕설 수위: joder, hostia 등은 교재에서 제외. 필요하면 각주로 '실제로는 더 거칠게 말한다'고만 알려 준다.

Sheet Anselmo_죽음
A1: Anselmo — 가장 까칠한 심술 영감이자 오늘내일하는 사람
A2: 10부 동안 매 겨울 '마지막'이라고 외치는 양치기 소년 → 11부에서 마지막으로 현역 외교관이 되어 브뤼셀에서 승리하고, 그 직후 12화에서 진짜로 죽는다.
A4: 1. 기본 설정
A5: 항목 | B5: 내용
A6: 나이 | B6: ="1부 "&INDEX(캐릭터!$E$5:$E$18,MATCH("Anselmo",캐릭터!$D$5:$D$18,0))&"세 → 11부 약 "&INDEX(캐릭터!$F$5:$F$18,MATCH("Anselmo",캐릭터!$D$5:$D$18,0))&"세 (경과 연수 가정 "&개요!$C$11&"년)"
A7: 성격 | B7: 정중하게 독을 뿌리는 심술 영감. 예의를 지키며 비꼬는 화법이라 Nieves의 큰 소리 화법과 구분된다. 낭독하면 '정중한데 기분 나쁜' 억양 연습이 된다.
A8: 심술 패턴 | B8: 커피가 맛없다고 매일 불평(«Qué manera de estropear un buen café.»). Diego를 «el de las diapositivas», Tomás의 원고를 «los mil borradores»라고 놀림. 모든 것이 «En mis tiempos»보다 못하다.
A9: 반복 개그 | B9: 매 겨울 «Este será mi último invierno.» 선언, 유언장을 계속 고쳐 씀 (Carmen에게 우산을 물려주겠다 등). 입버릇 «Anótenlo en mi testamento.» 모두 '또 시작이네' 하며 웃어넘긴다.
A10: 가짜 병 | B10: 무릎, 소화, 불면 — 전부 엄살. 소란스러운 엄살이 진짜 병의 위장이 된다.
A11: 진짜 병 | B11: 만성 심부전 (insuficiencia cardíaca crónica). 이것만 숨긴다.
A12: Javier의 딜레마 | B12: 진단을 알지만 의사의 비밀유지(secreto profesional)를 지킨다. Anselmo가 «Doctor, esto queda entre nosotros.»라고 못 박았기 때문. 시청자가 뒤늦게 'Javier가 왜 조용했는지' 깨닫는 구조.
A13: 최고의 칭찬 | B13: «No está mal.» — 극히 드물게 쓰는 표현. Carmen에게는 11부 12화(사망 직전)가 사실상 처음이어야 낙차가 산다.
A14: 호칭·욕 | B14: 여럿에게는 ustedes, Carmen에게는 tú(«muchacha»). 욕(«mentecata»)은 Carmen에게만, 폭발 장면 2회 한정.
A15: 죽음 이후 | B15: La Vieja Guardia는 Ramón + Raimundo + 빈 의자. 12부 10화 'El Hueco en la Guardia'에서 정면으로 다룬다.
A17: 2. 복선·사망 타임라인 (전부 대사로 처리)
A18: 부·화 | B18: 사건 | C18: 대화문 처리 방식 | D18: 대사 예시 (ES) | E18: 학습 어휘
A19: 1~10부 (매 겨울) | B19: '마지막 겨울' 선언과 유언장 수정. 1부 1화(개소 1개월 시점)부터 이미 반복되어 온 농담으로 등장한다. | C19: 본인이 선언하고 주변이 «Otra vez…»로 받는다. | D19: Este será mi último invierno. Anótenlo en mi testamento. | E19: testamento, legar, invierno
A20: 1~11부 | B20: 가짜 병 (무릎·소화·불면) | C20: Javier가 «No tiene nada.»로 넘긴다. | D20: Me duele la rodilla. Es el fin. | E20: rodilla, digestión, insomnio, dolencia
A21: 7부 | B21: «Puede tutearme.» 허락 — Carmen은 습관 때문에 usted 유지 | C21: 허락과 거절이 모두 대사로 나온다. | D21: Puede tutearme, muchacha. / Perdone, es la costumbre. | E21: tutear, costumbre
A22: 9부 | B22: Carmen 2차 폭발에서 Anselmo가 선을 넘음 → Ramón·Pepa이 나무람 | C22: 선을 넘는 말과 사과 모두 대사로. | D22: Retiro lo dicho… en parte. | E22: retirar lo dicho, disculparse
A23: 11부 6화 | B23: 청년 고용 협상에서 좋은 조언을 하지만 계단에서 숨이 가쁜 게 처음으로 드러남 (죽음은 아직 아님) | C23: «No tiene nada»가 아니라 «Estoy bien, solo las escaleras»로 처음 균열. | D23: Estoy bien. Son solo las escaleras, muchacha. | E23: escaleras, aliento, fatiga
A24: 11부 9화 | B24: 브뤼셀行 자원. Tomás에게 짐을 싸며 두 지도자를 특징으로만 묘사 — 건물에 금박 이름을 새긴 사업가 출신과, 정보기관 출신으로 이웃 나라 땅을 가져간 인물. 이름·국가는 끝내 말하지 않는다. | C24: 실명 대신 행동·이력의 특징만 나열. 실존 인물 실명 미사용. | D24: Uno puso su nombre en letras doradas sobre sus edificios. Ahora vende aranceles igual, a gritos. / Sonará a quien usted quiera, joven. Yo solo describo el paisaje. | E24: aranceles, servicios secretos, régimen, discreción diplomática
A25: 11부 10화 | B25: 직접 협상. 상대의 과장·거짓 주장을 옛 합의 날짜로 정확히 반박 | C25: «Permítame corregirle»로 시작하는 반박 대사. | D25: Los archivos los escribí yo, jovencito. Léalos con más cuidado. | E25: corregir, archivo, precisión diplomática
A26: 11부 11화 | B26: 타결. 귀국길에 피로를 숨기고 Sofía에게 메모를 남기라고 지시 | C26: 직접 증상을 말하지 않고 '메모를 남기라'는 명령으로 암시. | D26: Por si acaso, apunta esto también, Sofía. | E26: por si acaso, legado, instrucción
A27: 11부 12화 (사망) | B27: 귀국 직후 자택에서 심부전으로 사망. Carmen이 서명을 받으러 왔다가 발견 | C27: 사망은 지문 없이 호명과 확인 대사로: Carmen이 부르고 Javier가 «Ya no.»라고 말한다. | D27: No está mal. / ¿Anselmo? — Ya no está, Carmen. | E27: pulso, parada cardíaca, reanimación, fallecer
A28: 12부 1화 | B28: 장례식이 첫 화. Casa Pepa에 빈자리, Pepa가 커피 한 잔을 계속 내놓음. Carmen이 조사에서 처음으로 tú 사용 | C28: 장소·상황은 Pepa·Carmen의 대사로. | D28: Un café para Anselmo. Como siempre. / Para él, ‘no está mal’ era el mayor elogio. | E28: velatorio, entierro, pésame, elogio fúnebre
A29: 12부 2~3화 | B29: 유작 메모 발견 → 2차 브뤼셀 협상에서 Tomás가 다듬은 그의 문장을 인용 | C29: Tomás가 메모를 소리 내어 읽고 Sofía가 협상장에서 그 문장을 인용한다. | D29: Permítanme una última precisión: no ha estado mal. | E29: memorando, legado, precisión, ECOFIN
... A32: 12부 (선택) | B32: Lucía의 애도 상담 | C32: 다들 질색하던 «¿Y cómo te hace sentir eso?»가 처음으로 진지하게 쓰인다. | D32: ¿Y cómo te hace sentir eso? | E32: duelo, pérdida, aflicción

Sheet Raimundo_출처
A1: Raimundo — 결론 대신 출처를 가리키는 사람
A2: 직접 답하지 않고 '어디를 찾을지'만 알려 준다. 정보 요원의 논리: 정보의 대부분은 공개 출처에 있다.
A4: 1. 설정 변경
A5: 항목 | B5: 내용
A6: 답하는 방식 | B6: 침묵 → 결론은 말하지 않고 출처만 가리킨다.
A7: 시그니처 | B7: «Yo no he dicho nada. Pero mira en…» / «No te lo digo. Te digo dónde está.» / «Casi todo está en fuentes abiertas. Solo hay que saber leer.»
A8: 도구 (대화문 처리) | B8: 책을 꺼내 건네거나 카드에 적어 주는 행동은 지문 대신 대사로 말한다: «Tercera balda, a tu izquierda.» / «Anota. Busca: …»
A9: 호칭 | B9: 전원에게 tú — «Búscalo tú.»가 명령조라 더 섬뜩하다.
A10: Carmen과의 관계 | B10: Carmen이 «¡Dime la respuesta!» 하면 서가 위치만 말한다. 짜증 나지만 정답을 떠먹이지 않는 이 교재의 태도와 같다.
A11: 현실 요소 | B11: Cuesta de Moyano(레티로 공원 근처 헌책방 거리)와 국립도서관(Biblioteca Nacional, Recoletos)을 단골 출처로. 학습자가 실제 마드리드에서 따라 걸어 볼 수 있다.
A12: 서점 원칙 | B12: 손님이 찾던 답이 든 책일 때만 값을 받지 않는다.
A14: 2. 그의 서가 4칸
A15: 칸 | B15: 내용 | C15: 대표 출처
A16: 법령칸 | B16: 법과 조문 | C16: BOE(boe.es), 헌법, 각 법률
A17: 문서칸 | B17: 기록과 자료 | C17: 국립역사문서고(AHN), PARES 포털, 국회 회의록(Diario de Sesiones)
A18: 신문칸 | B18: 과거 기사 | C18: 국립도서관 디지털 신문 아카이브 (Hemeroteca Digital, BNE)
A19: 사전칸 | B19: 용어 | C19: DLE(dle.rae.es), 법률용어 사전 DPEJ(dpej.rae.es)
A21: 3. 주제별 출처표 (기획한 에피소드 기준)
A22: 상황 | B22: 관련 부·화 | C22: Raimundo의 대사 (ES) | D22: 찾을 곳 | E22: 검색어·키워드 | F22: 서가칸
A23: 정보기관 개혁 | B23: 10부 (자문 직책) | C23: Empieza por la ley que nos creó. | D23: Ley 11/2002 (CNI 규율법), Ley Orgánica 2/2002 (CNI 사법 통제) — BOE에서 검색 | E23: Ley 11/2002 CNI; control judicial previo | F23: 법령칸
A24: 도청의 합법성 | B24: 11부 7화 | C24: Una prueba ilícita no vale. Búscalo. | D24: 헌법 제18조 3항(통신의 비밀), 법원조직법(LOPJ) 제11조 1항(위법 수집 증거), 형사소송법(LECrim) 제588조 bis 이하 | E24: intervención telefónica, autorización judicial, cadena de custodia, prueba ilícita | F24: 법령칸
A25: 기밀 지정과 공개 | B25: 정보기관 개혁 관련 | C25: Hay un secreto oficial de 1968. | D25: Ley 9/1968 (기밀법), Ley 19/2013 (투명성법), transparencia.gob.es | E25: secretos oficiales, desclasificación | F25: 법령칸 (기밀법은 개정 논의 중 — 현행본 확인)
A26: 의사의 비밀유지 | B26: 11부 4~6화 (Anselmo 복선) | C26: Pregúntale al doctor qué dice su código. | D26: 헌법 제24조 2항 후단, Ley 41/2002 (환자 자율성법), 의사협회(OMC/CGCOM)의 Código de Deontología Médica | E26: secreto profesional, historia clínica | F26: 법령칸
A27: 자금 세탁 | B27: 4부, 11부 (주거·금융 전투) | C27: Todo dinero tiene una ley que lo vigila. Búscala. | D27: Ley 10/2010 (자금세탁방지법), SEPBLAC(스페인은행 산하 자금세탁 감시기구), Registro Mercantil | E27: blanqueo de capitales, titular real, paraíso fiscal | F27: 문서칸·법령칸
A28: 주거·퇴거 | B28: 1·2·11부 | C28: Compara lo que dicen con lo que existe. | D28: Ley 29/1994 (도시임대차법, LAU), Ley 12/2023 (주거권법), 민사소송법(LEC, Ley 1/2000)의 퇴거(desahucio) 절차 | E28: desahucio, arrendamiento, gran tenedor | F28: 법령칸
A29: 가격 담합 | B29: 11부 7화 | C29: Mira en Competencia. | D29: Ley 15/2007 (경쟁보호법), CNMC(cnmc.es)의 제재 결정문 | E29: cártel, expediente sancionador, competencia | F29: 법령칸·문서칸
A30: 횡재세 | B30: 11부 8화 | C30: No lo inventaste tú. Ya se hizo. | D30: Ley 38/2022 (에너지·금융권 한시 부담금) | E30: gravamen temporal energético, entidades de crédito | F30: 법령칸
A31: EU 긴축 압박 | B31: 11부 9화 | C31: Ese artículo no dice lo que te dijeron. | D31: 유럽연합기능조약(TFUE) 제126조(과도한 재정적자 절차), EUR-Lex(eur-lex.europa.eu) | E31: procedimiento de déficit excesivo | F31: 법령칸
A32: 과거 스캔들 조사 | B32: 6~7부 | C32: Los periódicos guardan lo que la gente olvida. | D32: 국립도서관 Hemeroteca Digital | E32: 'escuchas del CESID 1995'로 검색 | F32: 신문칸
A33: 의회 발언 확인 (제안) | B33: 9부 | C33: Todo lo que se dijo en la tribuna está escrito. | D33: 국회 회의록 Diario de Sesiones (congreso.es) | E33: diario de sesiones, intervención | F33: 문서칸
... A41: 모르는 단어 | B41: 전 부 | C41: Si no sabes la palabra, no sabes la ley. | D41: DLE, DPEJ | E41: — | F41: 사전칸
A42: ※ 법령 번호와 조항은 기획 시점 지식으로 정리한 것입니다. 교재에 넣기 전에 BOE의 현행 텍스트(texto consolidado)로 반드시 확인하세요. 참고 도서 제목은 지어낼 위험이 있어 제외하고 검색어만 적었습니다.
A44: 4. 카드(FICHA) 구술 템플릿 — 지문 없이 대사로만
A45: 화자 | B45: 기능 | C45: 대사 (ES) | D45: 한국어
A46: RAIMUNDO | B46: 검색어 (Busca) | C46: Anota. Busca: «prueba ilícita». | D46: 적어. 찾을 것: «위법 수집 증거».
A47: CARMEN | B47: 질문으로 다음 항목을 끌어냄 | C47: Vale. ¿Dónde? | D47: 알겠어요. 어디서요?
A48: RAIMUNDO | B48: 출처 (Dónde) | C48: BOE. Ley Orgánica del Poder Judicial, artículo 11. | D48: 관보(BOE). 법원조직법 제11조.
A49: CARMEN | B49: 질문 | C49: ¿Y qué palabras busco? | D49: 그럼 어떤 단어를 찾죠?
A50: RAIMUNDO | B50: 키워드 (Palabras clave) | C50: Intervención telefónica. Autorización judicial. Cadena de custodia. | D50: 통신 감청. 법원 허가. 증거 보관 연속성.
A51: CARMEN | B51: Carmen의 조급함 | C51: ¿Y la respuesta? | D51: 그럼 답은요?
A52: RAIMUNDO | B52: 시그니처 + 서가 위치 (손짓 지문 대체) | C52: Yo no he dicho nada. Tercera balda, a tu izquierda. | D52: 나는 아무 말도 안 했어. 세 번째 선반, 왼쪽이야.
A53: 카드는 3줄(검색어·출처·키워드)과 마지막 시그니처로 짧게 유지한다. 이 카드가 모이면 교재 전체의 스페인어 자료 색인이 된다. 카드를 넣을 화의 범위(전 화 vs Raimundo 등장 화)는 미결사항 참고.

Sheet 대화문규칙
A1: 대화문 규칙 — 모든 것은 대화문으로 풀어간다
A2: 이전 안(상황 30% + 대화 70%)을 폐기하고, 전 화를 「화자명: 대사」만으로 구성한다.
A4: 1. 원칙
A5: No | B5: 규칙 | C5: 내용 | D5: 예시
A6: 1 | B6: 전 화 100% 대화문 | C6: 지문(Narración)은 0%. 각 화는 화자명 + 대사로만 구성한다. | D6: PEPA: Son las cinco. Empieza la reunión.
A7: 2 | B7: 화 머리 표기 | C7: 부·화 번호, 제목, 장소·날짜는 낭독하지 않는 표기 전용 한 줄(메타). 낭독 본문에는 넣지 않는다. | D7: [3부 4화 · Colapso en Urgencias]
A8: 3 | B8: 괄호 무대지시 금지 | C8: 행동·표정·침묵은 괄호 지문이 아니라 대사로 표현한다. | D8: (Pepa deja el plato) → PEPA: Voy a dejar este plato antes de que vuele.
A9: 4 | B9: 장소·시간 소개 | C9: 지정 화자가 대사로 알린다: Pepa(식사·장소), Carmen(질문), Ramón(보고). | D9: PEPA: Son las cinco. Reunión en mi mesa.
A10: 5 | B10: 시간 경과·장면 전환 | C10: 인물이 말로 알린다. 전환은 화자 교체 + 장소 언급으로. | D10: INÉS: Han pasado tres meses desde el desahucio, ¿verdad?
A11: 6 | B11: 문서·기사·메모 | C11: 소리 내어 읽는다: Mateo=조항, Inés=기사, Tomás=초고·메모, Raimundo=카드. | D11: MATEO: Artículo 24: «Todas las personas tienen derecho…»
A12: 7 | B12: 무거운 장면 (죽음·침묵) | C12: 짧은 호명·확인 대사로 처리한다. | D12: CARMEN: ¿Anselmo? / JAVIER: Ya no está, Carmen.
A13: 8 | B13: 내면·감정 | C13: 독백은 '소리 내어 하는 말'로만 허용. 감정 노출은 Lucía의 되받기 화법을 활용. | D13: LUCÍA: Entonces te sientes sola. ¿Es así?
A14: 9 | B14: 문장 길이 | C14: 1부(B1): 대사 한 줄 15단어 이내. Anselmo·Mateo의 격식체는 한두 줄만 '어른들 말투 맛보기'. 부가 올라갈수록 인물별 허용 길이 확대. Carmen의 질문은 끝까지 짧게. | D14: '1부_시범대사' 시트에서 단어 수 자동 점검
A15: 10 | B15: 화당 분량 = 120턴 | C15: 한 화는 대화 120턴(화자 교대 1회 = 1턴)으로 구성한다. 한 턴은 1부 15단어 이내, 연설·조항·기사 낭독은 긴 턴 1개로 세되 화당 3개까지. 화 유형별 도입·장면·절정·마무리 배분과 화자 점유율은 '턴_설계' 시트. | D15: 120턴 중 장면 전환·시간·장소 안내 5~10턴, Carmen 질문→재설명 6~12턴
A16: 11 | B16: 시그니처 표현 | C16: 화자 식별 장치이자 반복 학습 문장. 한 화에 화자당 1~2회까지.
A17: 12 | B17: Carmen의 질문 장치 | C17: 어려운 용어 뒤에는 Carmen의 질문 → 쉬운 재설명이 온다 (전문 표현 → 쉬운 표현 짝). | D17: CARMEN: Perdone, ¿qué significa eso?
A18: 13 | B18: Raimundo의 카드 | C18: 카드는 구술로 처리한다 (Raimundo_출처 시트 템플릿). | D18: RAIMUNDO: Anota. Busca: …
A19: 14 | B19: 욕설 수위 | C19: joder, hostia 등은 교재 제외. 순한 표현만 (Carmen_폭발과욕 시트).
A20: 15 | B20: 호칭 전환 | C20: tú/usted 전환은 대사로 명시한다 (호칭규칙 시트). | D20: ANSELMO: Puede tutearme.
A21: 16 | B21: 가상 정치 세계 | C21: 정당·정치인은 전부 가상. 실존 정치인·정당명을 쓰지 않고, 국왕은 직접 대사를 주지 않는다 (의전 문구는 하원의장 대사로). | D21: PRESIDENTA DEL CONGRESO: Votos a favor: ciento setenta y cinco.
A22: 17 | B22: 현안을 다루는 법 | C22: 시사 현안은 가상 설정으로 각색하고 실존 인물·참사 희생자를 특정하지 않는다. 찬반 양측이 각자의 가장 강한 논거를 말하게 하고, 결론은 화 안에서 제도의 결과(표결·판결·협약)로만 닫는다. 수치는 Raimundo의 카드로 출처를 안내한다. | D22: CARMEN: Perdone, ¿qué significa «zona tensionada»? / SOFÍA: Es una zona donde el alquiler sube demasiado.
A23: 18 | B23: 화자 표기 | C23: 화자명은 대문자 + 콜론. 스페인어 본문과 한국어 번역은 열(또는 파일)을 분리해 낭독 시 번역이 섞이지 않게 한다. | D23: CARMEN: ¡BASTA!
A24: 19 | B24: 고전 인용 | C24: 인물마다 다른 스페인 고전 출처를 맡겨 화마다 1~2명이 짧게 인용한다. 전부 저작권 만료 공유 저작물(16~17세기 또는 사후 70년 경과)만 쓰고, 원문을 정확히 인용한다 (배정표는 아래 3번). | D24: ANSELMO: Nuestras vidas son los ríos que van a dar en la mar, que es el morir.
A26: 3. 고전 인용 배정 (화마다 1~2명)
A27: 인물마다 다른 출처를 맡겨 반복되지 않게 하고, Pepa가 거의 전 화에 등장하므로 로테이션 캐스트인 1부에서도 대부분의 화가 커버된다. 전부 저작권 만료 공유 저작물(공고라·케베도·칼데론·세르반테스·만리케는 16~17세기, 베케르·마차도·로르카는 사후 70년 경과)만 쓰고, 원문을 정확히 인용한다. 가짜로 떠도는 명언(예: 세르반테스가 실제로 쓰지 않은 «Ladran, Sancho…»)은 쓰지 않는다.
A28: 1 | B28: (Silencio.) 폭발 직후 정적 | C28: «Uy.» — 정적 대신 짧은 감탄으로 멈춤을 표현 | D28: Pepa
A29: 인물 | B29: 출처 | C29: 쓰는 방식 | D29: 실제 인용 예시 (ES) | E29: 등장 부
A30: Pepa | B30: 스페인 속담(refranes populares) | C30: 인용이 아니라 그냥 말버릇처럼 자연스럽게 섞인다. 따뜻하고 실용적. | D30: No hay mal que por bien no venga. / Dime con quién andas y te diré quién eres. | E30: 거의 전 화
A31: Anselmo | B31: 세르반테스·칼데론·만리케 | C31: 정중하게 비꼬는 코미디로(평소), 죽음 앞에서는 무겁게(11부). | D31: Toda la vida es sueño, y los sueños, sueños son. (Calderón) / Nuestras vidas son los ríos que van a dar en la mar, que es el morir. (Manrique) | E31: 1부, 11부
A32: Raimundo | B32: 케베도·공고라 등 | C32: 감정으로 낭송하지 않고 서지 정보처럼 인용한다 — 「몇 번째 선반」식 습관과 같은 화법. | D32: Polvo serán, mas polvo enamorado. Quevedo, soneto «Amor constante más allá de la muerte». | E32: 1·2·6·11·12부
A33: Tomás | B33: 로르카·마차도·베케르 | C33: 자기 글이 부끄러워 인용으로 도피한다. 시적이고 머뭇거리는 톤. | D33: Verde que te quiero verde. (Lorca, Romance sonámbulo) / ¿Qué es poesía? … Poesía… eres tú. (Bécquer) | E33: 6부 이후
A34: Mateo | B34: 마차도의 정치적 잠언 | C34: 총리가 되어 가며 연설에 섞어 쓴다. | D34: Caminante, no hay camino, se hace camino al andar. (Machado, Proverbios y cantares) | E34: 8~13부
A35: Cervantes | B35: 본인 저작 (Quijote·Novelas ejemplares 등) | C35: 본인 작품만 정확히 인용한다. 남이 틀리게 인용하면(가짜 명언 등) 본인이 직접 정정한다 — 교재의 '가짜 명언 금지' 원칙을 극화한 장치. | D35: «Cada uno es hijo de sus obras.» (Quijote, 1부 4장) / «Jamás escribí tal cosa.» (가짜 인용 정정) | E35: 3부 이후
A36: 8 | B36: 시간 경과 | C36: «Han pasado tres meses desde el desahucio.» | D36: Inés (질문 형태)
A37: 9 | B37: 신문 기사 삽입 | C37: Inés가 기사 첫 문단을 소리 내어 읽는다 | D37: Inés
A38: 10 | B38: 연설문 초고 삽입 | C38: Tomás가 초고를 읽고 Mateo가 고친다 | D38: Tomás, Mateo
A39: 11 | B39: 투표 결과 전광판·자막 | C39: 하원의장이 표결 결과를 낭독한다: «Votos emitidos: trescientos cincuenta. A favor…» | D39: PRESIDENTA DEL CONGRESO
A40: 12 | B40: 국왕 접견 | C40: 국왕은 대사 없이, 절차와 결과를 하원의장이 전달하고 Mateo가 선서 문구를 말한다 | D40: PRESIDENTA DEL CONGRESO, Mateo

Sheet 1부_시범대사
A1: 1부 시범 장면 — Carmen 1차 폭발 (지문 없이 대사만, B1, 일반화된 예시)
A2: 장소·시간·행동을 모두 대사로 처리한 샘플로, 한 화(120턴) 중 폭발 장면 22턴을 발췌했다. 단어 수는 수식으로 자동 계산되며 상한을 넘으면 '초과'로 표시됩니다.
C4: 1부 대사 상한 (단어) | D4: 15 | E4: ← 노란 셀은 가정값 (교재 규칙 초안: 15단어 이내)
C5: 총 대사 수 | D5: =COUNTA(B8:B29)
C6: 상한 초과 대사 수 | D6: =COUNTIF(G8:G29,"초과")
A7: No | B7: 화자 | C7: 대사 (ES) | D7: 한국어 (낭독 제외) | E7: 기능·학습 포인트 | F7: 단어 수 | G7: 판정
A8: 1 | B8: PEPA | C8: Son las cinco. Empieza la reunión del despacho, aquí abajo, en mi mesa. | D8: 5시예요. 사무소 회의 시작이야, 여기 아래 내 테이블에서. | E8: 지문 대체: 시간·장소를 Pepa가 알림 | F8: =LEN(TRIM(C8))-LEN(SUBSTITUTE(TRIM(C8)," ",""))+1 | G8: =IF(F8<=$D$4,"OK","초과")
A9: 2 | B9: DIEGO | C9: Es simple. Alineamos a los stakeholders y escalamos el impacto. | D9: 간단해요. 이해관계자를 정렬하고 임팩트를 확장합니다. | E9: 경영 용어 제시 (alinear, escalar, impacto) | F9: =LEN(TRIM(C9))-LEN(SUBSTITUTE(TRIM(C9)," ",""))+1 | G9: =IF(F9<=$D$4,"OK","초과")
A10: 3 | B10: CARMEN | C10: Perdone, ¿qué significa eso? | D10: 실례지만, 그게 무슨 뜻이에요? | E10: 1단계: 정중한 질문 | F10: =LEN(TRIM(C10))-LEN(SUBSTITUTE(TRIM(C10)," ",""))+1 | G10: =IF(F10<=$D$4,"OK","초과")
A11: 4 | B11: DIEGO | C11: Optimizamos el flujo de valor para maximizar las sinergias. | D11: 가치 흐름을 최적화해 시너지를 극대화합니다. | E11: 알맹이 없는 용어의 반복 | F11: =LEN(TRIM(C11))-LEN(SUBSTITUTE(TRIM(C11)," ",""))+1 | G11: =IF(F11<=$D$4,"OK","초과")
A12: 5 | B12: CARMEN | C12: ¿Me lo explica como si tuviera cinco años? | D12: 다섯 살한테 설명하듯 해 주실래요? | E12: 2단계: 슬슬 짜증 | F12: =LEN(TRIM(C12))-LEN(SUBSTITUTE(TRIM(C12)," ",""))+1 | G12: =IF(F12<=$D$4,"OK","초과")
A13: 6 | B13: DIEGO | C13: Claro. Generamos valor con un modelo escalable y alineado. | D13: 물론이죠. 확장 가능하고 정렬된 모델로 가치를 만듭니다. | E13: 동어반복 — 여전히 설명이 안 됨 | F13: =LEN(TRIM(C13))-LEN(SUBSTITUTE(TRIM(C13)," ",""))+1 | G13: =IF(F13<=$D$4,"OK","초과")
A14: 7 | B14: CARMEN | C14: ¡BASTA! ¡No entiendo nada! Llevo una hora asintiendo como una tonta. | D14: 그만! 하나도 모르겠어요! 한 시간째 바보처럼 고개만 끄덕였다고요. | E14: 3단계: 폭발 (톤 급상승) | F14: =LEN(TRIM(C14))-LEN(SUBSTITUTE(TRIM(C14)," ",""))+1 | G14: =IF(F14<=$D$4,"OK","초과")
A15: 8 | B15: PEPA | C15: Uy. Voy a dejar este plato en la mesa antes de que vuele. | D15: 어이쿠. 접시 날아가기 전에 식탁에 내려놔야겠네. | E15: 지문 대체: 접시 내려놓는 행동을 대사로 | F15: =LEN(TRIM(C15))-LEN(SUBSTITUTE(TRIM(C15)," ",""))+1 | G15: =IF(F15<=$D$4,"OK","초과")
A16: 9 | B16: JAVIER | C16: Primero, respira. | D16: 우선, 숨 쉬어요. | E16: Javier의 고정 반응 | F16: =LEN(TRIM(C16))-LEN(SUBSTITUTE(TRIM(C16)," ",""))+1 | G16: =IF(F16<=$D$4,"OK","초과")
A17: 10 | B17: CARMEN | C17: ¡No me diga «respira»! | D17: «숨 쉬어요»라고 하지 마세요! | E17: usted 유지 | F17: =LEN(TRIM(C17))-LEN(SUBSTITUTE(TRIM(C17)," ",""))+1 | G17: =IF(F17<=$D$4,"OK","초과")
A18: 11 | B18: RAMÓN | C18: Sin nov… No. Mejor me callo. | D18: 이상 없… 아니. 입 다무는 게 낫겠군. | E18: Ramón의 고정 반응 (카메오) | F18: =LEN(TRIM(C18))-LEN(SUBSTITUTE(TRIM(C18)," ",""))+1 | G18: =IF(F18<=$D$4,"OK","초과")
A19: 12 | B19: RAIMUNDO | C19: Yo no he dicho nada. | D19: 나는 아무 말도 안 했어. | E19: Raimundo의 고정 반응 (카메오) — 침묵 대신 시그니처 | F19: =LEN(TRIM(C19))-LEN(SUBSTITUTE(TRIM(C19)," ",""))+1 | G19: =IF(F19<=$D$4,"OK","초과")
... A23: 16 | B23: SOFÍA | C23: Lo traduzco yo. Quiere decir: despedir gente para ahorrar. | D23: 내가 번역하지. 사람을 해고해서 돈을 아끼자는 뜻이야. | E23: 쉬운 말로 재설명 (어휘 교습 장면) | F23: =LEN(TRIM(C23))-LEN(SUBSTITUTE(TRIM(C23)," ",""))+1 | G23: =IF(F23<=$D$4,"OK","초과")
A24: 17 | B24: DIEGO | C24: Eso no es exactamente lo que dije. | D24: 제가 말한 건 정확히 그게 아닌데요. | F24: =LEN(TRIM(C24))-LEN(SUBSTITUTE(TRIM(C24)," ",""))+1 | G24: =IF(F24<=$D$4,"OK","초과")
A25: 18 | B25: SOFÍA | C25: Es exactamente lo que dijiste. | D25: 정확히 네가 한 말이야. | E25: 짧은 반박 — 티키타카 | F25: =LEN(TRIM(C25))-LEN(SUBSTITUTE(TRIM(C25)," ",""))+1 | G25: =IF(F25<=$D$4,"OK","초과")
A26: 19 | B26: CARMEN | C26: ¿De verdad? ¿Tantas palabras para decir eso? | D26: 정말요? 겨우 그 말 하려고 그렇게 많은 단어를요? | E26: Carmen이 옳았음이 드러남 | F26: =LEN(TRIM(C26))-LEN(SUBSTITUTE(TRIM(C26)," ",""))+1 | G26: =IF(F26<=$D$4,"OK","초과")
A27: 20 | B27: DIEGO | C27: Bueno. A veces, sí. | D27: 음. 가끔은, 그렇죠. | E27: Diego의 성장 씨앗 | F27: =LEN(TRIM(C27))-LEN(SUBSTITUTE(TRIM(C27)," ",""))+1 | G27: =IF(F27<=$D$4,"OK","초과")
A28: 21 | B28: PEPA | C28: Sentaos, que os pongo algo. Con el estómago vacío no se piensa. | D28: 다들 앉아, 뭐 좀 내줄게. 배가 비면 생각이 안 돼. | E28: vosotros 명령형, Pepa의 시그니처 2개 | F28: =LEN(TRIM(C28))-LEN(SUBSTITUTE(TRIM(C28)," ",""))+1 | G28: =IF(F28<=$D$4,"OK","초과")
A29: 22 | B29: CARMEN | C29: Vale. Pero mañana, sin palabras raras, por favor. | D29: 알았어요. 그래도 내일은 이상한 말 없이 부탁해요. | F29: =LEN(TRIM(C29))-LEN(SUBSTITUTE(TRIM(C29)," ",""))+1 | G29: =IF(F29<=$D$4,"OK","초과")

Sheet 변경이력_미결
A1: 변경 이력과 미결 사항
A3: 1. 변경 이력
A4: No | B4: 항목 | C4: 이전 | D4: 이후 | E4: 반영 시트
A5: 1 | B5: 인원 | C5: 13인 (내각) | D5: 14인 — 정보부 요원 Raimundo, 은행원 Gonzalo 추가. 14인 모두가 장관은 아니므로 '내각'보다 핵심 그룹(El Círculo de Lavapiés) 개념 사용 | E5: 개요, 캐릭터
A6: 2 | B6: Raimundo 성 | C6: Bosch (카탈루냐·독일계 느낌) | D6: Salcedo Vera | E6: 캐릭터
A7: 3 | B7: 가상 상호명 | C7: Hartmann & Ruiz Auditores / Brandt Consulting (독일식) | D7: Ochoa & Ruiz Auditores / Cenit Consultores | E7: 캐릭터
A8: 4 | B8: 기관 실명 | C8: Santander, BBVA, La Paz 병원 등 | D8: Banco Ibérico, Hospital Universitario San Bartolomé 등 가상명 (이야기 속에서 부패와 얽히기 때문) | E8: 캐릭터
A9: 5 | B9: Anselmo | C9: 우아한 은퇴 외교관 | D9: 가장 까칠한 심술 영감 + 시한부 (11부 6화 사망). 가짜 병은 엄살, 진짜 병은 만성 심부전 | E9: Anselmo_죽음
A10: 6 | B10: Carmen 폭발 | C10: 자주 폭발하는 인물 (안) | D10: 폭발은 1부·9부 딱 2회. 욕은 폭발 장면 한정 | E10: Carmen_폭발과욕
A11: 7 | B11: Raimundo | C11: 침묵으로 대답 | D11: 결론 대신 출처(서가 위치·법령·검색어)를 가리킴 | E11: Raimundo_출처
A12: 8 | B12: Raimundo 대사 | C12: «Sigue el dinero. Y la ley que lo vigila.» | D12: «Todo dinero tiene una ley que lo vigila. Búscala.» — Gonzalo의 시그니처 «Sigue el dinero.»와 중복 방지 | E12: Raimundo_출처
A13: 9 | B13: 출처표 정정 | C13: 주거·퇴거: 형사·민사소송법 | D13: 민사소송법(LEC, Ley 1/2000)의 퇴거(desahucio) 절차 | E13: Raimundo_출처
A14: 10 | B14: 형식 | C14: 상황 설명 30% + 대화 70% | D14: 전 화 100% 대화문 (지문 없음) | E14: 대화문규칙
A15: 11 | B15: 1부 시범 장면 | C15: (Silencio.), (Pepa deja el plato…) 등 괄호 지문 포함 | D15: 모든 지문을 대사로 대체 | E15: 1부_시범대사
A16: 12 | B16: 부 수 | C16: 11부작 (132화) | D16: 12부작 (144화) — 12부는 1부 장면으로 돌아오는 원형 구조 | E16: 개요, 12부_구성
... A63: 59 | B63: 5부 4화 제목 확인 | C63: — | D63: 화별목차_전체 기준 5부 4화는 «Proyecto Ícaro»(이카로 프로젝트, GM의 18% 절감 요청 킥오프 회의)이며, 3화 말미의 다음 화 예고 "El informe que no escribí"는 오기. 다음 화 제작 시 Proyecto Ícaro로 진행할 것 | E63: 5부 3화 대본 예고 문구(사소한 오기, 본문 영향 없음)
A64: 60 | B64: 5부 4~6화 완성 | C64: — | D64: 4화 과거 «Proyecto Ícaro»(킥오프, Fermín의 질문), 5화 프레임 «Viernes: un Excel»(엑셀 한 장, Sofía 서명 연결, 힌트 C47), 6화 과거 «La celda C47»(모델 승인, 412, 샴페인). 형식은 5부 1~3화 docx와 동일(15·30·30·30·15턴). | E64: 화별목차_전체, 5부 대본 3편
A65: 61 | B65: 5부 4화 초안(v1) 폐기 | C65: 표 형식 docx, Marcos=Cenit 부하, Almudena 직급 가정, '약 2년 전' | D65: 1~3화 대본과 대조해 재작성: Marcos는 2화에서 18개월 만에 퇴사한 동기 → 고객 측 경영관리 담당으로 재등장. Almudena는 2화의 '파트너 직전' → 4화에서 파트너 승진(Meridiano가 그녀의 '큰 고객'). 형식도 1~3화 docx로 통일 | E65: 5부4화_Proyecto_Icaro.docx
A66: 62 | B66: 5부 시간선 확정 | C66: 미정 | D66: 2화 9년 전(입사 25세) → 3화 8년 전(매니저 28세, 첫 단독) → 4·6화 2년 전(Diego 프린시펄 약 34세). 4화는 3화로부터 6년 뒤, 6화는 4화로부터 6주 뒤 | E66: 이어쓰기_가이드
A67: 63 | B67: GM 자회사 설정 | C67: 'GM 임원(가상)' | D67: Meridiano Movilidad(시외버스·차고지·정비소, 직원 2,300명, 연 비용 2억 1,400만 유로). Nieves가 대중교통 노조위원장이라는 설정과 맞춤 | E67: 화별목차_전체, 이어쓰기_가이드
A68: 64 | B68: C47 셀 정의 | C68: '셀 하나가 412개 일자리' | D68: C열=사업장별 인원, 47행=합계 행 «Total puestos afectados, escenario seleccionado». 시나리오 B 선택 시 412(18.1%) | E68: 복선_회수, 이어쓰기_가이드
A69: 65 | B69: 호칭: Diego → Carmen | C69: 호칭규칙상 tú | D69: 1화 대본은 usted였음. 5부 5화에서 말실수 후 Carmen의 허락으로 tú 전환. Carmen은 usted 유지 | E69: 호칭규칙
A70: 66 | B70: Carmen의 과거 구체화 | C70: '대기업 인턴에서 부당하게 쫓겨남' | D70: 금요일에 이메일로 해고, 사유 «Reestructuración del área» (5부 5화) | E70: 캐릭터(확인 필요)
A71: 67 | B71: Sofía–Meridiano 연결의 프레임 처리 | C71: — | D71: 5부 5화에서 Sofía가 Lastra가 인용한 감사 의견이 자기 서명이었음을 밝힘. «Una cuenta limpia no lava una decisión.» 6부 6화 '같은 이름' 반전의 전모는 아직 말하지 않음 | E71: 복선_회수
A72: 68 | B72: 워크북 v23 갱신 | C72: v22 | D72: 요청에 따라 5부 중간 갱신. '이어쓰기_가이드' 시트 신설, 화별목차 5부 4~6화 인물·사건 보강, 복선 8건 추가(34~41), 호칭규칙 보강 | E72: 개요, 이어쓰기_가이드
A73: 69 | B73: 5부 7~12화 완성 | C73: — | D73: 7 «La mesa de negociación», 8 «El correo equivocado», 9(프레임) «Viernes: cuatrocientos doce», 10 «La huelga», 11 «La última reunión», 12(프레임) «Viernes: un martes en Vallecas». 5부 12화 완결. | E73: 화별목차_전체
A74: 70 | B74: 6부 1~12화 완성 | C74: — | D74: 6부(El Encuentro) 12화 완결. 과거 화 docx 틀, 난이도 B2, 15·30·30·30·15. 6부 12화 «Mañana, a las cinco»로 1부 1화에 원을 닫음. | E74: 화별목차_전체
A75: 71 | B75: ERE 결과 확정 | C75: 412(모델) | D75: 합의 345명(초과근무 분배로 67개 자리 감소), 희망퇴직 35일치, Nieves 노조는 미서명. Yolanda는 잔류. | E75: 이어쓰기_가이드
... A86: 82 | B86: 9부 1화 완성 | C86: — | D86: La constitución de la Corporación: PPS 제안 거절, 연령 의장단(Iker), LOREG 196으로 UCN 알칼데. 9부도 180턴으로 집필. | E86: 화별목차_전체, 9부 대본
A87: 83 | B87: 화별목차 턴 수 | C87: =턴_설계!$B$5 (120) | D87: 8·9부 행 턴 수를 180으로 입력(10부 이후는 수식 그대로). | E87: 화별목차_전체
A88: 84 | B88: 가상 정당 추가 | C88: CC·UCN·PPS·HU·TA·TB | D88: Plataforma Vecinal(PV) 추가, 시의회 결과·알칼데 표결 시뮬레이션(3-D) 추가. | E88: 정치경로_의석
A89: 85 | B89: 색 고정 추가 | C89: 일회성 색 | D89: Milagros A0522D, Iker A64D79 고정. 단역에 7F7F7F 사용 금지(Raimundo와 겹침). | E89: 이어쓰기_가이드
A90: 86 | B90: 복선 9건 추가 | C90: 50건 | D90: 51~59 추가(59 Iker는 회수 완료). | E90: 복선_회수
A92: 2. 미결 사항 (확정 필요)
A93: No | B93: 항목 | C93: 내용 | D93: 제안 | E93: 관련 시트
A94: 1 | B94: Ferrer / Iturbe 성 | C94: Mateo Ferrer(카탈루냐계), Ramón Iturbe(바스크계)는 스페인에 흔한 성이지만 지역색이 있다. | D94: 순수 카스티야식을 원하면 Ferrer → Fuentes, Iturbe → Cebrián | E94: 캐릭터
A95: 2 | B95: Raimundo 카드의 범위 | C95: 카드를 전 화(144화)에 넣을지, Raimundo 등장 화(약 57화)에만 넣을지. | D95: 등장 화에만 넣고, 미등장 화는 Carmen이 사전(DLE·DPEJ)을 찾는 짧은 대사로 대체 | E95: Raimundo_출처
A96: 3 | B96: Carmen → 주력 4인 호칭 전환 | C96: Anselmo에게만 11부 7화에서 tú로 전환한다는 것 외에, 다른 인물에게 언제 tú로 넘어가는지 미정. | D96: 6부 만남 이후 자연스럽게 tú (Anselmo·Ramón·Gonzalo는 usted 유지) | E96: 호칭규칙
A97: 4 | B97: 경과 연수 가정 | C97: 1부→11부 6년 가정(Anselmo 74→80세). 12부는 그 이후 시점. | D97: 확정 시 개요!C11만 수정 | E97: 개요
A98: 5 | B98: 정치 직책 | C98: 14인의 직책은 제안 단계. | D98: Raimundo는 CNI 국장이 아닌 '정보기관 감독 개혁 자문'으로 유지 | E98: 캐릭터
A99: 6 | B99: 법령·조항 확인 | C99: 출처표·제도표의 법령 번호·조항은 기획 시점 지식 기준. | D99: 교재 반영 전 BOE 현행본(texto consolidado)으로 확인. 기밀법은 특히 개정 논의 중 | E99: Raimundo_출처, 정치제도
A100: 7 | B100: 대화량 실측 교정 | C100: 화당 120턴은 확정. 화자 점유율·평균 단어/턴·낭독 속도(130단어/분)는 가정값이다. | D100: 1부 1~3화 대본을 쓴 뒤 실제 턴·단어를 재서 '턴_설계'의 파란 값을 교정 | E100: 턴_설계
A101: 8 | B101: Lucía 비중 보강 | C101: 약 36%로 가장 얇다. | D101: 3·5부 상담 장면 확대, 11부 Anselmo 애도 상담 배정 | E101: 등장비중, Anselmo_죽음
A102: 9 | B102: 정부 형태 | C102: CC 단독 소수 정부 + PPS·지역정당 법안별 지지 (현재 설정) | D102: PPS 장관을 포함한 연립으로 갈지 결정 | E102: 정치경로_의석
A103: 10 | B103: 겸직 규정 확인 | C103: Sofía는 시의원, Javier는 자치의원으로 직책을 분리하고 Mateo만 하원에 출마시키는 설정. | D103: 시의원·자치의원·하원의원의 겸직 가능 여부를 LOREG 등으로 확인한 뒤 확정 | E103: 정치제도
A104: 11 | B104: 가상 수치 | C104: 의석 수(62·112 등)와 1표 차 설정은 교육용 가상 수치. | D104: 드라마 효과에 맞춰 조정 가능 (정치경로_의석의 파란 셀) | E104: 정치경로_의석
A105: 12 | B105: 국왕 표현 방침 | C105: 국왕은 직접 대사 없이 하원의장이 절차를 전달. | D105: 확정 필요 | E105: 대화문규칙
... A117: 22 | B117: 12부 예산 반영 화(11화)와 N5 위치 조정 | C117: N5(녹색 갈등)의 회수 위치가 12부 11화로 이동했으나 실제 내용과의 정합성 재확인 필요. | D117: 12부 11화 대본 집필 시 태양광 재원 논쟁과 예산 편성을 함께 다룰지 결정 | E117: 현안_배치, 현안_분포
A118: 23 | B118: Irene·Borja 등 5부 신규 가상 인물 | C118: Almudena Roig·Marcos·Julián/Alba/Mariano/Rafa Rueda·Ernesto Lastra·Fermín Robles·Irene·Borja·경비원 | D118: 해결(v24): 이어쓰기_가이드 7번 5·6부 가상 인물 부록에 정리. 전체 부록 통합은 미결 15번으로 계속. | E118: 이어쓰기_가이드
A119: 24 | B119: ERE 보상금·협의 기간 수치 | C119: 6화: 근속 1년당 20일치(상한 12개월분). 7화에서 협의 기간 최대 30일, 30명 이상/직원 300명 이상 기준 사용 예정 | D119: 부분 해결: 5부 7·10화 집필. 집행 정지 제도는 검색 확인(v24 변경이력). 제51·53조 수치는 여전히 BOE 확인 필요. | E119: 화별목차_전체
A120: 25 | B120: Carmen → 주력 4인 tú 전환 시점 | C120: 5부 5화에서 Diego에게는 tú를 허락했지만 Carmen 본인은 usted 유지 | D120: 해결(v24): 6부 11~12화에서 인턴이 되며 usted로 전환(6부 tú → 1부 usted). 다시 tú로 돌아가는 시점만 미결 3번에 남김. | E120: 호칭규칙
A121: 26 | B121: Diego의 Fermín 약속 회수 위치 | C121: «Se lo prometo»와 미답장 문자 | D121: 해결: 5부 7화(«Me enteré por el comunicado»)·11화 도입(아래에서 Yolanda를 기다림). | E121: 복선_회수
A122: 27 | B122: Marcos의 이후 역할 | C122: 5부 4·6화 고객 측으로 반대 논거 제시 | D122: 해결: 5부 7화 협상 테이블 회사 측 실무자, 명단을 Diego에게 보낸 사람. | E122: 이어쓰기_가이드
A123: 28 | B123: Pepa의 남편 마놀로 | C123: 6부 12화: 1994년 간판을 칠한 고인 | D123: 1~4부에서 Pepa 가족을 다르게 썼는지 확인 | E123: 캐릭터
A124: 29 | B124: 7부 1화 설계 — Picasso 합류 방식 | C124: 7부부터 합류 결정. 첫 등장 장면·계기 미정 | D124: Cervantes처럼 Casa Pepa에 이유 없이 나타남 + Pepa의 규칙(어디서 왔는지 묻지 않음)으로 수용 제안. 인원·등장비중 표 재집계 필요(캐릭터 시트 행 추가 시 등장비중 수식 연동 확인) | E124: 아크_구성계획, 등장비중
A125: 30 | B125: 5·6부 법률 확인 목록 | C125: ERE(ET 51·53), 파업 공지 10일(RDL 17/1977), 노조대표 소명 절차(ET 68), GDPR 33·34, 대표 비밀유지(ET 65.2), LAU 9·14·21·36, SOCIMI·특수관계 거래, Ley 2/2023 | D125: 교재 반영 전 BOE 현행본 일괄 확인 | E125: 정치제도, Raimundo_출처
A126: 31 | B126: 8부 이후 화당 180턴 적용 여부 | C126: 7부 1화부터 화당 120→180턴으로 확대했으나, 8부 이후에도 유지할지는 아직 사용자 확정 없음. | D126: 해결(v26): 8부는 사용자 확정으로 180턴 유지, 9부 1화도 180턴. 9부 이후는 미결 33번 | E126: 턴_설계, 화별목차_전체
A127: 32 | B127: 7~9부 법령 확인 목록 | C127: 대본에 쓴 조항: LO 9/1983(집회 사전 통지), LO 3/1984(ILP), LO 6/2002(정당), LO 8/2007·LO 3/2015(정당 재정), LOREG 53·55·56·69·195·196, LO 2/1984(정정권), LBRL 75.7(재산 신고), 성별 교대 명부 근거 법, LECrim 490, 선서 문구(RD 707/1979). | D127: 교재 반영 전 BOE 현행본 일괄 확인 | E127: 정치제도, Raimundo_출처
A128: 33 | B128: 9부 이후 턴 수 | C128: 9부 1화는 180턴으로 집필. 설정집 9부 계획은 화당 120턴. | D128: 9부 전체 180 유지 여부 사용자 확인 | E128: 턴_설계, 화별목차_전체
A129: 34 | B129: 7부 6·7화 대본 확인 | C129: 7부 7화 docx는 형식 틀로 받음. 6화 «El expediente»는 이 작업에서 확인하지 못함. | D129: 7부 6화 파일 존재 여부 확인 | E129: 화별목차_전체
